Workbook

Sheet 🚀 Investor Dashboard
A2: AUTONOMA | C2: INVESTOR DASHBOARD · 24-MONTH PLAN
A3: Full Business Plan: 📋 Summary · 🌎 Market & GTM · 📈 P&L · 💰 Cash & Runway · ⚠️ Risks & Roadmap · 💎 Angel Summary
A5: ACTIVE SCENARIO | B5: ='🔧 Active Scenario'!B2 -> Conservative | C5: ← change in 🔧 Active Scenario!B2 (Conservative / Base / Optimistic) — the entire BP recalculates
A8: VALUATION · M24 | C8: ANGEL RETURN · M24 | E8: CUMUL. REVENUE · 24M | G8: CASH BREAKEVEN | I8: ENDING CASH · M24
A9: =IF('🔧 Active Scenario'!B2="Conservative",'📊 Scenario Summary'!B21,IF('🔧 Active Scenario'!B2="Base",'📊 Scenario Summary'!C21,'📊 Scenario Summary'!D21)) -> 19914787 | C9: =A9*'🎛️ Assumptions'!B59 -> 2987218 | E9: =IF('🔧 Active Scenario'!B2="Conservative",'📊 Scenario Summary'!B19,IF('🔧 Active Scenario'!B2="Base",'📊 Scenario Summary'!C19,'📊 Scenario Summary'!D19)) -> 6638262.2 | G9: {=IFERROR("M"&MATCH(TRUE,INDEX('📊 Monthly Base'!C25:Z25>0,0),0),">24m")} -> M5 | I9: ='💰 Cash & Runway'!Z10 -> 4275921.5
A10: ="cumul. rev. × "&TEXT('🔧 Active Scenario'!B50,"0.0")&"× (scenario multiple)" -> cumul. rev. × 03× (scenario multiple) | C10: =TEXT(C9/'🎛️ Assumptions'!B58,"0.0")&"× over R$ "&TEXT('🎛️ Assumptions'!B58/1000,"#,##0")&"K investment · "&TEXT('🎛️ Assumptions'!B59,"0%")&" stake" -> 03× over R$ 1000,0K investment · 15% stake | E10: official valuation base (📊 Scenario Summary) | G10: cumulative result turns positive | I10: ="cash never below R$ "&TEXT(MIN('💰 Cash & Runway'!C10:Z10)/1000,"#,##0")&"K" -> cash never below R$ 942,427K
A13: MRR · M24 | C13: PAYING SUBSCRIBERS · M24 | E13: LTV / CAC | G13: CAC PAYBACK | I13: GROSS MARGIN · M24
A14: ='📊 Monthly Base'!Z11*12 -> 5606367.6 | C14: ='📊 Monthly Base'!Z9 -> 8027 | E14: ='🔧 Active Scenario'!B56 -> 6.8861031 | G14: ='🔧 Active Scenario'!B57 -> 1.8152502 | I14: ='📊 Monthly Base'!Z26 -> 0.84939387
A15: ="ARR of R$ "&TEXT('📊 Monthly Base'!Z11*12/1000000,"0.0")&"M at end of Year 2" -> ARR of R$ 06M at end of Year 2 | C15: ="from "&TEXT(('🔧 Active Scenario'!B30+'🔧 Active Scenario'!B31)*12,"#,##0")&" cumul. sign-ups · 30d trial" -> from 78000,0 cumul. sign-ups · 30d trial | E15: ="CAC R$ "&TEXT('🔧 Active Scenario'!B47,"0")&" · LTV R$ "&TEXT('🔧 Active Scenario'!B55,"0")&" (Essencial)" -> CAC R$ 80 · LTV R$ 551 (Essencial) | G15: ="≈ "&TEXT('🔧 Active Scenario'!B57*30,"0")&" days to recover CAC" -> ≈ 54 days to recover CAC | I15: after API cost (Free Haiku · paid Sonnet)
A16: PROJECTIONS · 24 MONTHS | F16: ="Active scenario: "&'🔧 Active Scenario'!B2 -> Active scenario: Conservative
A30: REVENUE & SCENARIO COMPARISON
A35: RECEITA & COMPARATIVO DE CENÁRIOS
A53: Modelo 100% dinâmico · motor de cálculo em 📊 Base Mensal · premissas em 🎛️ Premissas e 🔧 Cenário Ativo · comparação em 📊 Resumo Cenários
A54: Este material é um estudo de projeção e não configura oferta de investimento. AutoNoma © 2025
L76: Month | M76: MRR | N76: Paying | O76: Free | P76: Result | Q76: Cumulative | R76: Essencial | S76: Autônoma | T76: Livre | U76: Total API | V76: Fixed Cost | W76: Margin%
L77: M01 | M77: ='📊 Monthly Base'!C11 -> 21562 | N77: ='📊 Monthly Base'!C9 -> 380 | O77: ='📊 Monthly Base'!C5 -> 2000 | P77: ='📊 Monthly Base'!C24 -> -39903.991 | Q77: ='📊 Monthly Base'!C25 -> -39903.991 | R77: ='📊 Monthly Base'!C6 -> 200 | S77: ='📊 Monthly Base'!C7 -> 140 | T77: ='📊 Monthly Base'!C8 -> 40 | U77: ='📊 Monthly Base'!C18 -> 3662.9307 | V77: ='📊 Monthly Base'!C20 -> 55000 | W77: ='📊 Monthly Base'!C26 -> 0.83012101
L78: M02 | M78: ='📊 Monthly Base'!D11 -> 52607.4 | N78: ='📊 Monthly Base'!D9 -> 926 | O78: ='📊 Monthly Base'!D5 -> 3000 | P78: ='📊 Monthly Base'!D24 -> -17668.581 | Q78: ='📊 Monthly Base'!D25 -> -57572.571 | R78: ='📊 Monthly Base'!D6 -> 484 | S78: ='📊 Monthly Base'!D7 -> 343 | T78: ='📊 Monthly Base'!D8 -> 99 | U78: ='📊 Monthly Base'!D18 -> 8437.0186 | V78: ='📊 Monthly Base'!D20 -> 55000 | W78: ='📊 Monthly Base'!D26 -> 0.83962297
L79: M03 | M79: ='📊 Monthly Base'!E11 -> 81746.3 | N79: ='📊 Monthly Base'!E9 -> 1437 | O79: ='📊 Monthly Base'!E5 -> 3000 | P79: ='📊 Monthly Base'!E24 -> 3441.7706 | Q79: ='📊 Monthly Base'!E25 -> -54130.801 | R79: ='📊 Monthly Base'!E6 -> 745 | S79: ='📊 Monthly Base'!E7 -> 536 | T79: ='📊 Monthly Base'!E8 -> 156 | U79: ='📊 Monthly Base'!E18 -> 12677.51 | V79: ='📊 Monthly Base'!E20 -> 55000 | W79: ='📊 Monthly Base'!E26 -> 0.8449164
L80: M04 | M80: ='📊 Monthly Base'!F11 -> 109078.5 | N80: ='📊 Monthly Base'!F9 -> 1915 | O80: ='📊 Monthly Base'!F5 -> 3000 | P80: ='📊 Monthly Base'!F24 -> 23230.937 | Q80: ='📊 Monthly Base'!F25 -> -30899.864 | R80: ='📊 Monthly Base'!F6 -> 985 | S80: ='📊 Monthly Base'!F7 -> 719 | T80: ='📊 Monthly Base'!F8 -> 211 | U80: ='📊 Monthly Base'!F18 -> 16667.358 | V80: ='📊 Monthly Base'!F20 -> 55000 | W80: ='📊 Monthly Base'!F26 -> 0.84719851
L81: M05 | M81: ='📊 Monthly Base'!G11 -> 134843.6 | N81: ='📊 Monthly Base'!G9 -> 2364 | O81: ='📊 Monthly Base'!G5 -> 3000 | P81: ='📊 Monthly Base'!G24 -> 41872.273 | Q81: ='📊 Monthly Base'!G25 -> 10972.41 | R81: ='📊 Monthly Base'!G6 -> 1206 | S81: ='📊 Monthly Base'!G7 -> 893 | T81: ='📊 Monthly Base'!G8 -> 265 | U81: ='📊 Monthly Base'!G18 -> 20441.659 | V81: ='📊 Monthly Base'!G20 -> 55000 | W81: ='📊 Monthly Base'!G26 -> 0.84840468
L82: M06 | M82: ='📊 Monthly Base'!H11 -> 159061.5 | N82: ='📊 Monthly Base'!H9 -> 2785 | O82: ='📊 Monthly Base'!H5 -> 3000 | P82: ='📊 Monthly Base'!H24 -> 59384.705 | Q82: ='📊 Monthly Base'!H25 -> 70357.115 | R82: ='📊 Monthly Base'!H6 -> 1410 | S82: ='📊 Monthly Base'!H7 -> 1058 | T82: ='📊 Monthly Base'!H8 -> 317 | U82: ='📊 Monthly Base'!H18 -> 23998.8 | V82: ='📊 Monthly Base'!H20 -> 55000 | W82: ='📊 Monthly Base'!H26 -> 0.84912251
L83: M07 | M83: ='📊 Monthly Base'!I11 -> 181792.1 | N83: ='📊 Monthly Base'!I9 -> 3179 | O83: ='📊 Monthly Base'!I5 -> 3000 | P83: ='📊 Monthly Base'!I24 -> 75810.175 | Q83: ='📊 Monthly Base'!I25 -> 146167.29 | R83: ='📊 Monthly Base'!I6 -> 1597 | S83: ='📊 Monthly Base'!I7 -> 1215 | T83: ='📊 Monthly Base'!I8 -> 367 | U83: ='📊 Monthly Base'!I18 -> 27348.952 | V83: ='📊 Monthly Base'!I20 -> 55000 | W83: ='📊 Monthly Base'!I26 -> 0.84955918
L84: M08 | M84: ='📊 Monthly Base'!J11 -> 203215.1 | N84: ='📊 Monthly Base'!J9 -> 3549 | O84: ='📊 Monthly Base'!J5 -> 3000 | P84: ='📊 Monthly Base'!J24 -> 91280.094 | Q84: ='📊 Monthly Base'!J25 -> 237447.38 | R84: ='📊 Monthly Base'!J6 -> 1769 | S84: ='📊 Monthly Base'!J7 -> 1364 | T84: ='📊 Monthly Base'!J8 -> 416 | U84: ='📊 Monthly Base'!J18 -> 30517.043 | V84: ='📊 Monthly Base'!J20 -> 55000 | W84: ='📊 Monthly Base'!J26 -> 0.84982886
L85: M09 | M85: ='📊 Monthly Base'!K11 -> 223440.3 | N85: ='📊 Monthly Base'!K9 -> 3897 | O85: ='📊 Monthly Base'!K5 -> 3000 | P85: ='📊 Monthly Base'!K24 -> 105873.99 | Q85: ='📊 Monthly Base'!K25 -> 343321.37 | R85: ='📊 Monthly Base'!K6 -> 1927 | S85: ='📊 Monthly Base'!K7 -> 1506 | T85: ='📊 Monthly Base'!K8 -> 464 | U85: ='📊 Monthly Base'!K18 -> 33519.071 | V85: ='📊 Monthly Base'!K20 -> 55000 | W85: ='📊 Monthly Base'!K26 -> 0.84998646
L86: M10 | M86: ='📊 Monthly Base'!L11 -> 242487.6 | N86: ='📊 Monthly Base'!L9 -> 4224 | O86: ='📊 Monthly Base'!L5 -> 3000 | P86: ='📊 Monthly Base'!L24 -> 119610.79 | Q86: ='📊 Monthly Base'!L25 -> 462932.16 | R86: ='📊 Monthly Base'!L6 -> 2073 | S86: ='📊 Monthly Base'!L7 -> 1641 | T86: ='📊 Monthly Base'!L8 -> 510 | U86: ='📊 Monthly Base'!L18 -> 36353.425 | V86: ='📊 Monthly Base'!L20 -> 55000 | W86: ='📊 Monthly Base'!L26 -> 0.85008131
L87: M11 | M87: ='📊 Monthly Base'!M11 -> 260436.9 | N87: ='📊 Monthly Base'!M9 -> 4531 | O87: ='📊 Monthly Base'!M5 -> 3000 | P87: ='📊 Monthly Base'!M24 -> 132546.73 | Q87: ='📊 Monthly Base'!M25 -> 595478.89 | R87: ='📊 Monthly Base'!M6 -> 2207 | S87: ='📊 Monthly Base'!M7 -> 1769 | T87: ='📊 Monthly Base'!M8 -> 555 | U87: ='📊 Monthly Base'!M18 -> 39033.373 | V87: ='📊 Monthly Base'!M20 -> 55000 | W87: ='📊 Monthly Base'!M26 -> 0.85012349
L88: M12 | M88: ='📊 Monthly Base'!N11 -> 277318.1 | N88: ='📊 Monthly Base'!N9 -> 4819 | O88: ='📊 Monthly Base'!N5 -> 3000 | P88: ='📊 Monthly Base'!N24 -> 144705.1 | Q88: ='📊 Monthly Base'!N25 -> 740183.99 | R88: ='📊 Monthly Base'!N6 -> 2330 | S88: ='📊 Monthly Base'!N7 -> 1891 | T88: ='📊 Monthly Base'!N8 -> 598 | U88: ='📊 Monthly Base'!N18 -> 41561.644 | V88: ='📊 Monthly Base'!N20 -> 55000 | W88: ='📊 Monthly Base'!N26 -> 0.85013007
L89: M13 | M89: ='📊 Monthly Base'!O11 -> 298641.5 | N89: ='📊 Monthly Base'!O9 -> 5185 | O89: ='📊 Monthly Base'!O5 -> 3500 | P89: ='📊 Monthly Base'!O24 -> 144949.37 | Q89: ='📊 Monthly Base'!O25 -> 885133.37 | R89: ='📊 Monthly Base'!O6 -> 2494 | S89: ='📊 Monthly Base'!O7 -> 2041 | T89: ='📊 Monthly Base'!O8 -> 650 | U89: ='📊 Monthly Base'!O18 -> 44868.731 | V89: ='📊 Monthly Base'!O20 -> 70000 | W89: ='📊 Monthly Base'!O26 -> 0.84975721
L90: M14 | M90: ='📊 Monthly Base'!P11 -> 318767.1 | N90: ='📊 Monthly Base'!P9 -> 5529 | O90: ='📊 Monthly Base'!P5 -> 3500 | P90: ='📊 Monthly Base'!P24 -> 159453.27 | Q90: ='📊 Monthly Base'!P25 -> 1044586.6 | R90: ='📊 Monthly Base'!P6 -> 2644 | S90: ='📊 Monthly Base'!P7 -> 2184 | T90: ='📊 Monthly Base'!P8 -> 701 | U90: ='📊 Monthly Base'!P18 -> 47874.107 | V90: ='📊 Monthly Base'!P20 -> 70000 | W90: ='📊 Monthly Base'!P26 -> 0.84981478
L91: M15 | M91: ='📊 Monthly Base'!Q11 -> 337714.8 | N91: ='📊 Monthly Base'!Q9 -> 5852 | O91: ='📊 Monthly Base'!Q5 -> 3500 | P91: ='📊 Monthly Base'!Q24 -> 173100.07 | Q91: ='📊 Monthly Base'!Q25 -> 1217686.7 | R91: ='📊 Monthly Base'!Q6 -> 2782 | S91: ='📊 Monthly Base'!Q7 -> 2320 | T91: ='📊 Monthly Base'!Q8 -> 750 | U91: ='📊 Monthly Base'!Q18 -> 50711.809 | V91: ='📊 Monthly Base'!Q20 -> 70000 | W91: ='📊 Monthly Base'!Q26 -> 0.84983836
L92: M16 | M92: ='📊 Monthly Base'!R11 -> 355614.4 | N92: ='📊 Monthly Base'!R9 -> 6156 | O92: ='📊 Monthly Base'!R5 -> 3500 | P92: ='📊 Monthly Base'!R24 -> 185983.59 | Q92: ='📊 Monthly Base'!R25 -> 1403670.3 | R92: ='📊 Monthly Base'!R6 -> 2909 | S92: ='📊 Monthly Base'!R7 -> 2449 | T92: ='📊 Monthly Base'!R8 -> 798 | U92: ='📊 Monthly Base'!R18 -> 53400.935 | V92: ='📊 Monthly Base'!R20 -> 70000 | W92: ='📊 Monthly Base'!R26 -> 0.84983472
L93: M17 | M93: ='📊 Monthly Base'!S11 -> 372495.8 | N93: ='📊 Monthly Base'!S9 -> 6442 | O93: ='📊 Monthly Base'!S5 -> 3500 | P93: ='📊 Monthly Base'!S24 -> 198127.13 | Q93: ='📊 Monthly Base'!S25 -> 1601797.4 | R93: ='📊 Monthly Base'!S6 -> 3026 | S93: ='📊 Monthly Base'!S7 -> 2572 | T93: ='📊 Monthly Base'!S8 -> 844 | U93: ='📊 Monthly Base'!S18 -> 55944.213 | V93: ='📊 Monthly Base'!S20 -> 70000 | W93: ='📊 Monthly Base'!S26 -> 0.8498125
L94: M18 | M94: ='📊 Monthly Base'!T11 -> 388428.9 | N94: ='📊 Monthly Base'!T9 -> 6711 | O94: ='📊 Monthly Base'!T5 -> 3500 | P94: ='📊 Monthly Base'!T24 -> 209582.57 | Q94: ='📊 Monthly Base'!T25 -> 1811380 | R94: ='📊 Monthly Base'!T6 -> 3134 | S94: ='📊 Monthly Base'!T7 -> 2688 | T94: ='📊 Monthly Base'!T8 -> 889 | U94: ='📊 Monthly Base'!T18 -> 58350.573 | V94: ='📊 Monthly Base'!T20 -> 70000 | W94: ='📊 Monthly Base'!T26 -> 0.84977798
L95: M19 | M95: ='📊 Monthly Base'!U11 -> 403453.6 | N95: ='📊 Monthly Base'!U9 -> 6964 | O95: ='📊 Monthly Base'!U5 -> 3500 | P95: ='📊 Monthly Base'!U24 -> 220377.55 | Q95: ='📊 Monthly Base'!U25 -> 2031757.5 | R95: ='📊 Monthly Base'!U6 -> 3233 | S95: ='📊 Monthly Base'!U7 -> 2799 | T95: ='📊 Monthly Base'!U8 -> 932 | U95: ='📊 Monthly Base'!U18 -> 60627.084 | V95: ='📊 Monthly Base'!U20 -> 70000 | W95: ='📊 Monthly Base'!U26 -> 0.84972972
L96: M20 | M96: ='📊 Monthly Base'!V11 -> 417639.8 | N96: ='📊 Monthly Base'!V9 -> 7202 | O96: ='📊 Monthly Base'!V5 -> 3500 | P96: ='📊 Monthly Base'!V24 -> 230563.95 | Q96: ='📊 Monthly Base'!V25 -> 2262321.5 | R96: ='📊 Monthly Base'!V6 -> 3324 | S96: ='📊 Monthly Base'!V7 -> 2904 | T96: ='📊 Monthly Base'!V8 -> 974 | U96: ='📊 Monthly Base'!V18 -> 62782.676 | V96: ='📊 Monthly Base'!V20 -> 70000 | W96: ='📊 Monthly Base'!V26 -> 0.84967267
L97: M21 | M97: ='📊 Monthly Base'!W11 -> 431097.3 | N97: ='📊 Monthly Base'!W9 -> 7427 | O97: ='📊 Monthly Base'!W5 -> 3500 | P97: ='📊 Monthly Base'!W24 -> 240221.3 | Q97: ='📊 Monthly Base'!W25 -> 2502542.8 | R97: ='📊 Monthly Base'!W6 -> 3408 | S97: ='📊 Monthly Base'!W7 -> 3004 | T97: ='📊 Monthly Base'!W8 -> 1015 | U97: ='📊 Monthly Base'!W18 -> 64833.346 | V97: ='📊 Monthly Base'!W20 -> 70000 | W97: ='📊 Monthly Base'!W26 -> 0.84960855
L98: M22 | M98: ='📊 Monthly Base'!X11 -> 443826.1 | N98: ='📊 Monthly Base'!X9 -> 7639 | O98: ='📊 Monthly Base'!X5 -> 3500 | P98: ='📊 Monthly Base'!X24 -> 249349.61 | Q98: ='📊 Monthly Base'!X25 -> 2751892.4 | R98: ='📊 Monthly Base'!X6 -> 3485 | S98: ='📊 Monthly Base'!X7 -> 3099 | T98: ='📊 Monthly Base'!X8 -> 1055 | U98: ='📊 Monthly Base'!X18 -> 66779.096 | V98: ='📊 Monthly Base'!X20 -> 70000 | W98: ='📊 Monthly Base'!X26 -> 0.8495377
L99: M23 | M99: ='📊 Monthly Base'!Y11 -> 455796.2 | N99: ='📊 Monthly Base'!Y9 -> 7838 | O99: ='📊 Monthly Base'!Y5 -> 3500 | P99: ='📊 Monthly Base'!Y24 -> 257930.21 | Q99: ='📊 Monthly Base'!Y25 -> 3009822.6 | R99: ='📊 Monthly Base'!Y6 -> 3556 | S99: ='📊 Monthly Base'!Y7 -> 3189 | T99: ='📊 Monthly Base'!Y8 -> 1093 | U99: ='📊 Monthly Base'!Y18 -> 68612.484 | V99: ='📊 Monthly Base'!Y20 -> 70000 | W99: ='📊 Monthly Base'!Y26 -> 0.84946675
L100: M24 | M100: ='📊 Monthly Base'!Z11 -> 467197.3 | N100: ='📊 Monthly Base'!Z9 -> 8027 | O100: ='📊 Monthly Base'!Z5 -> 3500 | P100: ='📊 Monthly Base'!Z24 -> 266098.87 | Q100: ='📊 Monthly Base'!Z25 -> 3275921.5 | R100: ='📊 Monthly Base'!Z6 -> 3622 | S100: ='📊 Monthly Base'!Z7 -> 3275 | T100: ='📊 Monthly Base'!Z8 -> 1130 | U100: ='📊 Monthly Base'!Z18 -> 70362.778 | V100: ='📊 Monthly Base'!Z20 -> 70000 | W100: ='📊 Monthly Base'!Z26 -> 0.84939387
L102: Scenario | M102: Investment R$1M | N102: Valuation 100% M24 | O102: ="Angel Return ("&TEXT('🎛️ Assumptions'!$B$59,"0%")&")" -> Angel Return (15%)
L103: Conservative | M103: ='🎛️ Assumptions'!$B$58/1000000 -> 1 | N103: ='📊 Scenario Summary'!B21/1000000 -> 19.914787 | O103: ='📊 Scenario Summary'!B22/1000000 -> 2.987218
L104: Base | M104: ='🎛️ Assumptions'!$B$58/1000000 -> 1 | N104: ='📊 Scenario Summary'!C21/1000000 -> 50.824494 | O104: ='📊 Scenario Summary'!C22/1000000 -> 7.623674
L105: Optimistic | M105: ='🎛️ Assumptions'!$B$58/1000000 -> 1 | N105: ='📊 Scenario Summary'!D21/1000000 -> 101.18223 | O105: ='📊 Scenario Summary'!D22/1000000 -> 15.177334

Sheet 📋 Executive Summary
B2: AUTONOMA · EXECUTIVE SUMMARY
B3: Asset-Light SaaS · Personal AI for Brazilian women · Brazil → LATAM · 24-month horizon
B6: 1 · THE COMPANY
B7: Vision | C7: To be the leading AI assistant for personal and financial autonomy in Latin America, starting with Brazil.
B8: Problem | C8: Generic assistants don't execute end-to-end tasks: the user still carries the mental load of planning, remembering, and solving.
B9: Solution | C9: Noma: assistant with memory + autonomous agents that complete full tasks (Sonnet 4.6 on paid plans; Haiku 4.5 on Free as acquisition cost).
B10: Why now | C10: Cost per token declining (caching -35% to -45%), agents mature for production, and Brazilian market with no player focused on this audience.
B12: 2 · BUSINESS MODEL · PLANS
B13: Plan | C13: Price (R$/month) | D13: AI Model | E13: Includes | F13: Funnel role
B14: Free | C14: 0 | D14: Haiku 4.5 | E14: 50 interactions/month | F14: Acquisition (mkt cost)
B15: Essencial | C15: ='🔧 Active Scenario'!B6 -> 39.9 | D15: Sonnet 4.6 | E15: Unlimited chat + memory · add-on specialized agents (avg R$ 10/month) | F15: Volume · revenue base
B16: Autônoma | C16: ='🔧 Active Scenario'!B7 -> 59.9 | D16: Sonnet 4.6 | E16: Chat + 1 autonomous agent | F16: Upsell · lock-in
B17: Livre | C17: ='🔧 Active Scenario'!B8 -> 79.9 | D17: Sonnet 4.6 | E17: Chat + 2 agents | F17: Premium · max lock-in
B18: Dynamic pricing per scenario selected in 🔧 Active Scenario!B2. Gross margin >80% sustained by caching and Free on Haiku.
B20: 3 · THE ANGEL INVESTOR OFFER
B21: Investment | C21: ='🎛️ Assumptions'!B58 -> 1000000 | D21: ← single entry, ~18-month runway
B22: Equity offered | C22: ='🎛️ Assumptions'!B59 -> 0.15 | D22: ← stake acquired in the investment
B23: Valuation pre-money | C23: ='🎛️ Assumptions'!B60 -> 5666666.7 | D23: = investment ÷ equity − investment
B24: Valuation post-money | C24: ='🎛️ Assumptions'!B61 -> 6666666.7 | D24: = investment ÷ equity
B25: Use of capital | C25: 40% Product · 30% Acquisition · 20% Team · 10% Reserve (detail in 💎 Angel Summary)
B27: 4 · FINANCIAL HIGHLIGHTS · ACTIVE SCENARIO: | C27: ='🔧 Active Scenario'!B2 -> Conservative
B28: Indicator | C28: M12 | D28: M24 | E28: Note
B29: Paying subscribers | C29: ='📊 Monthly Base'!N9 -> 4819 | D29: ='📊 Monthly Base'!Z9 -> 8027 | E29: compound growth from Free base
B30: MRR (R$/month) | C30: ='📊 Monthly Base'!N11 -> 277318.1 | D30: ='📊 Monthly Base'!Z11 -> 467197.3 | E30: monthly recurring revenue
B31: Cumulative revenue | C31: ='📊 Monthly Base'!N12 -> 1947589.4 | D31: ='📊 Monthly Base'!Z12 -> 6638262.2 | E31: sum of 24 months of MRR from active scenario (📊 Monthly Base)
B32: Monthly result | C32: ='📊 Monthly Base'!N24 -> 144705.1 | D32: ='📊 Monthly Base'!Z24 -> 266098.87 | E32: after API + fixed + taxes
B33: Gross margin (% MRR) | C33: ='📊 Monthly Base'!N26 -> 0.85013007 | D33: ='📊 Monthly Base'!Z26 -> 0.84939387 | E33: after API cost
B34: Cash breakeven | C34: {=IFERROR("M"&MATCH(TRUE,INDEX('📊 Monthly Base'!C25:Z25>0,0),0),">24m")} -> M5 | E34: cumulative result > 0
B35: LTV / CAC (Essencial) | C35: ='🔧 Active Scenario'!B56 -> 6.8861031 | E35: =IF(C35>=8,"✅ top quartile",IF(C35>=3,"✅ healthy","⚠️ review CAC")) -> ✅ healthy
B36: Valuation M24 (active scenario) | C36: =IF('🔧 Active Scenario'!B2="Conservative",'📊 Scenario Summary'!B21,IF('🔧 Active Scenario'!B2="Base",'📊 Scenario Summary'!C21,'📊 Scenario Summary'!D21)) -> 19914787 | E36: cumul. rev. 24m × scenario multiple
B37: Angel return (15% stake) | C37: =C36*'🎛️ Assumptions'!B59 -> 2987218 | D37: =C37/'🎛️ Assumptions'!B58 -> 2.987218 | E37: stake value ÷ investment
B39: 5 · INVESTMENT THESIS
B40: ① Unit economics proven from M1: LTV/CAC ≥5× even in the Conservative scenario; CAC payback < 3 months.
B41: ② Software margin (>80%) with controlled variable cost: Free runs on Haiku 4.5; paid on Sonnet 4.6 with caching.
B42: ③ Fast breakeven (M7 in Conservative) — the investment funds growth, not operating losses.
B43: ④ Churn decreases with agent adoption (8% → 3%): the more Noma executes, the greater the lock-in.
B44: ⑤ Viable exit in 24m: cumulative revenue supports Series A at 3–7× — 4–22× return on investment depending on scenario.
B46: Note: This study does not constitute an investment invitation or promise. All values are 100% dynamic — they recalculate when changing 🔧 Active Scenario!B2 and 🎛️ Assumptions. AutoNoma © 2025.

Sheet 🌎 Market & GTM
B2: AUTONOMA · MARKET & GO-TO-MARKET
B3: TAM/SAM/SOM sizing · acquisition funnel · channels · competitive positioning
B6: 1 · MARKET SIZE · BRAZIL (editable inputs in blue)
B7: Layer | C7: Users | D7: Annual potential (R$) | E7: % captured | F7: Definition
B8: TAM · total market | C8: 54000000 | D8: =C8*'🔧 Active Scenario'!B6*12 -> 25855200000 | F8: Connected adult women in Brazil (editable estimate)
B9: SAM · addressable market | C9: 12000000 | D9: =C9*'🔧 Active Scenario'!B6*12 -> 5745600000 | E9: =C9/C8 -> 0.22222222 | F9: Already pay for digital subscriptions and use AI/productivity apps
B10: SOM · captured by M24 (sign-ups) | C10: =('🔧 Active Scenario'!B30+'🔧 Active Scenario'!B31)*12 -> 78000 | D10: ='📊 Monthly Base'!Z11*12 -> 5606367.6 | E10: =C10/C9 -> 0.0065 | F10: Cumulative sign-ups in 24m (30-day trial) · potential = ARR at M24
B11: └ of which paying at M24 | C11: ='📊 Monthly Base'!Z9 -> 8027 | D11: ='📊 Monthly Base'!Z11 -> 467197.3 | E11: =C11/C10 -> 0.10291026 | F11: Cumulative Free → paid conversion rate
B12: Required SAM penetration in 24m is below 1% — the plan doesn't depend on dominating the market to deliver the projected return.
B14: 2 · ACQUISITION FUNNEL · ACTIVE SCENARIO (dynamic values)
B15: Funnel stage | C15: Value | D15: Unit | F15: Reading
B16: New Free sign-ups · M1–M12 | C16: ='🔧 Active Scenario'!B30 -> 3000 | D16: leads/month | F16: organic + viral + paid
B17: New Free sign-ups · M13–M24 | C17: ='🔧 Active Scenario'!B31 -> 3500 | D17: leads/month | F17: national scale
B18: Conversion Free → Essencial | C18: ='🔧 Active Scenario'!B32 -> 0.1 | D18: of eligible base/month | F18: paid entry door
B19: Upgrade Essencial → Autônoma | C19: ='🔧 Active Scenario'!B33 -> 0.07 | D19: of eligible base/month | F19: 1st autonomous agent
B20: Upgrade Autônoma → Livre | C20: ='🔧 Active Scenario'!B34 -> 0.02 | D20: of eligible base/month | F20: premium tier
B21: Monthly churn (Essencial / Autônoma / Livre) | C21: =TEXT('🔧 Active Scenario'!B35,"0%")&" / "&TEXT('🔧 Active Scenario'!B36,"0%")&" / "&TEXT('🔧 Active Scenario'!B37,"0%") -> 8% / 5% / 3% | D21: %/month | F21: lock-in grows with agents
B22: Full-loaded CAC | C22: ='🔧 Active Scenario'!B47 -> 80 | D22: per subscriber | F22: ="payback in "&TEXT('🔧 Active Scenario'!B57,"0.0")&" months" -> payback in 02 months
B23: % acquisition via paid (vs. organic) | C23: ='🔧 Active Scenario'!B48 -> 0.5 | D23: of new paying users | F23: remaining: organic, viral, partnerships
B25: 3 · CHANNELS & ENTRY STRATEGY
B26: Organic & viral | C26: Short-form content (TikTok/Reels/Shorts) showing Noma executing real tasks · in-app referral program
B27: Paid social | C27: Meta + TikTok Ads with use-case creatives · ~50% of new paying users · CAC cap governed by assumptions
B28: Partnerships & influencers | C28: Personal finance, career, and motherhood creators · trackable coupons per channel
B29: Free as engine | C29: Free plan (Haiku 4.5, 50 interactions/month) is the acquisition cost: the user experiences value before paying
B31: 4 · COMPETITIVE POSITIONING
B32: Player | C32: Price (R$/month) | D32: Focus | F32: Why AutoNoma wins
B33: ChatGPT / Gemini (generic) | C33: ~R$ 100+ | D33: generic chat | F33: End-to-end executing agents + personal context memory + affordable BRL pricing
B34: Productivity/organization apps | C34: R$ 20–50 | D34: lists and reminders | F34: Noma doesn’t remind the task — it does the task
B35: Embedded assistants (banks, e-commerce) | C35: free | D35: single vertical | F35: Cross-cutting view of the user’s life, not of a single product
B36: AutoNoma | C36: ="R$ "&TEXT('🔧 Active Scenario'!B6,"0,00")&"–"&TEXT('🔧 Active Scenario'!B8,"0,00") -> R$ 39,90–79,90 | D36: personal agents | F36: Audience focus, autonomous agents, optimized variable cost (Haiku Free / Sonnet paid)
B38: Note: market values are editable estimates for sizing — they do not replace formal research. AutoNoma © 2025.

Sheet 💎 Angel Summary
B2: AUTONOMA · ANGEL INVESTOR SUMMARY
B3: Asset-Light SaaS · Brazil → LATAM · Sonnet 4.6 (paid plans) + Haiku 4.5 (Free) · 24-month horizon
B5: 1 · THE OFFER
B6: Investment | C6: ='🎛️ Assumptions'!B58 -> 1000000 | D6: ← angel entry
B7: Equity offered | C7: ='🎛️ Assumptions'!B59 -> 0.15 | D7: ← stake acquired
B8: Valuation post-money | C8: ='🎛️ Assumptions'!B61 -> 6666666.7 | D8: = investment ÷ equity
B9: Valuation pre-money | C9: ='🎛️ Assumptions'!B60 -> 5666666.7
B11: 2 · MILESTONES TO SERIES A (Base scenario)
B12: Indicator | C12: M12 | D12: M24
B13: Paying subscribers | C13: ='📊 Monthly Base'!N9 -> 4819 | D13: ='📊 Monthly Base'!Z9 -> 8027
B14: MRR (R$/month) | C14: ='📊 Monthly Base'!N11 -> 277318.1 | D14: ='📊 Monthly Base'!Z11 -> 467197.3
B15: Cumulative revenue | C15: ='📊 Monthly Base'!N12 -> 1947589.4 | D15: ='📊 Monthly Base'!Z12 -> 6638262.2
B16: Gross margin | C16: ='📊 Monthly Base'!N26 -> 0.85013007 | D16: ='📊 Monthly Base'!Z26 -> 0.84939387
B17: Monthly result | C17: ='📊 Monthly Base'!N24 -> 144705.1 | D17: ='📊 Monthly Base'!Z24 -> 266098.87
B19: 3 · ANGEL RETURN (15% stake)
B20: Scenario | C20: Valuation M24 | D20: 15% stake value | E20: Multiple on investment
B21: Conservative | C21: ='📊 Scenario Summary'!B21 -> 19914787 | D21: =C21*'🎛️ Assumptions'!$B$59 -> 2987218 | E21: =D21/'🎛️ Assumptions'!$B$58 -> 2.987218
B22: Base | C22: ='📊 Scenario Summary'!C21 -> 50824494 | D22: =C22*'🎛️ Assumptions'!$B$59 -> 7623674 | E22: =D22/'🎛️ Assumptions'!$B$58 -> 7.623674
B23: Optimistic | C23: ='📊 Scenario Summary'!D21 -> 1.0118223e+08 | D23: =C23*'🎛️ Assumptions'!$B$59 -> 15177334 | E23: =D23/'🎛️ Assumptions'!$B$58 -> 15.177334
B25: 4 · USE OF CAPITAL (R$1M · ~18-month runway)
B26: Product & Engineering (Sonnet/Haiku, dev) | C26: 0.4 | D26: =C26*'🎛️ Assumptions'!$B$58 -> 400000
B27: Acquisition & Marketing (CAC, growth) | C27: 0.3 | D27: =C27*'🎛️ Assumptions'!$B$58 -> 300000
B28: Team & Operations (CS, founder comp) | C28: 0.2 | D28: =C28*'🎛️ Assumptions'!$B$58 -> 200000
B29: Reserve & Legal/Accounting | C29: 0.1 | D29: =C29*'🎛️ Assumptions'!$B$58 -> 100000
B30: Total | C30: =SUM(C26:C29) -> 1 | D30: =SUM(D26:D29) -> 1000000
B32: 5 · STRESS TEST / DOWNSIDE (transparency to the angel)
B33: ="• Even in the Conservative scenario, the investment returns ~"&TEXT('📊 Scenario Summary'!B23,"0.0")&"× in 24 months ("&TEXT('🎛️ Assumptions'!B59,"0%")&" stake = R$ "&TEXT('📊 Scenario Summary'!B22/1000000,"0.0")&"M)." -> • Even in the Conservative scenario, the investment returns ~03× in 24 months (15% stake = R$ 03M).
B34: • Differentiated churn by plan: Essencial 8%, Autônoma 5%, Livre 3% — lock-in grows with agent usage.
B35: • Cash break-even at M6; gross margin >80% sustained by running Free on Haiku (cost only).
B36: • Sensitive to: actual CAC (currently R$60 full-loaded) and Free→paid conversion. Both controllable in 🎛️ Assumptions.
B37: • Next milestone: Cumul. revenue R$15M at M24 supports Series A conversion at 5× revenue (≈R$75M).
B39: Note: This summary does not constitute an investment invitation or promise. All values recalculate when changing the scenario in 🔧 Active Scenario and assumptions in 🎛️ Assumptions. AutoNoma © 2025.
B42: 6 · SENSITIVITY: CHURN × LTV/CAC (Essencial plan, Base scenario)
B43: Churn/month | C43: Avg. lifetime (m) | D43: LTV (R$) | E43: LTV / CAC | F43: Reading
B44: 0.05 | C44: =1/B44 -> 20 | D44: ='📊 Scenario Summary'!$C$13*C44 -> 867.1112 | E44: =D44/'🎛️ Assumptions'!$C$48 -> 14.451853 | F44: =IF(E44>=8,"✅ top quartile",IF(E44>=3,"✅ healthy","⚠️ review CAC")) -> ✅ top quartile
B45: 0.06 | C45: =1/B45 -> 16.666667 | D45: ='📊 Scenario Summary'!$C$13*C45 -> 722.59267 | E45: =D45/'🎛️ Assumptions'!$C$48 -> 12.043211 | F45: =IF(E45>=8,"✅ top quartile",IF(E45>=3,"✅ healthy","⚠️ review CAC")) -> ✅ top quartile
B46: 0.07 | C46: =1/B46 -> 14.285714 | D46: ='📊 Scenario Summary'!$C$13*C46 -> 619.36514 | E46: =D46/'🎛️ Assumptions'!$C$48 -> 10.322752 | F46: =IF(E46>=8,"✅ top quartile",IF(E46>=3,"✅ healthy","⚠️ review CAC")) -> ✅ top quartile
B47: 0.08 | C47: =1/B47 -> 12.5 | D47: ='📊 Scenario Summary'!$C$13*C47 -> 541.9445 | E47: =D47/'🎛️ Assumptions'!$C$48 -> 9.0324083 | F47: =IF(E47>=8,"✅ top quartile",IF(E47>=3,"✅ healthy","⚠️ review CAC")) -> ✅ top quartile
B48: 0.1 | C48: =1/B48 -> 10 | D48: ='📊 Scenario Summary'!$C$13*C48 -> 433.5556 | E48: =D48/'🎛️ Assumptions'!$C$48 -> 7.2259267 | F48: =IF(E48>=8,"✅ top quartile",IF(E48>=3,"✅ healthy","⚠️ review CAC")) -> ✅ healthy
B49: 0.12 | C49: =1/B49 -> 8.3333333 | D49: ='📊 Scenario Summary'!$C$13*C49 -> 361.29633 | E49: =D49/'🎛️ Assumptions'!$C$48 -> 6.0216056 | F49: =IF(E49>=8,"✅ top quartile",IF(E49>=3,"✅ healthy","⚠️ review CAC")) -> ✅ healthy
B50: 0.15 | C50: =1/B50 -> 6.6666667 | D50: ='📊 Scenario Summary'!$C$13*C50 -> 289.03707 | E50: =D50/'🎛️ Assumptions'!$C$48 -> 4.8172844 | F50: =IF(E50>=8,"✅ top quartile",IF(E50>=3,"✅ healthy","⚠️ review CAC")) -> ✅ healthy
B51: Reading: even doubling churn to 15%/month (life ~7m), LTV/CAC remains healthy at 4.8×. The model doesn’t depend on optimistic retention — it survives the downside.

Sheet 📈 Annual P&L
B2: AUTONOMA · PROJECTED P&L · YEAR 1 & YEAR 2
B3: ="Consolidated from 📊 Monthly Base · active scenario: "&'🔧 Active Scenario'!B2&" · values recalculate when switching scenario" -> Consolidated from 📊 Monthly Base · active scenario: Conservative · values recalculate when switching scenario
B6: Line item (R$) | C6: Year 1 (M1–M12) | D6: Year 2 (M13–M24) | E6: Total 24m | F6: Note
B7: Gross revenue (subscriptions) | C7: =SUM('📊 Monthly Base'!C11:N11) -> 1947589.4 | D7: =SUM('📊 Monthly Base'!O11:Z11) -> 4690672.8 | E7: =C7+D7 -> 6638262.2 | F7: sum of monthly MRR
B8: (−) Taxes on revenue | C8: =-SUM('📊 Monthly Base'!C21:N21) -> -253186.62 | D8: =-SUM('📊 Monthly Base'!O21:Z21) -> -609787.46 | E8: =C8+D8 -> -862974.09 | F8: ="Simples Nacional "&TEXT('🔧 Active Scenario'!B59,"0.0%")&" on MRR" -> Simples Nacional 13% on MRR
B9: (=) Net revenue | C9: =C7+C8 -> 1694402.8 | D9: =D7+D8 -> 4080885.3 | E9: =C9+D9 -> 5775288.1
B10: (−) Variable cost · Anthropic API | C10: =-SUM('📊 Monthly Base'!C18:N18) -> -294218.78 | D10: =-SUM('📊 Monthly Base'!O18:Z18) -> -705147.83 | E10: =C10+D10 -> -999366.62 | F10: Free tokens (Haiku) + paid (Sonnet, w/ caching)
B11: (=) Gross profit | C11: =C9+C10 -> 1400184 | D11: =D9+D10 -> 3375737.5 | E11: =C11+D11 -> 4775921.5
B12: Gross margin (% gross revenue) | C12: =IF(C7=0,0,C11/C7) -> 0.71893182 | D12: =IF(D7=0,0,D11/D7) -> 0.71967022 | E12: =IF(E7=0,0,E11/E7) -> 0.71945358
B13: (−) Fixed operating costs | C13: =-SUM('📊 Monthly Base'!C20:N20) -> -660000 | D13: =-SUM('📊 Monthly Base'!O20:Z20) -> -840000 | E13: =C13+D13 -> -1500000 | F13: breakdown below
B14: ├ Team | C14: =-'🔧 Active Scenario'!B39*12 -> -480000 | D14: =-'🔧 Active Scenario'!B40*12 -> -600000 | E14: =C14+D14 -> -1080000
B15: ├ Infrastructure & tools | C15: =-'🔧 Active Scenario'!B41*12 -> -60000 | D15: =-'🔧 Active Scenario'!B42*12 -> -84000 | E15: =C15+D15 -> -144000
B16: ├ Marketing & acquisition | C16: =-'🔧 Active Scenario'!B43*12 -> -60000 | D16: =-'🔧 Active Scenario'!B44*12 -> -96000 | E16: =C16+D16 -> -156000
B17: └ Other (accounting, legal, admin) | C17: =-'🔧 Active Scenario'!B45*12 -> -60000 | D17: =-'🔧 Active Scenario'!B45*12 -> -60000 | E17: =C17+D17 -> -120000
B18: (=) EBITDA ≈ operating result | C18: =C11+C13 -> 740183.99 | D18: =D11+D13 -> 2535737.5 | E18: =C18+D18 -> 3275921.5 | F18: asset-light: no relevant capex, no debt
B19: EBITDA margin (% gross revenue) | C19: =IF(C7=0,0,C18/C7) -> 0.38005136 | D19: =IF(D7=0,0,D18/D7) -> 0.54059143 | E19: =IF(E7=0,0,E18/E7) -> 0.49349083
B21: Cumulative result at end of period | C21: ='📊 Monthly Base'!N25 -> 740183.99 | D21: ='📊 Monthly Base'!Z25 -> 3275921.5 | F21: cross-check with row 25 of 📊 Monthly Base
B22: Check · EBITDA 24m = cumul. result M24 | C22: =IF(ROUND(E18-D21,0)=0,"✅ matches","⚠️ diverges by R$ "&TEXT(E18-D21,"#,##0")) -> ✅ matches
B24: Note: Simplified accrual P&L (no D&A, financial result, or additional income tax — Simples Nacional on revenue). Paid CAC is included in Marketing & acquisition.

Sheet 💰 Cash & Runway
B2: AUTONOMA · CASH & RUNWAY · 24 MONTHS
B3: ="R$ "&TEXT('🎛️ Assumptions'!B58,"#,##0")&" investment at M1 + monthly operating result · scenario: "&'🔧 Active Scenario'!B2 -> R$ 1000000,0 investment at M1 + monthly operating result · scenario: Conservative
B6: MONTHLY CASH FLOW (R$)
B7: Month | C7: ='📊 Monthly Base'!C3 -> M01 | D7: ='📊 Monthly Base'!D3 -> M02 | E7: ='📊 Monthly Base'!E3 -> M03 | F7: ='📊 Monthly Base'!F3 -> M04 | G7: ='📊 Monthly Base'!G3 -> M05 | H7: ='📊 Monthly Base'!H3 -> M06 | I7: ='📊 Monthly Base'!I3 -> M07 | J7: ='📊 Monthly Base'!J3 -> M08 | ... Z7: ='📊 Monthly Base'!Z3 -> M24 ★
B8: Capital inflow (angel investment) | C8: =IF(C7="M01",'🎛️ Assumptions'!$B$58,0) -> 1000000 | D8: =IF(D7="M01",'🎛️ Assumptions'!$B$58,0) -> 0 | E8: =IF(E7="M01",'🎛️ Assumptions'!$B$58,0) -> 0 | F8: =IF(F7="M01",'🎛️ Assumptions'!$B$58,0) -> 0 | G8: =IF(G7="M01",'🎛️ Assumptions'!$B$58,0) -> 0 | H8: =IF(H7="M01",'🎛️ Assumptions'!$B$58,0) -> 0 | I8: =IF(I7="M01",'🎛️ Assumptions'!$B$58,0) -> 0 | J8: =IF(J7="M01",'🎛️ Assumptions'!$B$58,0) -> 0 | ... Z8: =IF(Z7="M01",'🎛️ Assumptions'!$B$58,0) -> 0
B9: Monthly operating result | C9: ='📊 Monthly Base'!C24 -> -39903.991 | D9: ='📊 Monthly Base'!D24 -> -17668.581 | E9: ='📊 Monthly Base'!E24 -> 3441.7706 | F9: ='📊 Monthly Base'!F24 -> 23230.937 | G9: ='📊 Monthly Base'!G24 -> 41872.273 | H9: ='📊 Monthly Base'!H24 -> 59384.705 | I9: ='📊 Monthly Base'!I24 -> 75810.175 | J9: ='📊 Monthly Base'!J24 -> 91280.094 | ... Z9: ='📊 Monthly Base'!Z24 -> 266098.87
B10: Cash balance (end of month) | C10: =C8+C9 -> 960096.01 | D10: =C10+D8+D9 -> 942427.43 | E10: =D10+E8+E9 -> 945869.2 | F10: =E10+F8+F9 -> 969100.14 | G10: =F10+G8+G9 -> 1010972.4 | H10: =G10+H8+H9 -> 1070357.1 | I10: =H10+I8+I9 -> 1146167.3 | J10: =I10+J8+J9 -> 1237447.4 | K10: =J10+K8+K9 -> 1343321.4 | ... Z10: =Y10+Z8+Z9 -> 4275921.5
B12: RUNWAY & SOLVENCY INDICATORS
B13: Minimum cash in period | C13: =MIN(C10:Z10) -> 942427.43 | G13: ="occurs at "&INDEX(C7:Z7,MATCH(MIN(C10:Z10),C10:Z10,0))&" — "&IF(MIN(C10:Z10)>0,"investment covers entire curve: cash never goes negative ✅","⚠️ cash goes negative: review assumptions or investment") -> occurs at M02 — investment covers entire curve: cash never goes negative ✅
B14: Ending cash · M24 | C14: =Z10 -> 4275921.5 | G14: investment + 24-month cumulative result
B15: Avg. burn pre-breakeven | C15: =IFERROR(AVERAGEIF(C9:Z9,"<0"),0) -> -28786.286 | G15: average of months with negative result
B16: Theoretical runway w/o revenue | C16: ='🎛️ Assumptions'!B58/AVERAGE('📊 Monthly Base'!C20:N20) -> 18.181818 | G16: investment ÷ avg. Year 1 fixed cost (extreme stress: zero revenue)
B17: Cash breakeven (cumul. result > 0) | C17: {=IFERROR("M"&MATCH(TRUE,INDEX('📊 Monthly Base'!C25:Z25>0,0),0),">24m")} -> M5 | G17: from this point the operation is self-financing
B19: Note: Simplified cash flow = investment + operating result (no capex, no debt, no dividends). Alternative scenarios in 📊 Scenario Summary.

Sheet ⚠️ Risks & Roadmap
B2: AUTONOMA · RISKS, MITIGATIONS & ROADMAP
B3: Risk matrix with monitoring triggers · 24-month execution roadmap · management guard-rails
B6: 1 · RISK MATRIX & MITIGATIONS
B7: Risk | C7: Probability | D7: Impact | E7: Mitigation | F7: Alert trigger
B8: CAC above forecast (paid saturated) | C8: Medium | D8: High | E8: LTV/CAC ≥3× discipline per channel; reallocate budget to organic/partnerships; creatives tested weekly | F8: Blended CAC > R$ 120
B9: Churn above plan | C9: Medium | D9: High | E9: Guided onboarding; 1st agent activation within first 7 days (churn drops from 8% to 5–3% with active agents) | F9: Essencial churn > 10%/month
B10: API price increase / end of caching | C10: Low | D10: High | E10: Multi-model architecture (abstraction layer); usage limits per plan; partial price pass-through if needed | F10: Gross margin < 70%
B11: USD/BRL FX rate (dollar-denominated API cost) | C11: Medium | D11: Medium | E11: Margin >80% absorbs fluctuations; editable FX assumption in 🎛️ Assumptions; annual price adjustment | F11: USD > R$ 6.50
B12: Big techs launch direct competitor | C12: High | D12: Medium | E12: Niche focus + brand + accumulated personal memory (switching cost); local execution speed | F12: Conversion drop in new cohorts
B13: Single-vendor dependency (Anthropic) | C13: Low | D13: High | E13: LLM-agnostic abstraction layer; periodic testing with alternative models; SLA contract | F13: Latency/SLA below standard
B14: LGPD · sensitive data privacy | C14: Medium | D14: High | E14: Privacy by design; encryption at rest and in transit; granular consent; DPO from M1 | F14: Any data incident
B15: Execution with lean team | C15: Medium | D15: Medium | E15: 20% of investment in team; product/growth advisors; roadmap with quarterly verifiable milestones | F15: Delay > 1 quarter on milestones
B17: 2 · EXECUTION ROADMAP · 24 MONTHS (dynamic goals from active scenario)
B18: Phase | C18: Period | E18: Key deliverables | F18: Verifiable target
B19: Launch | C19: M1–M3 | E19: App + Noma core (chat with memory) · onboarding · recurring billing · beta with waitlist | F19: =TEXT('📊 Monthly Base'!E9,"#,##0")&" paying at M3" -> 1437,0 paying at M3
B20: Traction | C20: M4–M6 | E20: 1st autonomous agent (Autônoma plan) · referral program · paid ads at scale begins | F20: {="Cash breakeven at "&IFERROR("M"&MATCH(TRUE,INDEX('📊 Monthly Base'!C25:Z25>0,0),0),">24m")} -> Cash breakeven at M5
B21: Scale · Year 1 | C21: M7–M12 | E21: Livre plan (2 agents) · influencer partnerships · paid channel expansion | F21: =TEXT('📊 Monthly Base'!N9,"#,##0")&" paying · MRR R$ "&TEXT('📊 Monthly Base'!N11,"#,##0")&" at M12" -> 4819,0 paying · MRR R$ 277318,10 at M12
B22: Expansion | C22: M13–M18 | E22: New vertical agents (finance, career, family) · retention improvement · data prep for due diligence | F22: ="MRR R$ "&TEXT('📊 Monthly Base'!T11,"#,##0")&" at M18" -> MRR R$ 388428,90 at M18
B23: Series A ready | C23: M19–M24 | E23: Margin efficiency · LATAM study (Spanish) · Series A fundraise with audited metrics | F23: =TEXT('📊 Monthly Base'!Z9,"#,##0")&" paying · valuation R$ "&TEXT(IF('🔧 Active Scenario'!B2="Conservative",'📊 Scenario Summary'!B21,IF('🔧 Active Scenario'!B2="Base",'📊 Scenario Summary'!C21,'📊 Scenario Summary'!D21))/1000000,"#,##0.0")&"M" -> 8027,0 paying · valuation R$ 19,9148M
B25: 3 · MANAGEMENT GUARD-RAILS (auto status · active scenario)
B26: Indicator | C26: Current | D26: Threshold | E26: Status
B27: LTV / CAC (Essencial) | C27: ='🔧 Active Scenario'!B56 -> 6.8861031 | D27: ≥ 3.0× | E27: =IF(C27>=3,"✅ within guard-rail","⚠️ below minimum — slow paid and review funnel") -> ✅ within guard-rail
B28: CAC payback | C28: ='🔧 Active Scenario'!B57 -> 1.8152502 | D28: ≤ 6 months | E28: =IF(C28<=6,"✅ within guard-rail","⚠️ long payback — review CAC or pricing") -> ✅ within guard-rail
B29: Gross margin M24 | C29: ='📊 Monthly Base'!Z26 -> 0.84939387 | D29: ≥ 70% | E29: =IF(C29>=0.7,"✅ within guard-rail","⚠️ compressed margin — renegotiate API/pass-through price") -> ✅ within guard-rail
B30: Minimum cash on curve | C30: =MIN('💰 Cash & Runway'!C10:Z10) -> 942427.43 | D30: > R$ 0 | E30: =IF(C30>0,"✅ investment covers entire cash curve","⚠️ negative cash — increase investment or cut costs") -> ✅ investment covers entire cash curve
B32: Note: Triggers and limits are suggested management policy — editable per governance agreed with the investor. AutoNoma © 2025.

Sheet 🔧 Active Scenario
A1: AutoNoma · Scenario Selector · Controller
A2: ▶ ACTIVE SCENARIO ◀ (change here to switch model) | B2: Conservative | C2: ← Select: Conservative / Base / Optimistic
A3: Assumptions column (internal use — do not edit) | B3: =MATCH(B2,{"Conservative","Base","Optimistic"},0)+1 -> 2
A4: Resolved assumptions for the selected scenario
A5: ── PRICING ──
A6: Essencial Price | B6: =INDEX('🎛️ Assumptions'!B5:D5,1,MATCH($B$2,{"Conservative","Base","Optimistic"},0)) -> 39.9 | C6: ← Assumptions!Essencial Price (row 5)
A7: Autônoma Price | B7: =INDEX('🎛️ Assumptions'!B6:D6,1,MATCH($B$2,{"Conservative","Base","Optimistic"},0)) -> 59.9 | C7: ← Assumptions!Autônoma Price (row 6)
A8: Livre Price | B8: =INDEX('🎛️ Assumptions'!B7:D7,1,MATCH($B$2,{"Conservative","Base","Optimistic"},0)) -> 79.9 | C8: ← Assumptions!Livre Price (row 7)
A9: Add-on agent revenue / Essencial subscriber | B9: =INDEX('🎛️ Assumptions'!B8:D8,1,MATCH($B$2,{"Conservative","Base","Optimistic"},0)) -> 10 | C9: ← Assumptions!Add-on agents (row 8)
A10: ── API ──
A11: FX Rate USD/BRL | B11: =INDEX('🎛️ Assumptions'!B10:D10,1,MATCH($B$2,{"Conservative","Base","Optimistic"},0)) -> 5.3 | C11: ← Assumptions!FX Rate USD/BRL (row 10)
A12: Sonnet Input $/MTok | B12: =INDEX('🎛️ Assumptions'!B13:D13,1,MATCH($B$2,{"Conservative","Base","Optimistic"},0)) -> 3 | C12: ← Assumptions!Sonnet 4.6 Input ($/MTok) (row 13)
A13: Sonnet Output $/MTok | B13: =INDEX('🎛️ Assumptions'!B14:D14,1,MATCH($B$2,{"Conservative","Base","Optimistic"},0)) -> 15 | C13: ← Assumptions!Sonnet 4.6 Output ($/MTok) (row 14)
A14: Haiku Input $/MTok | B14: =INDEX('🎛️ Assumptions'!B11:D11,1,MATCH($B$2,{"Conservative","Base","Optimistic"},0)) -> 1 | C14: ← Assumptions!Haiku 4.5 Input ($/MTok) (row 11)
A15: Haiku Output $/MTok | B15: =INDEX('🎛️ Assumptions'!B12:D12,1,MATCH($B$2,{"Conservative","Base","Optimistic"},0)) -> 5 | C15: ← Assumptions!Haiku 4.5 Output ($/MTok) (row 12)
A16: Caching Discount | B16: =INDEX('🎛️ Assumptions'!B15:D15,1,MATCH($B$2,{"Conservative","Base","Optimistic"},0)) -> 0.35 | C16: ← Assumptions!Prompt Caching Discount (%) (row 15)
A17: ── USAGE ──
A18: Free: interactions/month | B18: =INDEX('🎛️ Assumptions'!B17:D17,1,MATCH($B$2,{"Conservative","Base","Optimistic"},0)) -> 50 | C18: ← Assumptions!Free: interactions/month (LIMIT) (row 14)
A19: Free: tokens input | B19: =INDEX('🎛️ Assumptions'!B18:D18,1,MATCH($B$2,{"Conservative","Base","Optimistic"},0)) -> 900 | C19: ← Assumptions!Free: tokens input/interaction (row 15)
A20: Free: tokens output | B20: =INDEX('🎛️ Assumptions'!B19:D19,1,MATCH($B$2,{"Conservative","Base","Optimistic"},0)) -> 450 | C20: ← Assumptions!Free: tokens output/interaction (row 16)
A21: Free: % active/month | B21: =INDEX('🎛️ Assumptions'!B20:D20,1,MATCH($B$2,{"Conservative","Base","Optimistic"},0)) -> 0.5 | C21: ← Assumptions!Free: % active users/month (row 17)
A22: Essencial: interactions/month | B22: =INDEX('🎛️ Assumptions'!B21:D21,1,MATCH($B$2,{"Conservative","Base","Optimistic"},0)) -> 120 | C22: ← Assumptions!Essencial: chat interactions/month (row 18)
A23: Essencial: tokens input | B23: =INDEX('🎛️ Assumptions'!B22:D22,1,MATCH($B$2,{"Conservative","Base","Optimistic"},0)) -> 1200 | C23: ← Assumptions!Essencial: tokens input/interaction (row 19)
A24: Essencial: tokens output | B24: =INDEX('🎛️ Assumptions'!B23:D23,1,MATCH($B$2,{"Conservative","Base","Optimistic"},0)) -> 700 | C24: ← Assumptions!Essencial: tokens output/interaction (row 20)
A25: Autônoma: agent sessions/month | B25: =INDEX('🎛️ Assumptions'!B25:D25,1,MATCH($B$2,{"Conservative","Base","Optimistic"},0)) -> 35 | C25: ← Assumptions!Autônoma: agent sessions/month (row 22)
A26: Autônoma: tokens input/session | B26: =INDEX('🎛️ Assumptions'!B26:D26,1,MATCH($B$2,{"Conservative","Base","Optimistic"},0)) -> 3000 | C26: ← Assumptions!Autônoma: tokens input/agent session (row 23)
A27: Autônoma: tokens output/session | B27: =INDEX('🎛️ Assumptions'!B27:D27,1,MATCH($B$2,{"Conservative","Base","Optimistic"},0)) -> 1800 | C27: ← Assumptions!Autônoma: tokens output/agent session (row 24)
A28: Livre: total sessions/month | B28: =INDEX('🎛️ Assumptions'!B29:D29,1,MATCH($B$2,{"Conservative","Base","Optimistic"},0)) -> 60 | C28: ← Assumptions!Livre: total agent sessions/month (row 26)
A29: ── GROWTH ──
A30: Free leads M1–12 | B30: =INDEX('🎛️ Assumptions'!B31:D31,1,MATCH($B$2,{"Conservative","Base","Optimistic"},0)) -> 3000 | C30: ← Assumptions!Free Growth M1–12 (leads/month) (row 28)
A31: Free leads M13–24 | B31: =INDEX('🎛️ Assumptions'!B32:D32,1,MATCH($B$2,{"Conservative","Base","Optimistic"},0)) -> 3500 | C31: ← Assumptions!Free Growth M13–24 (leads/month) (row 29)
A32: Conv. Free→Essencial | B32: =INDEX('🎛️ Assumptions'!B33:D33,1,MATCH($B$2,{"Conservative","Base","Optimistic"},0)) -> 0.1 | C32: ← Assumptions!Free → Essencial Conversion (%) (row 31)
A33: Conv. Free→Autônoma | B33: =INDEX('🎛️ Assumptions'!B34:D34,1,MATCH($B$2,{"Conservative","Base","Optimistic"},0)) -> 0.07 | C33: ← Assumptions!Free → Autônoma Conversion (%) (row 32)
A34: Conv. Free→Livre | B34: =INDEX('🎛️ Assumptions'!B35:D35,1,MATCH($B$2,{"Conservative","Base","Optimistic"},0)) -> 0.02 | C34: ← Assumptions!Free → Livre Conversion (%) (row 33)
A35: Churn Essencial/month | B35: =INDEX('🎛️ Assumptions'!B36:D36,1,MATCH($B$2,{"Conservative","Base","Optimistic"},0)) -> 0.08 | C35: ← Assumptions!Monthly Churn Essencial (row 34)
A36: Churn Autônoma/month | B36: =INDEX('🎛️ Assumptions'!B37:D37,1,MATCH($B$2,{"Conservative","Base","Optimistic"},0)) -> 0.05 | C36: ← Assumptions!Monthly Churn Autônoma (row 35)
A37: Churn Livre/month | B37: =INDEX('🎛️ Assumptions'!B38:D38,1,MATCH($B$2,{"Conservative","Base","Optimistic"},0)) -> 0.03 | C37: ← Assumptions!Monthly Churn Livre (row 36)
A38: ── FIXED COSTS ──
A39: Team Year 1 | B39: =INDEX('🎛️ Assumptions'!B40:D40,1,MATCH($B$2,{"Conservative","Base","Optimistic"},0)) -> 40000 | C39: ← Assumptions!Team Year 1 (avg/month) (row 38)
A40: Team Year 2 | B40: =INDEX('🎛️ Assumptions'!B41:D41,1,MATCH($B$2,{"Conservative","Base","Optimistic"},0)) -> 50000 | C40: ← Assumptions!Team Year 2 (avg/month) (row 39)
A41: Infra Year 1 | B41: =INDEX('🎛️ Assumptions'!B42:D42,1,MATCH($B$2,{"Conservative","Base","Optimistic"},0)) -> 5000 | C41: ← Assumptions!Infrastructure Year 1 (row 41)
A42: Infra Year 2 | B42: =INDEX('🎛️ Assumptions'!B43:D43,1,MATCH($B$2,{"Conservative","Base","Optimistic"},0)) -> 7000 | C42: ← Assumptions!Infrastructure Year 2 (row 42)
A43: Marketing Year 1 | B43: =INDEX('🎛️ Assumptions'!B44:D44,1,MATCH($B$2,{"Conservative","Base","Optimistic"},0)) -> 5000 | C43: ← Assumptions!Base Marketing Year 1 (row 44)
A44: Marketing Year 2 | B44: =INDEX('🎛️ Assumptions'!B45:D45,1,MATCH($B$2,{"Conservative","Base","Optimistic"},0)) -> 8000 | C44: ← Assumptions!Base Marketing Year 2 (row 45)
A45: Other | B45: =INDEX('🎛️ Assumptions'!B46:D46,1,MATCH($B$2,{"Conservative","Base","Optimistic"},0)) -> 5000 | C45: ← Assumptions!Other (legal, accounting, misc.) (row 47)
A46: ── UNIT ECONOMICS ──
A47: Full-loaded CAC | B47: =INDEX('🎛️ Assumptions'!B48:D48,1,MATCH($B$2,{"Conservative","Base","Optimistic"},0)) -> 80 | C47: ← Assumptions!Full-loaded CAC (R$) (row 49)
A48: % acquisition via paid | B48: =INDEX('🎛️ Assumptions'!B50:D50,1,MATCH($B$2,{"Conservative","Base","Optimistic"},0)) -> 0.5 | C48: ← Assumptions!% acquisition via paid (row 51)
A49: ── VALUATION ──
A50: ARR Multiple M18 | B50: =INDEX('🎛️ Assumptions'!B52:D52,1,MATCH($B$2,{"Conservative","Base","Optimistic"},0)) -> 3 | C50: ← Assumptions!Series A ARR Multiple (× ARR) (row 53)
A51: CALCULATED UNIT ECONOMICS (helpers)
A52: API Cost per Essencial / month | B52: =B22*(B23/1000000*B12+B24/1000000*B13)*(1-B16)*B11 -> 5.82894 | C52: Does ARPU cover API cost?
A53: Unit Margin Essencial / month | B53: =B6+B9-B52 -> 44.07106 | C53: Price + add-on agents − API Cost
A54: Avg. Essencial lifetime (months) | B54: =1/B35 -> 12.5 | C54: 1 ÷ monthly churn
A55: LTV Essencial | B55: =B53*B54 -> 550.88825 | C55: Margin × avg. lifetime
A56: LTV / CAC | B56: =IFERROR(B55/B47,0) -> 6.8861031 | C56: ≥3× ok · ≥8× top quartile
A57: CAC Payback (months) | B57: =IFERROR(B47/B53,0) -> 1.8152502 | C57: CAC ÷ monthly margin · <12m = excellent
A58: TAXES
A59: Tax rate on revenue | B59: =IF($B$2="Conservative",'🎛️ Assumptions'!B70,IF($B$2="Base",'🎛️ Assumptions'!C70,'🎛️ Assumptions'!D70)) -> 0.13 | C59: ← Assumptions!Tax rate (row 67)

Sheet 🎛️ Assumptions
A1: AutoNoma · Assumptions · Single Source of Truth · Haiku Freemium / 100% Sonnet 4.6 Plans & Agents
A2: Blue = Editable input | B2: Black = Formula | C2: Purple = Cross-sheet link
A3: PARAMETER | B3: Conservative | C3: Base (default) | D3: Optimistic | E3: UNIT/NOTE
A4: 1 · PLAN PRICING (R$/month)
A5: Essencial Price | B5: 39.9 | C5: 39.9 | D5: 39.9 | E5: R$/month · + sporadic agent usage
A6: Autônoma Price | B6: 59.9 | C6: 59.9 | D6: 62.9 | E6: R$/month · chat + 1 agent
A7: Livre Price | B7: 79.9 | C7: 79.9 | D7: 79.9 | E7: R$/month · chat + 2 agents
A8: Add-on agent revenue per Essencial subscriber (R$/month) | B8: 10 | C8: 10 | D8: 10
A9: 2 · ANTHROPIC API COST (H1 2026)
A10: FX Rate USD/BRL | B10: 5.3 | C10: 5.3 | D10: 5.3 | E10: R$ per USD
A11: Haiku 4.5 Input ($/MTok) | B11: 1 | C11: 1 | D11: 1 | E11: USD — official Anthropic (Free plan)
A12: Haiku 4.5 Output ($/MTok) | B12: 5 | C12: 5 | D12: 5 | E12: USD — official Anthropic (Free plan)
A13: Sonnet 4.6 Input ($/MTok) | B13: 3 | C13: 3 | D13: 3 | E13: USD — official Anthropic
A14: Sonnet 4.6 Output ($/MTok) | B14: 15 | C14: 15 | D14: 15 | E14: USD — official Anthropic
A15: Prompt Caching Discount (%) | B15: 0.35 | C15: 0.4 | D15: 0.45 | E15: % reduction on fixed block
A16: 3 · USAGE PER PLAN — 100% SONNET 4.6
A17: Free: interactions/month (LIMIT) | B17: 50 | C17: 50 | D17: 50 | E17: Sonnet · product cap
A18: Free: tokens input/interaction | B18: 900 | C18: 900 | D18: 900 | E18: includes cached system prompt
A19: Free: tokens output/interaction | B19: 450 | C19: 450 | D19: 450 | E19: guided response
A20: Free: % active users/month | B20: 0.5 | C20: 0.5 | D20: 0.5 | E20: % of sign-ups active in the month
A21: Essencial: chat interactions/month | B21: 120 | C21: 140 | D21: 180 | E21: practical unlimited · 20 days × use
A22: Essencial: tokens input/interaction | B22: 1200 | C22: 1400 | D22: 1800 | E22: Noma context + memory
A23: Essencial: tokens output/interaction | B23: 700 | C23: 700 | D23: 700 | E23: response + autonomous action
A24: Autônoma: chat (= Essencial) | B24: 140 | C24: 140 | D24: 140 | E24: unlimited Sonnet chat
A25: Autônoma: agent sessions/month | B25: 35 | C25: 45 | D25: 60 | E25: deep sessions with 1 agent
A26: Autônoma: tokens input/agent session | B26: 3000 | C26: 3000 | D26: 3000 | E26: resolution context + memory
A27: Autônoma: tokens output/agent session | B27: 1800 | C27: 1800 | D27: 1800 | E27: full resolution + confirmation
A28: Livre: chat (= Essencial) | B28: 140 | C28: 140 | D28: 140 | E28: unlimited Sonnet chat
A29: Livre: total agent sessions/month | B29: 60 | C29: 80 | D29: 100 | E29: 2 agents · more than Autônoma
A30: 4 · USER BASE GROWTH
A31: Free Growth M1–12 (leads/month) | B31: 3000 | C31: 3500 | D31: 4000 | E31: organic+viral+paid sign-ups
A32: Free Growth M13–24 (leads/month) | B32: 3500 | C32: 4000 | D32: 4500 | E32: Brazil scale
A33: Conversion Free → Essencial (%) | B33: 0.1 | C33: 0.15 | D33: 0.2 | E33: % Free base becoming subscribers
A34: Conversion Free → Autônoma (%) | B34: 0.07 | C34: 0.07 | D34: 0.07 | E34: % Essencial that upgrade
A35: Conversion Free → Livre (%) | B35: 0.02 | C35: 0.03 | D35: 0.03 | E35: % Autônoma that upgrade
A36: Monthly Churn Essencial | B36: 0.08 | C36: 0.07 | D36: 0.05 | E36: % cancel per month
A37: Monthly Churn Autônoma | B37: 0.05 | C37: 0.05 | D37: 0.06 | E37: % cancel per month · agent = lock-in
A38: Monthly Churn Livre | B38: 0.03 | C38: 0.03 | D38: 0.02 | E38: % cancel · 2 agents = max lock-in
A39: 5 · MONTHLY FIXED COSTS (R$)
A40: Team Year 1 (avg/month) | B40: 40000 | C40: 45000 | D40: 50000 | E40: devs+CS+founder comp
A41: Team Year 2 (avg/month) | B41: 50000 | C41: 60000 | D41: 70000 | E41: team expansion
A42: Infrastructure Year 1 | B42: 5000 | C42: 6000 | D42: 8000 | E42: servers, DB, CDN
A43: Infrastructure Year 2 | B43: 7000 | C43: 8000 | D43: 10000 | E43: scales with base
A44: Base Marketing Year 1 | B44: 5000 | C44: 6000 | D44: 8000 | E44: beyond pre-seed paid
A45: Base Marketing Year 2 | B45: 8000 | C45: 10000 | D45: 15000 | E45: growth + paid
A46: Other (legal, accounting, misc.) | B46: 5000 | C46: 6000 | D46: 8000 | E46: fixed admin
A47: 6 · UNIT ECONOMICS (full-loaded CAC)
A48: Full-loaded CAC (R$) | B48: 80 | C48: 60 | D48: 60 | E48: includes mkt+CS+onboarding
A49: Paid-only CAC (R$) | B49: 27 | C49: 25 | D49: 20 | E49: reference only
A50: % acquisition via paid | B50: 0.5 | C50: 0.45 | D50: 0.4 | E50: % new paying via ads
A51: 7 · VALUATION M24 (on 24m Cumulative Revenue)
A52: Multiple × 24m Cumulative Revenue | B52: 3 | C52: 5 | D52: 7 | E52: × on 'Monthly Base'!Z12 (R$ 12.8M)
A53: 📐 Model note: Conversion applies to the monthly eligible pool (Free − already paying). Rate ≠ '% of monthly leads' but '% of cumulative eligible base that converts per month'. Calibrated to reproduce ~4,400 paying at M12 (Base scenario).
A57: 8 · ANGEL RAISE (R$1M = 15% equity)
A58: Max investment (R$) | B58: 1000000 | C58: ← editable (simulate here)
A59: % Equity offered | B59: 0.15 | C59: = 15% fixed (R$1M = 15%)
A60: Implied pre-money valuation | B60: =B58/B59-B58 -> 5666666.7 | C60: = Investment/%Equity − Investment
A61: Implied post-money valuation | B61: =B58/B59 -> 6666666.7 | C61: = Investment / %Equity
A63: 9 · MODEL PARAMETERS
A64: Free sign-ups at M1 (seed) | B64: 2000 | C64: ← M1 waitlist
A65: Floor YoY · Conservative | B65: 0.3 | C65: ← valuation adjustment floor
A66: Floor YoY · Base | B66: 0.4 | C66: ← valuation adjustment floor
A67: Floor YoY · Optimistic | B67: 0.6 | C67: ← valuation adjustment floor
A68: YoY divisor (smoothing) | B68: 18 | C68: ← higher = smoother adjustment
A69: Monthly discount rate (NPV/IRR) | B69: 0.018 | C69: =(1+B69)^12-1 -> 0.23872053 | D69: ← annualized
A70: Tax rate on revenue | B70: 0.13 | C70: 0.13 | D70: 0.15 | E70: ← Presumed

Sheet 📊 Monthly Base
A1: AutoNoma · Monthly Base · 24 Months · Dynamic Formulas · Scenario Controlled by 🔧 Active Scenario
A2: Active scenario: | C2: ='🔧 Active Scenario'!B2 -> Conservative
A3: Indicator | B3: Unit | C3: M01 | D3: M02 | E3: M03 | F3: M04 | G3: M05 | H3: M06 | I3: M07 | J3: M08 | K3: M09 | L3: M10 | M3: M11 | N3: M12 ★ | O3: M13 | P3: M14 | Q3: M15 | R3: M16 | S3: M17 | T3: M18 | U3: M19 | V3: M20 | W3: M21 | X3: M22 | Y3: M23 | Z3: M24 ★
A4: USERS
A5: Free · 30-day Trial (active in month) | B5: usr | C5: ='🎛️ Assumptions'!B64 -> 2000 | D5: ='🔧 Active Scenario'!$B$30 -> 3000 | E5: ='🔧 Active Scenario'!$B$30 -> 3000 | F5: ='🔧 Active Scenario'!$B$30 -> 3000 | G5: ='🔧 Active Scenario'!$B$30 -> 3000 | H5: ='🔧 Active Scenario'!$B$30 -> 3000 | I5: ='🔧 Active Scenario'!$B$30 -> 3000 | J5: ='🔧 Active Scenario'!$B$30 -> 3000 | K5: ='🔧 Active Scenario'!$B$30 -> 3000 | ... N5: ='🔧 Active Scenario'!$B$30 -> 3000 | O5: ='🔧 Active Scenario'!$B$31 -> 3500 | P5: ='🔧 Active Scenario'!$B$31 -> 3500 | Q5: ='🔧 Active Scenario'!$B$31 -> 3500 | R5: ='🔧 Active Scenario'!$B$31 -> 3500 | S5: ='🔧 Active Scenario'!$B$31 -> 3500 | T5: ='🔧 Active Scenario'!$B$31 -> 3500 | U5: ='🔧 Active Scenario'!$B$31 -> 3500 | V5: ='🔧 Active Scenario'!$B$31 -> 3500 | ... Z5: ='🔧 Active Scenario'!$B$31 -> 3500
A6: Essencial · Subscribers | B6: sub. | C6: =ROUND(C5*'🔧 Active Scenario'!$B$32,0) -> 200 | D6: =ROUND(C6*(1-'🔧 Active Scenario'!$B$35)+D5*'🔧 Active Scenario'!$B$32,0) -> 484 | E6: =ROUND(D6*(1-'🔧 Active Scenario'!$B$35)+E5*'🔧 Active Scenario'!$B$32,0) -> 745 | F6: =ROUND(E6*(1-'🔧 Active Scenario'!$B$35)+F5*'🔧 Active Scenario'!$B$32,0) -> 985 | G6: =ROUND(F6*(1-'🔧 Active Scenario'!$B$35)+G5*'🔧 Active Scenario'!$B$32,0) -> 1206 | H6: =ROUND(G6*(1-'🔧 Active Scenario'!$B$35)+H5*'🔧 Active Scenario'!$B$32,0) -> 1410 | I6: =ROUND(H6*(1-'🔧 Active Scenario'!$B$35)+I5*'🔧 Active Scenario'!$B$32,0) -> 1597 | J6: =ROUND(I6*(1-'🔧 Active Scenario'!$B$35)+J5*'🔧 Active Scenario'!$B$32,0) -> 1769 | K6: =ROUND(J6*(1-'🔧 Active Scenario'!$B$35)+K5*'🔧 Active Scenario'!$B$32,0) -> 1927 | ... Z6: =ROUND(Y6*(1-'🔧 Active Scenario'!$B$35)+Z5*'🔧 Active Scenario'!$B$32,0) -> 3622
A7: Autônoma · Subscribers | B7: sub. | C7: =ROUND(C5*'🔧 Active Scenario'!$B$33,0) -> 140 | D7: =ROUND(C7*(1-'🔧 Active Scenario'!$B$36)+D5*'🔧 Active Scenario'!$B$33,0) -> 343 | E7: =ROUND(D7*(1-'🔧 Active Scenario'!$B$36)+E5*'🔧 Active Scenario'!$B$33,0) -> 536 | F7: =ROUND(E7*(1-'🔧 Active Scenario'!$B$36)+F5*'🔧 Active Scenario'!$B$33,0) -> 719 | G7: =ROUND(F7*(1-'🔧 Active Scenario'!$B$36)+G5*'🔧 Active Scenario'!$B$33,0) -> 893 | H7: =ROUND(G7*(1-'🔧 Active Scenario'!$B$36)+H5*'🔧 Active Scenario'!$B$33,0) -> 1058 | I7: =ROUND(H7*(1-'🔧 Active Scenario'!$B$36)+I5*'🔧 Active Scenario'!$B$33,0) -> 1215 | J7: =ROUND(I7*(1-'🔧 Active Scenario'!$B$36)+J5*'🔧 Active Scenario'!$B$33,0) -> 1364 | K7: =ROUND(J7*(1-'🔧 Active Scenario'!$B$36)+K5*'🔧 Active Scenario'!$B$33,0) -> 1506 | ... Z7: =ROUND(Y7*(1-'🔧 Active Scenario'!$B$36)+Z5*'🔧 Active Scenario'!$B$33,0) -> 3275
A8: Livre · Subscribers | B8: sub. | C8: =ROUND(C5*'🔧 Active Scenario'!$B$34,0) -> 40 | D8: =ROUND(C8*(1-'🔧 Active Scenario'!$B$37)+D5*'🔧 Active Scenario'!$B$34,0) -> 99 | E8: =ROUND(D8*(1-'🔧 Active Scenario'!$B$37)+E5*'🔧 Active Scenario'!$B$34,0) -> 156 | F8: =ROUND(E8*(1-'🔧 Active Scenario'!$B$37)+F5*'🔧 Active Scenario'!$B$34,0) -> 211 | G8: =ROUND(F8*(1-'🔧 Active Scenario'!$B$37)+G5*'🔧 Active Scenario'!$B$34,0) -> 265 | H8: =ROUND(G8*(1-'🔧 Active Scenario'!$B$37)+H5*'🔧 Active Scenario'!$B$34,0) -> 317 | I8: =ROUND(H8*(1-'🔧 Active Scenario'!$B$37)+I5*'🔧 Active Scenario'!$B$34,0) -> 367 | J8: =ROUND(I8*(1-'🔧 Active Scenario'!$B$37)+J5*'🔧 Active Scenario'!$B$34,0) -> 416 | K8: =ROUND(J8*(1-'🔧 Active Scenario'!$B$37)+K5*'🔧 Active Scenario'!$B$34,0) -> 464 | ... Z8: =ROUND(Y8*(1-'🔧 Active Scenario'!$B$37)+Z5*'🔧 Active Scenario'!$B$34,0) -> 1130
A9: TOTAL PAYING | B9: sub. | C9: =SUM(C6:C8) -> 380 | D9: =SUM(D6:D8) -> 926 | E9: =SUM(E6:E8) -> 1437 | F9: =SUM(F6:F8) -> 1915 | G9: =SUM(G6:G8) -> 2364 | H9: =SUM(H6:H8) -> 2785 | I9: =SUM(I6:I8) -> 3179 | J9: =SUM(J6:J8) -> 3549 | ... Z9: =SUM(Z6:Z8) -> 8027
A10: REVENUE
A11: MONTHLY MRR | B11: R$ | C11: =C6*('🔧 Active Scenario'!$B$6+'🔧 Active Scenario'!$B$9)+C7*'🔧 Active Scenario'!$B$7+C8*'🔧 Active Scenario'!$B$8 -> 21562 | D11: =D6*('🔧 Active Scenario'!$B$6+'🔧 Active Scenario'!$B$9)+D7*'🔧 Active Scenario'!$B$7+D8*'🔧 Active Scenario'!$B$8 -> 52607.4 | E11: =E6*('🔧 Active Scenario'!$B$6+'🔧 Active Scenario'!$B$9)+E7*'🔧 Active Scenario'!$B$7+E8*'🔧 Active Scenario'!$B$8 -> 81746.3 | F11: =F6*('🔧 Active Scenario'!$B$6+'🔧 Active Scenario'!$B$9)+F7*'🔧 Active Scenario'!$B$7+F8*'🔧 Active Scenario'!$B$8 -> 109078.5 | G11: =G6*('🔧 Active Scenario'!$B$6+'🔧 Active Scenario'!$B$9)+G7*'🔧 Active Scenario'!$B$7+G8*'🔧 Active Scenario'!$B$8 -> 134843.6 | H11: =H6*('🔧 Active Scenario'!$B$6+'🔧 Active Scenario'!$B$9)+H7*'🔧 Active Scenario'!$B$7+H8*'🔧 Active Scenario'!$B$8 -> 159061.5 | I11: =I6*('🔧 Active Scenario'!$B$6+'🔧 Active Scenario'!$B$9)+I7*'🔧 Active Scenario'!$B$7+I8*'🔧 Active Scenario'!$B$8 -> 181792.1 | J11: =J6*('🔧 Active Scenario'!$B$6+'🔧 Active Scenario'!$B$9)+J7*'🔧 Active Scenario'!$B$7+J8*'🔧 Active Scenario'!$B$8 -> 203215.1 | ... Z11: =Z6*('🔧 Active Scenario'!$B$6+'🔧 Active Scenario'!$B$9)+Z7*'🔧 Active Scenario'!$B$7+Z8*'🔧 Active Scenario'!$B$8 -> 467197.3
A12: CUMULATIVE MRR | B12: R$ | C12: =C11 -> 21562 | D12: =C12+D11 -> 74169.4 | E12: =D12+E11 -> 155915.7 | F12: =E12+F11 -> 264994.2 | G12: =F12+G11 -> 399837.8 | H12: =G12+H11 -> 558899.3 | I12: =H12+I11 -> 740691.4 | J12: =I12+J11 -> 943906.5 | K12: =J12+K11 -> 1167346.8 | ... Z12: =Y12+Z11 -> 6638262.2
A13: API COST · 100% Sonnet 4.6 · Caching active
A14: API Free (Haiku · 40 int/month) | B14: R$ | C14: =C5*'🔧 Active Scenario'!$B$21*('🔧 Active Scenario'!$B$18*('🔧 Active Scenario'!$B$19/1000000*'🔧 Active Scenario'!$B$14+'🔧 Active Scenario'!$B$20/1000000*'🔧 Active Scenario'!$B$15)*(1-'🔧 Active Scenario'!$B$16)*'🔧 Active Scenario'!$B$11) -> 542.5875 | D14: =D5*'🔧 Active Scenario'!$B$21*('🔧 Active Scenario'!$B$18*('🔧 Active Scenario'!$B$19/1000000*'🔧 Active Scenario'!$B$14+'🔧 Active Scenario'!$B$20/1000000*'🔧 Active Scenario'!$B$15)*(1-'🔧 Active Scenario'!$B$16)*'🔧 Active Scenario'!$B$11) -> 813.88125 | E14: =E5*'🔧 Active Scenario'!$B$21*('🔧 Active Scenario'!$B$18*('🔧 Active Scenario'!$B$19/1000000*'🔧 Active Scenario'!$B$14+'🔧 Active Scenario'!$B$20/1000000*'🔧 Active Scenario'!$B$15)*(1-'🔧 Active Scenario'!$B$16)*'🔧 Active Scenario'!$B$11) -> 813.88125 | F14: =F5*'🔧 Active Scenario'!$B$21*('🔧 Active Scenario'!$B$18*('🔧 Active Scenario'!$B$19/1000000*'🔧 Active Scenario'!$B$14+'🔧 Active Scenario'!$B$20/1000000*'🔧 Active Scenario'!$B$15)*(1-'🔧 Active Scenario'!$B$16)*'🔧 Active Scenario'!$B$11) -> 813.88125 | G14: =G5*'🔧 Active Scenario'!$B$21*('🔧 Active Scenario'!$B$18*('🔧 Active Scenario'!$B$19/1000000*'🔧 Active Scenario'!$B$14+'🔧 Active Scenario'!$B$20/1000000*'🔧 Active Scenario'!$B$15)*(1-'🔧 Active Scenario'!$B$16)*'🔧 Active Scenario'!$B$11) -> 813.88125 | H14: =H5*'🔧 Active Scenario'!$B$21*('🔧 Active Scenario'!$B$18*('🔧 Active Scenario'!$B$19/1000000*'🔧 Active Scenario'!$B$14+'🔧 Active Scenario'!$B$20/1000000*'🔧 Active Scenario'!$B$15)*(1-'🔧 Active Scenario'!$B$16)*'🔧 Active Scenario'!$B$11) -> 813.88125 | I14: =I5*'🔧 Active Scenario'!$B$21*('🔧 Active Scenario'!$B$18*('🔧 Active Scenario'!$B$19/1000000*'🔧 Active Scenario'!$B$14+'🔧 Active Scenario'!$B$20/1000000*'🔧 Active Scenario'!$B$15)*(1-'🔧 Active Scenario'!$B$16)*'🔧 Active Scenario'!$B$11) -> 813.88125 | J14: =J5*'🔧 Active Scenario'!$B$21*('🔧 Active Scenario'!$B$18*('🔧 Active Scenario'!$B$19/1000000*'🔧 Active Scenario'!$B$14+'🔧 Active Scenario'!$B$20/1000000*'🔧 Active Scenario'!$B$15)*(1-'🔧 Active Scenario'!$B$16)*'🔧 Active Scenario'!$B$11) -> 813.88125 | ... Z14: =Z5*'🔧 Active Scenario'!$B$21*('🔧 Active Scenario'!$B$18*('🔧 Active Scenario'!$B$19/1000000*'🔧 Active Scenario'!$B$14+'🔧 Active Scenario'!$B$20/1000000*'🔧 Active Scenario'!$B$15)*(1-'🔧 Active Scenario'!$B$16)*'🔧 Active Scenario'!$B$11) -> 949.52813
A15: API Essencial (unlimited chat) | B15: R$ | C15: =C6*'🔧 Active Scenario'!B22*('🔧 Active Scenario'!B23/1000000*'🔧 Active Scenario'!B12+'🔧 Active Scenario'!B24/1000000*'🔧 Active Scenario'!B13)*(1-'🔧 Active Scenario'!B16)*'🔧 Active Scenario'!B11 -> 1165.788 | D15: =D6*'🔧 Active Scenario'!B22*('🔧 Active Scenario'!B23/1000000*'🔧 Active Scenario'!B12+'🔧 Active Scenario'!B24/1000000*'🔧 Active Scenario'!B13)*(1-'🔧 Active Scenario'!B16)*'🔧 Active Scenario'!B11 -> 2821.207 | E15: =E6*'🔧 Active Scenario'!B22*('🔧 Active Scenario'!B23/1000000*'🔧 Active Scenario'!B12+'🔧 Active Scenario'!B24/1000000*'🔧 Active Scenario'!B13)*(1-'🔧 Active Scenario'!B16)*'🔧 Active Scenario'!B11 -> 4342.5603 | F15: =F6*'🔧 Active Scenario'!B22*('🔧 Active Scenario'!B23/1000000*'🔧 Active Scenario'!B12+'🔧 Active Scenario'!B24/1000000*'🔧 Active Scenario'!B13)*(1-'🔧 Active Scenario'!B16)*'🔧 Active Scenario'!B11 -> 5741.5059 | G15: =G6*'🔧 Active Scenario'!B22*('🔧 Active Scenario'!B23/1000000*'🔧 Active Scenario'!B12+'🔧 Active Scenario'!B24/1000000*'🔧 Active Scenario'!B13)*(1-'🔧 Active Scenario'!B16)*'🔧 Active Scenario'!B11 -> 7029.7016 | H15: =H6*'🔧 Active Scenario'!B22*('🔧 Active Scenario'!B23/1000000*'🔧 Active Scenario'!B12+'🔧 Active Scenario'!B24/1000000*'🔧 Active Scenario'!B13)*(1-'🔧 Active Scenario'!B16)*'🔧 Active Scenario'!B11 -> 8218.8054 | I15: =I6*'🔧 Active Scenario'!B22*('🔧 Active Scenario'!B23/1000000*'🔧 Active Scenario'!B12+'🔧 Active Scenario'!B24/1000000*'🔧 Active Scenario'!B13)*(1-'🔧 Active Scenario'!B16)*'🔧 Active Scenario'!B11 -> 9308.8172 | J15: =J6*'🔧 Active Scenario'!B22*('🔧 Active Scenario'!B23/1000000*'🔧 Active Scenario'!B12+'🔧 Active Scenario'!B24/1000000*'🔧 Active Scenario'!B13)*(1-'🔧 Active Scenario'!B16)*'🔧 Active Scenario'!B11 -> 10311.395 | K15: =K6*'🔧 Active Scenario'!B22*('🔧 Active Scenario'!B23/1000000*'🔧 Active Scenario'!B12+'🔧 Active Scenario'!B24/1000000*'🔧 Active Scenario'!B13)*(1-'🔧 Active Scenario'!B16)*'🔧 Active Scenario'!B11 -> 11232.367 | L15: =L6*'🔧 Active Scenario'!B22*('🔧 Active Scenario'!B23/1000000*'🔧 Active Scenario'!B12+'🔧 Active Scenario'!B24/1000000*'🔧 Active Scenario'!B13)*(1-'🔧 Active Scenario'!B16)*'🔧 Active Scenario'!B11 -> 12083.393 | M15: =M6*'🔧 Active Scenario'!B22*('🔧 Active Scenario'!B23/1000000*'🔧 Active Scenario'!B12+'🔧 Active Scenario'!B24/1000000*'🔧 Active Scenario'!B13)*(1-'🔧 Active Scenario'!B16)*'🔧 Active Scenario'!B11 -> 12864.471 | N15: =N6*'🔧 Active Scenario'!B22*('🔧 Active Scenario'!B23/1000000*'🔧 Active Scenario'!B12+'🔧 Active Scenario'!B24/1000000*'🔧 Active Scenario'!B13)*(1-'🔧 Active Scenario'!B16)*'🔧 Active Scenario'!B11 -> 13581.43 | O15: =O6*'🔧 Active Scenario'!B22*('🔧 Active Scenario'!B23/1000000*'🔧 Active Scenario'!B12+'🔧 Active Scenario'!B24/1000000*'🔧 Active Scenario'!B13)*(1-'🔧 Active Scenario'!B16)*'🔧 Active Scenario'!B11 -> 14537.376 | P15: =P6*'🔧 Active Scenario'!B22*('🔧 Active Scenario'!B23/1000000*'🔧 Active Scenario'!B12+'🔧 Active Scenario'!B24/1000000*'🔧 Active Scenario'!B13)*(1-'🔧 Active Scenario'!B16)*'🔧 Active Scenario'!B11 -> 15411.717 | Q15: =Q6*'🔧 Active Scenario'!B22*('🔧 Active Scenario'!B23/1000000*'🔧 Active Scenario'!B12+'🔧 Active Scenario'!B24/1000000*'🔧 Active Scenario'!B13)*(1-'🔧 Active Scenario'!B16)*'🔧 Active Scenario'!B11 -> 16216.111 | R15: =R6*'🔧 Active Scenario'!B22*('🔧 Active Scenario'!B23/1000000*'🔧 Active Scenario'!B12+'🔧 Active Scenario'!B24/1000000*'🔧 Active Scenario'!B13)*(1-'🔧 Active Scenario'!B16)*'🔧 Active Scenario'!B11 -> 16956.386 | S15: =S6*'🔧 Active Scenario'!B22*('🔧 Active Scenario'!B23/1000000*'🔧 Active Scenario'!B12+'🔧 Active Scenario'!B24/1000000*'🔧 Active Scenario'!B13)*(1-'🔧 Active Scenario'!B16)*'🔧 Active Scenario'!B11 -> 17638.372 | T15: =T6*'🔧 Active Scenario'!B22*('🔧 Active Scenario'!B23/1000000*'🔧 Active Scenario'!B12+'🔧 Active Scenario'!B24/1000000*'🔧 Active Scenario'!B13)*(1-'🔧 Active Scenario'!B16)*'🔧 Active Scenario'!B11 -> 18267.898 | U15: =U6*'🔧 Active Scenario'!B22*('🔧 Active Scenario'!B23/1000000*'🔧 Active Scenario'!B12+'🔧 Active Scenario'!B24/1000000*'🔧 Active Scenario'!B13)*(1-'🔧 Active Scenario'!B16)*'🔧 Active Scenario'!B11 -> 18844.963 | V15: =V6*'🔧 Active Scenario'!B22*('🔧 Active Scenario'!B23/1000000*'🔧 Active Scenario'!B12+'🔧 Active Scenario'!B24/1000000*'🔧 Active Scenario'!B13)*(1-'🔧 Active Scenario'!B16)*'🔧 Active Scenario'!B11 -> 19375.397 | W15: =W6*'🔧 Active Scenario'!B22*('🔧 Active Scenario'!B23/1000000*'🔧 Active Scenario'!B12+'🔧 Active Scenario'!B24/1000000*'🔧 Active Scenario'!B13)*(1-'🔧 Active Scenario'!B16)*'🔧 Active Scenario'!B11 -> 19865.028 | X15: =X6*'🔧 Active Scenario'!B22*('🔧 Active Scenario'!B23/1000000*'🔧 Active Scenario'!B12+'🔧 Active Scenario'!B24/1000000*'🔧 Active Scenario'!B13)*(1-'🔧 Active Scenario'!B16)*'🔧 Active Scenario'!B11 -> 20313.856 | Y15: =Y6*'🔧 Active Scenario'!B22*('🔧 Active Scenario'!B23/1000000*'🔧 Active Scenario'!B12+'🔧 Active Scenario'!B24/1000000*'🔧 Active Scenario'!B13)*(1-'🔧 Active Scenario'!B16)*'🔧 Active Scenario'!B11 -> 20727.711 | Z15: =Z6*'🔧 Active Scenario'!B22*('🔧 Active Scenario'!B23/1000000*'🔧 Active Scenario'!B12+'🔧 Active Scenario'!B24/1000000*'🔧 Active Scenario'!B13)*(1-'🔧 Active Scenario'!B16)*'🔧 Active Scenario'!B11 -> 21112.421
A16: API Autônoma (+1 agent) | B16: R$ | C16: =C7*('🔧 Active Scenario'!B22*('🔧 Active Scenario'!B23/1000000*'🔧 Active Scenario'!B12+'🔧 Active Scenario'!B24/1000000*'🔧 Active Scenario'!B13)*(1-'🔧 Active Scenario'!B16)*'🔧 Active Scenario'!B11+'🔧 Active Scenario'!B25*('🔧 Active Scenario'!B26/1000000*'🔧 Active Scenario'!B12+'🔧 Active Scenario'!B27/1000000*'🔧 Active Scenario'!B13)*(1-'🔧 Active Scenario'!B16)*'🔧 Active Scenario'!B11) -> 1423.7496 | D16: =D7*('🔧 Active Scenario'!B22*('🔧 Active Scenario'!B23/1000000*'🔧 Active Scenario'!B12+'🔧 Active Scenario'!B24/1000000*'🔧 Active Scenario'!B13)*(1-'🔧 Active Scenario'!B16)*'🔧 Active Scenario'!B11+'🔧 Active Scenario'!B25*('🔧 Active Scenario'!B26/1000000*'🔧 Active Scenario'!B12+'🔧 Active Scenario'!B27/1000000*'🔧 Active Scenario'!B13)*(1-'🔧 Active Scenario'!B16)*'🔧 Active Scenario'!B11) -> 3488.1865 | E16: =E7*('🔧 Active Scenario'!B22*('🔧 Active Scenario'!B23/1000000*'🔧 Active Scenario'!B12+'🔧 Active Scenario'!B24/1000000*'🔧 Active Scenario'!B13)*(1-'🔧 Active Scenario'!B16)*'🔧 Active Scenario'!B11+'🔧 Active Scenario'!B25*('🔧 Active Scenario'!B26/1000000*'🔧 Active Scenario'!B12+'🔧 Active Scenario'!B27/1000000*'🔧 Active Scenario'!B13)*(1-'🔧 Active Scenario'!B16)*'🔧 Active Scenario'!B11) -> 5450.927 | F16: =F7*('🔧 Active Scenario'!B22*('🔧 Active Scenario'!B23/1000000*'🔧 Active Scenario'!B12+'🔧 Active Scenario'!B24/1000000*'🔧 Active Scenario'!B13)*(1-'🔧 Active Scenario'!B16)*'🔧 Active Scenario'!B11+'🔧 Active Scenario'!B25*('🔧 Active Scenario'!B26/1000000*'🔧 Active Scenario'!B12+'🔧 Active Scenario'!B27/1000000*'🔧 Active Scenario'!B13)*(1-'🔧 Active Scenario'!B16)*'🔧 Active Scenario'!B11) -> 7311.9712 | G16: =G7*('🔧 Active Scenario'!B22*('🔧 Active Scenario'!B23/1000000*'🔧 Active Scenario'!B12+'🔧 Active Scenario'!B24/1000000*'🔧 Active Scenario'!B13)*(1-'🔧 Active Scenario'!B16)*'🔧 Active Scenario'!B11+'🔧 Active Scenario'!B25*('🔧 Active Scenario'!B26/1000000*'🔧 Active Scenario'!B12+'🔧 Active Scenario'!B27/1000000*'🔧 Active Scenario'!B13)*(1-'🔧 Active Scenario'!B16)*'🔧 Active Scenario'!B11) -> 9081.4885 | H16: =H7*('🔧 Active Scenario'!B22*('🔧 Active Scenario'!B23/1000000*'🔧 Active Scenario'!B12+'🔧 Active Scenario'!B24/1000000*'🔧 Active Scenario'!B13)*(1-'🔧 Active Scenario'!B16)*'🔧 Active Scenario'!B11+'🔧 Active Scenario'!B25*('🔧 Active Scenario'!B26/1000000*'🔧 Active Scenario'!B12+'🔧 Active Scenario'!B27/1000000*'🔧 Active Scenario'!B13)*(1-'🔧 Active Scenario'!B16)*'🔧 Active Scenario'!B11) -> 10759.479 | I16: =I7*('🔧 Active Scenario'!B22*('🔧 Active Scenario'!B23/1000000*'🔧 Active Scenario'!B12+'🔧 Active Scenario'!B24/1000000*'🔧 Active Scenario'!B13)*(1-'🔧 Active Scenario'!B16)*'🔧 Active Scenario'!B11+'🔧 Active Scenario'!B25*('🔧 Active Scenario'!B26/1000000*'🔧 Active Scenario'!B12+'🔧 Active Scenario'!B27/1000000*'🔧 Active Scenario'!B13)*(1-'🔧 Active Scenario'!B16)*'🔧 Active Scenario'!B11) -> 12356.113 | J16: =J7*('🔧 Active Scenario'!B22*('🔧 Active Scenario'!B23/1000000*'🔧 Active Scenario'!B12+'🔧 Active Scenario'!B24/1000000*'🔧 Active Scenario'!B13)*(1-'🔧 Active Scenario'!B16)*'🔧 Active Scenario'!B11+'🔧 Active Scenario'!B25*('🔧 Active Scenario'!B26/1000000*'🔧 Active Scenario'!B12+'🔧 Active Scenario'!B27/1000000*'🔧 Active Scenario'!B13)*(1-'🔧 Active Scenario'!B16)*'🔧 Active Scenario'!B11) -> 13871.389 | K16: =K7*('🔧 Active Scenario'!B22*('🔧 Active Scenario'!B23/1000000*'🔧 Active Scenario'!B12+'🔧 Active Scenario'!B24/1000000*'🔧 Active Scenario'!B13)*(1-'🔧 Active Scenario'!B16)*'🔧 Active Scenario'!B11+'🔧 Active Scenario'!B25*('🔧 Active Scenario'!B26/1000000*'🔧 Active Scenario'!B12+'🔧 Active Scenario'!B27/1000000*'🔧 Active Scenario'!B13)*(1-'🔧 Active Scenario'!B16)*'🔧 Active Scenario'!B11) -> 15315.478 | L16: =L7*('🔧 Active Scenario'!B22*('🔧 Active Scenario'!B23/1000000*'🔧 Active Scenario'!B12+'🔧 Active Scenario'!B24/1000000*'🔧 Active Scenario'!B13)*(1-'🔧 Active Scenario'!B16)*'🔧 Active Scenario'!B11+'🔧 Active Scenario'!B25*('🔧 Active Scenario'!B26/1000000*'🔧 Active Scenario'!B12+'🔧 Active Scenario'!B27/1000000*'🔧 Active Scenario'!B13)*(1-'🔧 Active Scenario'!B16)*'🔧 Active Scenario'!B11) -> 16688.379 | M16: =M7*('🔧 Active Scenario'!B22*('🔧 Active Scenario'!B23/1000000*'🔧 Active Scenario'!B12+'🔧 Active Scenario'!B24/1000000*'🔧 Active Scenario'!B13)*(1-'🔧 Active Scenario'!B16)*'🔧 Active Scenario'!B11+'🔧 Active Scenario'!B25*('🔧 Active Scenario'!B26/1000000*'🔧 Active Scenario'!B12+'🔧 Active Scenario'!B27/1000000*'🔧 Active Scenario'!B13)*(1-'🔧 Active Scenario'!B16)*'🔧 Active Scenario'!B11) -> 17990.093 | N16: =N7*('🔧 Active Scenario'!B22*('🔧 Active Scenario'!B23/1000000*'🔧 Active Scenario'!B12+'🔧 Active Scenario'!B24/1000000*'🔧 Active Scenario'!B13)*(1-'🔧 Active Scenario'!B16)*'🔧 Active Scenario'!B11+'🔧 Active Scenario'!B25*('🔧 Active Scenario'!B26/1000000*'🔧 Active Scenario'!B12+'🔧 Active Scenario'!B27/1000000*'🔧 Active Scenario'!B13)*(1-'🔧 Active Scenario'!B16)*'🔧 Active Scenario'!B11) -> 19230.789 | O16: =O7*('🔧 Active Scenario'!B22*('🔧 Active Scenario'!B23/1000000*'🔧 Active Scenario'!B12+'🔧 Active Scenario'!B24/1000000*'🔧 Active Scenario'!B13)*(1-'🔧 Active Scenario'!B16)*'🔧 Active Scenario'!B11+'🔧 Active Scenario'!B25*('🔧 Active Scenario'!B26/1000000*'🔧 Active Scenario'!B12+'🔧 Active Scenario'!B27/1000000*'🔧 Active Scenario'!B13)*(1-'🔧 Active Scenario'!B16)*'🔧 Active Scenario'!B11) -> 20756.235 | P16: =P7*('🔧 Active Scenario'!B22*('🔧 Active Scenario'!B23/1000000*'🔧 Active Scenario'!B12+'🔧 Active Scenario'!B24/1000000*'🔧 Active Scenario'!B13)*(1-'🔧 Active Scenario'!B16)*'🔧 Active Scenario'!B11+'🔧 Active Scenario'!B25*('🔧 Active Scenario'!B26/1000000*'🔧 Active Scenario'!B12+'🔧 Active Scenario'!B27/1000000*'🔧 Active Scenario'!B13)*(1-'🔧 Active Scenario'!B16)*'🔧 Active Scenario'!B11) -> 22210.494 | Q16: =Q7*('🔧 Active Scenario'!B22*('🔧 Active Scenario'!B23/1000000*'🔧 Active Scenario'!B12+'🔧 Active Scenario'!B24/1000000*'🔧 Active Scenario'!B13)*(1-'🔧 Active Scenario'!B16)*'🔧 Active Scenario'!B11+'🔧 Active Scenario'!B25*('🔧 Active Scenario'!B26/1000000*'🔧 Active Scenario'!B12+'🔧 Active Scenario'!B27/1000000*'🔧 Active Scenario'!B13)*(1-'🔧 Active Scenario'!B16)*'🔧 Active Scenario'!B11) -> 23593.565 | R16: =R7*('🔧 Active Scenario'!B22*('🔧 Active Scenario'!B23/1000000*'🔧 Active Scenario'!B12+'🔧 Active Scenario'!B24/1000000*'🔧 Active Scenario'!B13)*(1-'🔧 Active Scenario'!B16)*'🔧 Active Scenario'!B11+'🔧 Active Scenario'!B25*('🔧 Active Scenario'!B26/1000000*'🔧 Active Scenario'!B12+'🔧 Active Scenario'!B27/1000000*'🔧 Active Scenario'!B13)*(1-'🔧 Active Scenario'!B16)*'🔧 Active Scenario'!B11) -> 24905.448 | S16: =S7*('🔧 Active Scenario'!B22*('🔧 Active Scenario'!B23/1000000*'🔧 Active Scenario'!B12+'🔧 Active Scenario'!B24/1000000*'🔧 Active Scenario'!B13)*(1-'🔧 Active Scenario'!B16)*'🔧 Active Scenario'!B11+'🔧 Active Scenario'!B25*('🔧 Active Scenario'!B26/1000000*'🔧 Active Scenario'!B12+'🔧 Active Scenario'!B27/1000000*'🔧 Active Scenario'!B13)*(1-'🔧 Active Scenario'!B16)*'🔧 Active Scenario'!B11) -> 26156.314 | T16: =T7*('🔧 Active Scenario'!B22*('🔧 Active Scenario'!B23/1000000*'🔧 Active Scenario'!B12+'🔧 Active Scenario'!B24/1000000*'🔧 Active Scenario'!B13)*(1-'🔧 Active Scenario'!B16)*'🔧 Active Scenario'!B11+'🔧 Active Scenario'!B25*('🔧 Active Scenario'!B26/1000000*'🔧 Active Scenario'!B12+'🔧 Active Scenario'!B27/1000000*'🔧 Active Scenario'!B13)*(1-'🔧 Active Scenario'!B16)*'🔧 Active Scenario'!B11) -> 27335.992 | U16: =U7*('🔧 Active Scenario'!B22*('🔧 Active Scenario'!B23/1000000*'🔧 Active Scenario'!B12+'🔧 Active Scenario'!B24/1000000*'🔧 Active Scenario'!B13)*(1-'🔧 Active Scenario'!B16)*'🔧 Active Scenario'!B11+'🔧 Active Scenario'!B25*('🔧 Active Scenario'!B26/1000000*'🔧 Active Scenario'!B12+'🔧 Active Scenario'!B27/1000000*'🔧 Active Scenario'!B13)*(1-'🔧 Active Scenario'!B16)*'🔧 Active Scenario'!B11) -> 28464.822 | V16: =V7*('🔧 Active Scenario'!B22*('🔧 Active Scenario'!B23/1000000*'🔧 Active Scenario'!B12+'🔧 Active Scenario'!B24/1000000*'🔧 Active Scenario'!B13)*(1-'🔧 Active Scenario'!B16)*'🔧 Active Scenario'!B11+'🔧 Active Scenario'!B25*('🔧 Active Scenario'!B26/1000000*'🔧 Active Scenario'!B12+'🔧 Active Scenario'!B27/1000000*'🔧 Active Scenario'!B13)*(1-'🔧 Active Scenario'!B16)*'🔧 Active Scenario'!B11) -> 29532.635 | W16: =W7*('🔧 Active Scenario'!B22*('🔧 Active Scenario'!B23/1000000*'🔧 Active Scenario'!B12+'🔧 Active Scenario'!B24/1000000*'🔧 Active Scenario'!B13)*(1-'🔧 Active Scenario'!B16)*'🔧 Active Scenario'!B11+'🔧 Active Scenario'!B25*('🔧 Active Scenario'!B26/1000000*'🔧 Active Scenario'!B12+'🔧 Active Scenario'!B27/1000000*'🔧 Active Scenario'!B13)*(1-'🔧 Active Scenario'!B16)*'🔧 Active Scenario'!B11) -> 30549.599 | X16: =X7*('🔧 Active Scenario'!B22*('🔧 Active Scenario'!B23/1000000*'🔧 Active Scenario'!B12+'🔧 Active Scenario'!B24/1000000*'🔧 Active Scenario'!B13)*(1-'🔧 Active Scenario'!B16)*'🔧 Active Scenario'!B11+'🔧 Active Scenario'!B25*('🔧 Active Scenario'!B26/1000000*'🔧 Active Scenario'!B12+'🔧 Active Scenario'!B27/1000000*'🔧 Active Scenario'!B13)*(1-'🔧 Active Scenario'!B16)*'🔧 Active Scenario'!B11) -> 31515.714 | Y16: =Y7*('🔧 Active Scenario'!B22*('🔧 Active Scenario'!B23/1000000*'🔧 Active Scenario'!B12+'🔧 Active Scenario'!B24/1000000*'🔧 Active Scenario'!B13)*(1-'🔧 Active Scenario'!B16)*'🔧 Active Scenario'!B11+'🔧 Active Scenario'!B25*('🔧 Active Scenario'!B26/1000000*'🔧 Active Scenario'!B12+'🔧 Active Scenario'!B27/1000000*'🔧 Active Scenario'!B13)*(1-'🔧 Active Scenario'!B16)*'🔧 Active Scenario'!B11) -> 32430.982 | Z16: =Z7*('🔧 Active Scenario'!B22*('🔧 Active Scenario'!B23/1000000*'🔧 Active Scenario'!B12+'🔧 Active Scenario'!B24/1000000*'🔧 Active Scenario'!B13)*(1-'🔧 Active Scenario'!B16)*'🔧 Active Scenario'!B11+'🔧 Active Scenario'!B25*('🔧 Active Scenario'!B26/1000000*'🔧 Active Scenario'!B12+'🔧 Active Scenario'!B27/1000000*'🔧 Active Scenario'!B13)*(1-'🔧 Active Scenario'!B16)*'🔧 Active Scenario'!B11) -> 33305.571
A17: API Livre (+2 agents) | B17: R$ | C17: =C8*('🔧 Active Scenario'!B22*('🔧 Active Scenario'!B23/1000000*'🔧 Active Scenario'!B12+'🔧 Active Scenario'!B24/1000000*'🔧 Active Scenario'!B13)*(1-'🔧 Active Scenario'!B16)*'🔧 Active Scenario'!B11+'🔧 Active Scenario'!B28*('🔧 Active Scenario'!B26/1000000*'🔧 Active Scenario'!B12+'🔧 Active Scenario'!B27/1000000*'🔧 Active Scenario'!B13)*(1-'🔧 Active Scenario'!B16)*'🔧 Active Scenario'!B11) -> 530.8056 | D17: =D8*('🔧 Active Scenario'!B22*('🔧 Active Scenario'!B23/1000000*'🔧 Active Scenario'!B12+'🔧 Active Scenario'!B24/1000000*'🔧 Active Scenario'!B13)*(1-'🔧 Active Scenario'!B16)*'🔧 Active Scenario'!B11+'🔧 Active Scenario'!B28*('🔧 Active Scenario'!B26/1000000*'🔧 Active Scenario'!B12+'🔧 Active Scenario'!B27/1000000*'🔧 Active Scenario'!B13)*(1-'🔧 Active Scenario'!B16)*'🔧 Active Scenario'!B11) -> 1313.7439 | E17: =E8*('🔧 Active Scenario'!B22*('🔧 Active Scenario'!B23/1000000*'🔧 Active Scenario'!B12+'🔧 Active Scenario'!B24/1000000*'🔧 Active Scenario'!B13)*(1-'🔧 Active Scenario'!B16)*'🔧 Active Scenario'!B11+'🔧 Active Scenario'!B28*('🔧 Active Scenario'!B26/1000000*'🔧 Active Scenario'!B12+'🔧 Active Scenario'!B27/1000000*'🔧 Active Scenario'!B13)*(1-'🔧 Active Scenario'!B16)*'🔧 Active Scenario'!B11) -> 2070.1418 | F17: =F8*('🔧 Active Scenario'!B22*('🔧 Active Scenario'!B23/1000000*'🔧 Active Scenario'!B12+'🔧 Active Scenario'!B24/1000000*'🔧 Active Scenario'!B13)*(1-'🔧 Active Scenario'!B16)*'🔧 Active Scenario'!B11+'🔧 Active Scenario'!B28*('🔧 Active Scenario'!B26/1000000*'🔧 Active Scenario'!B12+'🔧 Active Scenario'!B27/1000000*'🔧 Active Scenario'!B13)*(1-'🔧 Active Scenario'!B16)*'🔧 Active Scenario'!B11) -> 2799.9995 | G17: =G8*('🔧 Active Scenario'!B22*('🔧 Active Scenario'!B23/1000000*'🔧 Active Scenario'!B12+'🔧 Active Scenario'!B24/1000000*'🔧 Active Scenario'!B13)*(1-'🔧 Active Scenario'!B16)*'🔧 Active Scenario'!B11+'🔧 Active Scenario'!B28*('🔧 Active Scenario'!B26/1000000*'🔧 Active Scenario'!B12+'🔧 Active Scenario'!B27/1000000*'🔧 Active Scenario'!B13)*(1-'🔧 Active Scenario'!B16)*'🔧 Active Scenario'!B11) -> 3516.5871 | H17: =H8*('🔧 Active Scenario'!B22*('🔧 Active Scenario'!B23/1000000*'🔧 Active Scenario'!B12+'🔧 Active Scenario'!B24/1000000*'🔧 Active Scenario'!B13)*(1-'🔧 Active Scenario'!B16)*'🔧 Active Scenario'!B11+'🔧 Active Scenario'!B28*('🔧 Active Scenario'!B26/1000000*'🔧 Active Scenario'!B12+'🔧 Active Scenario'!B27/1000000*'🔧 Active Scenario'!B13)*(1-'🔧 Active Scenario'!B16)*'🔧 Active Scenario'!B11) -> 4206.6344 | I17: =I8*('🔧 Active Scenario'!B22*('🔧 Active Scenario'!B23/1000000*'🔧 Active Scenario'!B12+'🔧 Active Scenario'!B24/1000000*'🔧 Active Scenario'!B13)*(1-'🔧 Active Scenario'!B16)*'🔧 Active Scenario'!B11+'🔧 Active Scenario'!B28*('🔧 Active Scenario'!B26/1000000*'🔧 Active Scenario'!B12+'🔧 Active Scenario'!B27/1000000*'🔧 Active Scenario'!B13)*(1-'🔧 Active Scenario'!B16)*'🔧 Active Scenario'!B11) -> 4870.1414 | J17: =J8*('🔧 Active Scenario'!B22*('🔧 Active Scenario'!B23/1000000*'🔧 Active Scenario'!B12+'🔧 Active Scenario'!B24/1000000*'🔧 Active Scenario'!B13)*(1-'🔧 Active Scenario'!B16)*'🔧 Active Scenario'!B11+'🔧 Active Scenario'!B28*('🔧 Active Scenario'!B26/1000000*'🔧 Active Scenario'!B12+'🔧 Active Scenario'!B27/1000000*'🔧 Active Scenario'!B13)*(1-'🔧 Active Scenario'!B16)*'🔧 Active Scenario'!B11) -> 5520.3782 | K17: =K8*('🔧 Active Scenario'!B22*('🔧 Active Scenario'!B23/1000000*'🔧 Active Scenario'!B12+'🔧 Active Scenario'!B24/1000000*'🔧 Active Scenario'!B13)*(1-'🔧 Active Scenario'!B16)*'🔧 Active Scenario'!B11+'🔧 Active Scenario'!B28*('🔧 Active Scenario'!B26/1000000*'🔧 Active Scenario'!B12+'🔧 Active Scenario'!B27/1000000*'🔧 Active Scenario'!B13)*(1-'🔧 Active Scenario'!B16)*'🔧 Active Scenario'!B11) -> 6157.345 | L17: =L8*('🔧 Active Scenario'!B22*('🔧 Active Scenario'!B23/1000000*'🔧 Active Scenario'!B12+'🔧 Active Scenario'!B24/1000000*'🔧 Active Scenario'!B13)*(1-'🔧 Active Scenario'!B16)*'🔧 Active Scenario'!B11+'🔧 Active Scenario'!B28*('🔧 Active Scenario'!B26/1000000*'🔧 Active Scenario'!B12+'🔧 Active Scenario'!B27/1000000*'🔧 Active Scenario'!B13)*(1-'🔧 Active Scenario'!B16)*'🔧 Active Scenario'!B11) -> 6767.7714 | M17: =M8*('🔧 Active Scenario'!B22*('🔧 Active Scenario'!B23/1000000*'🔧 Active Scenario'!B12+'🔧 Active Scenario'!B24/1000000*'🔧 Active Scenario'!B13)*(1-'🔧 Active Scenario'!B16)*'🔧 Active Scenario'!B11+'🔧 Active Scenario'!B28*('🔧 Active Scenario'!B26/1000000*'🔧 Active Scenario'!B12+'🔧 Active Scenario'!B27/1000000*'🔧 Active Scenario'!B13)*(1-'🔧 Active Scenario'!B16)*'🔧 Active Scenario'!B11) -> 7364.9277 | N17: =N8*('🔧 Active Scenario'!B22*('🔧 Active Scenario'!B23/1000000*'🔧 Active Scenario'!B12+'🔧 Active Scenario'!B24/1000000*'🔧 Active Scenario'!B13)*(1-'🔧 Active Scenario'!B16)*'🔧 Active Scenario'!B11+'🔧 Active Scenario'!B28*('🔧 Active Scenario'!B26/1000000*'🔧 Active Scenario'!B12+'🔧 Active Scenario'!B27/1000000*'🔧 Active Scenario'!B13)*(1-'🔧 Active Scenario'!B16)*'🔧 Active Scenario'!B11) -> 7935.5437 | O17: =O8*('🔧 Active Scenario'!B22*('🔧 Active Scenario'!B23/1000000*'🔧 Active Scenario'!B12+'🔧 Active Scenario'!B24/1000000*'🔧 Active Scenario'!B13)*(1-'🔧 Active Scenario'!B16)*'🔧 Active Scenario'!B11+'🔧 Active Scenario'!B28*('🔧 Active Scenario'!B26/1000000*'🔧 Active Scenario'!B12+'🔧 Active Scenario'!B27/1000000*'🔧 Active Scenario'!B13)*(1-'🔧 Active Scenario'!B16)*'🔧 Active Scenario'!B11) -> 8625.591 | P17: =P8*('🔧 Active Scenario'!B22*('🔧 Active Scenario'!B23/1000000*'🔧 Active Scenario'!B12+'🔧 Active Scenario'!B24/1000000*'🔧 Active Scenario'!B13)*(1-'🔧 Active Scenario'!B16)*'🔧 Active Scenario'!B11+'🔧 Active Scenario'!B28*('🔧 Active Scenario'!B26/1000000*'🔧 Active Scenario'!B12+'🔧 Active Scenario'!B27/1000000*'🔧 Active Scenario'!B13)*(1-'🔧 Active Scenario'!B16)*'🔧 Active Scenario'!B11) -> 9302.3681 | Q17: =Q8*('🔧 Active Scenario'!B22*('🔧 Active Scenario'!B23/1000000*'🔧 Active Scenario'!B12+'🔧 Active Scenario'!B24/1000000*'🔧 Active Scenario'!B13)*(1-'🔧 Active Scenario'!B16)*'🔧 Active Scenario'!B11+'🔧 Active Scenario'!B28*('🔧 Active Scenario'!B26/1000000*'🔧 Active Scenario'!B12+'🔧 Active Scenario'!B27/1000000*'🔧 Active Scenario'!B13)*(1-'🔧 Active Scenario'!B16)*'🔧 Active Scenario'!B11) -> 9952.605 | R17: =R8*('🔧 Active Scenario'!B22*('🔧 Active Scenario'!B23/1000000*'🔧 Active Scenario'!B12+'🔧 Active Scenario'!B24/1000000*'🔧 Active Scenario'!B13)*(1-'🔧 Active Scenario'!B16)*'🔧 Active Scenario'!B11+'🔧 Active Scenario'!B28*('🔧 Active Scenario'!B26/1000000*'🔧 Active Scenario'!B12+'🔧 Active Scenario'!B27/1000000*'🔧 Active Scenario'!B13)*(1-'🔧 Active Scenario'!B16)*'🔧 Active Scenario'!B11) -> 10589.572 | S17: =S8*('🔧 Active Scenario'!B22*('🔧 Active Scenario'!B23/1000000*'🔧 Active Scenario'!B12+'🔧 Active Scenario'!B24/1000000*'🔧 Active Scenario'!B13)*(1-'🔧 Active Scenario'!B16)*'🔧 Active Scenario'!B11+'🔧 Active Scenario'!B28*('🔧 Active Scenario'!B26/1000000*'🔧 Active Scenario'!B12+'🔧 Active Scenario'!B27/1000000*'🔧 Active Scenario'!B13)*(1-'🔧 Active Scenario'!B16)*'🔧 Active Scenario'!B11) -> 11199.998 | T17: =T8*('🔧 Active Scenario'!B22*('🔧 Active Scenario'!B23/1000000*'🔧 Active Scenario'!B12+'🔧 Active Scenario'!B24/1000000*'🔧 Active Scenario'!B13)*(1-'🔧 Active Scenario'!B16)*'🔧 Active Scenario'!B11+'🔧 Active Scenario'!B28*('🔧 Active Scenario'!B26/1000000*'🔧 Active Scenario'!B12+'🔧 Active Scenario'!B27/1000000*'🔧 Active Scenario'!B13)*(1-'🔧 Active Scenario'!B16)*'🔧 Active Scenario'!B11) -> 11797.154 | U17: =U8*('🔧 Active Scenario'!B22*('🔧 Active Scenario'!B23/1000000*'🔧 Active Scenario'!B12+'🔧 Active Scenario'!B24/1000000*'🔧 Active Scenario'!B13)*(1-'🔧 Active Scenario'!B16)*'🔧 Active Scenario'!B11+'🔧 Active Scenario'!B28*('🔧 Active Scenario'!B26/1000000*'🔧 Active Scenario'!B12+'🔧 Active Scenario'!B27/1000000*'🔧 Active Scenario'!B13)*(1-'🔧 Active Scenario'!B16)*'🔧 Active Scenario'!B11) -> 12367.77 | V17: =V8*('🔧 Active Scenario'!B22*('🔧 Active Scenario'!B23/1000000*'🔧 Active Scenario'!B12+'🔧 Active Scenario'!B24/1000000*'🔧 Active Scenario'!B13)*(1-'🔧 Active Scenario'!B16)*'🔧 Active Scenario'!B11+'🔧 Active Scenario'!B28*('🔧 Active Scenario'!B26/1000000*'🔧 Active Scenario'!B12+'🔧 Active Scenario'!B27/1000000*'🔧 Active Scenario'!B13)*(1-'🔧 Active Scenario'!B16)*'🔧 Active Scenario'!B11) -> 12925.116 | W17: =W8*('🔧 Active Scenario'!B22*('🔧 Active Scenario'!B23/1000000*'🔧 Active Scenario'!B12+'🔧 Active Scenario'!B24/1000000*'🔧 Active Scenario'!B13)*(1-'🔧 Active Scenario'!B16)*'🔧 Active Scenario'!B11+'🔧 Active Scenario'!B28*('🔧 Active Scenario'!B26/1000000*'🔧 Active Scenario'!B12+'🔧 Active Scenario'!B27/1000000*'🔧 Active Scenario'!B13)*(1-'🔧 Active Scenario'!B16)*'🔧 Active Scenario'!B11) -> 13469.192 | X17: =X8*('🔧 Active Scenario'!B22*('🔧 Active Scenario'!B23/1000000*'🔧 Active Scenario'!B12+'🔧 Active Scenario'!B24/1000000*'🔧 Active Scenario'!B13)*(1-'🔧 Active Scenario'!B16)*'🔧 Active Scenario'!B11+'🔧 Active Scenario'!B28*('🔧 Active Scenario'!B26/1000000*'🔧 Active Scenario'!B12+'🔧 Active Scenario'!B27/1000000*'🔧 Active Scenario'!B13)*(1-'🔧 Active Scenario'!B16)*'🔧 Active Scenario'!B11) -> 13999.998 | Y17: =Y8*('🔧 Active Scenario'!B22*('🔧 Active Scenario'!B23/1000000*'🔧 Active Scenario'!B12+'🔧 Active Scenario'!B24/1000000*'🔧 Active Scenario'!B13)*(1-'🔧 Active Scenario'!B16)*'🔧 Active Scenario'!B11+'🔧 Active Scenario'!B28*('🔧 Active Scenario'!B26/1000000*'🔧 Active Scenario'!B12+'🔧 Active Scenario'!B27/1000000*'🔧 Active Scenario'!B13)*(1-'🔧 Active Scenario'!B16)*'🔧 Active Scenario'!B11) -> 14504.263 | Z17: =Z8*('🔧 Active Scenario'!B22*('🔧 Active Scenario'!B23/1000000*'🔧 Active Scenario'!B12+'🔧 Active Scenario'!B24/1000000*'🔧 Active Scenario'!B13)*(1-'🔧 Active Scenario'!B16)*'🔧 Active Scenario'!B11+'🔧 Active Scenario'!B28*('🔧 Active Scenario'!B26/1000000*'🔧 Active Scenario'!B12+'🔧 Active Scenario'!B27/1000000*'🔧 Active Scenario'!B13)*(1-'🔧 Active Scenario'!B16)*'🔧 Active Scenario'!B11) -> 14995.258
A18: TOTAL API | B18: R$ | C18: =SUM(C14:C17) -> 3662.9307 | D18: =SUM(D14:D17) -> 8437.0186 | E18: =SUM(E14:E17) -> 12677.51 | F18: =SUM(F14:F17) -> 16667.358 | G18: =SUM(G14:G17) -> 20441.659 | H18: =SUM(H14:H17) -> 23998.8 | I18: =SUM(I14:I17) -> 27348.952 | J18: =SUM(J14:J17) -> 30517.043 | ... Z18: =SUM(Z14:Z17) -> 70362.778
A19: FIXED COST
A20: Fixed Cost (team+infra+mkt) | B20: R$ | C20: ='🔧 Active Scenario'!B39+'🔧 Active Scenario'!B41+'🔧 Active Scenario'!B43+'🔧 Active Scenario'!B45 -> 55000 | D20: ='🔧 Active Scenario'!B39+'🔧 Active Scenario'!B41+'🔧 Active Scenario'!B43+'🔧 Active Scenario'!B45 -> 55000 | E20: ='🔧 Active Scenario'!B39+'🔧 Active Scenario'!B41+'🔧 Active Scenario'!B43+'🔧 Active Scenario'!B45 -> 55000 | F20: ='🔧 Active Scenario'!B39+'🔧 Active Scenario'!B41+'🔧 Active Scenario'!B43+'🔧 Active Scenario'!B45 -> 55000 | G20: ='🔧 Active Scenario'!B39+'🔧 Active Scenario'!B41+'🔧 Active Scenario'!B43+'🔧 Active Scenario'!B45 -> 55000 | H20: ='🔧 Active Scenario'!B39+'🔧 Active Scenario'!B41+'🔧 Active Scenario'!B43+'🔧 Active Scenario'!B45 -> 55000 | I20: ='🔧 Active Scenario'!B39+'🔧 Active Scenario'!B41+'🔧 Active Scenario'!B43+'🔧 Active Scenario'!B45 -> 55000 | J20: ='🔧 Active Scenario'!B39+'🔧 Active Scenario'!B41+'🔧 Active Scenario'!B43+'🔧 Active Scenario'!B45 -> 55000 | K20: ='🔧 Active Scenario'!B39+'🔧 Active Scenario'!B41+'🔧 Active Scenario'!B43+'🔧 Active Scenario'!B45 -> 55000 | L20: ='🔧 Active Scenario'!B39+'🔧 Active Scenario'!B41+'🔧 Active Scenario'!B43+'🔧 Active Scenario'!B45 -> 55000 | M20: ='🔧 Active Scenario'!B39+'🔧 Active Scenario'!B41+'🔧 Active Scenario'!B43+'🔧 Active Scenario'!B45 -> 55000 | N20: ='🔧 Active Scenario'!B39+'🔧 Active Scenario'!B41+'🔧 Active Scenario'!B43+'🔧 Active Scenario'!B45 -> 55000 | O20: ='🔧 Active Scenario'!B40+'🔧 Active Scenario'!B42+'🔧 Active Scenario'!B44+'🔧 Active Scenario'!B45 -> 70000 | P20: ='🔧 Active Scenario'!B40+'🔧 Active Scenario'!B42+'🔧 Active Scenario'!B44+'🔧 Active Scenario'!B45 -> 70000 | Q20: ='🔧 Active Scenario'!B40+'🔧 Active Scenario'!B42+'🔧 Active Scenario'!B44+'🔧 Active Scenario'!B45 -> 70000 | R20: ='🔧 Active Scenario'!B40+'🔧 Active Scenario'!B42+'🔧 Active Scenario'!B44+'🔧 Active Scenario'!B45 -> 70000 | S20: ='🔧 Active Scenario'!B40+'🔧 Active Scenario'!B42+'🔧 Active Scenario'!B44+'🔧 Active Scenario'!B45 -> 70000 | T20: ='🔧 Active Scenario'!B40+'🔧 Active Scenario'!B42+'🔧 Active Scenario'!B44+'🔧 Active Scenario'!B45 -> 70000 | U20: ='🔧 Active Scenario'!B40+'🔧 Active Scenario'!B42+'🔧 Active Scenario'!B44+'🔧 Active Scenario'!B45 -> 70000 | V20: ='🔧 Active Scenario'!B40+'🔧 Active Scenario'!B42+'🔧 Active Scenario'!B44+'🔧 Active Scenario'!B45 -> 70000 | W20: ='🔧 Active Scenario'!B40+'🔧 Active Scenario'!B42+'🔧 Active Scenario'!B44+'🔧 Active Scenario'!B45 -> 70000 | X20: ='🔧 Active Scenario'!B40+'🔧 Active Scenario'!B42+'🔧 Active Scenario'!B44+'🔧 Active Scenario'!B45 -> 70000 | Y20: ='🔧 Active Scenario'!B40+'🔧 Active Scenario'!B42+'🔧 Active Scenario'!B44+'🔧 Active Scenario'!B45 -> 70000 | Z20: ='🔧 Active Scenario'!B40+'🔧 Active Scenario'!B42+'🔧 Active Scenario'!B44+'🔧 Active Scenario'!B45 -> 70000
A21: TAXES | B21: R$ | C21: =C11*'🔧 Active Scenario'!$B$59 -> 2803.06 | D21: =D11*'🔧 Active Scenario'!$B$59 -> 6838.962 | E21: =E11*'🔧 Active Scenario'!$B$59 -> 10627.019 | F21: =F11*'🔧 Active Scenario'!$B$59 -> 14180.205 | G21: =G11*'🔧 Active Scenario'!$B$59 -> 17529.668 | H21: =H11*'🔧 Active Scenario'!$B$59 -> 20677.995 | I21: =I11*'🔧 Active Scenario'!$B$59 -> 23632.973 | J21: =J11*'🔧 Active Scenario'!$B$59 -> 26417.963 | ... Z21: =Z11*'🔧 Active Scenario'!$B$59 -> 60735.649
A22: RESULT
A23: Total Cost (API + Fixed + Taxes) | B23: R$ | C23: =C18+C20+C21 -> 61465.991 | D23: =D18+D20+D21 -> 70275.981 | E23: =E18+E20+E21 -> 78304.529 | F23: =F18+F20+F21 -> 85847.563 | G23: =G18+G20+G21 -> 92971.327 | H23: =H18+H20+H21 -> 99676.795 | I23: =I18+I20+I21 -> 105981.93 | J23: =J18+J20+J21 -> 111935.01 | ... Z23: =Z18+Z20+Z21 -> 201098.43
A24: MONTHLY RESULT | B24: R$ | C24: =C11-C23 -> -39903.991 | D24: =D11-D23 -> -17668.581 | E24: =E11-E23 -> 3441.7706 | F24: =F11-F23 -> 23230.937 | G24: =G11-G23 -> 41872.273 | H24: =H11-H23 -> 59384.705 | I24: =I11-I23 -> 75810.175 | J24: =J11-J23 -> 91280.094 | ... Z24: =Z11-Z23 -> 266098.87
A25: CUMULATIVE RESULT | B25: R$ | C25: =C24 -> -39903.991 | D25: =C25+D24 -> -57572.571 | E25: =D25+E24 -> -54130.801 | F25: =E25+F24 -> -30899.864 | G25: =F25+G24 -> 10972.41 | H25: =G25+H24 -> 70357.115 | I25: =H25+I24 -> 146167.29 | J25: =I25+J24 -> 237447.38 | K25: =J25+K24 -> 343321.37 | ... Z25: =Y25+Z24 -> 3275921.5
A26: Gross Margin API (% MRR) | B26: % | C26: =IF(C11=0,0,1-C18/C11) -> 0.83012101 | D26: =IF(D11=0,0,1-D18/D11) -> 0.83962297 | E26: =IF(E11=0,0,1-E18/E11) -> 0.8449164 | F26: =IF(F11=0,0,1-F18/F11) -> 0.84719851 | G26: =IF(G11=0,0,1-G18/G11) -> 0.84840468 | H26: =IF(H11=0,0,1-H18/H11) -> 0.84912251 | I26: =IF(I11=0,0,1-I18/I11) -> 0.84955918 | J26: =IF(J11=0,0,1-J18/J11) -> 0.84982886 | ... Z26: =IF(Z11=0,0,1-Z18/Z11) -> 0.84939387

Sheet 📊 Scenario Summary
A1: AutoNoma · Real Scenario Comparison · 3 Years · Dynamic Formulas
A2: Comparison of 3 scenarios · Assumptions / Unit Economics / Valuation / Operations · Independent
A3: INDICATOR | B3: Conservative | C3: Base (default) | D3: Optimistic | E3: UNIT
A4: DIFFERENTIATING ASSUMPTIONS BY SCENARIO
A5: Full-loaded CAC | B5: ='🎛️ Assumptions'!B48 -> 80 | C5: ='🎛️ Assumptions'!C48 -> 60 | D5: ='🎛️ Assumptions'!D48 -> 60 | E5: R$/subscriber
A6: Monthly Churn Essencial | B6: ='🎛️ Assumptions'!B36 -> 0.08 | C6: ='🎛️ Assumptions'!C36 -> 0.07 | D6: ='🎛️ Assumptions'!D36 -> 0.05 | E6: %/month
A7: Implied annual churn | B7: =1-(1-'🎛️ Assumptions'!B36)^12 -> 0.63233361 | C7: =1-(1-'🎛️ Assumptions'!C36)^12 -> 0.5814037 | D7: =1-(1-'🎛️ Assumptions'!D36)^12 -> 0.45963991 | E7: %/year
A8: Valuation multiple M24 | B8: ='🎛️ Assumptions'!B52 -> 3 | C8: ='🎛️ Assumptions'!C52 -> 5 | D8: ='🎛️ Assumptions'!D52 -> 7 | E8: × ARR (SaaS LATAM)
A9: Free: % active users | B9: ='🎛️ Assumptions'!B20 -> 0.5 | C9: ='🎛️ Assumptions'!C20 -> 0.5 | D9: ='🎛️ Assumptions'!D20 -> 0.5 | E9: % of sign-ups
A10: Conversion Free→Essencial | B10: ='🎛️ Assumptions'!B33 -> 0.1 | C10: ='🎛️ Assumptions'!C33 -> 0.15 | D10: ='🎛️ Assumptions'!D33 -> 0.2 | E10: % Free base
A11: UNIT ECONOMICS (calculated from assumptions)
A12: API Cost Essencial/month | B12: =('🎛️ Assumptions'!B21*('🎛️ Assumptions'!B22/1000000*'🎛️ Assumptions'!B13+'🎛️ Assumptions'!B23/1000000*'🎛️ Assumptions'!B14)*(1-'🎛️ Assumptions'!B15)*'🎛️ Assumptions'!B10) -> 5.82894 | C12: =('🎛️ Assumptions'!C21*('🎛️ Assumptions'!C22/1000000*'🎛️ Assumptions'!C13+'🎛️ Assumptions'!C23/1000000*'🎛️ Assumptions'!C14)*(1-'🎛️ Assumptions'!C15)*'🎛️ Assumptions'!C10) -> 6.54444 | D12: =('🎛️ Assumptions'!D21*('🎛️ Assumptions'!D22/1000000*'🎛️ Assumptions'!D13+'🎛️ Assumptions'!D23/1000000*'🎛️ Assumptions'!D14)*(1-'🎛️ Assumptions'!D15)*'🎛️ Assumptions'!D10) -> 8.34273 | E12: R$/subscriber/month
A13: Unit Margin Essencial/month | B13: =('🎛️ Assumptions'!B5+'🎛️ Assumptions'!B8-('🎛️ Assumptions'!B21*('🎛️ Assumptions'!B22/1000000*'🎛️ Assumptions'!B13+'🎛️ Assumptions'!B23/1000000*'🎛️ Assumptions'!B14)*(1-'🎛️ Assumptions'!B15)*'🎛️ Assumptions'!B10)) -> 44.07106 | C13: =('🎛️ Assumptions'!C5+'🎛️ Assumptions'!C8-('🎛️ Assumptions'!C21*('🎛️ Assumptions'!C22/1000000*'🎛️ Assumptions'!C13+'🎛️ Assumptions'!C23/1000000*'🎛️ Assumptions'!C14)*(1-'🎛️ Assumptions'!C15)*'🎛️ Assumptions'!C10)) -> 43.35556 | D13: =('🎛️ Assumptions'!D5+'🎛️ Assumptions'!D8-('🎛️ Assumptions'!D21*('🎛️ Assumptions'!D22/1000000*'🎛️ Assumptions'!D13+'🎛️ Assumptions'!D23/1000000*'🎛️ Assumptions'!D14)*(1-'🎛️ Assumptions'!D15)*'🎛️ Assumptions'!D10)) -> 41.55727 | E13: R$/month
A14: Avg. lifetime (months) | B14: =1/'🎛️ Assumptions'!B36 -> 12.5 | C14: =1/'🎛️ Assumptions'!C36 -> 14.285714 | D14: =1/'🎛️ Assumptions'!D36 -> 20 | E14: 1 ÷ churn
A15: LTV Essencial | B15: =B13*B14 -> 550.88825 | C15: =C13*C14 -> 619.36514 | D15: =D13*D14 -> 831.1454 | E15: R$ lifetime value
A16: LTV / CAC | B16: =IFERROR(B15/B5,0) -> 6.8861031 | C16: =IFERROR(C15/C5,0) -> 10.322752 | D16: =IFERROR(D15/D5,0) -> 13.852423 | E16: ≥3× ok · ≥8× top quartile
A17: CAC Payback (months) | B17: =IFERROR(B5/B13,0) -> 1.8152502 | C17: =IFERROR(C5/C13,0) -> 1.3839055 | D17: =IFERROR(D5/D13,0) -> 1.4437907 | E17: months
A18: VALUATION · MONTH 24 (Cumul. Revenue × multiple)
A19: Cumulative Revenue 24m (Z12) | B19: =SUM(B56:Y56) -> 6638262.2 | C19: =SUM(B68:Y68) -> 10164899 | D19: =SUM(B80:Y80) -> 14454604 | E19: R$ cumulative 24m
A20: Applied multiple | B20: ='🎛️ Assumptions'!B52 -> 3 | C20: ='🎛️ Assumptions'!C52 -> 5 | D20: ='🎛️ Assumptions'!D52 -> 7 | E20: × Cumul. revenue
A21: SUGGESTED VALUATION M24 | B21: =B19*B20 -> 19914787 | C21: =C19*C20 -> 50824494 | D21: =D19*D20 -> 1.0118223e+08 | E21: R$
A22: Angel equity (% Assumptions) | B22: =B21*'🎛️ Assumptions'!$B$59 -> 2987218 | C22: =C21*'🎛️ Assumptions'!$B$59 -> 7623674 | D22: =D21*'🎛️ Assumptions'!$B$59 -> 15177334 | E22: R$
A23: Return on investment (×) | B23: =B22/'🎛️ Assumptions'!$B$58 -> 2.987218 | C23: =C22/'🎛️ Assumptions'!$B$58 -> 7.623674 | D23: =D22/'🎛️ Assumptions'!$B$58 -> 15.177334 | E23: × on investment
A24: YEAR 1 · Results
A25: MRR December M12 | B25: =M56 -> 277318.1 | C25: =M68 -> 426821 | D25: =M80 -> 604340.5 | E25: R$/month
A26: ARR Year 1 (MRR×12) | B26: =M56*12 -> 3327817.2 | C26: =M68*12 -> 5121852 | D26: =M80*12 -> 7252086 | E26: R$/year
A27: Net Result for the Year | B27: =SUM(B60:M60) -> 733093.03 | C27: =SUM(B72:M72) -> 1335922.7 | D27: =SUM(B84:M84) -> 1847831.3 | E27: R$
A28: Paying M12 | B28: =M55 -> 4819 | C28: =M67 -> 7490 | D28: =M79 -> 10745 | E28: subscribers
A29: YEAR 2 · Results
A30: MRR December M24 | B30: =Y56 -> 467197.3 | C30: =Y68 -> 718322.8 | D30: =Y80 -> 1043502.1 | E30: R$/month
A31: ARR Year 2 (MRR×12) | B31: =Y56*12 -> 5606367.6 | C31: =Y68*12 -> 8619873.6 | D31: =Y80*12 -> 12522025 | E31: R$/year
A32: Net Result for the Year | B32: =SUM(N60:Y60) -> 2505012.9 | C32: =SUM(N72:Y72) -> 4075255.7 | D32: =SUM(N84:Y84) -> 5658891.8 | E32: R$
A33: Paying M24 | B33: =Y55 -> 8027 | C33: =Y67 -> 12472 | D33: =Y79 -> 18439 | E33: assinantes
A34: SUMMARY
A35: NPV (Net Present Value) | B35: =-'🎛️ Assumptions'!$B$58+NPV('🎛️ Assumptions'!$B$69,C86:Z86) -> 1400830.8 | C35: =-'🎛️ Assumptions'!$B$58+NPV('🎛️ Assumptions'!$B$69,C87:Z87) -> 3038852.7 | D35: =-'🎛️ Assumptions'!$B$58+NPV('🎛️ Assumptions'!$B$69,C88:Z88) -> 4602506.7 | E35: R$ · taxa B66 mensal
A36: IRR (annualized) | B36: =IFERROR((1+IRR(B86:Z86,'🎛️ Assumptions'!$B$69))^12-1,"n/a") -> 1.4017174 | C36: =IFERROR((1+IRR(B87:Z87,'🎛️ Assumptions'!$B$69))^12-1,"n/a") -> 2.8438196 | D36: =IFERROR((1+IRR(B88:Z88,'🎛️ Assumptions'!$B$69))^12-1,"n/a") -> 4.2078165 | E36: % a.a.
A37: ✅ All indicators above are independently calculated per scenario. Simulation helpers hidden in rows 50–89.
A49: ── HELPERS · 3 SCENARIOS · 24 MONTHS (hidden) ── | B49: M1 | C49: M2 | D49: M3 | E49: M4 | F49: M5 | G49: M6 | H49: M7 | I49: M8 | J49: M9 | K49: M10 | L49: M11 | M49: M12 | N49: M13 | O49: M14 | P49: M15 | Q49: M16 | R49: M17 | S49: M18 | T49: M19 | U49: M20 | V49: M21 | W49: M22 | X49: M23 | Y49: M24
A50: CONSERVATIVE
A51: Free Sign-ups | B51: ='🎛️ Assumptions'!$B$64 -> 2000 | C51: ='🎛️ Assumptions'!$B$31 -> 3000 | D51: ='🎛️ Assumptions'!$B$31 -> 3000 | E51: ='🎛️ Assumptions'!$B$31 -> 3000 | F51: ='🎛️ Assumptions'!$B$31 -> 3000 | G51: ='🎛️ Assumptions'!$B$31 -> 3000 | H51: ='🎛️ Assumptions'!$B$31 -> 3000 | I51: ='🎛️ Assumptions'!$B$31 -> 3000 | J51: ='🎛️ Assumptions'!$B$31 -> 3000 | ... M51: ='🎛️ Assumptions'!$B$31 -> 3000 | N51: ='🎛️ Assumptions'!$B$32 -> 3500 | O51: ='🎛️ Assumptions'!$B$32 -> 3500 | P51: ='🎛️ Assumptions'!$B$32 -> 3500 | Q51: ='🎛️ Assumptions'!$B$32 -> 3500 | R51: ='🎛️ Assumptions'!$B$32 -> 3500 | S51: ='🎛️ Assumptions'!$B$32 -> 3500 | T51: ='🎛️ Assumptions'!$B$32 -> 3500 | U51: ='🎛️ Assumptions'!$B$32 -> 3500 | ... Y51: ='🎛️ Assumptions'!$B$32 -> 3500
A52: Essencial | B52: =ROUND(B51*'🎛️ Assumptions'!$B$33,0) -> 200 | C52: =ROUND(B52*(1-'🎛️ Assumptions'!$B$36)+C51*'🎛️ Assumptions'!$B$33,0) -> 484 | D52: =ROUND(C52*(1-'🎛️ Assumptions'!$B$36)+D51*'🎛️ Assumptions'!$B$33,0) -> 745 | E52: =ROUND(D52*(1-'🎛️ Assumptions'!$B$36)+E51*'🎛️ Assumptions'!$B$33,0) -> 985 | F52: =ROUND(E52*(1-'🎛️ Assumptions'!$B$36)+F51*'🎛️ Assumptions'!$B$33,0) -> 1206 | G52: =ROUND(F52*(1-'🎛️ Assumptions'!$B$36)+G51*'🎛️ Assumptions'!$B$33,0) -> 1410 | H52: =ROUND(G52*(1-'🎛️ Assumptions'!$B$36)+H51*'🎛️ Assumptions'!$B$33,0) -> 1597 | I52: =ROUND(H52*(1-'🎛️ Assumptions'!$B$36)+I51*'🎛️ Assumptions'!$B$33,0) -> 1769 | J52: =ROUND(I52*(1-'🎛️ Assumptions'!$B$36)+J51*'🎛️ Assumptions'!$B$33,0) -> 1927 | ... Y52: =ROUND(X52*(1-'🎛️ Assumptions'!$B$36)+Y51*'🎛️ Assumptions'!$B$33,0) -> 3622
A53: Autônoma | B53: =ROUND(B51*'🎛️ Assumptions'!$B$34,0) -> 140 | C53: =ROUND(B53*(1-'🎛️ Assumptions'!$B$37)+C51*'🎛️ Assumptions'!$B$34,0) -> 343 | D53: =ROUND(C53*(1-'🎛️ Assumptions'!$B$37)+D51*'🎛️ Assumptions'!$B$34,0) -> 536 | E53: =ROUND(D53*(1-'🎛️ Assumptions'!$B$37)+E51*'🎛️ Assumptions'!$B$34,0) -> 719 | F53: =ROUND(E53*(1-'🎛️ Assumptions'!$B$37)+F51*'🎛️ Assumptions'!$B$34,0) -> 893 | G53: =ROUND(F53*(1-'🎛️ Assumptions'!$B$37)+G51*'🎛️ Assumptions'!$B$34,0) -> 1058 | H53: =ROUND(G53*(1-'🎛️ Assumptions'!$B$37)+H51*'🎛️ Assumptions'!$B$34,0) -> 1215 | I53: =ROUND(H53*(1-'🎛️ Assumptions'!$B$37)+I51*'🎛️ Assumptions'!$B$34,0) -> 1364 | J53: =ROUND(I53*(1-'🎛️ Assumptions'!$B$37)+J51*'🎛️ Assumptions'!$B$34,0) -> 1506 | ... Y53: =ROUND(X53*(1-'🎛️ Assumptions'!$B$37)+Y51*'🎛️ Assumptions'!$B$34,0) -> 3275
A54: Livre | B54: =ROUND(B51*'🎛️ Assumptions'!$B$35,0) -> 40 | C54: =ROUND(B54*(1-'🎛️ Assumptions'!$B$38)+C51*'🎛️ Assumptions'!$B$35,0) -> 99 | D54: =ROUND(C54*(1-'🎛️ Assumptions'!$B$38)+D51*'🎛️ Assumptions'!$B$35,0) -> 156 | E54: =ROUND(D54*(1-'🎛️ Assumptions'!$B$38)+E51*'🎛️ Assumptions'!$B$35,0) -> 211 | F54: =ROUND(E54*(1-'🎛️ Assumptions'!$B$38)+F51*'🎛️ Assumptions'!$B$35,0) -> 265 | G54: =ROUND(F54*(1-'🎛️ Assumptions'!$B$38)+G51*'🎛️ Assumptions'!$B$35,0) -> 317 | H54: =ROUND(G54*(1-'🎛️ Assumptions'!$B$38)+H51*'🎛️ Assumptions'!$B$35,0) -> 367 | I54: =ROUND(H54*(1-'🎛️ Assumptions'!$B$38)+I51*'🎛️ Assumptions'!$B$35,0) -> 416 | J54: =ROUND(I54*(1-'🎛️ Assumptions'!$B$38)+J51*'🎛️ Assumptions'!$B$35,0) -> 464 | ... Y54: =ROUND(X54*(1-'🎛️ Assumptions'!$B$38)+Y51*'🎛️ Assumptions'!$B$35,0) -> 1130
A55: Total Paying | B55: =SUM(B52:B54) -> 380 | C55: =SUM(C52:C54) -> 926 | D55: =SUM(D52:D54) -> 1437 | E55: =SUM(E52:E54) -> 1915 | F55: =SUM(F52:F54) -> 2364 | G55: =SUM(G52:G54) -> 2785 | H55: =SUM(H52:H54) -> 3179 | I55: =SUM(I52:I54) -> 3549 | ... Y55: =SUM(Y52:Y54) -> 8027
A56: MRR | B56: =B52*('🎛️ Assumptions'!$B$5+'🎛️ Assumptions'!$B$8)+B53*'🎛️ Assumptions'!$B$6+B54*'🎛️ Assumptions'!$B$7 -> 21562 | C56: =C52*('🎛️ Assumptions'!$B$5+'🎛️ Assumptions'!$B$8)+C53*'🎛️ Assumptions'!$B$6+C54*'🎛️ Assumptions'!$B$7 -> 52607.4 | D56: =D52*('🎛️ Assumptions'!$B$5+'🎛️ Assumptions'!$B$8)+D53*'🎛️ Assumptions'!$B$6+D54*'🎛️ Assumptions'!$B$7 -> 81746.3 | E56: =E52*('🎛️ Assumptions'!$B$5+'🎛️ Assumptions'!$B$8)+E53*'🎛️ Assumptions'!$B$6+E54*'🎛️ Assumptions'!$B$7 -> 109078.5 | F56: =F52*('🎛️ Assumptions'!$B$5+'🎛️ Assumptions'!$B$8)+F53*'🎛️ Assumptions'!$B$6+F54*'🎛️ Assumptions'!$B$7 -> 134843.6 | G56: =G52*('🎛️ Assumptions'!$B$5+'🎛️ Assumptions'!$B$8)+G53*'🎛️ Assumptions'!$B$6+G54*'🎛️ Assumptions'!$B$7 -> 159061.5 | H56: =H52*('🎛️ Assumptions'!$B$5+'🎛️ Assumptions'!$B$8)+H53*'🎛️ Assumptions'!$B$6+H54*'🎛️ Assumptions'!$B$7 -> 181792.1 | I56: =I52*('🎛️ Assumptions'!$B$5+'🎛️ Assumptions'!$B$8)+I53*'🎛️ Assumptions'!$B$6+I54*'🎛️ Assumptions'!$B$7 -> 203215.1 | ... Y56: =Y52*('🎛️ Assumptions'!$B$5+'🎛️ Assumptions'!$B$8)+Y53*'🎛️ Assumptions'!$B$6+Y54*'🎛️ Assumptions'!$B$7 -> 467197.3
A57: Total API | B57: =B51*('🎛️ Assumptions'!$B$17*('🎛️ Assumptions'!$B$18*('🎛️ Assumptions'!$G$10/1000000)+'🎛️ Assumptions'!$B$19*('🎛️ Assumptions'!$G$13/1000000))*(1-'🎛️ Assumptions'!$B$15)*'🎛️ Assumptions'!$B$10*'🎛️ Assumptions'!$B$20)+B52*('🎛️ Assumptions'!$B$21*('🎛️ Assumptions'!$B$22*('🎛️ Assumptions'!$B$13/1000000)+'🎛️ Assumptions'!$B$23*('🎛️ Assumptions'!$B$14/1000000))*(1-'🎛️ Assumptions'!$B$15)*'🎛️ Assumptions'!$B$10)+B53*(('🎛️ Assumptions'!$B$24*('🎛️ Assumptions'!$B$22*('🎛️ Assumptions'!$B$13/1000000)+'🎛️ Assumptions'!$B$23*('🎛️ Assumptions'!$B$14/1000000))*(1-'🎛️ Assumptions'!$B$15)*'🎛️ Assumptions'!$B$10)+('🎛️ Assumptions'!$B$25*('🎛️ Assumptions'!$B$26*('🎛️ Assumptions'!$B$13/1000000)+'🎛️ Assumptions'!$B$27*('🎛️ Assumptions'!$B$14/1000000))*(1-'🎛️ Assumptions'!$B$15)*'🎛️ Assumptions'!$B$10))+B54*(('🎛️ Assumptions'!$B$28*('🎛️ Assumptions'!$B$22*('🎛️ Assumptions'!$B$13/1000000)+'🎛️ Assumptions'!$B$23*('🎛️ Assumptions'!$B$14/1000000))*(1-'🎛️ Assumptions'!$B$15)*'🎛️ Assumptions'!$B$10)+('🎛️ Assumptions'!$B$29*('🎛️ Assumptions'!$B$26*('🎛️ Assumptions'!$B$13/1000000)+'🎛️ Assumptions'!$B$27*('🎛️ Assumptions'!$B$14/1000000))*(1-'🎛️ Assumptions'!$B$15)*'🎛️ Assumptions'!$B$10)) -> 3295.2114 | C57: =C51*('🎛️ Assumptions'!$B$17*('🎛️ Assumptions'!$B$18*('🎛️ Assumptions'!$G$10/1000000)+'🎛️ Assumptions'!$B$19*('🎛️ Assumptions'!$G$13/1000000))*(1-'🎛️ Assumptions'!$B$15)*'🎛️ Assumptions'!$B$10*'🎛️ Assumptions'!$B$20)+C52*('🎛️ Assumptions'!$B$21*('🎛️ Assumptions'!$B$22*('🎛️ Assumptions'!$B$13/1000000)+'🎛️ Assumptions'!$B$23*('🎛️ Assumptions'!$B$14/1000000))*(1-'🎛️ Assumptions'!$B$15)*'🎛️ Assumptions'!$B$10)+C53*(('🎛️ Assumptions'!$B$24*('🎛️ Assumptions'!$B$22*('🎛️ Assumptions'!$B$13/1000000)+'🎛️ Assumptions'!$B$23*('🎛️ Assumptions'!$B$14/1000000))*(1-'🎛️ Assumptions'!$B$15)*'🎛️ Assumptions'!$B$10)+('🎛️ Assumptions'!$B$25*('🎛️ Assumptions'!$B$26*('🎛️ Assumptions'!$B$13/1000000)+'🎛️ Assumptions'!$B$27*('🎛️ Assumptions'!$B$14/1000000))*(1-'🎛️ Assumptions'!$B$15)*'🎛️ Assumptions'!$B$10))+C54*(('🎛️ Assumptions'!$B$28*('🎛️ Assumptions'!$B$22*('🎛️ Assumptions'!$B$13/1000000)+'🎛️ Assumptions'!$B$23*('🎛️ Assumptions'!$B$14/1000000))*(1-'🎛️ Assumptions'!$B$15)*'🎛️ Assumptions'!$B$10)+('🎛️ Assumptions'!$B$29*('🎛️ Assumptions'!$B$26*('🎛️ Assumptions'!$B$13/1000000)+'🎛️ Assumptions'!$B$27*('🎛️ Assumptions'!$B$14/1000000))*(1-'🎛️ Assumptions'!$B$15)*'🎛️ Assumptions'!$B$10)) -> 8052.5359 | D57: =D51*('🎛️ Assumptions'!$B$17*('🎛️ Assumptions'!$B$18*('🎛️ Assumptions'!$G$10/1000000)+'🎛️ Assumptions'!$B$19*('🎛️ Assumptions'!$G$13/1000000))*(1-'🎛️ Assumptions'!$B$15)*'🎛️ Assumptions'!$B$10*'🎛️ Assumptions'!$B$20)+D52*('🎛️ Assumptions'!$B$21*('🎛️ Assumptions'!$B$22*('🎛️ Assumptions'!$B$13/1000000)+'🎛️ Assumptions'!$B$23*('🎛️ Assumptions'!$B$14/1000000))*(1-'🎛️ Assumptions'!$B$15)*'🎛️ Assumptions'!$B$10)+D53*(('🎛️ Assumptions'!$B$24*('🎛️ Assumptions'!$B$22*('🎛️ Assumptions'!$B$13/1000000)+'🎛️ Assumptions'!$B$23*('🎛️ Assumptions'!$B$14/1000000))*(1-'🎛️ Assumptions'!$B$15)*'🎛️ Assumptions'!$B$10)+('🎛️ Assumptions'!$B$25*('🎛️ Assumptions'!$B$26*('🎛️ Assumptions'!$B$13/1000000)+'🎛️ Assumptions'!$B$27*('🎛️ Assumptions'!$B$14/1000000))*(1-'🎛️ Assumptions'!$B$15)*'🎛️ Assumptions'!$B$10))+D54*(('🎛️ Assumptions'!$B$28*('🎛️ Assumptions'!$B$22*('🎛️ Assumptions'!$B$13/1000000)+'🎛️ Assumptions'!$B$23*('🎛️ Assumptions'!$B$14/1000000))*(1-'🎛️ Assumptions'!$B$15)*'🎛️ Assumptions'!$B$10)+('🎛️ Assumptions'!$B$29*('🎛️ Assumptions'!$B$26*('🎛️ Assumptions'!$B$13/1000000)+'🎛️ Assumptions'!$B$27*('🎛️ Assumptions'!$B$14/1000000))*(1-'🎛️ Assumptions'!$B$15)*'🎛️ Assumptions'!$B$10)) -> 12535.9 | E57: =E51*('🎛️ Assumptions'!$B$17*('🎛️ Assumptions'!$B$18*('🎛️ Assumptions'!$G$10/1000000)+'🎛️ Assumptions'!$B$19*('🎛️ Assumptions'!$G$13/1000000))*(1-'🎛️ Assumptions'!$B$15)*'🎛️ Assumptions'!$B$10*'🎛️ Assumptions'!$B$20)+E52*('🎛️ Assumptions'!$B$21*('🎛️ Assumptions'!$B$22*('🎛️ Assumptions'!$B$13/1000000)+'🎛️ Assumptions'!$B$23*('🎛️ Assumptions'!$B$14/1000000))*(1-'🎛️ Assumptions'!$B$15)*'🎛️ Assumptions'!$B$10)+E53*(('🎛️ Assumptions'!$B$24*('🎛️ Assumptions'!$B$22*('🎛️ Assumptions'!$B$13/1000000)+'🎛️ Assumptions'!$B$23*('🎛️ Assumptions'!$B$14/1000000))*(1-'🎛️ Assumptions'!$B$15)*'🎛️ Assumptions'!$B$10)+('🎛️ Assumptions'!$B$25*('🎛️ Assumptions'!$B$26*('🎛️ Assumptions'!$B$13/1000000)+'🎛️ Assumptions'!$B$27*('🎛️ Assumptions'!$B$14/1000000))*(1-'🎛️ Assumptions'!$B$15)*'🎛️ Assumptions'!$B$10))+E54*(('🎛️ Assumptions'!$B$28*('🎛️ Assumptions'!$B$22*('🎛️ Assumptions'!$B$13/1000000)+'🎛️ Assumptions'!$B$23*('🎛️ Assumptions'!$B$14/1000000))*(1-'🎛️ Assumptions'!$B$15)*'🎛️ Assumptions'!$B$10)+('🎛️ Assumptions'!$B$29*('🎛️ Assumptions'!$B$26*('🎛️ Assumptions'!$B$13/1000000)+'🎛️ Assumptions'!$B$27*('🎛️ Assumptions'!$B$14/1000000))*(1-'🎛️ Assumptions'!$B$15)*'🎛️ Assumptions'!$B$10)) -> 16756.962 | F57: =F51*('🎛️ Assumptions'!$B$17*('🎛️ Assumptions'!$B$18*('🎛️ Assumptions'!$G$10/1000000)+'🎛️ Assumptions'!$B$19*('🎛️ Assumptions'!$G$13/1000000))*(1-'🎛️ Assumptions'!$B$15)*'🎛️ Assumptions'!$B$10*'🎛️ Assumptions'!$B$20)+F52*('🎛️ Assumptions'!$B$21*('🎛️ Assumptions'!$B$22*('🎛️ Assumptions'!$B$13/1000000)+'🎛️ Assumptions'!$B$23*('🎛️ Assumptions'!$B$14/1000000))*(1-'🎛️ Assumptions'!$B$15)*'🎛️ Assumptions'!$B$10)+F53*(('🎛️ Assumptions'!$B$24*('🎛️ Assumptions'!$B$22*('🎛️ Assumptions'!$B$13/1000000)+'🎛️ Assumptions'!$B$23*('🎛️ Assumptions'!$B$14/1000000))*(1-'🎛️ Assumptions'!$B$15)*'🎛️ Assumptions'!$B$10)+('🎛️ Assumptions'!$B$25*('🎛️ Assumptions'!$B$26*('🎛️ Assumptions'!$B$13/1000000)+'🎛️ Assumptions'!$B$27*('🎛️ Assumptions'!$B$14/1000000))*(1-'🎛️ Assumptions'!$B$15)*'🎛️ Assumptions'!$B$10))+F54*(('🎛️ Assumptions'!$B$28*('🎛️ Assumptions'!$B$22*('🎛️ Assumptions'!$B$13/1000000)+'🎛️ Assumptions'!$B$23*('🎛️ Assumptions'!$B$14/1000000))*(1-'🎛️ Assumptions'!$B$15)*'🎛️ Assumptions'!$B$10)+('🎛️ Assumptions'!$B$29*('🎛️ Assumptions'!$B$26*('🎛️ Assumptions'!$B$13/1000000)+'🎛️ Assumptions'!$B$27*('🎛️ Assumptions'!$B$14/1000000))*(1-'🎛️ Assumptions'!$B$15)*'🎛️ Assumptions'!$B$10)) -> 20752.763 | G57: =G51*('🎛️ Assumptions'!$B$17*('🎛️ Assumptions'!$B$18*('🎛️ Assumptions'!$G$10/1000000)+'🎛️ Assumptions'!$B$19*('🎛️ Assumptions'!$G$13/1000000))*(1-'🎛️ Assumptions'!$B$15)*'🎛️ Assumptions'!$B$10*'🎛️ Assumptions'!$B$20)+G52*('🎛️ Assumptions'!$B$21*('🎛️ Assumptions'!$B$22*('🎛️ Assumptions'!$B$13/1000000)+'🎛️ Assumptions'!$B$23*('🎛️ Assumptions'!$B$14/1000000))*(1-'🎛️ Assumptions'!$B$15)*'🎛️ Assumptions'!$B$10)+G53*(('🎛️ Assumptions'!$B$24*('🎛️ Assumptions'!$B$22*('🎛️ Assumptions'!$B$13/1000000)+'🎛️ Assumptions'!$B$23*('🎛️ Assumptions'!$B$14/1000000))*(1-'🎛️ Assumptions'!$B$15)*'🎛️ Assumptions'!$B$10)+('🎛️ Assumptions'!$B$25*('🎛️ Assumptions'!$B$26*('🎛️ Assumptions'!$B$13/1000000)+'🎛️ Assumptions'!$B$27*('🎛️ Assumptions'!$B$14/1000000))*(1-'🎛️ Assumptions'!$B$15)*'🎛️ Assumptions'!$B$10))+G54*(('🎛️ Assumptions'!$B$28*('🎛️ Assumptions'!$B$22*('🎛️ Assumptions'!$B$13/1000000)+'🎛️ Assumptions'!$B$23*('🎛️ Assumptions'!$B$14/1000000))*(1-'🎛️ Assumptions'!$B$15)*'🎛️ Assumptions'!$B$10)+('🎛️ Assumptions'!$B$29*('🎛️ Assumptions'!$B$26*('🎛️ Assumptions'!$B$13/1000000)+'🎛️ Assumptions'!$B$27*('🎛️ Assumptions'!$B$14/1000000))*(1-'🎛️ Assumptions'!$B$15)*'🎛️ Assumptions'!$B$10)) -> 24520.718 | H57: =H51*('🎛️ Assumptions'!$B$17*('🎛️ Assumptions'!$B$18*('🎛️ Assumptions'!$G$10/1000000)+'🎛️ Assumptions'!$B$19*('🎛️ Assumptions'!$G$13/1000000))*(1-'🎛️ Assumptions'!$B$15)*'🎛️ Assumptions'!$B$10*'🎛️ Assumptions'!$B$20)+H52*('🎛️ Assumptions'!$B$21*('🎛️ Assumptions'!$B$22*('🎛️ Assumptions'!$B$13/1000000)+'🎛️ Assumptions'!$B$23*('🎛️ Assumptions'!$B$14/1000000))*(1-'🎛️ Assumptions'!$B$15)*'🎛️ Assumptions'!$B$10)+H53*(('🎛️ Assumptions'!$B$24*('🎛️ Assumptions'!$B$22*('🎛️ Assumptions'!$B$13/1000000)+'🎛️ Assumptions'!$B$23*('🎛️ Assumptions'!$B$14/1000000))*(1-'🎛️ Assumptions'!$B$15)*'🎛️ Assumptions'!$B$10)+('🎛️ Assumptions'!$B$25*('🎛️ Assumptions'!$B$26*('🎛️ Assumptions'!$B$13/1000000)+'🎛️ Assumptions'!$B$27*('🎛️ Assumptions'!$B$14/1000000))*(1-'🎛️ Assumptions'!$B$15)*'🎛️ Assumptions'!$B$10))+H54*(('🎛️ Assumptions'!$B$28*('🎛️ Assumptions'!$B$22*('🎛️ Assumptions'!$B$13/1000000)+'🎛️ Assumptions'!$B$23*('🎛️ Assumptions'!$B$14/1000000))*(1-'🎛️ Assumptions'!$B$15)*'🎛️ Assumptions'!$B$10)+('🎛️ Assumptions'!$B$29*('🎛️ Assumptions'!$B$26*('🎛️ Assumptions'!$B$13/1000000)+'🎛️ Assumptions'!$B$27*('🎛️ Assumptions'!$B$14/1000000))*(1-'🎛️ Assumptions'!$B$15)*'🎛️ Assumptions'!$B$10)) -> 28071.968 | I57: =I51*('🎛️ Assumptions'!$B$17*('🎛️ Assumptions'!$B$18*('🎛️ Assumptions'!$G$10/1000000)+'🎛️ Assumptions'!$B$19*('🎛️ Assumptions'!$G$13/1000000))*(1-'🎛️ Assumptions'!$B$15)*'🎛️ Assumptions'!$B$10*'🎛️ Assumptions'!$B$20)+I52*('🎛️ Assumptions'!$B$21*('🎛️ Assumptions'!$B$22*('🎛️ Assumptions'!$B$13/1000000)+'🎛️ Assumptions'!$B$23*('🎛️ Assumptions'!$B$14/1000000))*(1-'🎛️ Assumptions'!$B$15)*'🎛️ Assumptions'!$B$10)+I53*(('🎛️ Assumptions'!$B$24*('🎛️ Assumptions'!$B$22*('🎛️ Assumptions'!$B$13/1000000)+'🎛️ Assumptions'!$B$23*('🎛️ Assumptions'!$B$14/1000000))*(1-'🎛️ Assumptions'!$B$15)*'🎛️ Assumptions'!$B$10)+('🎛️ Assumptions'!$B$25*('🎛️ Assumptions'!$B$26*('🎛️ Assumptions'!$B$13/1000000)+'🎛️ Assumptions'!$B$27*('🎛️ Assumptions'!$B$14/1000000))*(1-'🎛️ Assumptions'!$B$15)*'🎛️ Assumptions'!$B$10))+I54*(('🎛️ Assumptions'!$B$28*('🎛️ Assumptions'!$B$22*('🎛️ Assumptions'!$B$13/1000000)+'🎛️ Assumptions'!$B$23*('🎛️ Assumptions'!$B$14/1000000))*(1-'🎛️ Assumptions'!$B$15)*'🎛️ Assumptions'!$B$10)+('🎛️ Assumptions'!$B$29*('🎛️ Assumptions'!$B$26*('🎛️ Assumptions'!$B$13/1000000)+'🎛️ Assumptions'!$B$27*('🎛️ Assumptions'!$B$14/1000000))*(1-'🎛️ Assumptions'!$B$15)*'🎛️ Assumptions'!$B$10)) -> 31432.414 | ... Y57: =Y51*('🎛️ Assumptions'!$B$17*('🎛️ Assumptions'!$B$18*('🎛️ Assumptions'!$G$10/1000000)+'🎛️ Assumptions'!$B$19*('🎛️ Assumptions'!$G$13/1000000))*(1-'🎛️ Assumptions'!$B$15)*'🎛️ Assumptions'!$B$10*'🎛️ Assumptions'!$B$20)+Y52*('🎛️ Assumptions'!$B$21*('🎛️ Assumptions'!$B$22*('🎛️ Assumptions'!$B$13/1000000)+'🎛️ Assumptions'!$B$23*('🎛️ Assumptions'!$B$14/1000000))*(1-'🎛️ Assumptions'!$B$15)*'🎛️ Assumptions'!$B$10)+Y53*(('🎛️ Assumptions'!$B$24*('🎛️ Assumptions'!$B$22*('🎛️ Assumptions'!$B$13/1000000)+'🎛️ Assumptions'!$B$23*('🎛️ Assumptions'!$B$14/1000000))*(1-'🎛️ Assumptions'!$B$15)*'🎛️ Assumptions'!$B$10)+('🎛️ Assumptions'!$B$25*('🎛️ Assumptions'!$B$26*('🎛️ Assumptions'!$B$13/1000000)+'🎛️ Assumptions'!$B$27*('🎛️ Assumptions'!$B$14/1000000))*(1-'🎛️ Assumptions'!$B$15)*'🎛️ Assumptions'!$B$10))+Y54*(('🎛️ Assumptions'!$B$28*('🎛️ Assumptions'!$B$22*('🎛️ Assumptions'!$B$13/1000000)+'🎛️ Assumptions'!$B$23*('🎛️ Assumptions'!$B$14/1000000))*(1-'🎛️ Assumptions'!$B$15)*'🎛️ Assumptions'!$B$10)+('🎛️ Assumptions'!$B$29*('🎛️ Assumptions'!$B$26*('🎛️ Assumptions'!$B$13/1000000)+'🎛️ Assumptions'!$B$27*('🎛️ Assumptions'!$B$14/1000000))*(1-'🎛️ Assumptions'!$B$15)*'🎛️ Assumptions'!$B$10)) -> 73692.663
A58: Fixed Cost | B58: ='🎛️ Assumptions'!$B$40+'🎛️ Assumptions'!$B$42+'🎛️ Assumptions'!$B$44+'🎛️ Assumptions'!$B$46 -> 55000 | C58: ='🎛️ Assumptions'!$B$40+'🎛️ Assumptions'!$B$42+'🎛️ Assumptions'!$B$44+'🎛️ Assumptions'!$B$46 -> 55000 | D58: ='🎛️ Assumptions'!$B$40+'🎛️ Assumptions'!$B$42+'🎛️ Assumptions'!$B$44+'🎛️ Assumptions'!$B$46 -> 55000 | E58: ='🎛️ Assumptions'!$B$40+'🎛️ Assumptions'!$B$42+'🎛️ Assumptions'!$B$44+'🎛️ Assumptions'!$B$46 -> 55000 | F58: ='🎛️ Assumptions'!$B$40+'🎛️ Assumptions'!$B$42+'🎛️ Assumptions'!$B$44+'🎛️ Assumptions'!$B$46 -> 55000 | G58: ='🎛️ Assumptions'!$B$40+'🎛️ Assumptions'!$B$42+'🎛️ Assumptions'!$B$44+'🎛️ Assumptions'!$B$46 -> 55000 | H58: ='🎛️ Assumptions'!$B$40+'🎛️ Assumptions'!$B$42+'🎛️ Assumptions'!$B$44+'🎛️ Assumptions'!$B$46 -> 55000 | I58: ='🎛️ Assumptions'!$B$40+'🎛️ Assumptions'!$B$42+'🎛️ Assumptions'!$B$44+'🎛️ Assumptions'!$B$46 -> 55000 | ... M58: ='🎛️ Assumptions'!$B$40+'🎛️ Assumptions'!$B$42+'🎛️ Assumptions'!$B$44+'🎛️ Assumptions'!$B$46 -> 55000 | N58: ='🎛️ Assumptions'!$B$41+'🎛️ Assumptions'!$B$43+'🎛️ Assumptions'!$B$45+'🎛️ Assumptions'!$B$46 -> 70000 | O58: ='🎛️ Assumptions'!$B$41+'🎛️ Assumptions'!$B$43+'🎛️ Assumptions'!$B$45+'🎛️ Assumptions'!$B$46 -> 70000 | P58: ='🎛️ Assumptions'!$B$41+'🎛️ Assumptions'!$B$43+'🎛️ Assumptions'!$B$45+'🎛️ Assumptions'!$B$46 -> 70000 | Q58: ='🎛️ Assumptions'!$B$41+'🎛️ Assumptions'!$B$43+'🎛️ Assumptions'!$B$45+'🎛️ Assumptions'!$B$46 -> 70000 | R58: ='🎛️ Assumptions'!$B$41+'🎛️ Assumptions'!$B$43+'🎛️ Assumptions'!$B$45+'🎛️ Assumptions'!$B$46 -> 70000 | S58: ='🎛️ Assumptions'!$B$41+'🎛️ Assumptions'!$B$43+'🎛️ Assumptions'!$B$45+'🎛️ Assumptions'!$B$46 -> 70000 | T58: ='🎛️ Assumptions'!$B$41+'🎛️ Assumptions'!$B$43+'🎛️ Assumptions'!$B$45+'🎛️ Assumptions'!$B$46 -> 70000 | U58: ='🎛️ Assumptions'!$B$41+'🎛️ Assumptions'!$B$43+'🎛️ Assumptions'!$B$45+'🎛️ Assumptions'!$B$46 -> 70000 | ... Y58: ='🎛️ Assumptions'!$B$41+'🎛️ Assumptions'!$B$43+'🎛️ Assumptions'!$B$45+'🎛️ Assumptions'!$B$46 -> 70000
A59: Taxes | B59: =B56*'🎛️ Assumptions'!$B$70 -> 2803.06 | C59: =C56*'🎛️ Assumptions'!$B$70 -> 6838.962 | D59: =D56*'🎛️ Assumptions'!$B$70 -> 10627.019 | E59: =E56*'🎛️ Assumptions'!$B$70 -> 14180.205 | F59: =F56*'🎛️ Assumptions'!$B$70 -> 17529.668 | G59: =G56*'🎛️ Assumptions'!$B$70 -> 20677.995 | H59: =H56*'🎛️ Assumptions'!$B$70 -> 23632.973 | I59: =I56*'🎛️ Assumptions'!$B$70 -> 26417.963 | ... Y59: =Y56*'🎛️ Assumptions'!$B$70 -> 60735.649
A60: Monthly Result | B60: =B56-B57-B58-B59 -> -39536.271 | C60: =C56-C57-C58-C59 -> -17284.098 | D60: =D56-D57-D58-D59 -> 3583.3807 | E60: =E56-E57-E58-E59 -> 23141.333 | F60: =F56-F57-F58-F59 -> 41561.169 | G60: =G56-G57-G58-G59 -> 58862.787 | H60: =H56-H57-H58-H59 -> 75087.159 | I60: =I56-I57-I58-I59 -> 90364.723 | ... Y60: =Y56-Y57-Y58-Y59 -> 262768.99
A62: BASE
A63: Free Sign-ups | B63: ='🎛️ Assumptions'!$B$64 -> 2000 | C63: ='🎛️ Assumptions'!$C$31 -> 3500 | D63: ='🎛️ Assumptions'!$C$31 -> 3500 | E63: ='🎛️ Assumptions'!$C$31 -> 3500 | F63: ='🎛️ Assumptions'!$C$31 -> 3500 | G63: ='🎛️ Assumptions'!$C$31 -> 3500 | H63: ='🎛️ Assumptions'!$C$31 -> 3500 | I63: ='🎛️ Assumptions'!$C$31 -> 3500 | J63: ='🎛️ Assumptions'!$C$31 -> 3500 | ... M63: ='🎛️ Assumptions'!$C$31 -> 3500 | N63: ='🎛️ Assumptions'!$C$32 -> 4000 | O63: ='🎛️ Assumptions'!$C$32 -> 4000 | P63: ='🎛️ Assumptions'!$C$32 -> 4000 | Q63: ='🎛️ Assumptions'!$C$32 -> 4000 | R63: ='🎛️ Assumptions'!$C$32 -> 4000 | S63: ='🎛️ Assumptions'!$C$32 -> 4000 | T63: ='🎛️ Assumptions'!$C$32 -> 4000 | U63: ='🎛️ Assumptions'!$C$32 -> 4000 | ... Y63: ='🎛️ Assumptions'!$C$32 -> 4000
A64: Essencial | B64: =ROUND(B63*'🎛️ Assumptions'!$C$33,0) -> 300 | C64: =ROUND(B64*(1-'🎛️ Assumptions'!$C$36)+C63*'🎛️ Assumptions'!$C$33,0) -> 804 | D64: =ROUND(C64*(1-'🎛️ Assumptions'!$C$36)+D63*'🎛️ Assumptions'!$C$33,0) -> 1273 | E64: =ROUND(D64*(1-'🎛️ Assumptions'!$C$36)+E63*'🎛️ Assumptions'!$C$33,0) -> 1709 | F64: =ROUND(E64*(1-'🎛️ Assumptions'!$C$36)+F63*'🎛️ Assumptions'!$C$33,0) -> 2114 | G64: =ROUND(F64*(1-'🎛️ Assumptions'!$C$36)+G63*'🎛️ Assumptions'!$C$33,0) -> 2491 | H64: =ROUND(G64*(1-'🎛️ Assumptions'!$C$36)+H63*'🎛️ Assumptions'!$C$33,0) -> 2842 | I64: =ROUND(H64*(1-'🎛️ Assumptions'!$C$36)+I63*'🎛️ Assumptions'!$C$33,0) -> 3168 | J64: =ROUND(I64*(1-'🎛️ Assumptions'!$C$36)+J63*'🎛️ Assumptions'!$C$33,0) -> 3471 | ... Y64: =ROUND(X64*(1-'🎛️ Assumptions'!$C$36)+Y63*'🎛️ Assumptions'!$C$33,0) -> 6767
A65: Autônoma | B65: =ROUND(B63*'🎛️ Assumptions'!$C$34,0) -> 140 | C65: =ROUND(B65*(1-'🎛️ Assumptions'!$C$37)+C63*'🎛️ Assumptions'!$C$34,0) -> 378 | D65: =ROUND(C65*(1-'🎛️ Assumptions'!$C$37)+D63*'🎛️ Assumptions'!$C$34,0) -> 604 | E65: =ROUND(D65*(1-'🎛️ Assumptions'!$C$37)+E63*'🎛️ Assumptions'!$C$34,0) -> 819 | F65: =ROUND(E65*(1-'🎛️ Assumptions'!$C$37)+F63*'🎛️ Assumptions'!$C$34,0) -> 1023 | G65: =ROUND(F65*(1-'🎛️ Assumptions'!$C$37)+G63*'🎛️ Assumptions'!$C$34,0) -> 1217 | H65: =ROUND(G65*(1-'🎛️ Assumptions'!$C$37)+H63*'🎛️ Assumptions'!$C$34,0) -> 1401 | I65: =ROUND(H65*(1-'🎛️ Assumptions'!$C$37)+I63*'🎛️ Assumptions'!$C$34,0) -> 1576 | J65: =ROUND(I65*(1-'🎛️ Assumptions'!$C$37)+J63*'🎛️ Assumptions'!$C$34,0) -> 1742 | ... Y65: =ROUND(X65*(1-'🎛️ Assumptions'!$C$37)+Y63*'🎛️ Assumptions'!$C$34,0) -> 3759
A66: Livre | B66: =ROUND(B63*'🎛️ Assumptions'!$C$35,0) -> 60 | C66: =ROUND(B66*(1-'🎛️ Assumptions'!$C$38)+C63*'🎛️ Assumptions'!$C$35,0) -> 163 | D66: =ROUND(C66*(1-'🎛️ Assumptions'!$C$38)+D63*'🎛️ Assumptions'!$C$35,0) -> 263 | E66: =ROUND(D66*(1-'🎛️ Assumptions'!$C$38)+E63*'🎛️ Assumptions'!$C$35,0) -> 360 | F66: =ROUND(E66*(1-'🎛️ Assumptions'!$C$38)+F63*'🎛️ Assumptions'!$C$35,0) -> 454 | G66: =ROUND(F66*(1-'🎛️ Assumptions'!$C$38)+G63*'🎛️ Assumptions'!$C$35,0) -> 545 | H66: =ROUND(G66*(1-'🎛️ Assumptions'!$C$38)+H63*'🎛️ Assumptions'!$C$35,0) -> 634 | I66: =ROUND(H66*(1-'🎛️ Assumptions'!$C$38)+I63*'🎛️ Assumptions'!$C$35,0) -> 720 | J66: =ROUND(I66*(1-'🎛️ Assumptions'!$C$38)+J63*'🎛️ Assumptions'!$C$35,0) -> 803 | ... Y66: =ROUND(X66*(1-'🎛️ Assumptions'!$C$38)+Y63*'🎛️ Assumptions'!$C$35,0) -> 1946
A67: Total Paying | B67: =SUM(B64:B66) -> 500 | C67: =SUM(C64:C66) -> 1345 | D67: =SUM(D64:D66) -> 2140 | E67: =SUM(E64:E66) -> 2888 | F67: =SUM(F64:F66) -> 3591 | G67: =SUM(G64:G66) -> 4253 | H67: =SUM(H64:H66) -> 4877 | I67: =SUM(I64:I66) -> 5464 | ... Y67: =SUM(Y64:Y66) -> 12472
A68: MRR | B68: =B64*('🎛️ Assumptions'!$C$5+'🎛️ Assumptions'!$C$8)+B65*'🎛️ Assumptions'!$C$6+B66*'🎛️ Assumptions'!$C$7 -> 28150 | C68: =C64*('🎛️ Assumptions'!$C$5+'🎛️ Assumptions'!$C$8)+C65*'🎛️ Assumptions'!$C$6+C66*'🎛️ Assumptions'!$C$7 -> 75785.5 | D68: =D64*('🎛️ Assumptions'!$C$5+'🎛️ Assumptions'!$C$8)+D65*'🎛️ Assumptions'!$C$6+D66*'🎛️ Assumptions'!$C$7 -> 120716 | E68: =E64*('🎛️ Assumptions'!$C$5+'🎛️ Assumptions'!$C$8)+E65*'🎛️ Assumptions'!$C$6+E66*'🎛️ Assumptions'!$C$7 -> 163101.2 | F68: =F64*('🎛️ Assumptions'!$C$5+'🎛️ Assumptions'!$C$8)+F65*'🎛️ Assumptions'!$C$6+F66*'🎛️ Assumptions'!$C$7 -> 203040.9 | G68: =G64*('🎛️ Assumptions'!$C$5+'🎛️ Assumptions'!$C$8)+G65*'🎛️ Assumptions'!$C$6+G66*'🎛️ Assumptions'!$C$7 -> 240744.7 | H68: =H64*('🎛️ Assumptions'!$C$5+'🎛️ Assumptions'!$C$8)+H65*'🎛️ Assumptions'!$C$6+H66*'🎛️ Assumptions'!$C$7 -> 276392.3 | I68: =I64*('🎛️ Assumptions'!$C$5+'🎛️ Assumptions'!$C$8)+I65*'🎛️ Assumptions'!$C$6+I66*'🎛️ Assumptions'!$C$7 -> 310013.6 | ... Y68: =Y64*('🎛️ Assumptions'!$C$5+'🎛️ Assumptions'!$C$8)+Y65*'🎛️ Assumptions'!$C$6+Y66*'🎛️ Assumptions'!$C$7 -> 718322.8
A69: Total API | B69: =B63*('🎛️ Assumptions'!$C$17*('🎛️ Assumptions'!$C$18*('🎛️ Assumptions'!$G$10/1000000)+'🎛️ Assumptions'!$C$19*('🎛️ Assumptions'!$G$13/1000000))*(1-'🎛️ Assumptions'!$C$15)*'🎛️ Assumptions'!$C$10*'🎛️ Assumptions'!$C$20)+B64*('🎛️ Assumptions'!$C$21*('🎛️ Assumptions'!$C$22*('🎛️ Assumptions'!$C$13/1000000)+'🎛️ Assumptions'!$C$23*('🎛️ Assumptions'!$C$14/1000000))*(1-'🎛️ Assumptions'!$C$15)*'🎛️ Assumptions'!$C$10)+B65*(('🎛️ Assumptions'!$C$24*('🎛️ Assumptions'!$C$22*('🎛️ Assumptions'!$C$13/1000000)+'🎛️ Assumptions'!$C$23*('🎛️ Assumptions'!$C$14/1000000))*(1-'🎛️ Assumptions'!$C$15)*'🎛️ Assumptions'!$C$10)+('🎛️ Assumptions'!$C$25*('🎛️ Assumptions'!$C$26*('🎛️ Assumptions'!$C$13/1000000)+'🎛️ Assumptions'!$C$27*('🎛️ Assumptions'!$C$14/1000000))*(1-'🎛️ Assumptions'!$C$15)*'🎛️ Assumptions'!$C$10))+B66*(('🎛️ Assumptions'!$C$28*('🎛️ Assumptions'!$C$22*('🎛️ Assumptions'!$C$13/1000000)+'🎛️ Assumptions'!$C$23*('🎛️ Assumptions'!$C$14/1000000))*(1-'🎛️ Assumptions'!$C$15)*'🎛️ Assumptions'!$C$10)+('🎛️ Assumptions'!$C$29*('🎛️ Assumptions'!$C$26*('🎛️ Assumptions'!$C$13/1000000)+'🎛️ Assumptions'!$C$27*('🎛️ Assumptions'!$C$14/1000000))*(1-'🎛️ Assumptions'!$C$15)*'🎛️ Assumptions'!$C$10)) -> 4542.948 | C69: =C63*('🎛️ Assumptions'!$C$17*('🎛️ Assumptions'!$C$18*('🎛️ Assumptions'!$G$10/1000000)+'🎛️ Assumptions'!$C$19*('🎛️ Assumptions'!$G$13/1000000))*(1-'🎛️ Assumptions'!$C$15)*'🎛️ Assumptions'!$C$10*'🎛️ Assumptions'!$C$20)+C64*('🎛️ Assumptions'!$C$21*('🎛️ Assumptions'!$C$22*('🎛️ Assumptions'!$C$13/1000000)+'🎛️ Assumptions'!$C$23*('🎛️ Assumptions'!$C$14/1000000))*(1-'🎛️ Assumptions'!$C$15)*'🎛️ Assumptions'!$C$10)+C65*(('🎛️ Assumptions'!$C$24*('🎛️ Assumptions'!$C$22*('🎛️ Assumptions'!$C$13/1000000)+'🎛️ Assumptions'!$C$23*('🎛️ Assumptions'!$C$14/1000000))*(1-'🎛️ Assumptions'!$C$15)*'🎛️ Assumptions'!$C$10)+('🎛️ Assumptions'!$C$25*('🎛️ Assumptions'!$C$26*('🎛️ Assumptions'!$C$13/1000000)+'🎛️ Assumptions'!$C$27*('🎛️ Assumptions'!$C$14/1000000))*(1-'🎛️ Assumptions'!$C$15)*'🎛️ Assumptions'!$C$10))+C66*(('🎛️ Assumptions'!$C$28*('🎛️ Assumptions'!$C$22*('🎛️ Assumptions'!$C$13/1000000)+'🎛️ Assumptions'!$C$23*('🎛️ Assumptions'!$C$14/1000000))*(1-'🎛️ Assumptions'!$C$15)*'🎛️ Assumptions'!$C$10)+('🎛️ Assumptions'!$C$29*('🎛️ Assumptions'!$C$26*('🎛️ Assumptions'!$C$13/1000000)+'🎛️ Assumptions'!$C$27*('🎛️ Assumptions'!$C$14/1000000))*(1-'🎛️ Assumptions'!$C$15)*'🎛️ Assumptions'!$C$10)) -> 12242.396 | D69: =D63*('🎛️ Assumptions'!$C$17*('🎛️ Assumptions'!$C$18*('🎛️ Assumptions'!$G$10/1000000)+'🎛️ Assumptions'!$C$19*('🎛️ Assumptions'!$G$13/1000000))*(1-'🎛️ Assumptions'!$C$15)*'🎛️ Assumptions'!$C$10*'🎛️ Assumptions'!$C$20)+D64*('🎛️ Assumptions'!$C$21*('🎛️ Assumptions'!$C$22*('🎛️ Assumptions'!$C$13/1000000)+'🎛️ Assumptions'!$C$23*('🎛️ Assumptions'!$C$14/1000000))*(1-'🎛️ Assumptions'!$C$15)*'🎛️ Assumptions'!$C$10)+D65*(('🎛️ Assumptions'!$C$24*('🎛️ Assumptions'!$C$22*('🎛️ Assumptions'!$C$13/1000000)+'🎛️ Assumptions'!$C$23*('🎛️ Assumptions'!$C$14/1000000))*(1-'🎛️ Assumptions'!$C$15)*'🎛️ Assumptions'!$C$10)+('🎛️ Assumptions'!$C$25*('🎛️ Assumptions'!$C$26*('🎛️ Assumptions'!$C$13/1000000)+'🎛️ Assumptions'!$C$27*('🎛️ Assumptions'!$C$14/1000000))*(1-'🎛️ Assumptions'!$C$15)*'🎛️ Assumptions'!$C$10))+D66*(('🎛️ Assumptions'!$C$28*('🎛️ Assumptions'!$C$22*('🎛️ Assumptions'!$C$13/1000000)+'🎛️ Assumptions'!$C$23*('🎛️ Assumptions'!$C$14/1000000))*(1-'🎛️ Assumptions'!$C$15)*'🎛️ Assumptions'!$C$10)+('🎛️ Assumptions'!$C$29*('🎛️ Assumptions'!$C$26*('🎛️ Assumptions'!$C$13/1000000)+'🎛️ Assumptions'!$C$27*('🎛️ Assumptions'!$C$14/1000000))*(1-'🎛️ Assumptions'!$C$15)*'🎛️ Assumptions'!$C$10)) -> 19525.327 | E69: =E63*('🎛️ Assumptions'!$C$17*('🎛️ Assumptions'!$C$18*('🎛️ Assumptions'!$G$10/1000000)+'🎛️ Assumptions'!$C$19*('🎛️ Assumptions'!$G$13/1000000))*(1-'🎛️ Assumptions'!$C$15)*'🎛️ Assumptions'!$C$10*'🎛️ Assumptions'!$C$20)+E64*('🎛️ Assumptions'!$C$21*('🎛️ Assumptions'!$C$22*('🎛️ Assumptions'!$C$13/1000000)+'🎛️ Assumptions'!$C$23*('🎛️ Assumptions'!$C$14/1000000))*(1-'🎛️ Assumptions'!$C$15)*'🎛️ Assumptions'!$C$10)+E65*(('🎛️ Assumptions'!$C$24*('🎛️ Assumptions'!$C$22*('🎛️ Assumptions'!$C$13/1000000)+'🎛️ Assumptions'!$C$23*('🎛️ Assumptions'!$C$14/1000000))*(1-'🎛️ Assumptions'!$C$15)*'🎛️ Assumptions'!$C$10)+('🎛️ Assumptions'!$C$25*('🎛️ Assumptions'!$C$26*('🎛️ Assumptions'!$C$13/1000000)+'🎛️ Assumptions'!$C$27*('🎛️ Assumptions'!$C$14/1000000))*(1-'🎛️ Assumptions'!$C$15)*'🎛️ Assumptions'!$C$10))+E66*(('🎛️ Assumptions'!$C$28*('🎛️ Assumptions'!$C$22*('🎛️ Assumptions'!$C$13/1000000)+'🎛️ Assumptions'!$C$23*('🎛️ Assumptions'!$C$14/1000000))*(1-'🎛️ Assumptions'!$C$15)*'🎛️ Assumptions'!$C$10)+('🎛️ Assumptions'!$C$29*('🎛️ Assumptions'!$C$26*('🎛️ Assumptions'!$C$13/1000000)+'🎛️ Assumptions'!$C$27*('🎛️ Assumptions'!$C$14/1000000))*(1-'🎛️ Assumptions'!$C$15)*'🎛️ Assumptions'!$C$10)) -> 26416.527 | F69: =F63*('🎛️ Assumptions'!$C$17*('🎛️ Assumptions'!$C$18*('🎛️ Assumptions'!$G$10/1000000)+'🎛️ Assumptions'!$C$19*('🎛️ Assumptions'!$G$13/1000000))*(1-'🎛️ Assumptions'!$C$15)*'🎛️ Assumptions'!$C$10*'🎛️ Assumptions'!$C$20)+F64*('🎛️ Assumptions'!$C$21*('🎛️ Assumptions'!$C$22*('🎛️ Assumptions'!$C$13/1000000)+'🎛️ Assumptions'!$C$23*('🎛️ Assumptions'!$C$14/1000000))*(1-'🎛️ Assumptions'!$C$15)*'🎛️ Assumptions'!$C$10)+F65*(('🎛️ Assumptions'!$C$24*('🎛️ Assumptions'!$C$22*('🎛️ Assumptions'!$C$13/1000000)+'🎛️ Assumptions'!$C$23*('🎛️ Assumptions'!$C$14/1000000))*(1-'🎛️ Assumptions'!$C$15)*'🎛️ Assumptions'!$C$10)+('🎛️ Assumptions'!$C$25*('🎛️ Assumptions'!$C$26*('🎛️ Assumptions'!$C$13/1000000)+'🎛️ Assumptions'!$C$27*('🎛️ Assumptions'!$C$14/1000000))*(1-'🎛️ Assumptions'!$C$15)*'🎛️ Assumptions'!$C$10))+F66*(('🎛️ Assumptions'!$C$28*('🎛️ Assumptions'!$C$22*('🎛️ Assumptions'!$C$13/1000000)+'🎛️ Assumptions'!$C$23*('🎛️ Assumptions'!$C$14/1000000))*(1-'🎛️ Assumptions'!$C$15)*'🎛️ Assumptions'!$C$10)+('🎛️ Assumptions'!$C$29*('🎛️ Assumptions'!$C$26*('🎛️ Assumptions'!$C$13/1000000)+'🎛️ Assumptions'!$C$27*('🎛️ Assumptions'!$C$14/1000000))*(1-'🎛️ Assumptions'!$C$15)*'🎛️ Assumptions'!$C$10)) -> 32929.084 | G69: =G63*('🎛️ Assumptions'!$C$17*('🎛️ Assumptions'!$C$18*('🎛️ Assumptions'!$G$10/1000000)+'🎛️ Assumptions'!$C$19*('🎛️ Assumptions'!$G$13/1000000))*(1-'🎛️ Assumptions'!$C$15)*'🎛️ Assumptions'!$C$10*'🎛️ Assumptions'!$C$20)+G64*('🎛️ Assumptions'!$C$21*('🎛️ Assumptions'!$C$22*('🎛️ Assumptions'!$C$13/1000000)+'🎛️ Assumptions'!$C$23*('🎛️ Assumptions'!$C$14/1000000))*(1-'🎛️ Assumptions'!$C$15)*'🎛️ Assumptions'!$C$10)+G65*(('🎛️ Assumptions'!$C$24*('🎛️ Assumptions'!$C$22*('🎛️ Assumptions'!$C$13/1000000)+'🎛️ Assumptions'!$C$23*('🎛️ Assumptions'!$C$14/1000000))*(1-'🎛️ Assumptions'!$C$15)*'🎛️ Assumptions'!$C$10)+('🎛️ Assumptions'!$C$25*('🎛️ Assumptions'!$C$26*('🎛️ Assumptions'!$C$13/1000000)+'🎛️ Assumptions'!$C$27*('🎛️ Assumptions'!$C$14/1000000))*(1-'🎛️ Assumptions'!$C$15)*'🎛️ Assumptions'!$C$10))+G66*(('🎛️ Assumptions'!$C$28*('🎛️ Assumptions'!$C$22*('🎛️ Assumptions'!$C$13/1000000)+'🎛️ Assumptions'!$C$23*('🎛️ Assumptions'!$C$14/1000000))*(1-'🎛️ Assumptions'!$C$15)*'🎛️ Assumptions'!$C$10)+('🎛️ Assumptions'!$C$29*('🎛️ Assumptions'!$C$26*('🎛️ Assumptions'!$C$13/1000000)+'🎛️ Assumptions'!$C$27*('🎛️ Assumptions'!$C$14/1000000))*(1-'🎛️ Assumptions'!$C$15)*'🎛️ Assumptions'!$C$10)) -> 39094.329 | H69: =H63*('🎛️ Assumptions'!$C$17*('🎛️ Assumptions'!$C$18*('🎛️ Assumptions'!$G$10/1000000)+'🎛️ Assumptions'!$C$19*('🎛️ Assumptions'!$G$13/1000000))*(1-'🎛️ Assumptions'!$C$15)*'🎛️ Assumptions'!$C$10*'🎛️ Assumptions'!$C$20)+H64*('🎛️ Assumptions'!$C$21*('🎛️ Assumptions'!$C$22*('🎛️ Assumptions'!$C$13/1000000)+'🎛️ Assumptions'!$C$23*('🎛️ Assumptions'!$C$14/1000000))*(1-'🎛️ Assumptions'!$C$15)*'🎛️ Assumptions'!$C$10)+H65*(('🎛️ Assumptions'!$C$24*('🎛️ Assumptions'!$C$22*('🎛️ Assumptions'!$C$13/1000000)+'🎛️ Assumptions'!$C$23*('🎛️ Assumptions'!$C$14/1000000))*(1-'🎛️ Assumptions'!$C$15)*'🎛️ Assumptions'!$C$10)+('🎛️ Assumptions'!$C$25*('🎛️ Assumptions'!$C$26*('🎛️ Assumptions'!$C$13/1000000)+'🎛️ Assumptions'!$C$27*('🎛️ Assumptions'!$C$14/1000000))*(1-'🎛️ Assumptions'!$C$15)*'🎛️ Assumptions'!$C$10))+H66*(('🎛️ Assumptions'!$C$28*('🎛️ Assumptions'!$C$22*('🎛️ Assumptions'!$C$13/1000000)+'🎛️ Assumptions'!$C$23*('🎛️ Assumptions'!$C$14/1000000))*(1-'🎛️ Assumptions'!$C$15)*'🎛️ Assumptions'!$C$10)+('🎛️ Assumptions'!$C$29*('🎛️ Assumptions'!$C$26*('🎛️ Assumptions'!$C$13/1000000)+'🎛️ Assumptions'!$C$27*('🎛️ Assumptions'!$C$14/1000000))*(1-'🎛️ Assumptions'!$C$15)*'🎛️ Assumptions'!$C$10)) -> 44941.051 | I69: =I63*('🎛️ Assumptions'!$C$17*('🎛️ Assumptions'!$C$18*('🎛️ Assumptions'!$G$10/1000000)+'🎛️ Assumptions'!$C$19*('🎛️ Assumptions'!$G$13/1000000))*(1-'🎛️ Assumptions'!$C$15)*'🎛️ Assumptions'!$C$10*'🎛️ Assumptions'!$C$20)+I64*('🎛️ Assumptions'!$C$21*('🎛️ Assumptions'!$C$22*('🎛️ Assumptions'!$C$13/1000000)+'🎛️ Assumptions'!$C$23*('🎛️ Assumptions'!$C$14/1000000))*(1-'🎛️ Assumptions'!$C$15)*'🎛️ Assumptions'!$C$10)+I65*(('🎛️ Assumptions'!$C$24*('🎛️ Assumptions'!$C$22*('🎛️ Assumptions'!$C$13/1000000)+'🎛️ Assumptions'!$C$23*('🎛️ Assumptions'!$C$14/1000000))*(1-'🎛️ Assumptions'!$C$15)*'🎛️ Assumptions'!$C$10)+('🎛️ Assumptions'!$C$25*('🎛️ Assumptions'!$C$26*('🎛️ Assumptions'!$C$13/1000000)+'🎛️ Assumptions'!$C$27*('🎛️ Assumptions'!$C$14/1000000))*(1-'🎛️ Assumptions'!$C$15)*'🎛️ Assumptions'!$C$10))+I66*(('🎛️ Assumptions'!$C$28*('🎛️ Assumptions'!$C$22*('🎛️ Assumptions'!$C$13/1000000)+'🎛️ Assumptions'!$C$23*('🎛️ Assumptions'!$C$14/1000000))*(1-'🎛️ Assumptions'!$C$15)*'🎛️ Assumptions'!$C$10)+('🎛️ Assumptions'!$C$29*('🎛️ Assumptions'!$C$26*('🎛️ Assumptions'!$C$13/1000000)+'🎛️ Assumptions'!$C$27*('🎛️ Assumptions'!$C$14/1000000))*(1-'🎛️ Assumptions'!$C$15)*'🎛️ Assumptions'!$C$10)) -> 50471.79 | ... Y69: =Y63*('🎛️ Assumptions'!$C$17*('🎛️ Assumptions'!$C$18*('🎛️ Assumptions'!$G$10/1000000)+'🎛️ Assumptions'!$C$19*('🎛️ Assumptions'!$G$13/1000000))*(1-'🎛️ Assumptions'!$C$15)*'🎛️ Assumptions'!$C$10*'🎛️ Assumptions'!$C$20)+Y64*('🎛️ Assumptions'!$C$21*('🎛️ Assumptions'!$C$22*('🎛️ Assumptions'!$C$13/1000000)+'🎛️ Assumptions'!$C$23*('🎛️ Assumptions'!$C$14/1000000))*(1-'🎛️ Assumptions'!$C$15)*'🎛️ Assumptions'!$C$10)+Y65*(('🎛️ Assumptions'!$C$24*('🎛️ Assumptions'!$C$22*('🎛️ Assumptions'!$C$13/1000000)+'🎛️ Assumptions'!$C$23*('🎛️ Assumptions'!$C$14/1000000))*(1-'🎛️ Assumptions'!$C$15)*'🎛️ Assumptions'!$C$10)+('🎛️ Assumptions'!$C$25*('🎛️ Assumptions'!$C$26*('🎛️ Assumptions'!$C$13/1000000)+'🎛️ Assumptions'!$C$27*('🎛️ Assumptions'!$C$14/1000000))*(1-'🎛️ Assumptions'!$C$15)*'🎛️ Assumptions'!$C$10))+Y66*(('🎛️ Assumptions'!$C$28*('🎛️ Assumptions'!$C$22*('🎛️ Assumptions'!$C$13/1000000)+'🎛️ Assumptions'!$C$23*('🎛️ Assumptions'!$C$14/1000000))*(1-'🎛️ Assumptions'!$C$15)*'🎛️ Assumptions'!$C$10)+('🎛️ Assumptions'!$C$29*('🎛️ Assumptions'!$C$26*('🎛️ Assumptions'!$C$13/1000000)+'🎛️ Assumptions'!$C$27*('🎛️ Assumptions'!$C$14/1000000))*(1-'🎛️ Assumptions'!$C$15)*'🎛️ Assumptions'!$C$10)) -> 118809.37
A70: Fixed Cost | B70: ='🎛️ Assumptions'!$C$40+'🎛️ Assumptions'!$C$42+'🎛️ Assumptions'!$C$44+'🎛️ Assumptions'!$C$46 -> 63000 | C70: ='🎛️ Assumptions'!$C$40+'🎛️ Assumptions'!$C$42+'🎛️ Assumptions'!$C$44+'🎛️ Assumptions'!$C$46 -> 63000 | D70: ='🎛️ Assumptions'!$C$40+'🎛️ Assumptions'!$C$42+'🎛️ Assumptions'!$C$44+'🎛️ Assumptions'!$C$46 -> 63000 | E70: ='🎛️ Assumptions'!$C$40+'🎛️ Assumptions'!$C$42+'🎛️ Assumptions'!$C$44+'🎛️ Assumptions'!$C$46 -> 63000 | F70: ='🎛️ Assumptions'!$C$40+'🎛️ Assumptions'!$C$42+'🎛️ Assumptions'!$C$44+'🎛️ Assumptions'!$C$46 -> 63000 | G70: ='🎛️ Assumptions'!$C$40+'🎛️ Assumptions'!$C$42+'🎛️ Assumptions'!$C$44+'🎛️ Assumptions'!$C$46 -> 63000 | H70: ='🎛️ Assumptions'!$C$40+'🎛️ Assumptions'!$C$42+'🎛️ Assumptions'!$C$44+'🎛️ Assumptions'!$C$46 -> 63000 | I70: ='🎛️ Assumptions'!$C$40+'🎛️ Assumptions'!$C$42+'🎛️ Assumptions'!$C$44+'🎛️ Assumptions'!$C$46 -> 63000 | ... M70: ='🎛️ Assumptions'!$C$40+'🎛️ Assumptions'!$C$42+'🎛️ Assumptions'!$C$44+'🎛️ Assumptions'!$C$46 -> 63000 | N70: ='🎛️ Assumptions'!$C$41+'🎛️ Assumptions'!$C$43+'🎛️ Assumptions'!$C$45+'🎛️ Assumptions'!$C$46 -> 84000 | O70: ='🎛️ Assumptions'!$C$41+'🎛️ Assumptions'!$C$43+'🎛️ Assumptions'!$C$45+'🎛️ Assumptions'!$C$46 -> 84000 | P70: ='🎛️ Assumptions'!$C$41+'🎛️ Assumptions'!$C$43+'🎛️ Assumptions'!$C$45+'🎛️ Assumptions'!$C$46 -> 84000 | Q70: ='🎛️ Assumptions'!$C$41+'🎛️ Assumptions'!$C$43+'🎛️ Assumptions'!$C$45+'🎛️ Assumptions'!$C$46 -> 84000 | R70: ='🎛️ Assumptions'!$C$41+'🎛️ Assumptions'!$C$43+'🎛️ Assumptions'!$C$45+'🎛️ Assumptions'!$C$46 -> 84000 | S70: ='🎛️ Assumptions'!$C$41+'🎛️ Assumptions'!$C$43+'🎛️ Assumptions'!$C$45+'🎛️ Assumptions'!$C$46 -> 84000 | T70: ='🎛️ Assumptions'!$C$41+'🎛️ Assumptions'!$C$43+'🎛️ Assumptions'!$C$45+'🎛️ Assumptions'!$C$46 -> 84000 | U70: ='🎛️ Assumptions'!$C$41+'🎛️ Assumptions'!$C$43+'🎛️ Assumptions'!$C$45+'🎛️ Assumptions'!$C$46 -> 84000 | ... Y70: ='🎛️ Assumptions'!$C$41+'🎛️ Assumptions'!$C$43+'🎛️ Assumptions'!$C$45+'🎛️ Assumptions'!$C$46 -> 84000
A71: Taxes | B71: =B68*'🎛️ Assumptions'!$C$70 -> 3659.5 | C71: =C68*'🎛️ Assumptions'!$C$70 -> 9852.115 | D71: =D68*'🎛️ Assumptions'!$C$70 -> 15693.08 | E71: =E68*'🎛️ Assumptions'!$C$70 -> 21203.156 | F71: =F68*'🎛️ Assumptions'!$C$70 -> 26395.317 | G71: =G68*'🎛️ Assumptions'!$C$70 -> 31296.811 | H71: =H68*'🎛️ Assumptions'!$C$70 -> 35930.999 | I71: =I68*'🎛️ Assumptions'!$C$70 -> 40301.768 | ... Y71: =Y68*'🎛️ Assumptions'!$C$70 -> 93381.964
A72: Monthly Result | B72: =B68-B69-B70-B71 -> -43052.448 | C72: =C68-C69-C70-C71 -> -9309.0108 | D72: =D68-D69-D70-D71 -> 22497.593 | E72: =E68-E69-E70-E71 -> 52481.517 | F72: =F68-F69-F70-F71 -> 80716.499 | G72: =G68-G69-G70-G71 -> 107353.56 | H72: =H68-H69-H70-H71 -> 132520.25 | I72: =I68-I69-I70-I71 -> 156240.04 | ... Y72: =Y68-Y69-Y70-Y71 -> 422131.47
A74: OPTIMISTIC
A75: Free Sign-ups | B75: ='🎛️ Assumptions'!$B$64 -> 2000 | C75: ='🎛️ Assumptions'!$D$31 -> 4000 | D75: ='🎛️ Assumptions'!$D$31 -> 4000 | E75: ='🎛️ Assumptions'!$D$31 -> 4000 | F75: ='🎛️ Assumptions'!$D$31 -> 4000 | G75: ='🎛️ Assumptions'!$D$31 -> 4000 | H75: ='🎛️ Assumptions'!$D$31 -> 4000 | I75: ='🎛️ Assumptions'!$D$31 -> 4000 | J75: ='🎛️ Assumptions'!$D$31 -> 4000 | ... M75: ='🎛️ Assumptions'!$D$31 -> 4000 | N75: ='🎛️ Assumptions'!$D$32 -> 4500 | O75: ='🎛️ Assumptions'!$D$32 -> 4500 | P75: ='🎛️ Assumptions'!$D$32 -> 4500 | Q75: ='🎛️ Assumptions'!$D$32 -> 4500 | R75: ='🎛️ Assumptions'!$D$32 -> 4500 | S75: ='🎛️ Assumptions'!$D$32 -> 4500 | T75: ='🎛️ Assumptions'!$D$32 -> 4500 | U75: ='🎛️ Assumptions'!$D$32 -> 4500 | ... Y75: ='🎛️ Assumptions'!$D$32 -> 4500
A76: Essencial | B76: =ROUND(B75*'🎛️ Assumptions'!$D$33,0) -> 400 | C76: =ROUND(B76*(1-'🎛️ Assumptions'!$D$36)+C75*'🎛️ Assumptions'!$D$33,0) -> 1180 | D76: =ROUND(C76*(1-'🎛️ Assumptions'!$D$36)+D75*'🎛️ Assumptions'!$D$33,0) -> 1921 | E76: =ROUND(D76*(1-'🎛️ Assumptions'!$D$36)+E75*'🎛️ Assumptions'!$D$33,0) -> 2625 | F76: =ROUND(E76*(1-'🎛️ Assumptions'!$D$36)+F75*'🎛️ Assumptions'!$D$33,0) -> 3294 | G76: =ROUND(F76*(1-'🎛️ Assumptions'!$D$36)+G75*'🎛️ Assumptions'!$D$33,0) -> 3929 | H76: =ROUND(G76*(1-'🎛️ Assumptions'!$D$36)+H75*'🎛️ Assumptions'!$D$33,0) -> 4533 | I76: =ROUND(H76*(1-'🎛️ Assumptions'!$D$36)+I75*'🎛️ Assumptions'!$D$33,0) -> 5106 | J76: =ROUND(I76*(1-'🎛️ Assumptions'!$D$36)+J75*'🎛️ Assumptions'!$D$33,0) -> 5651 | ... Y76: =ROUND(X76*(1-'🎛️ Assumptions'!$D$36)+Y75*'🎛️ Assumptions'!$D$33,0) -> 12126
A77: Autônoma | B77: =ROUND(B75*'🎛️ Assumptions'!$D$34,0) -> 140 | C77: =ROUND(B77*(1-'🎛️ Assumptions'!$D$37)+C75*'🎛️ Assumptions'!$D$34,0) -> 412 | D77: =ROUND(C77*(1-'🎛️ Assumptions'!$D$37)+D75*'🎛️ Assumptions'!$D$34,0) -> 667 | E77: =ROUND(D77*(1-'🎛️ Assumptions'!$D$37)+E75*'🎛️ Assumptions'!$D$34,0) -> 907 | F77: =ROUND(E77*(1-'🎛️ Assumptions'!$D$37)+F75*'🎛️ Assumptions'!$D$34,0) -> 1133 | G77: =ROUND(F77*(1-'🎛️ Assumptions'!$D$37)+G75*'🎛️ Assumptions'!$D$34,0) -> 1345 | H77: =ROUND(G77*(1-'🎛️ Assumptions'!$D$37)+H75*'🎛️ Assumptions'!$D$34,0) -> 1544 | I77: =ROUND(H77*(1-'🎛️ Assumptions'!$D$37)+I75*'🎛️ Assumptions'!$D$34,0) -> 1731 | J77: =ROUND(I77*(1-'🎛️ Assumptions'!$D$37)+J75*'🎛️ Assumptions'!$D$34,0) -> 1907 | ... Y77: =ROUND(X77*(1-'🎛️ Assumptions'!$D$37)+Y75*'🎛️ Assumptions'!$D$34,0) -> 3882
A78: Livre | B78: =ROUND(B75*'🎛️ Assumptions'!$D$35,0) -> 60 | C78: =ROUND(B78*(1-'🎛️ Assumptions'!$D$38)+C75*'🎛️ Assumptions'!$D$35,0) -> 179 | D78: =ROUND(C78*(1-'🎛️ Assumptions'!$D$38)+D75*'🎛️ Assumptions'!$D$35,0) -> 295 | E78: =ROUND(D78*(1-'🎛️ Assumptions'!$D$38)+E75*'🎛️ Assumptions'!$D$35,0) -> 409 | F78: =ROUND(E78*(1-'🎛️ Assumptions'!$D$38)+F75*'🎛️ Assumptions'!$D$35,0) -> 521 | G78: =ROUND(F78*(1-'🎛️ Assumptions'!$D$38)+G75*'🎛️ Assumptions'!$D$35,0) -> 631 | H78: =ROUND(G78*(1-'🎛️ Assumptions'!$D$38)+H75*'🎛️ Assumptions'!$D$35,0) -> 738 | I78: =ROUND(H78*(1-'🎛️ Assumptions'!$D$38)+I75*'🎛️ Assumptions'!$D$35,0) -> 843 | J78: =ROUND(I78*(1-'🎛️ Assumptions'!$D$38)+J75*'🎛️ Assumptions'!$D$35,0) -> 946 | ... Y78: =ROUND(X78*(1-'🎛️ Assumptions'!$D$38)+Y75*'🎛️ Assumptions'!$D$35,0) -> 2431
A79: Total Paying | B79: =SUM(B76:B78) -> 600 | C79: =SUM(C76:C78) -> 1771 | D79: =SUM(D76:D78) -> 2883 | E79: =SUM(E76:E78) -> 3941 | F79: =SUM(F76:F78) -> 4948 | G79: =SUM(G76:G78) -> 5905 | H79: =SUM(H76:H78) -> 6815 | I79: =SUM(I76:I78) -> 7680 | ... Y79: =SUM(Y76:Y78) -> 18439
A80: MRR | B80: =B76*('🎛️ Assumptions'!$D$5+'🎛️ Assumptions'!$D$8)+B77*'🎛️ Assumptions'!$D$6+B78*'🎛️ Assumptions'!$D$7 -> 33560 | C80: =C76*('🎛️ Assumptions'!$D$5+'🎛️ Assumptions'!$D$8)+C77*'🎛️ Assumptions'!$D$6+C78*'🎛️ Assumptions'!$D$7 -> 99098.9 | D80: =D76*('🎛️ Assumptions'!$D$5+'🎛️ Assumptions'!$D$8)+D77*'🎛️ Assumptions'!$D$6+D78*'🎛️ Assumptions'!$D$7 -> 161382.7 | E80: =E76*('🎛️ Assumptions'!$D$5+'🎛️ Assumptions'!$D$8)+E77*'🎛️ Assumptions'!$D$6+E78*'🎛️ Assumptions'!$D$7 -> 220716.9 | F80: =F76*('🎛️ Assumptions'!$D$5+'🎛️ Assumptions'!$D$8)+F77*'🎛️ Assumptions'!$D$6+F78*'🎛️ Assumptions'!$D$7 -> 277264.2 | G80: =G76*('🎛️ Assumptions'!$D$5+'🎛️ Assumptions'!$D$8)+G77*'🎛️ Assumptions'!$D$6+G78*'🎛️ Assumptions'!$D$7 -> 331074.5 | H80: =H76*('🎛️ Assumptions'!$D$5+'🎛️ Assumptions'!$D$8)+H77*'🎛️ Assumptions'!$D$6+H78*'🎛️ Assumptions'!$D$7 -> 382280.5 | I80: =I76*('🎛️ Assumptions'!$D$5+'🎛️ Assumptions'!$D$8)+I77*'🎛️ Assumptions'!$D$6+I78*'🎛️ Assumptions'!$D$7 -> 431025 | ... Y80: =Y76*('🎛️ Assumptions'!$D$5+'🎛️ Assumptions'!$D$8)+Y77*'🎛️ Assumptions'!$D$6+Y78*'🎛️ Assumptions'!$D$7 -> 1043502.1
A81: Total API | B81: =B75*('🎛️ Assumptions'!$D$17*('🎛️ Assumptions'!$D$18*('🎛️ Assumptions'!$G$10/1000000)+'🎛️ Assumptions'!$D$19*('🎛️ Assumptions'!$G$13/1000000))*(1-'🎛️ Assumptions'!$D$15)*'🎛️ Assumptions'!$D$10*'🎛️ Assumptions'!$D$20)+B76*('🎛️ Assumptions'!$D$21*('🎛️ Assumptions'!$D$22*('🎛️ Assumptions'!$D$13/1000000)+'🎛️ Assumptions'!$D$23*('🎛️ Assumptions'!$D$14/1000000))*(1-'🎛️ Assumptions'!$D$15)*'🎛️ Assumptions'!$D$10)+B77*(('🎛️ Assumptions'!$D$24*('🎛️ Assumptions'!$D$22*('🎛️ Assumptions'!$D$13/1000000)+'🎛️ Assumptions'!$D$23*('🎛️ Assumptions'!$D$14/1000000))*(1-'🎛️ Assumptions'!$D$15)*'🎛️ Assumptions'!$D$10)+('🎛️ Assumptions'!$D$25*('🎛️ Assumptions'!$D$26*('🎛️ Assumptions'!$D$13/1000000)+'🎛️ Assumptions'!$D$27*('🎛️ Assumptions'!$D$14/1000000))*(1-'🎛️ Assumptions'!$D$15)*'🎛️ Assumptions'!$D$10))+B78*(('🎛️ Assumptions'!$D$28*('🎛️ Assumptions'!$D$22*('🎛️ Assumptions'!$D$13/1000000)+'🎛️ Assumptions'!$D$23*('🎛️ Assumptions'!$D$14/1000000))*(1-'🎛️ Assumptions'!$D$15)*'🎛️ Assumptions'!$D$10)+('🎛️ Assumptions'!$D$29*('🎛️ Assumptions'!$D$26*('🎛️ Assumptions'!$D$13/1000000)+'🎛️ Assumptions'!$D$27*('🎛️ Assumptions'!$D$14/1000000))*(1-'🎛️ Assumptions'!$D$15)*'🎛️ Assumptions'!$D$10)) -> 6145.986 | C81: =C75*('🎛️ Assumptions'!$D$17*('🎛️ Assumptions'!$D$18*('🎛️ Assumptions'!$G$10/1000000)+'🎛️ Assumptions'!$D$19*('🎛️ Assumptions'!$G$13/1000000))*(1-'🎛️ Assumptions'!$D$15)*'🎛️ Assumptions'!$D$10*'🎛️ Assumptions'!$D$20)+C76*('🎛️ Assumptions'!$D$21*('🎛️ Assumptions'!$D$22*('🎛️ Assumptions'!$D$13/1000000)+'🎛️ Assumptions'!$D$23*('🎛️ Assumptions'!$D$14/1000000))*(1-'🎛️ Assumptions'!$D$15)*'🎛️ Assumptions'!$D$10)+C77*(('🎛️ Assumptions'!$D$24*('🎛️ Assumptions'!$D$22*('🎛️ Assumptions'!$D$13/1000000)+'🎛️ Assumptions'!$D$23*('🎛️ Assumptions'!$D$14/1000000))*(1-'🎛️ Assumptions'!$D$15)*'🎛️ Assumptions'!$D$10)+('🎛️ Assumptions'!$D$25*('🎛️ Assumptions'!$D$26*('🎛️ Assumptions'!$D$13/1000000)+'🎛️ Assumptions'!$D$27*('🎛️ Assumptions'!$D$14/1000000))*(1-'🎛️ Assumptions'!$D$15)*'🎛️ Assumptions'!$D$10))+C78*(('🎛️ Assumptions'!$D$28*('🎛️ Assumptions'!$D$22*('🎛️ Assumptions'!$D$13/1000000)+'🎛️ Assumptions'!$D$23*('🎛️ Assumptions'!$D$14/1000000))*(1-'🎛️ Assumptions'!$D$15)*'🎛️ Assumptions'!$D$10)+('🎛️ Assumptions'!$D$29*('🎛️ Assumptions'!$D$26*('🎛️ Assumptions'!$D$13/1000000)+'🎛️ Assumptions'!$D$27*('🎛️ Assumptions'!$D$14/1000000))*(1-'🎛️ Assumptions'!$D$15)*'🎛️ Assumptions'!$D$10)) -> 18151.839 | D81: =D75*('🎛️ Assumptions'!$D$17*('🎛️ Assumptions'!$D$18*('🎛️ Assumptions'!$G$10/1000000)+'🎛️ Assumptions'!$D$19*('🎛️ Assumptions'!$G$13/1000000))*(1-'🎛️ Assumptions'!$D$15)*'🎛️ Assumptions'!$D$10*'🎛️ Assumptions'!$D$20)+D76*('🎛️ Assumptions'!$D$21*('🎛️ Assumptions'!$D$22*('🎛️ Assumptions'!$D$13/1000000)+'🎛️ Assumptions'!$D$23*('🎛️ Assumptions'!$D$14/1000000))*(1-'🎛️ Assumptions'!$D$15)*'🎛️ Assumptions'!$D$10)+D77*(('🎛️ Assumptions'!$D$24*('🎛️ Assumptions'!$D$22*('🎛️ Assumptions'!$D$13/1000000)+'🎛️ Assumptions'!$D$23*('🎛️ Assumptions'!$D$14/1000000))*(1-'🎛️ Assumptions'!$D$15)*'🎛️ Assumptions'!$D$10)+('🎛️ Assumptions'!$D$25*('🎛️ Assumptions'!$D$26*('🎛️ Assumptions'!$D$13/1000000)+'🎛️ Assumptions'!$D$27*('🎛️ Assumptions'!$D$14/1000000))*(1-'🎛️ Assumptions'!$D$15)*'🎛️ Assumptions'!$D$10))+D78*(('🎛️ Assumptions'!$D$28*('🎛️ Assumptions'!$D$22*('🎛️ Assumptions'!$D$13/1000000)+'🎛️ Assumptions'!$D$23*('🎛️ Assumptions'!$D$14/1000000))*(1-'🎛️ Assumptions'!$D$15)*'🎛️ Assumptions'!$D$10)+('🎛️ Assumptions'!$D$29*('🎛️ Assumptions'!$D$26*('🎛️ Assumptions'!$D$13/1000000)+'🎛️ Assumptions'!$D$27*('🎛️ Assumptions'!$D$14/1000000))*(1-'🎛️ Assumptions'!$D$15)*'🎛️ Assumptions'!$D$10)) -> 29564.029 | E81: =E75*('🎛️ Assumptions'!$D$17*('🎛️ Assumptions'!$D$18*('🎛️ Assumptions'!$G$10/1000000)+'🎛️ Assumptions'!$D$19*('🎛️ Assumptions'!$G$13/1000000))*(1-'🎛️ Assumptions'!$D$15)*'🎛️ Assumptions'!$D$10*'🎛️ Assumptions'!$D$20)+E76*('🎛️ Assumptions'!$D$21*('🎛️ Assumptions'!$D$22*('🎛️ Assumptions'!$D$13/1000000)+'🎛️ Assumptions'!$D$23*('🎛️ Assumptions'!$D$14/1000000))*(1-'🎛️ Assumptions'!$D$15)*'🎛️ Assumptions'!$D$10)+E77*(('🎛️ Assumptions'!$D$24*('🎛️ Assumptions'!$D$22*('🎛️ Assumptions'!$D$13/1000000)+'🎛️ Assumptions'!$D$23*('🎛️ Assumptions'!$D$14/1000000))*(1-'🎛️ Assumptions'!$D$15)*'🎛️ Assumptions'!$D$10)+('🎛️ Assumptions'!$D$25*('🎛️ Assumptions'!$D$26*('🎛️ Assumptions'!$D$13/1000000)+'🎛️ Assumptions'!$D$27*('🎛️ Assumptions'!$D$14/1000000))*(1-'🎛️ Assumptions'!$D$15)*'🎛️ Assumptions'!$D$10))+E78*(('🎛️ Assumptions'!$D$28*('🎛️ Assumptions'!$D$22*('🎛️ Assumptions'!$D$13/1000000)+'🎛️ Assumptions'!$D$23*('🎛️ Assumptions'!$D$14/1000000))*(1-'🎛️ Assumptions'!$D$15)*'🎛️ Assumptions'!$D$10)+('🎛️ Assumptions'!$D$29*('🎛️ Assumptions'!$D$26*('🎛️ Assumptions'!$D$13/1000000)+'🎛️ Assumptions'!$D$27*('🎛️ Assumptions'!$D$14/1000000))*(1-'🎛️ Assumptions'!$D$15)*'🎛️ Assumptions'!$D$10)) -> 40441.795 | F81: =F75*('🎛️ Assumptions'!$D$17*('🎛️ Assumptions'!$D$18*('🎛️ Assumptions'!$G$10/1000000)+'🎛️ Assumptions'!$D$19*('🎛️ Assumptions'!$G$13/1000000))*(1-'🎛️ Assumptions'!$D$15)*'🎛️ Assumptions'!$D$10*'🎛️ Assumptions'!$D$20)+F76*('🎛️ Assumptions'!$D$21*('🎛️ Assumptions'!$D$22*('🎛️ Assumptions'!$D$13/1000000)+'🎛️ Assumptions'!$D$23*('🎛️ Assumptions'!$D$14/1000000))*(1-'🎛️ Assumptions'!$D$15)*'🎛️ Assumptions'!$D$10)+F77*(('🎛️ Assumptions'!$D$24*('🎛️ Assumptions'!$D$22*('🎛️ Assumptions'!$D$13/1000000)+'🎛️ Assumptions'!$D$23*('🎛️ Assumptions'!$D$14/1000000))*(1-'🎛️ Assumptions'!$D$15)*'🎛️ Assumptions'!$D$10)+('🎛️ Assumptions'!$D$25*('🎛️ Assumptions'!$D$26*('🎛️ Assumptions'!$D$13/1000000)+'🎛️ Assumptions'!$D$27*('🎛️ Assumptions'!$D$14/1000000))*(1-'🎛️ Assumptions'!$D$15)*'🎛️ Assumptions'!$D$10))+F78*(('🎛️ Assumptions'!$D$28*('🎛️ Assumptions'!$D$22*('🎛️ Assumptions'!$D$13/1000000)+'🎛️ Assumptions'!$D$23*('🎛️ Assumptions'!$D$14/1000000))*(1-'🎛️ Assumptions'!$D$15)*'🎛️ Assumptions'!$D$10)+('🎛️ Assumptions'!$D$29*('🎛️ Assumptions'!$D$26*('🎛️ Assumptions'!$D$13/1000000)+'🎛️ Assumptions'!$D$27*('🎛️ Assumptions'!$D$14/1000000))*(1-'🎛️ Assumptions'!$D$15)*'🎛️ Assumptions'!$D$10)) -> 50814.606 | G81: =G75*('🎛️ Assumptions'!$D$17*('🎛️ Assumptions'!$D$18*('🎛️ Assumptions'!$G$10/1000000)+'🎛️ Assumptions'!$D$19*('🎛️ Assumptions'!$G$13/1000000))*(1-'🎛️ Assumptions'!$D$15)*'🎛️ Assumptions'!$D$10*'🎛️ Assumptions'!$D$20)+G76*('🎛️ Assumptions'!$D$21*('🎛️ Assumptions'!$D$22*('🎛️ Assumptions'!$D$13/1000000)+'🎛️ Assumptions'!$D$23*('🎛️ Assumptions'!$D$14/1000000))*(1-'🎛️ Assumptions'!$D$15)*'🎛️ Assumptions'!$D$10)+G77*(('🎛️ Assumptions'!$D$24*('🎛️ Assumptions'!$D$22*('🎛️ Assumptions'!$D$13/1000000)+'🎛️ Assumptions'!$D$23*('🎛️ Assumptions'!$D$14/1000000))*(1-'🎛️ Assumptions'!$D$15)*'🎛️ Assumptions'!$D$10)+('🎛️ Assumptions'!$D$25*('🎛️ Assumptions'!$D$26*('🎛️ Assumptions'!$D$13/1000000)+'🎛️ Assumptions'!$D$27*('🎛️ Assumptions'!$D$14/1000000))*(1-'🎛️ Assumptions'!$D$15)*'🎛️ Assumptions'!$D$10))+G78*(('🎛️ Assumptions'!$D$28*('🎛️ Assumptions'!$D$22*('🎛️ Assumptions'!$D$13/1000000)+'🎛️ Assumptions'!$D$23*('🎛️ Assumptions'!$D$14/1000000))*(1-'🎛️ Assumptions'!$D$15)*'🎛️ Assumptions'!$D$10)+('🎛️ Assumptions'!$D$29*('🎛️ Assumptions'!$D$26*('🎛️ Assumptions'!$D$13/1000000)+'🎛️ Assumptions'!$D$27*('🎛️ Assumptions'!$D$14/1000000))*(1-'🎛️ Assumptions'!$D$15)*'🎛️ Assumptions'!$D$10)) -> 60690.807 | H81: =H75*('🎛️ Assumptions'!$D$17*('🎛️ Assumptions'!$D$18*('🎛️ Assumptions'!$G$10/1000000)+'🎛️ Assumptions'!$D$19*('🎛️ Assumptions'!$G$13/1000000))*(1-'🎛️ Assumptions'!$D$15)*'🎛️ Assumptions'!$D$10*'🎛️ Assumptions'!$D$20)+H76*('🎛️ Assumptions'!$D$21*('🎛️ Assumptions'!$D$22*('🎛️ Assumptions'!$D$13/1000000)+'🎛️ Assumptions'!$D$23*('🎛️ Assumptions'!$D$14/1000000))*(1-'🎛️ Assumptions'!$D$15)*'🎛️ Assumptions'!$D$10)+H77*(('🎛️ Assumptions'!$D$24*('🎛️ Assumptions'!$D$22*('🎛️ Assumptions'!$D$13/1000000)+'🎛️ Assumptions'!$D$23*('🎛️ Assumptions'!$D$14/1000000))*(1-'🎛️ Assumptions'!$D$15)*'🎛️ Assumptions'!$D$10)+('🎛️ Assumptions'!$D$25*('🎛️ Assumptions'!$D$26*('🎛️ Assumptions'!$D$13/1000000)+'🎛️ Assumptions'!$D$27*('🎛️ Assumptions'!$D$14/1000000))*(1-'🎛️ Assumptions'!$D$15)*'🎛️ Assumptions'!$D$10))+H78*(('🎛️ Assumptions'!$D$28*('🎛️ Assumptions'!$D$22*('🎛️ Assumptions'!$D$13/1000000)+'🎛️ Assumptions'!$D$23*('🎛️ Assumptions'!$D$14/1000000))*(1-'🎛️ Assumptions'!$D$15)*'🎛️ Assumptions'!$D$10)+('🎛️ Assumptions'!$D$29*('🎛️ Assumptions'!$D$26*('🎛️ Assumptions'!$D$13/1000000)+'🎛️ Assumptions'!$D$27*('🎛️ Assumptions'!$D$14/1000000))*(1-'🎛️ Assumptions'!$D$15)*'🎛️ Assumptions'!$D$10)) -> 70091.227 | I81: =I75*('🎛️ Assumptions'!$D$17*('🎛️ Assumptions'!$D$18*('🎛️ Assumptions'!$G$10/1000000)+'🎛️ Assumptions'!$D$19*('🎛️ Assumptions'!$G$13/1000000))*(1-'🎛️ Assumptions'!$D$15)*'🎛️ Assumptions'!$D$10*'🎛️ Assumptions'!$D$20)+I76*('🎛️ Assumptions'!$D$21*('🎛️ Assumptions'!$D$22*('🎛️ Assumptions'!$D$13/1000000)+'🎛️ Assumptions'!$D$23*('🎛️ Assumptions'!$D$14/1000000))*(1-'🎛️ Assumptions'!$D$15)*'🎛️ Assumptions'!$D$10)+I77*(('🎛️ Assumptions'!$D$24*('🎛️ Assumptions'!$D$22*('🎛️ Assumptions'!$D$13/1000000)+'🎛️ Assumptions'!$D$23*('🎛️ Assumptions'!$D$14/1000000))*(1-'🎛️ Assumptions'!$D$15)*'🎛️ Assumptions'!$D$10)+('🎛️ Assumptions'!$D$25*('🎛️ Assumptions'!$D$26*('🎛️ Assumptions'!$D$13/1000000)+'🎛️ Assumptions'!$D$27*('🎛️ Assumptions'!$D$14/1000000))*(1-'🎛️ Assumptions'!$D$15)*'🎛️ Assumptions'!$D$10))+I78*(('🎛️ Assumptions'!$D$28*('🎛️ Assumptions'!$D$22*('🎛️ Assumptions'!$D$13/1000000)+'🎛️ Assumptions'!$D$23*('🎛️ Assumptions'!$D$14/1000000))*(1-'🎛️ Assumptions'!$D$15)*'🎛️ Assumptions'!$D$10)+('🎛️ Assumptions'!$D$29*('🎛️ Assumptions'!$D$26*('🎛️ Assumptions'!$D$13/1000000)+'🎛️ Assumptions'!$D$27*('🎛️ Assumptions'!$D$14/1000000))*(1-'🎛️ Assumptions'!$D$15)*'🎛️ Assumptions'!$D$10)) -> 79045.635 | ... Y81: =Y75*('🎛️ Assumptions'!$D$17*('🎛️ Assumptions'!$D$18*('🎛️ Assumptions'!$G$10/1000000)+'🎛️ Assumptions'!$D$19*('🎛️ Assumptions'!$G$13/1000000))*(1-'🎛️ Assumptions'!$D$15)*'🎛️ Assumptions'!$D$10*'🎛️ Assumptions'!$D$20)+Y76*('🎛️ Assumptions'!$D$21*('🎛️ Assumptions'!$D$22*('🎛️ Assumptions'!$D$13/1000000)+'🎛️ Assumptions'!$D$23*('🎛️ Assumptions'!$D$14/1000000))*(1-'🎛️ Assumptions'!$D$15)*'🎛️ Assumptions'!$D$10)+Y77*(('🎛️ Assumptions'!$D$24*('🎛️ Assumptions'!$D$22*('🎛️ Assumptions'!$D$13/1000000)+'🎛️ Assumptions'!$D$23*('🎛️ Assumptions'!$D$14/1000000))*(1-'🎛️ Assumptions'!$D$15)*'🎛️ Assumptions'!$D$10)+('🎛️ Assumptions'!$D$25*('🎛️ Assumptions'!$D$26*('🎛️ Assumptions'!$D$13/1000000)+'🎛️ Assumptions'!$D$27*('🎛️ Assumptions'!$D$14/1000000))*(1-'🎛️ Assumptions'!$D$15)*'🎛️ Assumptions'!$D$10))+Y78*(('🎛️ Assumptions'!$D$28*('🎛️ Assumptions'!$D$22*('🎛️ Assumptions'!$D$13/1000000)+'🎛️ Assumptions'!$D$23*('🎛️ Assumptions'!$D$14/1000000))*(1-'🎛️ Assumptions'!$D$15)*'🎛️ Assumptions'!$D$10)+('🎛️ Assumptions'!$D$29*('🎛️ Assumptions'!$D$26*('🎛️ Assumptions'!$D$13/1000000)+'🎛️ Assumptions'!$D$27*('🎛️ Assumptions'!$D$14/1000000))*(1-'🎛️ Assumptions'!$D$15)*'🎛️ Assumptions'!$D$10)) -> 192081.21
A82: Fixed Cost | B82: ='🎛️ Assumptions'!$D$40+'🎛️ Assumptions'!$D$42+'🎛️ Assumptions'!$D$44+'🎛️ Assumptions'!$D$46 -> 74000 | C82: ='🎛️ Assumptions'!$D$40+'🎛️ Assumptions'!$D$42+'🎛️ Assumptions'!$D$44+'🎛️ Assumptions'!$D$46 -> 74000 | D82: ='🎛️ Assumptions'!$D$40+'🎛️ Assumptions'!$D$42+'🎛️ Assumptions'!$D$44+'🎛️ Assumptions'!$D$46 -> 74000 | E82: ='🎛️ Assumptions'!$D$40+'🎛️ Assumptions'!$D$42+'🎛️ Assumptions'!$D$44+'🎛️ Assumptions'!$D$46 -> 74000 | F82: ='🎛️ Assumptions'!$D$40+'🎛️ Assumptions'!$D$42+'🎛️ Assumptions'!$D$44+'🎛️ Assumptions'!$D$46 -> 74000 | G82: ='🎛️ Assumptions'!$D$40+'🎛️ Assumptions'!$D$42+'🎛️ Assumptions'!$D$44+'🎛️ Assumptions'!$D$46 -> 74000 | H82: ='🎛️ Assumptions'!$D$40+'🎛️ Assumptions'!$D$42+'🎛️ Assumptions'!$D$44+'🎛️ Assumptions'!$D$46 -> 74000 | I82: ='🎛️ Assumptions'!$D$40+'🎛️ Assumptions'!$D$42+'🎛️ Assumptions'!$D$44+'🎛️ Assumptions'!$D$46 -> 74000 | ... M82: ='🎛️ Assumptions'!$D$40+'🎛️ Assumptions'!$D$42+'🎛️ Assumptions'!$D$44+'🎛️ Assumptions'!$D$46 -> 74000 | N82: ='🎛️ Assumptions'!$D$41+'🎛️ Assumptions'!$D$43+'🎛️ Assumptions'!$D$45+'🎛️ Assumptions'!$D$46 -> 103000 | O82: ='🎛️ Assumptions'!$D$41+'🎛️ Assumptions'!$D$43+'🎛️ Assumptions'!$D$45+'🎛️ Assumptions'!$D$46 -> 103000 | P82: ='🎛️ Assumptions'!$D$41+'🎛️ Assumptions'!$D$43+'🎛️ Assumptions'!$D$45+'🎛️ Assumptions'!$D$46 -> 103000 | Q82: ='🎛️ Assumptions'!$D$41+'🎛️ Assumptions'!$D$43+'🎛️ Assumptions'!$D$45+'🎛️ Assumptions'!$D$46 -> 103000 | R82: ='🎛️ Assumptions'!$D$41+'🎛️ Assumptions'!$D$43+'🎛️ Assumptions'!$D$45+'🎛️ Assumptions'!$D$46 -> 103000 | S82: ='🎛️ Assumptions'!$D$41+'🎛️ Assumptions'!$D$43+'🎛️ Assumptions'!$D$45+'🎛️ Assumptions'!$D$46 -> 103000 | T82: ='🎛️ Assumptions'!$D$41+'🎛️ Assumptions'!$D$43+'🎛️ Assumptions'!$D$45+'🎛️ Assumptions'!$D$46 -> 103000 | U82: ='🎛️ Assumptions'!$D$41+'🎛️ Assumptions'!$D$43+'🎛️ Assumptions'!$D$45+'🎛️ Assumptions'!$D$46 -> 103000 | ... Y82: ='🎛️ Assumptions'!$D$41+'🎛️ Assumptions'!$D$43+'🎛️ Assumptions'!$D$45+'🎛️ Assumptions'!$D$46 -> 103000
A83: Taxes | B83: =B80*'🎛️ Assumptions'!$D$70 -> 5034 | C83: =C80*'🎛️ Assumptions'!$D$70 -> 14864.835 | D83: =D80*'🎛️ Assumptions'!$D$70 -> 24207.405 | E83: =E80*'🎛️ Assumptions'!$D$70 -> 33107.535 | F83: =F80*'🎛️ Assumptions'!$D$70 -> 41589.63 | G83: =G80*'🎛️ Assumptions'!$D$70 -> 49661.175 | H83: =H80*'🎛️ Assumptions'!$D$70 -> 57342.075 | I83: =I80*'🎛️ Assumptions'!$D$70 -> 64653.75 | ... Y83: =Y80*'🎛️ Assumptions'!$D$70 -> 156525.32
A84: Monthly Result | B84: =B80-B81-B82-B83 -> -51619.986 | C84: =C80-C81-C82-C83 -> -7917.7741 | D84: =D80-D81-D82-D83 -> 33611.266 | E84: =E80-E81-E82-E83 -> 73167.57 | F84: =F80-F81-F82-F83 -> 110859.96 | G84: =G80-G81-G82-G83 -> 146722.52 | H84: =H80-H81-H82-H83 -> 180847.2 | I84: =I80-I81-I82-I83 -> 213325.61 | ... Y84: =Y80-Y81-Y82-Y83 -> 591895.57
A86: Cons CF (IRR helper) | B86: =-'🎛️ Assumptions'!$B$58 -> -1000000 | C86: =B60 -> -39536.271 | D86: =C60 -> -17284.098 | E86: =D60 -> 3583.3807 | F86: =E60 -> 23141.333 | G86: =F60 -> 41561.169 | H86: =G60 -> 58862.787 | I86: =H60 -> 75087.159 | J86: =I60 -> 90364.723 | ... Z86: =Y60 -> 262768.99
A87: Base CF (IRR helper) | B87: =-'🎛️ Assumptions'!$B$58 -> -1000000 | C87: =B72 -> -43052.448 | D87: =C72 -> -9309.0108 | E87: =D72 -> 22497.593 | F87: =E72 -> 52481.517 | G87: =F72 -> 80716.499 | H87: =G72 -> 107353.56 | I87: =H72 -> 132520.25 | J87: =I72 -> 156240.04 | ... Z87: =Y72 -> 422131.47
A88: Optim CF (IRR helper) | B88: =-'🎛️ Assumptions'!$B$58 -> -1000000 | C88: =B84 -> -51619.986 | D88: =C84 -> -7917.7741 | E88: =D84 -> 33611.266 | F88: =E84 -> 73167.57 | G88: =F84 -> 110859.96 | H88: =G84 -> 146722.52 | I88: =H84 -> 180847.2 | J88: =I84 -> 213325.61 | ... Z88: =Y84 -> 591895.57
