Workbook

Sheet 🚀 Dashboard Investidor
A2: AUTONOMA · DASHBOARD
A3: Asset Light SaaS · Brasil → LATAM · 100% Sonnet 4.6 · Projeto de 24 meses com valuation M24
A5: CENÁRIO ATIVO: | B5: ='🔧 Cenário Ativo'!B2 | C5: ← altere em '🔧 Cenário Ativo'!B2 · Opções: Conservador / Base / Otimista
A7: PAYBACK CAC | C7: VALUATION M24 | E7: RECEITA ACUM 24m | G7: BREAKEVEN | I7: RETORNO ANJO
A8: ='🔧 Cenário Ativo'!B54 | C8: =IF('🔧 Cenário Ativo'!B2="Conservador",'📊 Resumo Cenários'!B21,IF('🔧 Cenário Ativo'!B2="Base",'📊 Resumo Cenários'!C21,'📊 Resumo Cenários'!D21)) | E8: =IF('🔧 Cenário Ativo'!B2="Conservador",'📊 Resumo Cenários'!B19,IF('🔧 Cenário Ativo'!B2="Base",'📊 Resumo Cenários'!C19,'📊 Resumo Cenários'!D19)) | G8: {=IFERROR("M"&MATCH(TRUE,INDEX('📊 Base Mensal'!C25:Z25>0,0),0),">24m")} | I8: =C8*'🎛️ Premissas'!B56
A9: tempo para recuperar CAC | C9: Receita acum 24m × múltiplo cenário | E9: soma MRR M1–M24 | G9: resultado acum. > 0 | I9: valor da fatia % sobre aporte
A11: FLUXO DE CAIXA ACUMULADO | F11: BREAKEVEN
A29: MRR & ASSINANTES | F29: VALUATION 3 CENARIOS
A47: UNIT ECONOMICS · CENARIO ATIVO
A49: CAC | C49: LTV Essencial | E49: LTV / CAC | G49: CHURN MENSAL | I49: MARGEM M24
A50: ='🔧 Cenário Ativo'!B44 | C50: ='🔧 Cenário Ativo'!B52 | E50: ='🔧 Cenário Ativo'!B53 | G50: ='🔧 Cenário Ativo'!B32 | I50: ='📊 Base Mensal'!Z26
A51: full-loaded | C51: margem × vida média | E51: =IF(E50>=8,"✅ top quartile",IF(E50>=3,"✅ saudável","⚠️ rever CAC")) | G51: anual ~46% | I51: bruta sobre MRR
A52: Obs.: Este estudo não configura convite ou promessa de investimento. Valores projetados com base em premissas controláveis em 🎛️ Premissas e 🔧 Cenário Ativo.
A53: AutoNoma © 2025 · Dashboard dinâmico · Todos os valores recalculam ao mudar o cenário em '🔧 Cenário Ativo'!B2
L76: Mês | M76: MRR | N76: Pagantes | O76: Free | P76: Resultado | Q76: Acumulado | R76: Essencial | S76: Autônoma | T76: Livre | U76: API Total | V76: Custo Fixo | W76: Margem%
L77: M01 | M77: ='📊 Base Mensal'!C11 | N77: ='📊 Base Mensal'!C9 | O77: ='📊 Base Mensal'!C5 | P77: ='📊 Base Mensal'!C24 | Q77: ='📊 Base Mensal'!C25 | R77: ='📊 Base Mensal'!C6 | S77: ='📊 Base Mensal'!C7 | T77: ='📊 Base Mensal'!C8 | U77: ='📊 Base Mensal'!C18 | V77: ='📊 Base Mensal'!C20 | W77: ='📊 Base Mensal'!C26
L78: M02 | M78: ='📊 Base Mensal'!D11 | N78: ='📊 Base Mensal'!D9 | O78: ='📊 Base Mensal'!D5 | P78: ='📊 Base Mensal'!D24 | Q78: ='📊 Base Mensal'!D25 | R78: ='📊 Base Mensal'!D6 | S78: ='📊 Base Mensal'!D7 | T78: ='📊 Base Mensal'!D8 | U78: ='📊 Base Mensal'!D18 | V78: ='📊 Base Mensal'!D20 | W78: ='📊 Base Mensal'!D26
L79: M03 | M79: ='📊 Base Mensal'!E11 | N79: ='📊 Base Mensal'!E9 | O79: ='📊 Base Mensal'!E5 | P79: ='📊 Base Mensal'!E24 | Q79: ='📊 Base Mensal'!E25 | R79: ='📊 Base Mensal'!E6 | S79: ='📊 Base Mensal'!E7 | T79: ='📊 Base Mensal'!E8 | U79: ='📊 Base Mensal'!E18 | V79: ='📊 Base Mensal'!E20 | W79: ='📊 Base Mensal'!E26
L80: M04 | M80: ='📊 Base Mensal'!F11 | N80: ='📊 Base Mensal'!F9 | O80: ='📊 Base Mensal'!F5 | P80: ='📊 Base Mensal'!F24 | Q80: ='📊 Base Mensal'!F25 | R80: ='📊 Base Mensal'!F6 | S80: ='📊 Base Mensal'!F7 | T80: ='📊 Base Mensal'!F8 | U80: ='📊 Base Mensal'!F18 | V80: ='📊 Base Mensal'!F20 | W80: ='📊 Base Mensal'!F26
L81: M05 | M81: ='📊 Base Mensal'!G11 | N81: ='📊 Base Mensal'!G9 | O81: ='📊 Base Mensal'!G5 | P81: ='📊 Base Mensal'!G24 | Q81: ='📊 Base Mensal'!G25 | R81: ='📊 Base Mensal'!G6 | S81: ='📊 Base Mensal'!G7 | T81: ='📊 Base Mensal'!G8 | U81: ='📊 Base Mensal'!G18 | V81: ='📊 Base Mensal'!G20 | W81: ='📊 Base Mensal'!G26
L82: M06 | M82: ='📊 Base Mensal'!H11 | N82: ='📊 Base Mensal'!H9 | O82: ='📊 Base Mensal'!H5 | P82: ='📊 Base Mensal'!H24 | Q82: ='📊 Base Mensal'!H25 | R82: ='📊 Base Mensal'!H6 | S82: ='📊 Base Mensal'!H7 | T82: ='📊 Base Mensal'!H8 | U82: ='📊 Base Mensal'!H18 | V82: ='📊 Base Mensal'!H20 | W82: ='📊 Base Mensal'!H26
L83: M07 | M83: ='📊 Base Mensal'!I11 | N83: ='📊 Base Mensal'!I9 | O83: ='📊 Base Mensal'!I5 | P83: ='📊 Base Mensal'!I24 | Q83: ='📊 Base Mensal'!I25 | R83: ='📊 Base Mensal'!I6 | S83: ='📊 Base Mensal'!I7 | T83: ='📊 Base Mensal'!I8 | U83: ='📊 Base Mensal'!I18 | V83: ='📊 Base Mensal'!I20 | W83: ='📊 Base Mensal'!I26
L84: M08 | M84: ='📊 Base Mensal'!J11 | N84: ='📊 Base Mensal'!J9 | O84: ='📊 Base Mensal'!J5 | P84: ='📊 Base Mensal'!J24 | Q84: ='📊 Base Mensal'!J25 | R84: ='📊 Base Mensal'!J6 | S84: ='📊 Base Mensal'!J7 | T84: ='📊 Base Mensal'!J8 | U84: ='📊 Base Mensal'!J18 | V84: ='📊 Base Mensal'!J20 | W84: ='📊 Base Mensal'!J26
L85: M09 | M85: ='📊 Base Mensal'!K11 | N85: ='📊 Base Mensal'!K9 | O85: ='📊 Base Mensal'!K5 | P85: ='📊 Base Mensal'!K24 | Q85: ='📊 Base Mensal'!K25 | R85: ='📊 Base Mensal'!K6 | S85: ='📊 Base Mensal'!K7 | T85: ='📊 Base Mensal'!K8 | U85: ='📊 Base Mensal'!K18 | V85: ='📊 Base Mensal'!K20 | W85: ='📊 Base Mensal'!K26
L86: M10 | M86: ='📊 Base Mensal'!L11 | N86: ='📊 Base Mensal'!L9 | O86: ='📊 Base Mensal'!L5 | P86: ='📊 Base Mensal'!L24 | Q86: ='📊 Base Mensal'!L25 | R86: ='📊 Base Mensal'!L6 | S86: ='📊 Base Mensal'!L7 | T86: ='📊 Base Mensal'!L8 | U86: ='📊 Base Mensal'!L18 | V86: ='📊 Base Mensal'!L20 | W86: ='📊 Base Mensal'!L26
L87: M11 | M87: ='📊 Base Mensal'!M11 | N87: ='📊 Base Mensal'!M9 | O87: ='📊 Base Mensal'!M5 | P87: ='📊 Base Mensal'!M24 | Q87: ='📊 Base Mensal'!M25 | R87: ='📊 Base Mensal'!M6 | S87: ='📊 Base Mensal'!M7 | T87: ='📊 Base Mensal'!M8 | U87: ='📊 Base Mensal'!M18 | V87: ='📊 Base Mensal'!M20 | W87: ='📊 Base Mensal'!M26
L88: M12 | M88: ='📊 Base Mensal'!N11 | N88: ='📊 Base Mensal'!N9 | O88: ='📊 Base Mensal'!N5 | P88: ='📊 Base Mensal'!N24 | Q88: ='📊 Base Mensal'!N25 | R88: ='📊 Base Mensal'!N6 | S88: ='📊 Base Mensal'!N7 | T88: ='📊 Base Mensal'!N8 | U88: ='📊 Base Mensal'!N18 | V88: ='📊 Base Mensal'!N20 | W88: ='📊 Base Mensal'!N26
L89: M13 | M89: ='📊 Base Mensal'!O11 | N89: ='📊 Base Mensal'!O9 | O89: ='📊 Base Mensal'!O5 | P89: ='📊 Base Mensal'!O24 | Q89: ='📊 Base Mensal'!O25 | R89: ='📊 Base Mensal'!O6 | S89: ='📊 Base Mensal'!O7 | T89: ='📊 Base Mensal'!O8 | U89: ='📊 Base Mensal'!O18 | V89: ='📊 Base Mensal'!O20 | W89: ='📊 Base Mensal'!O26
L90: M14 | M90: ='📊 Base Mensal'!P11 | N90: ='📊 Base Mensal'!P9 | O90: ='📊 Base Mensal'!P5 | P90: ='📊 Base Mensal'!P24 | Q90: ='📊 Base Mensal'!P25 | R90: ='📊 Base Mensal'!P6 | S90: ='📊 Base Mensal'!P7 | T90: ='📊 Base Mensal'!P8 | U90: ='📊 Base Mensal'!P18 | V90: ='📊 Base Mensal'!P20 | W90: ='📊 Base Mensal'!P26
L91: M15 | M91: ='📊 Base Mensal'!Q11 | N91: ='📊 Base Mensal'!Q9 | O91: ='📊 Base Mensal'!Q5 | P91: ='📊 Base Mensal'!Q24 | Q91: ='📊 Base Mensal'!Q25 | R91: ='📊 Base Mensal'!Q6 | S91: ='📊 Base Mensal'!Q7 | T91: ='📊 Base Mensal'!Q8 | U91: ='📊 Base Mensal'!Q18 | V91: ='📊 Base Mensal'!Q20 | W91: ='📊 Base Mensal'!Q26
L92: M16 | M92: ='📊 Base Mensal'!R11 | N92: ='📊 Base Mensal'!R9 | O92: ='📊 Base Mensal'!R5 | P92: ='📊 Base Mensal'!R24 | Q92: ='📊 Base Mensal'!R25 | R92: ='📊 Base Mensal'!R6 | S92: ='📊 Base Mensal'!R7 | T92: ='📊 Base Mensal'!R8 | U92: ='📊 Base Mensal'!R18 | V92: ='📊 Base Mensal'!R20 | W92: ='📊 Base Mensal'!R26
L93: M17 | M93: ='📊 Base Mensal'!S11 | N93: ='📊 Base Mensal'!S9 | O93: ='📊 Base Mensal'!S5 | P93: ='📊 Base Mensal'!S24 | Q93: ='📊 Base Mensal'!S25 | R93: ='📊 Base Mensal'!S6 | S93: ='📊 Base Mensal'!S7 | T93: ='📊 Base Mensal'!S8 | U93: ='📊 Base Mensal'!S18 | V93: ='📊 Base Mensal'!S20 | W93: ='📊 Base Mensal'!S26
L94: M18 | M94: ='📊 Base Mensal'!T11 | N94: ='📊 Base Mensal'!T9 | O94: ='📊 Base Mensal'!T5 | P94: ='📊 Base Mensal'!T24 | Q94: ='📊 Base Mensal'!T25 | R94: ='📊 Base Mensal'!T6 | S94: ='📊 Base Mensal'!T7 | T94: ='📊 Base Mensal'!T8 | U94: ='📊 Base Mensal'!T18 | V94: ='📊 Base Mensal'!T20 | W94: ='📊 Base Mensal'!T26
L95: M19 | M95: ='📊 Base Mensal'!U11 | N95: ='📊 Base Mensal'!U9 | O95: ='📊 Base Mensal'!U5 | P95: ='📊 Base Mensal'!U24 | Q95: ='📊 Base Mensal'!U25 | R95: ='📊 Base Mensal'!U6 | S95: ='📊 Base Mensal'!U7 | T95: ='📊 Base Mensal'!U8 | U95: ='📊 Base Mensal'!U18 | V95: ='📊 Base Mensal'!U20 | W95: ='📊 Base Mensal'!U26
L96: M20 | M96: ='📊 Base Mensal'!V11 | N96: ='📊 Base Mensal'!V9 | O96: ='📊 Base Mensal'!V5 | P96: ='📊 Base Mensal'!V24 | Q96: ='📊 Base Mensal'!V25 | R96: ='📊 Base Mensal'!V6 | S96: ='📊 Base Mensal'!V7 | T96: ='📊 Base Mensal'!V8 | U96: ='📊 Base Mensal'!V18 | V96: ='📊 Base Mensal'!V20 | W96: ='📊 Base Mensal'!V26
L97: M21 | M97: ='📊 Base Mensal'!W11 | N97: ='📊 Base Mensal'!W9 | O97: ='📊 Base Mensal'!W5 | P97: ='📊 Base Mensal'!W24 | Q97: ='📊 Base Mensal'!W25 | R97: ='📊 Base Mensal'!W6 | S97: ='📊 Base Mensal'!W7 | T97: ='📊 Base Mensal'!W8 | U97: ='📊 Base Mensal'!W18 | V97: ='📊 Base Mensal'!W20 | W97: ='📊 Base Mensal'!W26
L98: M22 | M98: ='📊 Base Mensal'!X11 | N98: ='📊 Base Mensal'!X9 | O98: ='📊 Base Mensal'!X5 | P98: ='📊 Base Mensal'!X24 | Q98: ='📊 Base Mensal'!X25 | R98: ='📊 Base Mensal'!X6 | S98: ='📊 Base Mensal'!X7 | T98: ='📊 Base Mensal'!X8 | U98: ='📊 Base Mensal'!X18 | V98: ='📊 Base Mensal'!X20 | W98: ='📊 Base Mensal'!X26
L99: M23 | M99: ='📊 Base Mensal'!Y11 | N99: ='📊 Base Mensal'!Y9 | O99: ='📊 Base Mensal'!Y5 | P99: ='📊 Base Mensal'!Y24 | Q99: ='📊 Base Mensal'!Y25 | R99: ='📊 Base Mensal'!Y6 | S99: ='📊 Base Mensal'!Y7 | T99: ='📊 Base Mensal'!Y8 | U99: ='📊 Base Mensal'!Y18 | V99: ='📊 Base Mensal'!Y20 | W99: ='📊 Base Mensal'!Y26
L100: M24 | M100: ='📊 Base Mensal'!Z11 | N100: ='📊 Base Mensal'!Z9 | O100: ='📊 Base Mensal'!Z5 | P100: ='📊 Base Mensal'!Z24 | Q100: ='📊 Base Mensal'!Z25 | R100: ='📊 Base Mensal'!Z6 | S100: ='📊 Base Mensal'!Z7 | T100: ='📊 Base Mensal'!Z8 | U100: ='📊 Base Mensal'!Z18 | V100: ='📊 Base Mensal'!Z20 | W100: ='📊 Base Mensal'!Z26
L102: Cenário | M102: Aporte R$5M | N102: Valuation 100% M24 | O102: Retorno Anjo (49%)
L103: Conservador | M103: ='🎛️ Premissas'!$B$55/1000000 | N103: ='📊 Resumo Cenários'!B21/1000000 | O103: ='📊 Resumo Cenários'!B22/1000000
L104: Base | M104: ='🎛️ Premissas'!$B$55/1000000 | N104: ='📊 Resumo Cenários'!C21/1000000 | O104: ='📊 Resumo Cenários'!C22/1000000
L105: Otimista | M105: ='🎛️ Premissas'!$B$55/1000000 | N105: ='📊 Resumo Cenários'!D21/1000000 | O105: ='📊 Resumo Cenários'!D22/1000000

Sheet 🔧 Cenário Ativo
A1: AutoNoma · Seletor de Cenário · Controler
A2: ▶ CENÁRIO ATIVO ◀ (altere aqui o modelo) | B2: Base | C2: ← Selecione: Conservador / Base / Otimista
A3: Coluna das premissas (uso interno — não edite) | B3: =MATCH(B2,{"Conservador","Base","Otimista"},0)+1
A4: Premissas resolvidas para o cenário selecionado
A5: ── PREÇOS ──
A6: Preço Essencial | B6: =INDEX('🎛️ Premissas'!B5:D5,1,MATCH($B$2,{"Conservador","Base","Otimista"},0)) | C6: ← Premissas!Preço Essencial (linha 5)
A7: Preço Autônoma | B7: =INDEX('🎛️ Premissas'!B6:D6,1,MATCH($B$2,{"Conservador","Base","Otimista"},0)) | C7: ← Premissas!Preço Autônoma (linha 6)
A8: Preço Livre | B8: =INDEX('🎛️ Premissas'!B7:D7,1,MATCH($B$2,{"Conservador","Base","Otimista"},0)) | C8: ← Premissas!Preço Livre (linha 7)
A9: ── API ──
A10: Câmbio USD/BRL | B10: =INDEX('🎛️ Premissas'!B9:D9,1,MATCH($B$2,{"Conservador","Base","Otimista"},0)) | C10: ← Premissas!Câmbio USD/BRL (linha 9)
A11: Sonnet Input $/MTok | B11: =INDEX('🎛️ Premissas'!B10:D10,1,MATCH($B$2,{"Conservador","Base","Otimista"},0)) | C11: ← Premissas!Sonnet 4.6 Input ($/MTok) (linha 10)
A12: Sonnet Output $/MTok | B12: =INDEX('🎛️ Premissas'!B11:D11,1,MATCH($B$2,{"Conservador","Base","Otimista"},0)) | C12: ← Premissas!Sonnet 4.6 Output ($/MTok) (linha 11)
A13: Desconto Caching | B13: =INDEX('🎛️ Premissas'!B12:D12,1,MATCH($B$2,{"Conservador","Base","Otimista"},0)) | C13: ← Premissas!Desconto Prompt Caching (%) (linha 12)
A14: ── USO ──
A15: Free: interações/mês | B15: =INDEX('🎛️ Premissas'!B14:D14,1,MATCH($B$2,{"Conservador","Base","Otimista"},0)) | C15: ← Premissas!Free: interações/mês (LIMITE) (linha 14)
A16: Free: tokens input | B16: =INDEX('🎛️ Premissas'!B15:D15,1,MATCH($B$2,{"Conservador","Base","Otimista"},0)) | C16: ← Premissas!Free: tokens input/interação (linha 15)
A17: Free: tokens output | B17: =INDEX('🎛️ Premissas'!B16:D16,1,MATCH($B$2,{"Conservador","Base","Otimista"},0)) | C17: ← Premissas!Free: tokens output/interação (linha 16)
A18: Free: % ativas/mês | B18: =INDEX('🎛️ Premissas'!B17:D17,1,MATCH($B$2,{"Conservador","Base","Otimista"},0)) | C18: ← Premissas!Free: % usuárias ativas/mês (linha 17)
A19: Essencial: interações/mês | B19: =INDEX('🎛️ Premissas'!B18:D18,1,MATCH($B$2,{"Conservador","Base","Otimista"},0)) | C19: ← Premissas!Essencial: interações chat/mês (linha 18)
A20: Essencial: tokens input | B20: =INDEX('🎛️ Premissas'!B19:D19,1,MATCH($B$2,{"Conservador","Base","Otimista"},0)) | C20: ← Premissas!Essencial: tokens input/interação (linha 19)
A21: Essencial: tokens output | B21: =INDEX('🎛️ Premissas'!B20:D20,1,MATCH($B$2,{"Conservador","Base","Otimista"},0)) | C21: ← Premissas!Essencial: tokens output/interação (linha 20)
A22: Autônoma: sessões agente/mês | B22: =INDEX('🎛️ Premissas'!B22:D22,1,MATCH($B$2,{"Conservador","Base","Otimista"},0)) | C22: ← Premissas!Autônoma: sessões agente/mês (linha 22)
A23: Autônoma: tokens input/sessão | B23: =INDEX('🎛️ Premissas'!B23:D23,1,MATCH($B$2,{"Conservador","Base","Otimista"},0)) | C23: ← Premissas!Autônoma: tokens input/sessão agente (linha 23)
A24: Autônoma: tokens output/sessão | B24: =INDEX('🎛️ Premissas'!B24:D24,1,MATCH($B$2,{"Conservador","Base","Otimista"},0)) | C24: ← Premissas!Autônoma: tokens output/sessão agente (linha 24)
A25: Livre: sessões totais/mês | B25: =INDEX('🎛️ Premissas'!B26:D26,1,MATCH($B$2,{"Conservador","Base","Otimista"},0)) | C25: ← Premissas!Livre: sessões totais agentes/mês (linha 26)
A26: ── CRESCIMENTO ──
A27: Free leads M1–12 | B27: =INDEX('🎛️ Premissas'!B28:D28,1,MATCH($B$2,{"Conservador","Base","Otimista"},0)) | C27: ← Premissas!Crescimento Free M1–12 (leads/mês) (linha 28)
A28: Free leads M13–24 | B28: =INDEX('🎛️ Premissas'!B29:D29,1,MATCH($B$2,{"Conservador","Base","Otimista"},0)) | C28: ← Premissas!Crescimento Free M13–24 (leads/mês) (linha 29)
A29: Conv. Free→Essencial | B29: =INDEX('🎛️ Premissas'!B30:D30,1,MATCH($B$2,{"Conservador","Base","Otimista"},0)) | C29: ← Premissas!Conversão Free → Essencial (%) (linha 31)
A30: Conv. Free→Autônoma | B30: =INDEX('🎛️ Premissas'!B31:D31,1,MATCH($B$2,{"Conservador","Base","Otimista"},0)) | C30: ← Premissas!Conversão Free → Autônoma (%) (linha 32)
A31: Conv. Free→Livre | B31: =INDEX('🎛️ Premissas'!B32:D32,1,MATCH($B$2,{"Conservador","Base","Otimista"},0)) | C31: ← Premissas!Conversão Free → Livre (%) (linha 33)
A32: Churn Essencial/mês | B32: =INDEX('🎛️ Premissas'!B33:D33,1,MATCH($B$2,{"Conservador","Base","Otimista"},0)) | C32: ← Premissas!Churn mensal Essencial (linha 34)
A33: Churn Autônoma/mês | B33: =INDEX('🎛️ Premissas'!B34:D34,1,MATCH($B$2,{"Conservador","Base","Otimista"},0)) | C33: ← Premissas!Churn mensal Autônoma (linha 35)
A34: Churn Livre/mês | B34: =INDEX('🎛️ Premissas'!B35:D35,1,MATCH($B$2,{"Conservador","Base","Otimista"},0)) | C34: ← Premissas!Churn mensal Livre (linha 36)
A35: ── CUSTO FIXO ──
A36: Equipe Ano 1 | B36: =INDEX('🎛️ Premissas'!B37:D37,1,MATCH($B$2,{"Conservador","Base","Otimista"},0)) | C36: ← Premissas!Equipe Ano 1 (média/mês) (linha 38)
A37: Equipe Ano 2 | B37: =INDEX('🎛️ Premissas'!B38:D38,1,MATCH($B$2,{"Conservador","Base","Otimista"},0)) | C37: ← Premissas!Equipe Ano 2 (média/mês) (linha 39)
A38: Infra Ano 1 | B38: =INDEX('🎛️ Premissas'!B39:D39,1,MATCH($B$2,{"Conservador","Base","Otimista"},0)) | C38: ← Premissas!Infraestrutura Ano 1 (linha 41)
A39: Infra Ano 2 | B39: =INDEX('🎛️ Premissas'!B40:D40,1,MATCH($B$2,{"Conservador","Base","Otimista"},0)) | C39: ← Premissas!Infraestrutura Ano 2 (linha 42)
A40: Marketing Ano 1 | B40: =INDEX('🎛️ Premissas'!B41:D41,1,MATCH($B$2,{"Conservador","Base","Otimista"},0)) | C40: ← Premissas!Marketing base Ano 1 (linha 44)
A41: Marketing Ano 2 | B41: =INDEX('🎛️ Premissas'!B42:D42,1,MATCH($B$2,{"Conservador","Base","Otimista"},0)) | C41: ← Premissas!Marketing base Ano 2 (linha 45)
A42: Outros | B42: =INDEX('🎛️ Premissas'!B43:D43,1,MATCH($B$2,{"Conservador","Base","Otimista"},0)) | C42: ← Premissas!Outros (jurídico, contab, misc.) (linha 47)
A43: ── UNIT ECONOMICS ──
A44: CAC full-loaded | B44: =INDEX('🎛️ Premissas'!B45:D45,1,MATCH($B$2,{"Conservador","Base","Otimista"},0)) | C44: ← Premissas!CAC real full-loaded (R$) (linha 49)
A45: % aquisição via paid | B45: =INDEX('🎛️ Premissas'!B47:D47,1,MATCH($B$2,{"Conservador","Base","Otimista"},0)) | C45: ← Premissas!% aquisição via paid (linha 51)
A46: ── VALUATION ──
A47: Múltiplo ARR M18 | B47: =INDEX('🎛️ Premissas'!B49:D49,1,MATCH($B$2,{"Conservador","Base","Otimista"},0)) | C47: ← Premissas!Múltiplo ARR Série A (× ARR) (linha 53)
A48: UNIT ECONOMICS CALCULADOS (helpers)
A49: Custo API por Essencial / mês | B49: =B19*(B20/1000000*B11+B21/1000000*B12)*(1-B13)*B10 | C49: ARPU cobre custo API?
A50: Margem Unitária Essencial / mês | B50: =B6-B49 | C50: Preço − Custo API (contribuição)
A51: Vida média Essencial (meses) | B51: 15 | C51: 1 ÷ churn mensal
A52: LTV Essencial | B52: =B50*B51 | C52: Margem × vida média
A53: LTV / CAC | B53: =IFERROR(B52/B44,0) | C53: ≥3× ok · ≥8× top quartile
A54: Payback CAC (meses) | B54: =IFERROR(B44/B50,0) | C54: CAC ÷ margem mensal · <12m = excelente
A55: IMPOSTOS
A56: Alíquota imposto/receita | B56: =IF($B$2="Conservador",'🎛️ Premissas'!B67,IF($B$2="Base",'🎛️ Premissas'!C67,'🎛️ Premissas'!D67)) | C56: ← Premissas!Alíquota (linha 67)

Sheet 🎛️ Premissas
A1: AutoNoma · Premissas · Fonte Única de Verdade · 100% Sonnet 4.6
A2: Azul = Input editável | B2: Preto = Fórmula | C2: Verde = Link cross-sheet
A3: PARAMETRO | B3: Conservador | C3: Base (padrão) | D3: Otimista | E3: UNIDADE/NOTA
A4: 1 · PREÇOS DOS PLANOS (R$/mês)
A5: Preço Essencial | B5: 39.9 | C5: 49.9 | D5: 49.9 | E5: R$/mês · + uso esporadico agente
A6: Preço Autônoma | B6: 59.9 | C6: 59.9 | D6: 62.9 | E6: R$/mês · chat + 1 agente
A7: Preço Livre | B7: 79.9 | C7: 79.9 | D7: 79.9 | E7: R$/mês · chat + 2 agentes
A8: 2 · CUSTO API ANTHROPIC (1 semestre 2026)
A9: Câmbio USD/BRL | B9: 5.3 | C9: 5.3 | D9: 5.3 | E9: R$ por USD
A10: Sonnet 4.6 Input ($/MTok) | B10: 3 | C10: 3 | D10: 3 | E10: USD — oficial Anthropic
A11: Sonnet 4.6 Output ($/MTok) | B11: 15 | C11: 15 | D11: 15 | E11: USD — oficial Anthropic
A12: Desconto Prompt Caching (%) | B12: 0.35 | C12: 0.4 | D12: 0.45 | E12: % redução no bloco fixo
A13: 3 · USO POR PLANO — 100% SONNET 4.6
A14: Free: interações/mês (LIMITE) | B14: 50 | C14: 50 | D14: 50 | E14: Sonnet · teto produto
A15: Free: tokens input/interação | B15: 900 | C15: 900 | D15: 900 | E15: inclui system prompt cacheado
A16: Free: tokens output/interação | B16: 450 | C16: 450 | D16: 450 | E16: resposta orientada
A17: Free: % usuárias ativas/mês | B17: 0.5 | C17: 0.5 | D17: 0.5 | E17: % do cadastro que usa no mês
A18: Essencial: interações chat/mês | B18: 120 | C18: 140 | D18: 180 | E18: ilimitado prático · 20 dias × uso
A19: Essencial: tokens input/interação | B19: 1200 | C19: 1400 | D19: 1800 | E19: contexto Noma + memória
A20: Essencial: tokens output/interação | B20: 700 | C20: 700 | D20: 700 | E20: resposta + ação autônoma
A21: Autônoma: chat (= Essencial) | B21: 140 | C21: 140 | D21: 140 | E21: chat ilimitado Sonnet
A22: Autônoma: sessões agente/mês | B22: 35 | C22: 45 | D22: 60 | E22: sessões profundas com 1 agente
A23: Autônoma: tokens input/sessão agente | B23: 3000 | C23: 3000 | D23: 3000 | E23: contexto resolução + memória
A24: Autônoma: tokens output/sessão agente | B24: 1800 | C24: 1800 | D24: 1800 | E24: resolução completa + confirmação
A25: Livre: chat (= Essencial) | B25: 140 | C25: 140 | D25: 140 | E25: chat ilimitado Sonnet
A26: Livre: sessões totais agentes/mês | B26: 60 | C26: 80 | D26: 100 | E26: 2 agentes · mais que Autônoma
A27: 4 · CRESCIMENTO DA BASE
A28: Crescimento Free M1–12 (leads/mês) | B28: 3000 | C28: 3500 | D28: 4000 | E28: cadastros orgânicos+viral+paid
A29: Crescimento Free M13–24 (leads/mês) | B29: 3500 | C29: 4000 | D29: 4500 | E29: escala Brasil
A30: Conversão Free → Essencial (%) | B30: 0.07 | C30: 0.08 | D30: 0.1 | E30: % base Free que vira assinante
A31: Conversão Free → Autônoma (%) | B31: 0.03 | C31: 0.04 | D31: 0.05 | E31: % Essenciais que sobem
A32: Conversão Free → Livre (%) | B32: 0.01 | C32: 0.02 | D32: 0.03 | E32: % Autônomas que sobem
A33: Churn mensal Essencial | B33: 0.05 | C33: 0.05 | D33: 0.05 | E33: % cancela por mês
A34: Churn mensal Autônoma | B34: 0.04 | C34: 0.04 | D34: 0.03 | E34: % cancela por mês · agente = lock-in
A35: Churn mensal Livre | B35: 0.02 | C35: 0.02 | D35: 0.02 | E35: % cancela · 2 agentes = máximo lock-in
A36: 5 · CUSTO FIXO MENSAL (R$)
A37: Equipe Ano 1 (média/mês) | B37: 40000 | C37: 45000 | D37: 50000 | E37: devs+CS+pró-labore fundadores
A38: Equipe Ano 2 (média/mês) | B38: 50000 | C38: 60000 | D38: 70000 | E38: expansão de time
A39: Infraestrutura Ano 1 | B39: 5000 | C39: 6000 | D39: 8000 | E39: servidores, DB, CDN
A40: Infraestrutura Ano 2 | B40: 7000 | C40: 8000 | D40: 10000 | E40: escala com base
A41: Marketing base Ano 1 | B41: 5000 | C41: 6000 | D41: 8000 | E41: além do paid do pre-seed
A42: Marketing base Ano 2 | B42: 8000 | C42: 10000 | D42: 15000 | E42: crescimento + paid
A43: Outros (jurídico, contab, misc.) | B43: 5000 | C43: 6000 | D43: 8000 | E43: fixo administrativo
A44: 6 · UNIT ECONOMICS (CAC full-loaded)
A45: CAC real full-loaded (R$) | B45: 80 | C45: 60 | D45: 50 | E45: inclui mkt+CS+onboarding
A46: CAC via paid apenas (R$) | B46: 27 | C46: 25 | D46: 20 | E46: referência apenas
A47: % aquisição via paid | B47: 0.5 | C47: 0.45 | D47: 0.4 | E47: % novos pagantes via ads
A48: 7 · VALUATION M24 (sobre Receita Acumulada 24m)
A49: Múltiplo × Receita Acumulada 24m | B49: 3 | C49: 5 | D49: 7 | E49: × sobre 'Base Mensal'!Z12 (R$ 12,8M)
A50: 📐 Nota modelo: Conversão aplica-se ao pool elegível mensal (Free - já pagantes). Taxa ≠ '% dos leads mensais' mas '% da base elegível acumulada que converte por mês'. Calibrado para reproduzir ~4.400 pagantes no M12 (cenário Base).
A54: 8 · CAPTAÇÃO ANJO (ÂNCORA: R$5M = 49% equity)
A55: Aporte máximo (R$) | B55: 2500000 | C55: ← editável (simule aqui)
A56: % Equity oferecido | B56: =B55/5000000*0.49 | C56: = calculado (R$5M = 49%)
A57: Valuation pre-money implícito | B57: =B55/B56-B55 | C57: = Aporte/%Equity - Aporte
A58: Valuation post-money implícito | B58: =B55/B56 | C58: = Aporte / %Equity
A60: 9 · PARÂMETROS DO MODELO
A61: Free cadastradas no M1 (semente) | B61: 4000 | C61: ← lista de espera M1
A62: Floor YoY · Conservador | B62: 0.3 | C62: ← piso ajuste valuation
A63: Floor YoY · Base | B63: 0.4 | C63: ← piso ajuste valuation
A64: Floor YoY · Otimista | B64: 0.6 | C64: ← piso ajuste valuation
A65: Divisor YoY (suavização) | B65: 20 | C65: ← maior = ajuste mais suave
A66: Taxa de desconto mensal (NPV/IRR) | B66: 0.018 | C66: =(1+B66)^12-1 | D66: ← anualizada
A67: Alíquota imposto sobre receita | B67: 0.12 | C67: 0.12 | D67: 0.15 | E67: ← Simples Nacional

Sheet 📊 Base Mensal
A1: AutoNoma · Base Mensal · 24 Meses · Fórmulas Dinâmicas · Cenário Controlado por 🔧 Cenário Ativo
A2: Cenário ativo: | C2: ='🔧 Cenário Ativo'!B2
A3: Indicador | B3: Unid. | C3: M01 | D3: M02 | E3: M03 | F3: M04 | G3: M05 | H3: M06 | I3: M07 | J3: M08 | K3: M09 | L3: M10 | M3: M11 | N3: M12 ★ | O3: M13 | P3: M14 | Q3: M15 | R3: M16 | S3: M17 | T3: M18 | U3: M19 | V3: M20 | W3: M21 | X3: M22 | Y3: M23 | Z3: M24 ★
A4: USUÁRIOS
A5: Free · Cadastros (Sonnet 40 int/mês) | B5: usr | C5: ='🎛️ Premissas'!B61 | D5: =C5+'🔧 Cenário Ativo'!$B$27 | E5: =D5+'🔧 Cenário Ativo'!$B$27 | F5: =E5+'🔧 Cenário Ativo'!$B$27 | G5: =F5+'🔧 Cenário Ativo'!$B$27 | H5: =G5+'🔧 Cenário Ativo'!$B$27 | I5: =H5+'🔧 Cenário Ativo'!$B$27 | J5: =I5+'🔧 Cenário Ativo'!$B$27 | K5: =J5+'🔧 Cenário Ativo'!$B$27 | ... N5: =M5+'🔧 Cenário Ativo'!$B$27 | O5: =N5+'🔧 Cenário Ativo'!$B$28 | P5: =O5+'🔧 Cenário Ativo'!$B$28 | Q5: =P5+'🔧 Cenário Ativo'!$B$28 | R5: =Q5+'🔧 Cenário Ativo'!$B$28 | S5: =R5+'🔧 Cenário Ativo'!$B$28 | T5: =S5+'🔧 Cenário Ativo'!$B$28 | U5: =T5+'🔧 Cenário Ativo'!$B$28 | V5: =U5+'🔧 Cenário Ativo'!$B$28 | ... Z5: =Y5+'🔧 Cenário Ativo'!$B$28
A6: Essencial · Assinantes | B6: ass. | C6: =ROUND(C5*'🔧 Cenário Ativo'!$B$29,0) | D6: =ROUND(D5*'🔧 Cenário Ativo'!$B$29,0) | E6: =ROUND(E5*'🔧 Cenário Ativo'!$B$29,0) | F6: =ROUND(F5*'🔧 Cenário Ativo'!$B$29,0) | G6: =ROUND(G5*'🔧 Cenário Ativo'!$B$29,0) | H6: =ROUND(H5*'🔧 Cenário Ativo'!$B$29,0) | I6: =ROUND(I5*'🔧 Cenário Ativo'!$B$29,0) | J6: =ROUND(J5*'🔧 Cenário Ativo'!$B$29,0) | ... Q6: =ROUND(Q5*'🔧 Cenário Ativo'!$B$29,0) | R6: =ROUND(Q6*(1-'🔧 Cenário Ativo'!B32)+MAX(0,R5-Q9)*'🔧 Cenário Ativo'!B29,0) | S6: =ROUND(R6*(1-'🔧 Cenário Ativo'!B32)+MAX(0,S5-R9)*'🔧 Cenário Ativo'!B29,0) | T6: =ROUND(S6*(1-'🔧 Cenário Ativo'!B32)+MAX(0,T5-S9)*'🔧 Cenário Ativo'!B29,0) | U6: =ROUND(T6*(1-'🔧 Cenário Ativo'!B32)+MAX(0,U5-T9)*'🔧 Cenário Ativo'!B29,0) | V6: =ROUND(U6*(1-'🔧 Cenário Ativo'!B32)+MAX(0,V5-U9)*'🔧 Cenário Ativo'!B29,0) | W6: =ROUND(V6*(1-'🔧 Cenário Ativo'!B32)+MAX(0,W5-V9)*'🔧 Cenário Ativo'!B29,0) | X6: =ROUND(W6*(1-'🔧 Cenário Ativo'!B32)+MAX(0,X5-W9)*'🔧 Cenário Ativo'!B29,0) | Y6: =ROUND(X6*(1-'🔧 Cenário Ativo'!B32)+MAX(0,Y5-X9)*'🔧 Cenário Ativo'!B29,0) | Z6: =ROUND(Y6*(1-'🔧 Cenário Ativo'!B32)+MAX(0,Z5-Y9)*'🔧 Cenário Ativo'!B29,0)
A7: Autônoma · Assinantes | B7: ass. | C7: =ROUND(C5*'🔧 Cenário Ativo'!$B$30,0) | D7: =ROUND(D5*'🔧 Cenário Ativo'!$B$30,0) | E7: =ROUND(E5*'🔧 Cenário Ativo'!$B$30,0) | F7: =ROUND(F5*'🔧 Cenário Ativo'!$B$30,0) | G7: =ROUND(G5*'🔧 Cenário Ativo'!$B$30,0) | H7: =ROUND(H5*'🔧 Cenário Ativo'!$B$30,0) | I7: =ROUND(I5*'🔧 Cenário Ativo'!$B$30,0) | J7: =ROUND(J5*'🔧 Cenário Ativo'!$B$30,0) | ... Q7: =ROUND(Q5*'🔧 Cenário Ativo'!$B$30,0) | R7: =ROUND(Q7*(1-'🔧 Cenário Ativo'!B33)+MAX(0,R6-Q7-Q8)*'🔧 Cenário Ativo'!B30,0) | S7: =ROUND(R7*(1-'🔧 Cenário Ativo'!B33)+MAX(0,S6-R7-R8)*'🔧 Cenário Ativo'!B30,0) | T7: =ROUND(S7*(1-'🔧 Cenário Ativo'!B33)+MAX(0,T6-S7-S8)*'🔧 Cenário Ativo'!B30,0) | U7: =ROUND(T7*(1-'🔧 Cenário Ativo'!B33)+MAX(0,U6-T7-T8)*'🔧 Cenário Ativo'!B30,0) | V7: =ROUND(U7*(1-'🔧 Cenário Ativo'!B33)+MAX(0,V6-U7-U8)*'🔧 Cenário Ativo'!B30,0) | W7: =ROUND(V7*(1-'🔧 Cenário Ativo'!B33)+MAX(0,W6-V7-V8)*'🔧 Cenário Ativo'!B30,0) | X7: =ROUND(W7*(1-'🔧 Cenário Ativo'!B33)+MAX(0,X6-W7-W8)*'🔧 Cenário Ativo'!B30,0) | Y7: =ROUND(X7*(1-'🔧 Cenário Ativo'!B33)+MAX(0,Y6-X7-X8)*'🔧 Cenário Ativo'!B30,0) | Z7: =ROUND(Y7*(1-'🔧 Cenário Ativo'!B33)+MAX(0,Z6-Y7-Y8)*'🔧 Cenário Ativo'!B30,0)
A8: Livre · Assinantes | B8: ass. | C8: =ROUND(C5*'🔧 Cenário Ativo'!$B$31,0) | D8: =ROUND(D5*'🔧 Cenário Ativo'!$B$31,0) | E8: =ROUND(E5*'🔧 Cenário Ativo'!$B$31,0) | F8: =ROUND(F5*'🔧 Cenário Ativo'!$B$31,0) | G8: =ROUND(G5*'🔧 Cenário Ativo'!$B$31,0) | H8: =ROUND(H5*'🔧 Cenário Ativo'!$B$31,0) | I8: =ROUND(I5*'🔧 Cenário Ativo'!$B$31,0) | J8: =ROUND(J5*'🔧 Cenário Ativo'!$B$31,0) | ... Q8: =ROUND(Q5*'🔧 Cenário Ativo'!$B$31,0) | R8: =ROUND(Q8*(1-'🔧 Cenário Ativo'!B34)+MAX(0,R7-Q8)*'🔧 Cenário Ativo'!B31,0) | S8: =ROUND(R8*(1-'🔧 Cenário Ativo'!B34)+MAX(0,S7-R8)*'🔧 Cenário Ativo'!B31,0) | T8: =ROUND(S8*(1-'🔧 Cenário Ativo'!B34)+MAX(0,T7-S8)*'🔧 Cenário Ativo'!B31,0) | U8: =ROUND(T8*(1-'🔧 Cenário Ativo'!B34)+MAX(0,U7-T8)*'🔧 Cenário Ativo'!B31,0) | V8: =ROUND(U8*(1-'🔧 Cenário Ativo'!B34)+MAX(0,V7-U8)*'🔧 Cenário Ativo'!B31,0) | W8: =ROUND(V8*(1-'🔧 Cenário Ativo'!B34)+MAX(0,W7-V8)*'🔧 Cenário Ativo'!B31,0) | X8: =ROUND(W8*(1-'🔧 Cenário Ativo'!B34)+MAX(0,X7-W8)*'🔧 Cenário Ativo'!B31,0) | Y8: =ROUND(X8*(1-'🔧 Cenário Ativo'!B34)+MAX(0,Y7-X8)*'🔧 Cenário Ativo'!B31,0) | Z8: =ROUND(Y8*(1-'🔧 Cenário Ativo'!B34)+MAX(0,Z7-Y8)*'🔧 Cenário Ativo'!B31,0)
A9: TOTAL PAGANTES | B9: ass. | C9: =SUM(C6:C8) | D9: =SUM(D6:D8) | E9: =SUM(E6:E8) | F9: =SUM(F6:F8) | G9: =SUM(G6:G8) | H9: =SUM(H6:H8) | I9: =SUM(I6:I8) | J9: =SUM(J6:J8) | ... Z9: =SUM(Z6:Z8)
A10: RECEITA
A11: MRR MENSAL | B11: R$ | C11: =C6*'🔧 Cenário Ativo'!B6+C7*'🔧 Cenário Ativo'!B7+C8*'🔧 Cenário Ativo'!B8 | D11: =D6*'🔧 Cenário Ativo'!B6+D7*'🔧 Cenário Ativo'!B7+D8*'🔧 Cenário Ativo'!B8 | E11: =E6*'🔧 Cenário Ativo'!B6+E7*'🔧 Cenário Ativo'!B7+E8*'🔧 Cenário Ativo'!B8 | F11: =F6*'🔧 Cenário Ativo'!B6+F7*'🔧 Cenário Ativo'!B7+F8*'🔧 Cenário Ativo'!B8 | G11: =G6*'🔧 Cenário Ativo'!B6+G7*'🔧 Cenário Ativo'!B7+G8*'🔧 Cenário Ativo'!B8 | H11: =H6*'🔧 Cenário Ativo'!B6+H7*'🔧 Cenário Ativo'!B7+H8*'🔧 Cenário Ativo'!B8 | I11: =I6*'🔧 Cenário Ativo'!B6+I7*'🔧 Cenário Ativo'!B7+I8*'🔧 Cenário Ativo'!B8 | J11: =J6*'🔧 Cenário Ativo'!B6+J7*'🔧 Cenário Ativo'!B7+J8*'🔧 Cenário Ativo'!B8 | K11: =K6*'🔧 Cenário Ativo'!B6+K7*'🔧 Cenário Ativo'!B7+K8*'🔧 Cenário Ativo'!B8 | L11: =L6*'🔧 Cenário Ativo'!B6+L7*'🔧 Cenário Ativo'!B7+L8*'🔧 Cenário Ativo'!B8 | M11: =M6*'🔧 Cenário Ativo'!B6+M7*'🔧 Cenário Ativo'!B7+M8*'🔧 Cenário Ativo'!B8 | N11: =N6*'🔧 Cenário Ativo'!B6+N7*'🔧 Cenário Ativo'!B7+N8*'🔧 Cenário Ativo'!B8 | O11: =O6*'🔧 Cenário Ativo'!B6+O7*'🔧 Cenário Ativo'!B7+O8*'🔧 Cenário Ativo'!B8 | P11: =P6*'🔧 Cenário Ativo'!B6+P7*'🔧 Cenário Ativo'!B7+P8*'🔧 Cenário Ativo'!B8 | Q11: =Q6*'🔧 Cenário Ativo'!B6+Q7*'🔧 Cenário Ativo'!B7+Q8*'🔧 Cenário Ativo'!B8 | R11: =R6*'🔧 Cenário Ativo'!B6+R7*'🔧 Cenário Ativo'!B7+R8*'🔧 Cenário Ativo'!B8 | S11: =S6*'🔧 Cenário Ativo'!B6+S7*'🔧 Cenário Ativo'!B7+S8*'🔧 Cenário Ativo'!B8 | T11: =T6*'🔧 Cenário Ativo'!B6+T7*'🔧 Cenário Ativo'!B7+T8*'🔧 Cenário Ativo'!B8 | U11: =U6*'🔧 Cenário Ativo'!B6+U7*'🔧 Cenário Ativo'!B7+U8*'🔧 Cenário Ativo'!B8 | V11: =V6*'🔧 Cenário Ativo'!B6+V7*'🔧 Cenário Ativo'!B7+V8*'🔧 Cenário Ativo'!B8 | W11: =W6*'🔧 Cenário Ativo'!B6+W7*'🔧 Cenário Ativo'!B7+W8*'🔧 Cenário Ativo'!B8 | X11: =X6*'🔧 Cenário Ativo'!B6+X7*'🔧 Cenário Ativo'!B7+X8*'🔧 Cenário Ativo'!B8 | Y11: =Y6*'🔧 Cenário Ativo'!B6+Y7*'🔧 Cenário Ativo'!B7+Y8*'🔧 Cenário Ativo'!B8 | Z11: =Z6*'🔧 Cenário Ativo'!B6+Z7*'🔧 Cenário Ativo'!B7+Z8*'🔧 Cenário Ativo'!B8
A12: MRR ACUMULADO | B12: R$ | C12: =C11 | D12: =C12+D11 | E12: =D12+E11 | F12: =E12+F11 | G12: =F12+G11 | H12: =G12+H11 | I12: =H12+I11 | J12: =I12+J11 | K12: =J12+K11 | ... Z12: =Y12+Z11
A13: CUSTO API · 100% Sonnet 4.6 · Caching ativo
A14: API Free (Sonnet · 40 int/mês) | B14: R$ | C14: =C5*'🔧 Cenário Ativo'!B18*('🔧 Cenário Ativo'!B15*('🔧 Cenário Ativo'!B16/1000000*'🔧 Cenário Ativo'!B11+'🔧 Cenário Ativo'!B17/1000000*'🔧 Cenário Ativo'!B12)*(1-'🔧 Cenário Ativo'!B13)*'🔧 Cenário Ativo'!B10) | D14: =D5*'🔧 Cenário Ativo'!B18*('🔧 Cenário Ativo'!B15*('🔧 Cenário Ativo'!B16/1000000*'🔧 Cenário Ativo'!B11+'🔧 Cenário Ativo'!B17/1000000*'🔧 Cenário Ativo'!B12)*(1-'🔧 Cenário Ativo'!B13)*'🔧 Cenário Ativo'!B10) | E14: =E5*'🔧 Cenário Ativo'!B18*('🔧 Cenário Ativo'!B15*('🔧 Cenário Ativo'!B16/1000000*'🔧 Cenário Ativo'!B11+'🔧 Cenário Ativo'!B17/1000000*'🔧 Cenário Ativo'!B12)*(1-'🔧 Cenário Ativo'!B13)*'🔧 Cenário Ativo'!B10) | F14: =F5*'🔧 Cenário Ativo'!B18*('🔧 Cenário Ativo'!B15*('🔧 Cenário Ativo'!B16/1000000*'🔧 Cenário Ativo'!B11+'🔧 Cenário Ativo'!B17/1000000*'🔧 Cenário Ativo'!B12)*(1-'🔧 Cenário Ativo'!B13)*'🔧 Cenário Ativo'!B10) | G14: =G5*'🔧 Cenário Ativo'!B18*('🔧 Cenário Ativo'!B15*('🔧 Cenário Ativo'!B16/1000000*'🔧 Cenário Ativo'!B11+'🔧 Cenário Ativo'!B17/1000000*'🔧 Cenário Ativo'!B12)*(1-'🔧 Cenário Ativo'!B13)*'🔧 Cenário Ativo'!B10) | H14: =H5*'🔧 Cenário Ativo'!B18*('🔧 Cenário Ativo'!B15*('🔧 Cenário Ativo'!B16/1000000*'🔧 Cenário Ativo'!B11+'🔧 Cenário Ativo'!B17/1000000*'🔧 Cenário Ativo'!B12)*(1-'🔧 Cenário Ativo'!B13)*'🔧 Cenário Ativo'!B10) | I14: =I5*'🔧 Cenário Ativo'!B18*('🔧 Cenário Ativo'!B15*('🔧 Cenário Ativo'!B16/1000000*'🔧 Cenário Ativo'!B11+'🔧 Cenário Ativo'!B17/1000000*'🔧 Cenário Ativo'!B12)*(1-'🔧 Cenário Ativo'!B13)*'🔧 Cenário Ativo'!B10) | J14: =J5*'🔧 Cenário Ativo'!B18*('🔧 Cenário Ativo'!B15*('🔧 Cenário Ativo'!B16/1000000*'🔧 Cenário Ativo'!B11+'🔧 Cenário Ativo'!B17/1000000*'🔧 Cenário Ativo'!B12)*(1-'🔧 Cenário Ativo'!B13)*'🔧 Cenário Ativo'!B10) | K14: =K5*'🔧 Cenário Ativo'!B18*('🔧 Cenário Ativo'!B15*('🔧 Cenário Ativo'!B16/1000000*'🔧 Cenário Ativo'!B11+'🔧 Cenário Ativo'!B17/1000000*'🔧 Cenário Ativo'!B12)*(1-'🔧 Cenário Ativo'!B13)*'🔧 Cenário Ativo'!B10) | L14: =L5*'🔧 Cenário Ativo'!B18*('🔧 Cenário Ativo'!B15*('🔧 Cenário Ativo'!B16/1000000*'🔧 Cenário Ativo'!B11+'🔧 Cenário Ativo'!B17/1000000*'🔧 Cenário Ativo'!B12)*(1-'🔧 Cenário Ativo'!B13)*'🔧 Cenário Ativo'!B10) | M14: =M5*'🔧 Cenário Ativo'!B18*('🔧 Cenário Ativo'!B15*('🔧 Cenário Ativo'!B16/1000000*'🔧 Cenário Ativo'!B11+'🔧 Cenário Ativo'!B17/1000000*'🔧 Cenário Ativo'!B12)*(1-'🔧 Cenário Ativo'!B13)*'🔧 Cenário Ativo'!B10) | N14: =N5*'🔧 Cenário Ativo'!B18*('🔧 Cenário Ativo'!B15*('🔧 Cenário Ativo'!B16/1000000*'🔧 Cenário Ativo'!B11+'🔧 Cenário Ativo'!B17/1000000*'🔧 Cenário Ativo'!B12)*(1-'🔧 Cenário Ativo'!B13)*'🔧 Cenário Ativo'!B10) | O14: =O5*'🔧 Cenário Ativo'!B18*('🔧 Cenário Ativo'!B15*('🔧 Cenário Ativo'!B16/1000000*'🔧 Cenário Ativo'!B11+'🔧 Cenário Ativo'!B17/1000000*'🔧 Cenário Ativo'!B12)*(1-'🔧 Cenário Ativo'!B13)*'🔧 Cenário Ativo'!B10) | P14: =P5*'🔧 Cenário Ativo'!B18*('🔧 Cenário Ativo'!B15*('🔧 Cenário Ativo'!B16/1000000*'🔧 Cenário Ativo'!B11+'🔧 Cenário Ativo'!B17/1000000*'🔧 Cenário Ativo'!B12)*(1-'🔧 Cenário Ativo'!B13)*'🔧 Cenário Ativo'!B10) | Q14: =Q5*'🔧 Cenário Ativo'!B18*('🔧 Cenário Ativo'!B15*('🔧 Cenário Ativo'!B16/1000000*'🔧 Cenário Ativo'!B11+'🔧 Cenário Ativo'!B17/1000000*'🔧 Cenário Ativo'!B12)*(1-'🔧 Cenário Ativo'!B13)*'🔧 Cenário Ativo'!B10) | R14: =R5*'🔧 Cenário Ativo'!B18*('🔧 Cenário Ativo'!B15*('🔧 Cenário Ativo'!B16/1000000*'🔧 Cenário Ativo'!B11+'🔧 Cenário Ativo'!B17/1000000*'🔧 Cenário Ativo'!B12)*(1-'🔧 Cenário Ativo'!B13)*'🔧 Cenário Ativo'!B10) | S14: =S5*'🔧 Cenário Ativo'!B18*('🔧 Cenário Ativo'!B15*('🔧 Cenário Ativo'!B16/1000000*'🔧 Cenário Ativo'!B11+'🔧 Cenário Ativo'!B17/1000000*'🔧 Cenário Ativo'!B12)*(1-'🔧 Cenário Ativo'!B13)*'🔧 Cenário Ativo'!B10) | T14: =T5*'🔧 Cenário Ativo'!B18*('🔧 Cenário Ativo'!B15*('🔧 Cenário Ativo'!B16/1000000*'🔧 Cenário Ativo'!B11+'🔧 Cenário Ativo'!B17/1000000*'🔧 Cenário Ativo'!B12)*(1-'🔧 Cenário Ativo'!B13)*'🔧 Cenário Ativo'!B10) | U14: =U5*'🔧 Cenário Ativo'!B18*('🔧 Cenário Ativo'!B15*('🔧 Cenário Ativo'!B16/1000000*'🔧 Cenário Ativo'!B11+'🔧 Cenário Ativo'!B17/1000000*'🔧 Cenário Ativo'!B12)*(1-'🔧 Cenário Ativo'!B13)*'🔧 Cenário Ativo'!B10) | V14: =V5*'🔧 Cenário Ativo'!B18*('🔧 Cenário Ativo'!B15*('🔧 Cenário Ativo'!B16/1000000*'🔧 Cenário Ativo'!B11+'🔧 Cenário Ativo'!B17/1000000*'🔧 Cenário Ativo'!B12)*(1-'🔧 Cenário Ativo'!B13)*'🔧 Cenário Ativo'!B10) | W14: =W5*'🔧 Cenário Ativo'!B18*('🔧 Cenário Ativo'!B15*('🔧 Cenário Ativo'!B16/1000000*'🔧 Cenário Ativo'!B11+'🔧 Cenário Ativo'!B17/1000000*'🔧 Cenário Ativo'!B12)*(1-'🔧 Cenário Ativo'!B13)*'🔧 Cenário Ativo'!B10) | X14: =X5*'🔧 Cenário Ativo'!B18*('🔧 Cenário Ativo'!B15*('🔧 Cenário Ativo'!B16/1000000*'🔧 Cenário Ativo'!B11+'🔧 Cenário Ativo'!B17/1000000*'🔧 Cenário Ativo'!B12)*(1-'🔧 Cenário Ativo'!B13)*'🔧 Cenário Ativo'!B10) | Y14: =Y5*'🔧 Cenário Ativo'!B18*('🔧 Cenário Ativo'!B15*('🔧 Cenário Ativo'!B16/1000000*'🔧 Cenário Ativo'!B11+'🔧 Cenário Ativo'!B17/1000000*'🔧 Cenário Ativo'!B12)*(1-'🔧 Cenário Ativo'!B13)*'🔧 Cenário Ativo'!B10) | Z14: =Z5*'🔧 Cenário Ativo'!B18*('🔧 Cenário Ativo'!B15*('🔧 Cenário Ativo'!B16/1000000*'🔧 Cenário Ativo'!B11+'🔧 Cenário Ativo'!B17/1000000*'🔧 Cenário Ativo'!B12)*(1-'🔧 Cenário Ativo'!B13)*'🔧 Cenário Ativo'!B10)
A15: API Essencial (chat ilimitado) | B15: R$ | C15: =C6*'🔧 Cenário Ativo'!B19*('🔧 Cenário Ativo'!B20/1000000*'🔧 Cenário Ativo'!B11+'🔧 Cenário Ativo'!B21/1000000*'🔧 Cenário Ativo'!B12)*(1-'🔧 Cenário Ativo'!B13)*'🔧 Cenário Ativo'!B10 | D15: =D6*'🔧 Cenário Ativo'!B19*('🔧 Cenário Ativo'!B20/1000000*'🔧 Cenário Ativo'!B11+'🔧 Cenário Ativo'!B21/1000000*'🔧 Cenário Ativo'!B12)*(1-'🔧 Cenário Ativo'!B13)*'🔧 Cenário Ativo'!B10 | E15: =E6*'🔧 Cenário Ativo'!B19*('🔧 Cenário Ativo'!B20/1000000*'🔧 Cenário Ativo'!B11+'🔧 Cenário Ativo'!B21/1000000*'🔧 Cenário Ativo'!B12)*(1-'🔧 Cenário Ativo'!B13)*'🔧 Cenário Ativo'!B10 | F15: =F6*'🔧 Cenário Ativo'!B19*('🔧 Cenário Ativo'!B20/1000000*'🔧 Cenário Ativo'!B11+'🔧 Cenário Ativo'!B21/1000000*'🔧 Cenário Ativo'!B12)*(1-'🔧 Cenário Ativo'!B13)*'🔧 Cenário Ativo'!B10 | G15: =G6*'🔧 Cenário Ativo'!B19*('🔧 Cenário Ativo'!B20/1000000*'🔧 Cenário Ativo'!B11+'🔧 Cenário Ativo'!B21/1000000*'🔧 Cenário Ativo'!B12)*(1-'🔧 Cenário Ativo'!B13)*'🔧 Cenário Ativo'!B10 | H15: =H6*'🔧 Cenário Ativo'!B19*('🔧 Cenário Ativo'!B20/1000000*'🔧 Cenário Ativo'!B11+'🔧 Cenário Ativo'!B21/1000000*'🔧 Cenário Ativo'!B12)*(1-'🔧 Cenário Ativo'!B13)*'🔧 Cenário Ativo'!B10 | I15: =I6*'🔧 Cenário Ativo'!B19*('🔧 Cenário Ativo'!B20/1000000*'🔧 Cenário Ativo'!B11+'🔧 Cenário Ativo'!B21/1000000*'🔧 Cenário Ativo'!B12)*(1-'🔧 Cenário Ativo'!B13)*'🔧 Cenário Ativo'!B10 | J15: =J6*'🔧 Cenário Ativo'!B19*('🔧 Cenário Ativo'!B20/1000000*'🔧 Cenário Ativo'!B11+'🔧 Cenário Ativo'!B21/1000000*'🔧 Cenário Ativo'!B12)*(1-'🔧 Cenário Ativo'!B13)*'🔧 Cenário Ativo'!B10 | K15: =K6*'🔧 Cenário Ativo'!B19*('🔧 Cenário Ativo'!B20/1000000*'🔧 Cenário Ativo'!B11+'🔧 Cenário Ativo'!B21/1000000*'🔧 Cenário Ativo'!B12)*(1-'🔧 Cenário Ativo'!B13)*'🔧 Cenário Ativo'!B10 | L15: =L6*'🔧 Cenário Ativo'!B19*('🔧 Cenário Ativo'!B20/1000000*'🔧 Cenário Ativo'!B11+'🔧 Cenário Ativo'!B21/1000000*'🔧 Cenário Ativo'!B12)*(1-'🔧 Cenário Ativo'!B13)*'🔧 Cenário Ativo'!B10 | M15: =M6*'🔧 Cenário Ativo'!B19*('🔧 Cenário Ativo'!B20/1000000*'🔧 Cenário Ativo'!B11+'🔧 Cenário Ativo'!B21/1000000*'🔧 Cenário Ativo'!B12)*(1-'🔧 Cenário Ativo'!B13)*'🔧 Cenário Ativo'!B10 | N15: =N6*'🔧 Cenário Ativo'!B19*('🔧 Cenário Ativo'!B20/1000000*'🔧 Cenário Ativo'!B11+'🔧 Cenário Ativo'!B21/1000000*'🔧 Cenário Ativo'!B12)*(1-'🔧 Cenário Ativo'!B13)*'🔧 Cenário Ativo'!B10 | O15: =O6*'🔧 Cenário Ativo'!B19*('🔧 Cenário Ativo'!B20/1000000*'🔧 Cenário Ativo'!B11+'🔧 Cenário Ativo'!B21/1000000*'🔧 Cenário Ativo'!B12)*(1-'🔧 Cenário Ativo'!B13)*'🔧 Cenário Ativo'!B10 | P15: =P6*'🔧 Cenário Ativo'!B19*('🔧 Cenário Ativo'!B20/1000000*'🔧 Cenário Ativo'!B11+'🔧 Cenário Ativo'!B21/1000000*'🔧 Cenário Ativo'!B12)*(1-'🔧 Cenário Ativo'!B13)*'🔧 Cenário Ativo'!B10 | Q15: =Q6*'🔧 Cenário Ativo'!B19*('🔧 Cenário Ativo'!B20/1000000*'🔧 Cenário Ativo'!B11+'🔧 Cenário Ativo'!B21/1000000*'🔧 Cenário Ativo'!B12)*(1-'🔧 Cenário Ativo'!B13)*'🔧 Cenário Ativo'!B10 | R15: =R6*'🔧 Cenário Ativo'!B19*('🔧 Cenário Ativo'!B20/1000000*'🔧 Cenário Ativo'!B11+'🔧 Cenário Ativo'!B21/1000000*'🔧 Cenário Ativo'!B12)*(1-'🔧 Cenário Ativo'!B13)*'🔧 Cenário Ativo'!B10 | S15: =S6*'🔧 Cenário Ativo'!B19*('🔧 Cenário Ativo'!B20/1000000*'🔧 Cenário Ativo'!B11+'🔧 Cenário Ativo'!B21/1000000*'🔧 Cenário Ativo'!B12)*(1-'🔧 Cenário Ativo'!B13)*'🔧 Cenário Ativo'!B10 | T15: =T6*'🔧 Cenário Ativo'!B19*('🔧 Cenário Ativo'!B20/1000000*'🔧 Cenário Ativo'!B11+'🔧 Cenário Ativo'!B21/1000000*'🔧 Cenário Ativo'!B12)*(1-'🔧 Cenário Ativo'!B13)*'🔧 Cenário Ativo'!B10 | U15: =U6*'🔧 Cenário Ativo'!B19*('🔧 Cenário Ativo'!B20/1000000*'🔧 Cenário Ativo'!B11+'🔧 Cenário Ativo'!B21/1000000*'🔧 Cenário Ativo'!B12)*(1-'🔧 Cenário Ativo'!B13)*'🔧 Cenário Ativo'!B10 | V15: =V6*'🔧 Cenário Ativo'!B19*('🔧 Cenário Ativo'!B20/1000000*'🔧 Cenário Ativo'!B11+'🔧 Cenário Ativo'!B21/1000000*'🔧 Cenário Ativo'!B12)*(1-'🔧 Cenário Ativo'!B13)*'🔧 Cenário Ativo'!B10 | W15: =W6*'🔧 Cenário Ativo'!B19*('🔧 Cenário Ativo'!B20/1000000*'🔧 Cenário Ativo'!B11+'🔧 Cenário Ativo'!B21/1000000*'🔧 Cenário Ativo'!B12)*(1-'🔧 Cenário Ativo'!B13)*'🔧 Cenário Ativo'!B10 | X15: =X6*'🔧 Cenário Ativo'!B19*('🔧 Cenário Ativo'!B20/1000000*'🔧 Cenário Ativo'!B11+'🔧 Cenário Ativo'!B21/1000000*'🔧 Cenário Ativo'!B12)*(1-'🔧 Cenário Ativo'!B13)*'🔧 Cenário Ativo'!B10 | Y15: =Y6*'🔧 Cenário Ativo'!B19*('🔧 Cenário Ativo'!B20/1000000*'🔧 Cenário Ativo'!B11+'🔧 Cenário Ativo'!B21/1000000*'🔧 Cenário Ativo'!B12)*(1-'🔧 Cenário Ativo'!B13)*'🔧 Cenário Ativo'!B10 | Z15: =Z6*'🔧 Cenário Ativo'!B19*('🔧 Cenário Ativo'!B20/1000000*'🔧 Cenário Ativo'!B11+'🔧 Cenário Ativo'!B21/1000000*'🔧 Cenário Ativo'!B12)*(1-'🔧 Cenário Ativo'!B13)*'🔧 Cenário Ativo'!B10
A16: API Autônoma (+1 agente) | B16: R$ | C16: =C7*('🔧 Cenário Ativo'!B19*('🔧 Cenário Ativo'!B20/1000000*'🔧 Cenário Ativo'!B11+'🔧 Cenário Ativo'!B21/1000000*'🔧 Cenário Ativo'!B12)*(1-'🔧 Cenário Ativo'!B13)*'🔧 Cenário Ativo'!B10+'🔧 Cenário Ativo'!B22*('🔧 Cenário Ativo'!B23/1000000*'🔧 Cenário Ativo'!B11+'🔧 Cenário Ativo'!B24/1000000*'🔧 Cenário Ativo'!B12)*(1-'🔧 Cenário Ativo'!B13)*'🔧 Cenário Ativo'!B10) | D16: =D7*('🔧 Cenário Ativo'!B19*('🔧 Cenário Ativo'!B20/1000000*'🔧 Cenário Ativo'!B11+'🔧 Cenário Ativo'!B21/1000000*'🔧 Cenário Ativo'!B12)*(1-'🔧 Cenário Ativo'!B13)*'🔧 Cenário Ativo'!B10+'🔧 Cenário Ativo'!B22*('🔧 Cenário Ativo'!B23/1000000*'🔧 Cenário Ativo'!B11+'🔧 Cenário Ativo'!B24/1000000*'🔧 Cenário Ativo'!B12)*(1-'🔧 Cenário Ativo'!B13)*'🔧 Cenário Ativo'!B10) | E16: =E7*('🔧 Cenário Ativo'!B19*('🔧 Cenário Ativo'!B20/1000000*'🔧 Cenário Ativo'!B11+'🔧 Cenário Ativo'!B21/1000000*'🔧 Cenário Ativo'!B12)*(1-'🔧 Cenário Ativo'!B13)*'🔧 Cenário Ativo'!B10+'🔧 Cenário Ativo'!B22*('🔧 Cenário Ativo'!B23/1000000*'🔧 Cenário Ativo'!B11+'🔧 Cenário Ativo'!B24/1000000*'🔧 Cenário Ativo'!B12)*(1-'🔧 Cenário Ativo'!B13)*'🔧 Cenário Ativo'!B10) | F16: =F7*('🔧 Cenário Ativo'!B19*('🔧 Cenário Ativo'!B20/1000000*'🔧 Cenário Ativo'!B11+'🔧 Cenário Ativo'!B21/1000000*'🔧 Cenário Ativo'!B12)*(1-'🔧 Cenário Ativo'!B13)*'🔧 Cenário Ativo'!B10+'🔧 Cenário Ativo'!B22*('🔧 Cenário Ativo'!B23/1000000*'🔧 Cenário Ativo'!B11+'🔧 Cenário Ativo'!B24/1000000*'🔧 Cenário Ativo'!B12)*(1-'🔧 Cenário Ativo'!B13)*'🔧 Cenário Ativo'!B10) | G16: =G7*('🔧 Cenário Ativo'!B19*('🔧 Cenário Ativo'!B20/1000000*'🔧 Cenário Ativo'!B11+'🔧 Cenário Ativo'!B21/1000000*'🔧 Cenário Ativo'!B12)*(1-'🔧 Cenário Ativo'!B13)*'🔧 Cenário Ativo'!B10+'🔧 Cenário Ativo'!B22*('🔧 Cenário Ativo'!B23/1000000*'🔧 Cenário Ativo'!B11+'🔧 Cenário Ativo'!B24/1000000*'🔧 Cenário Ativo'!B12)*(1-'🔧 Cenário Ativo'!B13)*'🔧 Cenário Ativo'!B10) | H16: =H7*('🔧 Cenário Ativo'!B19*('🔧 Cenário Ativo'!B20/1000000*'🔧 Cenário Ativo'!B11+'🔧 Cenário Ativo'!B21/1000000*'🔧 Cenário Ativo'!B12)*(1-'🔧 Cenário Ativo'!B13)*'🔧 Cenário Ativo'!B10+'🔧 Cenário Ativo'!B22*('🔧 Cenário Ativo'!B23/1000000*'🔧 Cenário Ativo'!B11+'🔧 Cenário Ativo'!B24/1000000*'🔧 Cenário Ativo'!B12)*(1-'🔧 Cenário Ativo'!B13)*'🔧 Cenário Ativo'!B10) | I16: =I7*('🔧 Cenário Ativo'!B19*('🔧 Cenário Ativo'!B20/1000000*'🔧 Cenário Ativo'!B11+'🔧 Cenário Ativo'!B21/1000000*'🔧 Cenário Ativo'!B12)*(1-'🔧 Cenário Ativo'!B13)*'🔧 Cenário Ativo'!B10+'🔧 Cenário Ativo'!B22*('🔧 Cenário Ativo'!B23/1000000*'🔧 Cenário Ativo'!B11+'🔧 Cenário Ativo'!B24/1000000*'🔧 Cenário Ativo'!B12)*(1-'🔧 Cenário Ativo'!B13)*'🔧 Cenário Ativo'!B10) | J16: =J7*('🔧 Cenário Ativo'!B19*('🔧 Cenário Ativo'!B20/1000000*'🔧 Cenário Ativo'!B11+'🔧 Cenário Ativo'!B21/1000000*'🔧 Cenário Ativo'!B12)*(1-'🔧 Cenário Ativo'!B13)*'🔧 Cenário Ativo'!B10+'🔧 Cenário Ativo'!B22*('🔧 Cenário Ativo'!B23/1000000*'🔧 Cenário Ativo'!B11+'🔧 Cenário Ativo'!B24/1000000*'🔧 Cenário Ativo'!B12)*(1-'🔧 Cenário Ativo'!B13)*'🔧 Cenário Ativo'!B10) | K16: =K7*('🔧 Cenário Ativo'!B19*('🔧 Cenário Ativo'!B20/1000000*'🔧 Cenário Ativo'!B11+'🔧 Cenário Ativo'!B21/1000000*'🔧 Cenário Ativo'!B12)*(1-'🔧 Cenário Ativo'!B13)*'🔧 Cenário Ativo'!B10+'🔧 Cenário Ativo'!B22*('🔧 Cenário Ativo'!B23/1000000*'🔧 Cenário Ativo'!B11+'🔧 Cenário Ativo'!B24/1000000*'🔧 Cenário Ativo'!B12)*(1-'🔧 Cenário Ativo'!B13)*'🔧 Cenário Ativo'!B10) | L16: =L7*('🔧 Cenário Ativo'!B19*('🔧 Cenário Ativo'!B20/1000000*'🔧 Cenário Ativo'!B11+'🔧 Cenário Ativo'!B21/1000000*'🔧 Cenário Ativo'!B12)*(1-'🔧 Cenário Ativo'!B13)*'🔧 Cenário Ativo'!B10+'🔧 Cenário Ativo'!B22*('🔧 Cenário Ativo'!B23/1000000*'🔧 Cenário Ativo'!B11+'🔧 Cenário Ativo'!B24/1000000*'🔧 Cenário Ativo'!B12)*(1-'🔧 Cenário Ativo'!B13)*'🔧 Cenário Ativo'!B10) | M16: =M7*('🔧 Cenário Ativo'!B19*('🔧 Cenário Ativo'!B20/1000000*'🔧 Cenário Ativo'!B11+'🔧 Cenário Ativo'!B21/1000000*'🔧 Cenário Ativo'!B12)*(1-'🔧 Cenário Ativo'!B13)*'🔧 Cenário Ativo'!B10+'🔧 Cenário Ativo'!B22*('🔧 Cenário Ativo'!B23/1000000*'🔧 Cenário Ativo'!B11+'🔧 Cenário Ativo'!B24/1000000*'🔧 Cenário Ativo'!B12)*(1-'🔧 Cenário Ativo'!B13)*'🔧 Cenário Ativo'!B10) | N16: =N7*('🔧 Cenário Ativo'!B19*('🔧 Cenário Ativo'!B20/1000000*'🔧 Cenário Ativo'!B11+'🔧 Cenário Ativo'!B21/1000000*'🔧 Cenário Ativo'!B12)*(1-'🔧 Cenário Ativo'!B13)*'🔧 Cenário Ativo'!B10+'🔧 Cenário Ativo'!B22*('🔧 Cenário Ativo'!B23/1000000*'🔧 Cenário Ativo'!B11+'🔧 Cenário Ativo'!B24/1000000*'🔧 Cenário Ativo'!B12)*(1-'🔧 Cenário Ativo'!B13)*'🔧 Cenário Ativo'!B10) | O16: =O7*('🔧 Cenário Ativo'!B19*('🔧 Cenário Ativo'!B20/1000000*'🔧 Cenário Ativo'!B11+'🔧 Cenário Ativo'!B21/1000000*'🔧 Cenário Ativo'!B12)*(1-'🔧 Cenário Ativo'!B13)*'🔧 Cenário Ativo'!B10+'🔧 Cenário Ativo'!B22*('🔧 Cenário Ativo'!B23/1000000*'🔧 Cenário Ativo'!B11+'🔧 Cenário Ativo'!B24/1000000*'🔧 Cenário Ativo'!B12)*(1-'🔧 Cenário Ativo'!B13)*'🔧 Cenário Ativo'!B10) | P16: =P7*('🔧 Cenário Ativo'!B19*('🔧 Cenário Ativo'!B20/1000000*'🔧 Cenário Ativo'!B11+'🔧 Cenário Ativo'!B21/1000000*'🔧 Cenário Ativo'!B12)*(1-'🔧 Cenário Ativo'!B13)*'🔧 Cenário Ativo'!B10+'🔧 Cenário Ativo'!B22*('🔧 Cenário Ativo'!B23/1000000*'🔧 Cenário Ativo'!B11+'🔧 Cenário Ativo'!B24/1000000*'🔧 Cenário Ativo'!B12)*(1-'🔧 Cenário Ativo'!B13)*'🔧 Cenário Ativo'!B10) | Q16: =Q7*('🔧 Cenário Ativo'!B19*('🔧 Cenário Ativo'!B20/1000000*'🔧 Cenário Ativo'!B11+'🔧 Cenário Ativo'!B21/1000000*'🔧 Cenário Ativo'!B12)*(1-'🔧 Cenário Ativo'!B13)*'🔧 Cenário Ativo'!B10+'🔧 Cenário Ativo'!B22*('🔧 Cenário Ativo'!B23/1000000*'🔧 Cenário Ativo'!B11+'🔧 Cenário Ativo'!B24/1000000*'🔧 Cenário Ativo'!B12)*(1-'🔧 Cenário Ativo'!B13)*'🔧 Cenário Ativo'!B10) | R16: =R7*('🔧 Cenário Ativo'!B19*('🔧 Cenário Ativo'!B20/1000000*'🔧 Cenário Ativo'!B11+'🔧 Cenário Ativo'!B21/1000000*'🔧 Cenário Ativo'!B12)*(1-'🔧 Cenário Ativo'!B13)*'🔧 Cenário Ativo'!B10+'🔧 Cenário Ativo'!B22*('🔧 Cenário Ativo'!B23/1000000*'🔧 Cenário Ativo'!B11+'🔧 Cenário Ativo'!B24/1000000*'🔧 Cenário Ativo'!B12)*(1-'🔧 Cenário Ativo'!B13)*'🔧 Cenário Ativo'!B10) | S16: =S7*('🔧 Cenário Ativo'!B19*('🔧 Cenário Ativo'!B20/1000000*'🔧 Cenário Ativo'!B11+'🔧 Cenário Ativo'!B21/1000000*'🔧 Cenário Ativo'!B12)*(1-'🔧 Cenário Ativo'!B13)*'🔧 Cenário Ativo'!B10+'🔧 Cenário Ativo'!B22*('🔧 Cenário Ativo'!B23/1000000*'🔧 Cenário Ativo'!B11+'🔧 Cenário Ativo'!B24/1000000*'🔧 Cenário Ativo'!B12)*(1-'🔧 Cenário Ativo'!B13)*'🔧 Cenário Ativo'!B10) | T16: =T7*('🔧 Cenário Ativo'!B19*('🔧 Cenário Ativo'!B20/1000000*'🔧 Cenário Ativo'!B11+'🔧 Cenário Ativo'!B21/1000000*'🔧 Cenário Ativo'!B12)*(1-'🔧 Cenário Ativo'!B13)*'🔧 Cenário Ativo'!B10+'🔧 Cenário Ativo'!B22*('🔧 Cenário Ativo'!B23/1000000*'🔧 Cenário Ativo'!B11+'🔧 Cenário Ativo'!B24/1000000*'🔧 Cenário Ativo'!B12)*(1-'🔧 Cenário Ativo'!B13)*'🔧 Cenário Ativo'!B10) | U16: =U7*('🔧 Cenário Ativo'!B19*('🔧 Cenário Ativo'!B20/1000000*'🔧 Cenário Ativo'!B11+'🔧 Cenário Ativo'!B21/1000000*'🔧 Cenário Ativo'!B12)*(1-'🔧 Cenário Ativo'!B13)*'🔧 Cenário Ativo'!B10+'🔧 Cenário Ativo'!B22*('🔧 Cenário Ativo'!B23/1000000*'🔧 Cenário Ativo'!B11+'🔧 Cenário Ativo'!B24/1000000*'🔧 Cenário Ativo'!B12)*(1-'🔧 Cenário Ativo'!B13)*'🔧 Cenário Ativo'!B10) | V16: =V7*('🔧 Cenário Ativo'!B19*('🔧 Cenário Ativo'!B20/1000000*'🔧 Cenário Ativo'!B11+'🔧 Cenário Ativo'!B21/1000000*'🔧 Cenário Ativo'!B12)*(1-'🔧 Cenário Ativo'!B13)*'🔧 Cenário Ativo'!B10+'🔧 Cenário Ativo'!B22*('🔧 Cenário Ativo'!B23/1000000*'🔧 Cenário Ativo'!B11+'🔧 Cenário Ativo'!B24/1000000*'🔧 Cenário Ativo'!B12)*(1-'🔧 Cenário Ativo'!B13)*'🔧 Cenário Ativo'!B10) | W16: =W7*('🔧 Cenário Ativo'!B19*('🔧 Cenário Ativo'!B20/1000000*'🔧 Cenário Ativo'!B11+'🔧 Cenário Ativo'!B21/1000000*'🔧 Cenário Ativo'!B12)*(1-'🔧 Cenário Ativo'!B13)*'🔧 Cenário Ativo'!B10+'🔧 Cenário Ativo'!B22*('🔧 Cenário Ativo'!B23/1000000*'🔧 Cenário Ativo'!B11+'🔧 Cenário Ativo'!B24/1000000*'🔧 Cenário Ativo'!B12)*(1-'🔧 Cenário Ativo'!B13)*'🔧 Cenário Ativo'!B10) | X16: =X7*('🔧 Cenário Ativo'!B19*('🔧 Cenário Ativo'!B20/1000000*'🔧 Cenário Ativo'!B11+'🔧 Cenário Ativo'!B21/1000000*'🔧 Cenário Ativo'!B12)*(1-'🔧 Cenário Ativo'!B13)*'🔧 Cenário Ativo'!B10+'🔧 Cenário Ativo'!B22*('🔧 Cenário Ativo'!B23/1000000*'🔧 Cenário Ativo'!B11+'🔧 Cenário Ativo'!B24/1000000*'🔧 Cenário Ativo'!B12)*(1-'🔧 Cenário Ativo'!B13)*'🔧 Cenário Ativo'!B10) | Y16: =Y7*('🔧 Cenário Ativo'!B19*('🔧 Cenário Ativo'!B20/1000000*'🔧 Cenário Ativo'!B11+'🔧 Cenário Ativo'!B21/1000000*'🔧 Cenário Ativo'!B12)*(1-'🔧 Cenário Ativo'!B13)*'🔧 Cenário Ativo'!B10+'🔧 Cenário Ativo'!B22*('🔧 Cenário Ativo'!B23/1000000*'🔧 Cenário Ativo'!B11+'🔧 Cenário Ativo'!B24/1000000*'🔧 Cenário Ativo'!B12)*(1-'🔧 Cenário Ativo'!B13)*'🔧 Cenário Ativo'!B10) | Z16: =Z7*('🔧 Cenário Ativo'!B19*('🔧 Cenário Ativo'!B20/1000000*'🔧 Cenário Ativo'!B11+'🔧 Cenário Ativo'!B21/1000000*'🔧 Cenário Ativo'!B12)*(1-'🔧 Cenário Ativo'!B13)*'🔧 Cenário Ativo'!B10+'🔧 Cenário Ativo'!B22*('🔧 Cenário Ativo'!B23/1000000*'🔧 Cenário Ativo'!B11+'🔧 Cenário Ativo'!B24/1000000*'🔧 Cenário Ativo'!B12)*(1-'🔧 Cenário Ativo'!B13)*'🔧 Cenário Ativo'!B10)
A17: API Livre (+2 agentes) | B17: R$ | C17: =C8*('🔧 Cenário Ativo'!B19*('🔧 Cenário Ativo'!B20/1000000*'🔧 Cenário Ativo'!B11+'🔧 Cenário Ativo'!B21/1000000*'🔧 Cenário Ativo'!B12)*(1-'🔧 Cenário Ativo'!B13)*'🔧 Cenário Ativo'!B10+'🔧 Cenário Ativo'!B25*('🔧 Cenário Ativo'!B23/1000000*'🔧 Cenário Ativo'!B11+'🔧 Cenário Ativo'!B24/1000000*'🔧 Cenário Ativo'!B12)*(1-'🔧 Cenário Ativo'!B13)*'🔧 Cenário Ativo'!B10) | D17: =D8*('🔧 Cenário Ativo'!B19*('🔧 Cenário Ativo'!B20/1000000*'🔧 Cenário Ativo'!B11+'🔧 Cenário Ativo'!B21/1000000*'🔧 Cenário Ativo'!B12)*(1-'🔧 Cenário Ativo'!B13)*'🔧 Cenário Ativo'!B10+'🔧 Cenário Ativo'!B25*('🔧 Cenário Ativo'!B23/1000000*'🔧 Cenário Ativo'!B11+'🔧 Cenário Ativo'!B24/1000000*'🔧 Cenário Ativo'!B12)*(1-'🔧 Cenário Ativo'!B13)*'🔧 Cenário Ativo'!B10) | E17: =E8*('🔧 Cenário Ativo'!B19*('🔧 Cenário Ativo'!B20/1000000*'🔧 Cenário Ativo'!B11+'🔧 Cenário Ativo'!B21/1000000*'🔧 Cenário Ativo'!B12)*(1-'🔧 Cenário Ativo'!B13)*'🔧 Cenário Ativo'!B10+'🔧 Cenário Ativo'!B25*('🔧 Cenário Ativo'!B23/1000000*'🔧 Cenário Ativo'!B11+'🔧 Cenário Ativo'!B24/1000000*'🔧 Cenário Ativo'!B12)*(1-'🔧 Cenário Ativo'!B13)*'🔧 Cenário Ativo'!B10) | F17: =F8*('🔧 Cenário Ativo'!B19*('🔧 Cenário Ativo'!B20/1000000*'🔧 Cenário Ativo'!B11+'🔧 Cenário Ativo'!B21/1000000*'🔧 Cenário Ativo'!B12)*(1-'🔧 Cenário Ativo'!B13)*'🔧 Cenário Ativo'!B10+'🔧 Cenário Ativo'!B25*('🔧 Cenário Ativo'!B23/1000000*'🔧 Cenário Ativo'!B11+'🔧 Cenário Ativo'!B24/1000000*'🔧 Cenário Ativo'!B12)*(1-'🔧 Cenário Ativo'!B13)*'🔧 Cenário Ativo'!B10) | G17: =G8*('🔧 Cenário Ativo'!B19*('🔧 Cenário Ativo'!B20/1000000*'🔧 Cenário Ativo'!B11+'🔧 Cenário Ativo'!B21/1000000*'🔧 Cenário Ativo'!B12)*(1-'🔧 Cenário Ativo'!B13)*'🔧 Cenário Ativo'!B10+'🔧 Cenário Ativo'!B25*('🔧 Cenário Ativo'!B23/1000000*'🔧 Cenário Ativo'!B11+'🔧 Cenário Ativo'!B24/1000000*'🔧 Cenário Ativo'!B12)*(1-'🔧 Cenário Ativo'!B13)*'🔧 Cenário Ativo'!B10) | H17: =H8*('🔧 Cenário Ativo'!B19*('🔧 Cenário Ativo'!B20/1000000*'🔧 Cenário Ativo'!B11+'🔧 Cenário Ativo'!B21/1000000*'🔧 Cenário Ativo'!B12)*(1-'🔧 Cenário Ativo'!B13)*'🔧 Cenário Ativo'!B10+'🔧 Cenário Ativo'!B25*('🔧 Cenário Ativo'!B23/1000000*'🔧 Cenário Ativo'!B11+'🔧 Cenário Ativo'!B24/1000000*'🔧 Cenário Ativo'!B12)*(1-'🔧 Cenário Ativo'!B13)*'🔧 Cenário Ativo'!B10) | I17: =I8*('🔧 Cenário Ativo'!B19*('🔧 Cenário Ativo'!B20/1000000*'🔧 Cenário Ativo'!B11+'🔧 Cenário Ativo'!B21/1000000*'🔧 Cenário Ativo'!B12)*(1-'🔧 Cenário Ativo'!B13)*'🔧 Cenário Ativo'!B10+'🔧 Cenário Ativo'!B25*('🔧 Cenário Ativo'!B23/1000000*'🔧 Cenário Ativo'!B11+'🔧 Cenário Ativo'!B24/1000000*'🔧 Cenário Ativo'!B12)*(1-'🔧 Cenário Ativo'!B13)*'🔧 Cenário Ativo'!B10) | J17: =J8*('🔧 Cenário Ativo'!B19*('🔧 Cenário Ativo'!B20/1000000*'🔧 Cenário Ativo'!B11+'🔧 Cenário Ativo'!B21/1000000*'🔧 Cenário Ativo'!B12)*(1-'🔧 Cenário Ativo'!B13)*'🔧 Cenário Ativo'!B10+'🔧 Cenário Ativo'!B25*('🔧 Cenário Ativo'!B23/1000000*'🔧 Cenário Ativo'!B11+'🔧 Cenário Ativo'!B24/1000000*'🔧 Cenário Ativo'!B12)*(1-'🔧 Cenário Ativo'!B13)*'🔧 Cenário Ativo'!B10) | K17: =K8*('🔧 Cenário Ativo'!B19*('🔧 Cenário Ativo'!B20/1000000*'🔧 Cenário Ativo'!B11+'🔧 Cenário Ativo'!B21/1000000*'🔧 Cenário Ativo'!B12)*(1-'🔧 Cenário Ativo'!B13)*'🔧 Cenário Ativo'!B10+'🔧 Cenário Ativo'!B25*('🔧 Cenário Ativo'!B23/1000000*'🔧 Cenário Ativo'!B11+'🔧 Cenário Ativo'!B24/1000000*'🔧 Cenário Ativo'!B12)*(1-'🔧 Cenário Ativo'!B13)*'🔧 Cenário Ativo'!B10) | L17: =L8*('🔧 Cenário Ativo'!B19*('🔧 Cenário Ativo'!B20/1000000*'🔧 Cenário Ativo'!B11+'🔧 Cenário Ativo'!B21/1000000*'🔧 Cenário Ativo'!B12)*(1-'🔧 Cenário Ativo'!B13)*'🔧 Cenário Ativo'!B10+'🔧 Cenário Ativo'!B25*('🔧 Cenário Ativo'!B23/1000000*'🔧 Cenário Ativo'!B11+'🔧 Cenário Ativo'!B24/1000000*'🔧 Cenário Ativo'!B12)*(1-'🔧 Cenário Ativo'!B13)*'🔧 Cenário Ativo'!B10) | M17: =M8*('🔧 Cenário Ativo'!B19*('🔧 Cenário Ativo'!B20/1000000*'🔧 Cenário Ativo'!B11+'🔧 Cenário Ativo'!B21/1000000*'🔧 Cenário Ativo'!B12)*(1-'🔧 Cenário Ativo'!B13)*'🔧 Cenário Ativo'!B10+'🔧 Cenário Ativo'!B25*('🔧 Cenário Ativo'!B23/1000000*'🔧 Cenário Ativo'!B11+'🔧 Cenário Ativo'!B24/1000000*'🔧 Cenário Ativo'!B12)*(1-'🔧 Cenário Ativo'!B13)*'🔧 Cenário Ativo'!B10) | N17: =N8*('🔧 Cenário Ativo'!B19*('🔧 Cenário Ativo'!B20/1000000*'🔧 Cenário Ativo'!B11+'🔧 Cenário Ativo'!B21/1000000*'🔧 Cenário Ativo'!B12)*(1-'🔧 Cenário Ativo'!B13)*'🔧 Cenário Ativo'!B10+'🔧 Cenário Ativo'!B25*('🔧 Cenário Ativo'!B23/1000000*'🔧 Cenário Ativo'!B11+'🔧 Cenário Ativo'!B24/1000000*'🔧 Cenário Ativo'!B12)*(1-'🔧 Cenário Ativo'!B13)*'🔧 Cenário Ativo'!B10) | O17: =O8*('🔧 Cenário Ativo'!B19*('🔧 Cenário Ativo'!B20/1000000*'🔧 Cenário Ativo'!B11+'🔧 Cenário Ativo'!B21/1000000*'🔧 Cenário Ativo'!B12)*(1-'🔧 Cenário Ativo'!B13)*'🔧 Cenário Ativo'!B10+'🔧 Cenário Ativo'!B25*('🔧 Cenário Ativo'!B23/1000000*'🔧 Cenário Ativo'!B11+'🔧 Cenário Ativo'!B24/1000000*'🔧 Cenário Ativo'!B12)*(1-'🔧 Cenário Ativo'!B13)*'🔧 Cenário Ativo'!B10) | P17: =P8*('🔧 Cenário Ativo'!B19*('🔧 Cenário Ativo'!B20/1000000*'🔧 Cenário Ativo'!B11+'🔧 Cenário Ativo'!B21/1000000*'🔧 Cenário Ativo'!B12)*(1-'🔧 Cenário Ativo'!B13)*'🔧 Cenário Ativo'!B10+'🔧 Cenário Ativo'!B25*('🔧 Cenário Ativo'!B23/1000000*'🔧 Cenário Ativo'!B11+'🔧 Cenário Ativo'!B24/1000000*'🔧 Cenário Ativo'!B12)*(1-'🔧 Cenário Ativo'!B13)*'🔧 Cenário Ativo'!B10) | Q17: =Q8*('🔧 Cenário Ativo'!B19*('🔧 Cenário Ativo'!B20/1000000*'🔧 Cenário Ativo'!B11+'🔧 Cenário Ativo'!B21/1000000*'🔧 Cenário Ativo'!B12)*(1-'🔧 Cenário Ativo'!B13)*'🔧 Cenário Ativo'!B10+'🔧 Cenário Ativo'!B25*('🔧 Cenário Ativo'!B23/1000000*'🔧 Cenário Ativo'!B11+'🔧 Cenário Ativo'!B24/1000000*'🔧 Cenário Ativo'!B12)*(1-'🔧 Cenário Ativo'!B13)*'🔧 Cenário Ativo'!B10) | R17: =R8*('🔧 Cenário Ativo'!B19*('🔧 Cenário Ativo'!B20/1000000*'🔧 Cenário Ativo'!B11+'🔧 Cenário Ativo'!B21/1000000*'🔧 Cenário Ativo'!B12)*(1-'🔧 Cenário Ativo'!B13)*'🔧 Cenário Ativo'!B10+'🔧 Cenário Ativo'!B25*('🔧 Cenário Ativo'!B23/1000000*'🔧 Cenário Ativo'!B11+'🔧 Cenário Ativo'!B24/1000000*'🔧 Cenário Ativo'!B12)*(1-'🔧 Cenário Ativo'!B13)*'🔧 Cenário Ativo'!B10) | S17: =S8*('🔧 Cenário Ativo'!B19*('🔧 Cenário Ativo'!B20/1000000*'🔧 Cenário Ativo'!B11+'🔧 Cenário Ativo'!B21/1000000*'🔧 Cenário Ativo'!B12)*(1-'🔧 Cenário Ativo'!B13)*'🔧 Cenário Ativo'!B10+'🔧 Cenário Ativo'!B25*('🔧 Cenário Ativo'!B23/1000000*'🔧 Cenário Ativo'!B11+'🔧 Cenário Ativo'!B24/1000000*'🔧 Cenário Ativo'!B12)*(1-'🔧 Cenário Ativo'!B13)*'🔧 Cenário Ativo'!B10) | T17: =T8*('🔧 Cenário Ativo'!B19*('🔧 Cenário Ativo'!B20/1000000*'🔧 Cenário Ativo'!B11+'🔧 Cenário Ativo'!B21/1000000*'🔧 Cenário Ativo'!B12)*(1-'🔧 Cenário Ativo'!B13)*'🔧 Cenário Ativo'!B10+'🔧 Cenário Ativo'!B25*('🔧 Cenário Ativo'!B23/1000000*'🔧 Cenário Ativo'!B11+'🔧 Cenário Ativo'!B24/1000000*'🔧 Cenário Ativo'!B12)*(1-'🔧 Cenário Ativo'!B13)*'🔧 Cenário Ativo'!B10) | U17: =U8*('🔧 Cenário Ativo'!B19*('🔧 Cenário Ativo'!B20/1000000*'🔧 Cenário Ativo'!B11+'🔧 Cenário Ativo'!B21/1000000*'🔧 Cenário Ativo'!B12)*(1-'🔧 Cenário Ativo'!B13)*'🔧 Cenário Ativo'!B10+'🔧 Cenário Ativo'!B25*('🔧 Cenário Ativo'!B23/1000000*'🔧 Cenário Ativo'!B11+'🔧 Cenário Ativo'!B24/1000000*'🔧 Cenário Ativo'!B12)*(1-'🔧 Cenário Ativo'!B13)*'🔧 Cenário Ativo'!B10) | V17: =V8*('🔧 Cenário Ativo'!B19*('🔧 Cenário Ativo'!B20/1000000*'🔧 Cenário Ativo'!B11+'🔧 Cenário Ativo'!B21/1000000*'🔧 Cenário Ativo'!B12)*(1-'🔧 Cenário Ativo'!B13)*'🔧 Cenário Ativo'!B10+'🔧 Cenário Ativo'!B25*('🔧 Cenário Ativo'!B23/1000000*'🔧 Cenário Ativo'!B11+'🔧 Cenário Ativo'!B24/1000000*'🔧 Cenário Ativo'!B12)*(1-'🔧 Cenário Ativo'!B13)*'🔧 Cenário Ativo'!B10) | W17: =W8*('🔧 Cenário Ativo'!B19*('🔧 Cenário Ativo'!B20/1000000*'🔧 Cenário Ativo'!B11+'🔧 Cenário Ativo'!B21/1000000*'🔧 Cenário Ativo'!B12)*(1-'🔧 Cenário Ativo'!B13)*'🔧 Cenário Ativo'!B10+'🔧 Cenário Ativo'!B25*('🔧 Cenário Ativo'!B23/1000000*'🔧 Cenário Ativo'!B11+'🔧 Cenário Ativo'!B24/1000000*'🔧 Cenário Ativo'!B12)*(1-'🔧 Cenário Ativo'!B13)*'🔧 Cenário Ativo'!B10) | X17: =X8*('🔧 Cenário Ativo'!B19*('🔧 Cenário Ativo'!B20/1000000*'🔧 Cenário Ativo'!B11+'🔧 Cenário Ativo'!B21/1000000*'🔧 Cenário Ativo'!B12)*(1-'🔧 Cenário Ativo'!B13)*'🔧 Cenário Ativo'!B10+'🔧 Cenário Ativo'!B25*('🔧 Cenário Ativo'!B23/1000000*'🔧 Cenário Ativo'!B11+'🔧 Cenário Ativo'!B24/1000000*'🔧 Cenário Ativo'!B12)*(1-'🔧 Cenário Ativo'!B13)*'🔧 Cenário Ativo'!B10) | Y17: =Y8*('🔧 Cenário Ativo'!B19*('🔧 Cenário Ativo'!B20/1000000*'🔧 Cenário Ativo'!B11+'🔧 Cenário Ativo'!B21/1000000*'🔧 Cenário Ativo'!B12)*(1-'🔧 Cenário Ativo'!B13)*'🔧 Cenário Ativo'!B10+'🔧 Cenário Ativo'!B25*('🔧 Cenário Ativo'!B23/1000000*'🔧 Cenário Ativo'!B11+'🔧 Cenário Ativo'!B24/1000000*'🔧 Cenário Ativo'!B12)*(1-'🔧 Cenário Ativo'!B13)*'🔧 Cenário Ativo'!B10) | Z17: =Z8*('🔧 Cenário Ativo'!B19*('🔧 Cenário Ativo'!B20/1000000*'🔧 Cenário Ativo'!B11+'🔧 Cenário Ativo'!B21/1000000*'🔧 Cenário Ativo'!B12)*(1-'🔧 Cenário Ativo'!B13)*'🔧 Cenário Ativo'!B10+'🔧 Cenário Ativo'!B25*('🔧 Cenário Ativo'!B23/1000000*'🔧 Cenário Ativo'!B11+'🔧 Cenário Ativo'!B24/1000000*'🔧 Cenário Ativo'!B12)*(1-'🔧 Cenário Ativo'!B13)*'🔧 Cenário Ativo'!B10)
A18: TOTAL API | B18: R$ | C18: =SUM(C14:C17) | D18: =SUM(D14:D17) | E18: =SUM(E14:E17) | F18: =SUM(F14:F17) | G18: =SUM(G14:G17) | H18: =SUM(H14:H17) | I18: =SUM(I14:I17) | J18: =SUM(J14:J17) | ... Z18: =SUM(Z14:Z17)
A19: CUSTO FIXO
A20: Custo Fixo (equipe+infra+mkt) | B20: R$ | C20: ='🔧 Cenário Ativo'!B36+'🔧 Cenário Ativo'!B38+'🔧 Cenário Ativo'!B40+'🔧 Cenário Ativo'!B42 | D20: ='🔧 Cenário Ativo'!B36+'🔧 Cenário Ativo'!B38+'🔧 Cenário Ativo'!B40+'🔧 Cenário Ativo'!B42 | E20: ='🔧 Cenário Ativo'!B36+'🔧 Cenário Ativo'!B38+'🔧 Cenário Ativo'!B40+'🔧 Cenário Ativo'!B42 | F20: ='🔧 Cenário Ativo'!B36+'🔧 Cenário Ativo'!B38+'🔧 Cenário Ativo'!B40+'🔧 Cenário Ativo'!B42 | G20: ='🔧 Cenário Ativo'!B36+'🔧 Cenário Ativo'!B38+'🔧 Cenário Ativo'!B40+'🔧 Cenário Ativo'!B42 | H20: ='🔧 Cenário Ativo'!B36+'🔧 Cenário Ativo'!B38+'🔧 Cenário Ativo'!B40+'🔧 Cenário Ativo'!B42 | I20: ='🔧 Cenário Ativo'!B36+'🔧 Cenário Ativo'!B38+'🔧 Cenário Ativo'!B40+'🔧 Cenário Ativo'!B42 | J20: ='🔧 Cenário Ativo'!B36+'🔧 Cenário Ativo'!B38+'🔧 Cenário Ativo'!B40+'🔧 Cenário Ativo'!B42 | K20: ='🔧 Cenário Ativo'!B36+'🔧 Cenário Ativo'!B38+'🔧 Cenário Ativo'!B40+'🔧 Cenário Ativo'!B42 | L20: ='🔧 Cenário Ativo'!B36+'🔧 Cenário Ativo'!B38+'🔧 Cenário Ativo'!B40+'🔧 Cenário Ativo'!B42 | M20: ='🔧 Cenário Ativo'!B36+'🔧 Cenário Ativo'!B38+'🔧 Cenário Ativo'!B40+'🔧 Cenário Ativo'!B42 | N20: ='🔧 Cenário Ativo'!B36+'🔧 Cenário Ativo'!B38+'🔧 Cenário Ativo'!B40+'🔧 Cenário Ativo'!B42 | O20: ='🔧 Cenário Ativo'!B37+'🔧 Cenário Ativo'!B39+'🔧 Cenário Ativo'!B41+'🔧 Cenário Ativo'!B42 | P20: ='🔧 Cenário Ativo'!B37+'🔧 Cenário Ativo'!B39+'🔧 Cenário Ativo'!B41+'🔧 Cenário Ativo'!B42 | Q20: ='🔧 Cenário Ativo'!B37+'🔧 Cenário Ativo'!B39+'🔧 Cenário Ativo'!B41+'🔧 Cenário Ativo'!B42 | R20: ='🔧 Cenário Ativo'!B37+'🔧 Cenário Ativo'!B39+'🔧 Cenário Ativo'!B41+'🔧 Cenário Ativo'!B42 | S20: ='🔧 Cenário Ativo'!B37+'🔧 Cenário Ativo'!B39+'🔧 Cenário Ativo'!B41+'🔧 Cenário Ativo'!B42 | T20: ='🔧 Cenário Ativo'!B37+'🔧 Cenário Ativo'!B39+'🔧 Cenário Ativo'!B41+'🔧 Cenário Ativo'!B42 | U20: ='🔧 Cenário Ativo'!B37+'🔧 Cenário Ativo'!B39+'🔧 Cenário Ativo'!B41+'🔧 Cenário Ativo'!B42 | V20: ='🔧 Cenário Ativo'!B37+'🔧 Cenário Ativo'!B39+'🔧 Cenário Ativo'!B41+'🔧 Cenário Ativo'!B42 | W20: ='🔧 Cenário Ativo'!B37+'🔧 Cenário Ativo'!B39+'🔧 Cenário Ativo'!B41+'🔧 Cenário Ativo'!B42 | X20: ='🔧 Cenário Ativo'!B37+'🔧 Cenário Ativo'!B39+'🔧 Cenário Ativo'!B41+'🔧 Cenário Ativo'!B42 | Y20: ='🔧 Cenário Ativo'!B37+'🔧 Cenário Ativo'!B39+'🔧 Cenário Ativo'!B41+'🔧 Cenário Ativo'!B42 | Z20: ='🔧 Cenário Ativo'!B37+'🔧 Cenário Ativo'!B39+'🔧 Cenário Ativo'!B41+'🔧 Cenário Ativo'!B42
A21: IMPOSTOS | B21: R$ | C21: =C11*'🔧 Cenário Ativo'!$B$56 | D21: =D11*'🔧 Cenário Ativo'!$B$56 | E21: =E11*'🔧 Cenário Ativo'!$B$56 | F21: =F11*'🔧 Cenário Ativo'!$B$56 | G21: =G11*'🔧 Cenário Ativo'!$B$56 | H21: =H11*'🔧 Cenário Ativo'!$B$56 | I21: =I11*'🔧 Cenário Ativo'!$B$56 | J21: =J11*'🔧 Cenário Ativo'!$B$56 | ... Z21: =Z11*'🔧 Cenário Ativo'!$B$56
A22: RESULTADO
A23: Custo Total (API + Fixo + Impostos) | B23: R$ | C23: =C18+C20+C21 | D23: =D18+D20+D21 | E23: =E18+E20+E21 | F23: =F18+F20+F21 | G23: =G18+G20+G21 | H23: =H18+H20+H21 | I23: =I18+I20+I21 | J23: =J18+J20+J21 | ... Z23: =Z18+Z20+Z21
A24: RESULTADO MENSAL | B24: R$ | C24: =C11-C23 | D24: =D11-D23 | E24: =E11-E23 | F24: =F11-F23 | G24: =G11-G23 | H24: =H11-H23 | I24: =I11-I23 | J24: =J11-J23 | ... Z24: =Z11-Z23
A25: RESULTADO ACUMULADO | B25: R$ | C25: =C24 | D25: =C25+D24 | E25: =D25+E24 | F25: =E25+F24 | G25: =F25+G24 | H25: =G25+H24 | I25: =H25+I24 | J25: =I25+J24 | K25: =J25+K24 | ... Z25: =Y25+Z24
A26: Margem Bruta API (% MRR) | B26: % | C26: =IF(C11=0,0,1-C18/C11) | D26: =IF(D11=0,0,1-D18/D11) | E26: =IF(E11=0,0,1-E18/E11) | F26: =IF(F11=0,0,1-F18/F11) | G26: =IF(G11=0,0,1-G18/G11) | H26: =IF(H11=0,0,1-H18/H11) | I26: =IF(I11=0,0,1-I18/I11) | J26: =IF(J11=0,0,1-J18/J11) | ... Z26: =IF(Z11=0,0,1-Z18/Z11)

Sheet 📊 Resumo Cenários
A1: AutoNoma · Comparativo Real de Cenários · 3 Anos · Fórmulas Dinâmicas
A2: Comparativo dos 3 cenários · Premissas / Unit Economics / Valuation / Operacional · Independentes
A3: INDICADOR | B3: Conservador | C3: Base (padrão) | D3: Otimista | E3: UNIDADE
A4: PREMISSAS DIFERENCIADORAS POR CENÁRIO
A5: CAC Real (full-loaded) | B5: ='🎛️ Premissas'!B45 | C5: ='🎛️ Premissas'!C45 | D5: ='🎛️ Premissas'!D45 | E5: R$/assinante
A6: Churn mensal Essencial | B6: ='🎛️ Premissas'!B33 | C6: ='🎛️ Premissas'!C33 | D6: ='🎛️ Premissas'!D33 | E6: %/mês
A7: Churn anual implícito | B7: =1-(1-'🎛️ Premissas'!B33)^12 | C7: =1-(1-'🎛️ Premissas'!C33)^12 | D7: =1-(1-'🎛️ Premissas'!D33)^12 | E7: %/ano
A8: Múltiplo valuation M24 | B8: ='🎛️ Premissas'!B49 | C8: ='🎛️ Premissas'!C49 | D8: ='🎛️ Premissas'!D49 | E8: × ARR (SaaS LATAM)
A9: Free: % usuárias ativas | B9: ='🎛️ Premissas'!B17 | C9: ='🎛️ Premissas'!C17 | D9: ='🎛️ Premissas'!D17 | E9: % do cadastro
A10: Conversão Free→Essencial | B10: ='🎛️ Premissas'!B30 | C10: ='🎛️ Premissas'!C30 | D10: ='🎛️ Premissas'!D30 | E10: % base Free
A11: UNIT ECONOMICS (calculado das premissas)
A12: Custo API Essencial/mês | B12: =('🎛️ Premissas'!B18*('🎛️ Premissas'!B19/1000000*'🎛️ Premissas'!B10+'🎛️ Premissas'!B20/1000000*'🎛️ Premissas'!B11)*(1-'🎛️ Premissas'!B12)*'🎛️ Premissas'!B9) | C12: =('🎛️ Premissas'!C18*('🎛️ Premissas'!C19/1000000*'🎛️ Premissas'!C10+'🎛️ Premissas'!C20/1000000*'🎛️ Premissas'!C11)*(1-'🎛️ Premissas'!C12)*'🎛️ Premissas'!C9) | D12: =('🎛️ Premissas'!D18*('🎛️ Premissas'!D19/1000000*'🎛️ Premissas'!D10+'🎛️ Premissas'!D20/1000000*'🎛️ Premissas'!D11)*(1-'🎛️ Premissas'!D12)*'🎛️ Premissas'!D9) | E12: R$/assinante/mês
A13: Margem Unitária Essencial/mês | B13: =('🎛️ Premissas'!B5-('🎛️ Premissas'!B18*('🎛️ Premissas'!B19/1000000*'🎛️ Premissas'!B10+'🎛️ Premissas'!B20/1000000*'🎛️ Premissas'!B11)*(1-'🎛️ Premissas'!B12)*'🎛️ Premissas'!B9)) | C13: =('🎛️ Premissas'!C5-('🎛️ Premissas'!C18*('🎛️ Premissas'!C19/1000000*'🎛️ Premissas'!C10+'🎛️ Premissas'!C20/1000000*'🎛️ Premissas'!C11)*(1-'🎛️ Premissas'!C12)*'🎛️ Premissas'!C9)) | D13: =('🎛️ Premissas'!D5-('🎛️ Premissas'!D18*('🎛️ Premissas'!D19/1000000*'🎛️ Premissas'!D10+'🎛️ Premissas'!D20/1000000*'🎛️ Premissas'!D11)*(1-'🎛️ Premissas'!D12)*'🎛️ Premissas'!D9)) | E13: R$/mês
A14: Vida média (meses) | B14: 15 | C14: 15 | D14: 15 | E14: 1 ÷ churn
A15: LTV Essencial | B15: =B13*B14 | C15: =C13*C14 | D15: =D13*D14 | E15: R$ vida útil
A16: LTV / CAC | B16: =IFERROR(B15/B5,0) | C16: =IFERROR(C15/C5,0) | D16: =IFERROR(D15/D5,0) | E16: ≥3× ok · ≥8× top quartile
A17: Payback CAC (meses) | B17: =IFERROR(B5/B13,0) | C17: =IFERROR(C5/C13,0) | D17: =IFERROR(D5/D13,0) | E17: meses
A18: VALUATION · MÊS 24 (Receita Acum × múltiplo)
A19: Receita Acumulada 24m (Z12) | B19: =SUM(B56:Y56) | C19: =SUM(B68:Y68) | D19: =SUM(B80:Y80) | E19: R$ acumulado 24m
A20: Múltiplo aplicado | B20: ='🎛️ Premissas'!B49 | C20: ='🎛️ Premissas'!C49 | D20: ='🎛️ Premissas'!D49 | E20: × Receita acum
A21: VALUATION SUGERIDO M24 | B21: =B19*B20 | C21: =C19*C20 | D21: =D19*D20 | E21: R$
A22: Equity anjo (% Premissas) | B22: =B21*'🎛️ Premissas'!$B$56 | C22: =C21*'🎛️ Premissas'!$B$56 | D22: =D21*'🎛️ Premissas'!$B$56 | E22: R$
A23: Retorno sobre aporte (×) | B23: =B22/'🎛️ Premissas'!$B$55 | C23: =C22/'🎛️ Premissas'!$B$55 | D23: =D22/'🎛️ Premissas'!$B$55 | E23: × sobre aporte
A24: ANO 1 · Resultados
A25: MRR Dezembro M12 | B25: =M56 | C25: =M68 | D25: =M80 | E25: R$/mês
A26: ARR Ano 1 (MRR×12) | B26: =M56*12 | C26: =M68*12 | D26: =M80*12 | E26: R$/ano
A27: Resultado Líquido no Ano | B27: =SUM(B60:M60) | C27: =SUM(B72:M72) | D27: =SUM(B84:M84) | E27: R$
A28: Pagantes M12 | B28: =M55 | C28: =M67 | D28: =M79 | E28: assinantes
A29: ANO 2 · Resultados
A30: MRR Dezembro M24 | B30: =Y56 | C30: =Y68 | D30: =Y80 | E30: R$/mês
A31: ARR Ano 2 (MRR×12) | B31: =Y56*12 | C31: =Y68*12 | D31: =Y80*12 | E31: R$/ano
A32: Resultado Líquido no Ano | B32: =SUM(N60:Y60) | C32: =SUM(N72:Y72) | D32: =SUM(N84:Y84) | E32: R$
A33: Pagantes M24 | B33: =Y55 | C33: =Y67 | D33: =Y79 | E33: assinantes
A34: RESUMO
A35: VPL (Valor Presente Líquido) | B35: =-'🎛️ Premissas'!$B$55+NPV('🎛️ Premissas'!$B$66,C86:Z86) | C35: =-'🎛️ Premissas'!$B$55+NPV('🎛️ Premissas'!$B$66,C87:Z87) | D35: =-'🎛️ Premissas'!$B$55+NPV('🎛️ Premissas'!$B$66,C88:Z88) | E35: R$ · taxa B66 mensal
A36: TIR (anualizada) | B36: =IFERROR((1+IRR(B86:Z86,'🎛️ Premissas'!$B$66))^12-1,"n/a") | C36: =IFERROR((1+IRR(B87:Z87,'🎛️ Premissas'!$B$66))^12-1,"n/a") | D36: =IFERROR((1+IRR(B88:Z88,'🎛️ Premissas'!$B$66))^12-1,"n/a") | E36: % a.a.
A37: ✅ Todos os indicadores acima são calculados independentemente por cenário. Helpers de simulação ocultos linhas 50-89.
A49: ── HELPERS · 3 CENÁRIOS · 24 MESES (oculto) ── | B49: M1 | C49: M2 | D49: M3 | E49: M4 | F49: M5 | G49: M6 | H49: M7 | I49: M8 | J49: M9 | K49: M10 | L49: M11 | M49: M12 | N49: M13 | O49: M14 | P49: M15 | Q49: M16 | R49: M17 | S49: M18 | T49: M19 | U49: M20 | V49: M21 | W49: M22 | X49: M23 | Y49: M24
A50: CONSERVADOR
A51: Free Cadastros | B51: ='🎛️ Premissas'!$B$61 | C51: =B51+'🎛️ Premissas'!$B$28 | D51: =C51+'🎛️ Premissas'!$B$28 | E51: =D51+'🎛️ Premissas'!$B$28 | F51: =E51+'🎛️ Premissas'!$B$28 | G51: =F51+'🎛️ Premissas'!$B$28 | H51: =G51+'🎛️ Premissas'!$B$28 | I51: =H51+'🎛️ Premissas'!$B$28 | J51: =I51+'🎛️ Premissas'!$B$28 | ... M51: =L51+'🎛️ Premissas'!$B$28 | N51: =M51+'🎛️ Premissas'!$B$29 | O51: =N51+'🎛️ Premissas'!$B$29 | P51: =O51+'🎛️ Premissas'!$B$29 | Q51: =P51+'🎛️ Premissas'!$B$29 | R51: =Q51+'🎛️ Premissas'!$B$29 | S51: =R51+'🎛️ Premissas'!$B$29 | T51: =S51+'🎛️ Premissas'!$B$29 | U51: =T51+'🎛️ Premissas'!$B$29 | ... Y51: =X51+'🎛️ Premissas'!$B$29
A52: Essencial | B52: =ROUND(B51*'🎛️ Premissas'!$B$30,0) | C52: =ROUND(C51*'🎛️ Premissas'!$B$30,0) | D52: =ROUND(D51*'🎛️ Premissas'!$B$30,0) | E52: =ROUND(E51*'🎛️ Premissas'!$B$30,0) | F52: =ROUND(F51*'🎛️ Premissas'!$B$30,0) | G52: =ROUND(G51*'🎛️ Premissas'!$B$30,0) | H52: =ROUND(H51*'🎛️ Premissas'!$B$30,0) | I52: =ROUND(I51*'🎛️ Premissas'!$B$30,0) | ... M52: =ROUND(M51*'🎛️ Premissas'!$B$30,0) | N52: =ROUND(M52*(1-'🎛️ Premissas'!$B$33)+MAX(0,N51-M55)*'🎛️ Premissas'!$B$30,0) | O52: =ROUND(N52*(1-'🎛️ Premissas'!$B$33)+MAX(0,O51-N55)*'🎛️ Premissas'!$B$30,0) | P52: =ROUND(O52*(1-'🎛️ Premissas'!$B$33)+MAX(0,P51-O55)*'🎛️ Premissas'!$B$30,0) | Q52: =ROUND(P52*(1-'🎛️ Premissas'!$B$33)+MAX(0,Q51-P55)*'🎛️ Premissas'!$B$30,0) | R52: =ROUND(Q52*(1-'🎛️ Premissas'!$B$33)+MAX(0,R51-Q55)*'🎛️ Premissas'!$B$30,0) | S52: =ROUND(R52*(1-'🎛️ Premissas'!$B$33)+MAX(0,S51-R55)*'🎛️ Premissas'!$B$30,0) | T52: =ROUND(S52*(1-'🎛️ Premissas'!$B$33)+MAX(0,T51-S55)*'🎛️ Premissas'!$B$30,0) | U52: =ROUND(T52*(1-'🎛️ Premissas'!$B$33)+MAX(0,U51-T55)*'🎛️ Premissas'!$B$30,0) | ... Y52: =ROUND(X52*(1-'🎛️ Premissas'!$B$33)+MAX(0,Y51-X55)*'🎛️ Premissas'!$B$30,0)
A53: Autônoma | B53: =ROUND(B51*'🎛️ Premissas'!$B$31,0) | C53: =ROUND(C51*'🎛️ Premissas'!$B$31,0) | D53: =ROUND(D51*'🎛️ Premissas'!$B$31,0) | E53: =ROUND(E51*'🎛️ Premissas'!$B$31,0) | F53: =ROUND(F51*'🎛️ Premissas'!$B$31,0) | G53: =ROUND(G51*'🎛️ Premissas'!$B$31,0) | H53: =ROUND(H51*'🎛️ Premissas'!$B$31,0) | I53: =ROUND(I51*'🎛️ Premissas'!$B$31,0) | ... M53: =ROUND(M51*'🎛️ Premissas'!$B$31,0) | N53: =ROUND(M53*(1-'🎛️ Premissas'!$B$34)+MAX(0,N52-M52-M53)*'🎛️ Premissas'!$B$31,0) | O53: =ROUND(N53*(1-'🎛️ Premissas'!$B$34)+MAX(0,O52-N52-N53)*'🎛️ Premissas'!$B$31,0) | P53: =ROUND(O53*(1-'🎛️ Premissas'!$B$34)+MAX(0,P52-O52-O53)*'🎛️ Premissas'!$B$31,0) | Q53: =ROUND(P53*(1-'🎛️ Premissas'!$B$34)+MAX(0,Q52-P52-P53)*'🎛️ Premissas'!$B$31,0) | R53: =ROUND(Q53*(1-'🎛️ Premissas'!$B$34)+MAX(0,R52-Q52-Q53)*'🎛️ Premissas'!$B$31,0) | S53: =ROUND(R53*(1-'🎛️ Premissas'!$B$34)+MAX(0,S52-R52-R53)*'🎛️ Premissas'!$B$31,0) | T53: =ROUND(S53*(1-'🎛️ Premissas'!$B$34)+MAX(0,T52-S52-S53)*'🎛️ Premissas'!$B$31,0) | U53: =ROUND(T53*(1-'🎛️ Premissas'!$B$34)+MAX(0,U52-T52-T53)*'🎛️ Premissas'!$B$31,0) | ... Y53: =ROUND(X53*(1-'🎛️ Premissas'!$B$34)+MAX(0,Y52-X52-X53)*'🎛️ Premissas'!$B$31,0)
A54: Livre | B54: =ROUND(B51*'🎛️ Premissas'!$B$32,0) | C54: =ROUND(C51*'🎛️ Premissas'!$B$32,0) | D54: =ROUND(D51*'🎛️ Premissas'!$B$32,0) | E54: =ROUND(E51*'🎛️ Premissas'!$B$32,0) | F54: =ROUND(F51*'🎛️ Premissas'!$B$32,0) | G54: =ROUND(G51*'🎛️ Premissas'!$B$32,0) | H54: =ROUND(H51*'🎛️ Premissas'!$B$32,0) | I54: =ROUND(I51*'🎛️ Premissas'!$B$32,0) | ... M54: =ROUND(M51*'🎛️ Premissas'!$B$32,0) | N54: =ROUND(M54*(1-'🎛️ Premissas'!$B$35)+MAX(0,N53-M53)*'🎛️ Premissas'!$B$32,0) | O54: =ROUND(N54*(1-'🎛️ Premissas'!$B$35)+MAX(0,O53-N53)*'🎛️ Premissas'!$B$32,0) | P54: =ROUND(O54*(1-'🎛️ Premissas'!$B$35)+MAX(0,P53-O53)*'🎛️ Premissas'!$B$32,0) | Q54: =ROUND(P54*(1-'🎛️ Premissas'!$B$35)+MAX(0,Q53-P53)*'🎛️ Premissas'!$B$32,0) | R54: =ROUND(Q54*(1-'🎛️ Premissas'!$B$35)+MAX(0,R53-Q53)*'🎛️ Premissas'!$B$32,0) | S54: =ROUND(R54*(1-'🎛️ Premissas'!$B$35)+MAX(0,S53-R53)*'🎛️ Premissas'!$B$32,0) | T54: =ROUND(S54*(1-'🎛️ Premissas'!$B$35)+MAX(0,T53-S53)*'🎛️ Premissas'!$B$32,0) | U54: =ROUND(T54*(1-'🎛️ Premissas'!$B$35)+MAX(0,U53-T53)*'🎛️ Premissas'!$B$32,0) | ... Y54: =ROUND(X54*(1-'🎛️ Premissas'!$B$35)+MAX(0,Y53-X53)*'🎛️ Premissas'!$B$32,0)
A55: Total Pagantes | B55: =SUM(B52:B54) | C55: =SUM(C52:C54) | D55: =SUM(D52:D54) | E55: =SUM(E52:E54) | F55: =SUM(F52:F54) | G55: =SUM(G52:G54) | H55: =SUM(H52:H54) | I55: =SUM(I52:I54) | ... Y55: =SUM(Y52:Y54)
A56: MRR | B56: =B52*'🎛️ Premissas'!$B$5+B53*'🎛️ Premissas'!$B$6+B54*'🎛️ Premissas'!$B$7 | C56: =C52*'🎛️ Premissas'!$B$5+C53*'🎛️ Premissas'!$B$6+C54*'🎛️ Premissas'!$B$7 | D56: =D52*'🎛️ Premissas'!$B$5+D53*'🎛️ Premissas'!$B$6+D54*'🎛️ Premissas'!$B$7 | E56: =E52*'🎛️ Premissas'!$B$5+E53*'🎛️ Premissas'!$B$6+E54*'🎛️ Premissas'!$B$7 | F56: =F52*'🎛️ Premissas'!$B$5+F53*'🎛️ Premissas'!$B$6+F54*'🎛️ Premissas'!$B$7 | G56: =G52*'🎛️ Premissas'!$B$5+G53*'🎛️ Premissas'!$B$6+G54*'🎛️ Premissas'!$B$7 | H56: =H52*'🎛️ Premissas'!$B$5+H53*'🎛️ Premissas'!$B$6+H54*'🎛️ Premissas'!$B$7 | I56: =I52*'🎛️ Premissas'!$B$5+I53*'🎛️ Premissas'!$B$6+I54*'🎛️ Premissas'!$B$7 | ... Y56: =Y52*'🎛️ Premissas'!$B$5+Y53*'🎛️ Premissas'!$B$6+Y54*'🎛️ Premissas'!$B$7
A57: API Total | B57: =B51*('🎛️ Premissas'!$B$14*('🎛️ Premissas'!$B$15*('🎛️ Premissas'!$B$10/1000000)+'🎛️ Premissas'!$B$16*('🎛️ Premissas'!$B$11/1000000))*(1-'🎛️ Premissas'!$B$12)*'🎛️ Premissas'!$B$9*'🎛️ Premissas'!$B$17)+B52*('🎛️ Premissas'!$B$18*('🎛️ Premissas'!$B$19*('🎛️ Premissas'!$B$10/1000000)+'🎛️ Premissas'!$B$20*('🎛️ Premissas'!$B$11/1000000))*(1-'🎛️ Premissas'!$B$12)*'🎛️ Premissas'!$B$9)+B53*(('🎛️ Premissas'!$B$21*('🎛️ Premissas'!$B$19*('🎛️ Premissas'!$B$10/1000000)+'🎛️ Premissas'!$B$20*('🎛️ Premissas'!$B$11/1000000))*(1-'🎛️ Premissas'!$B$12)*'🎛️ Premissas'!$B$9)+('🎛️ Premissas'!$B$22*('🎛️ Premissas'!$B$23*('🎛️ Premissas'!$B$10/1000000)+'🎛️ Premissas'!$B$24*('🎛️ Premissas'!$B$11/1000000))*(1-'🎛️ Premissas'!$B$12)*'🎛️ Premissas'!$B$9))+B54*(('🎛️ Premissas'!$B$25*('🎛️ Premissas'!$B$19*('🎛️ Premissas'!$B$10/1000000)+'🎛️ Premissas'!$B$20*('🎛️ Premissas'!$B$11/1000000))*(1-'🎛️ Premissas'!$B$12)*'🎛️ Premissas'!$B$9)+('🎛️ Premissas'!$B$26*('🎛️ Premissas'!$B$23*('🎛️ Premissas'!$B$10/1000000)+'🎛️ Premissas'!$B$24*('🎛️ Premissas'!$B$11/1000000))*(1-'🎛️ Premissas'!$B$12)*'🎛️ Premissas'!$B$9)) | C57: =C51*('🎛️ Premissas'!$B$14*('🎛️ Premissas'!$B$15*('🎛️ Premissas'!$B$10/1000000)+'🎛️ Premissas'!$B$16*('🎛️ Premissas'!$B$11/1000000))*(1-'🎛️ Premissas'!$B$12)*'🎛️ Premissas'!$B$9*'🎛️ Premissas'!$B$17)+C52*('🎛️ Premissas'!$B$18*('🎛️ Premissas'!$B$19*('🎛️ Premissas'!$B$10/1000000)+'🎛️ Premissas'!$B$20*('🎛️ Premissas'!$B$11/1000000))*(1-'🎛️ Premissas'!$B$12)*'🎛️ Premissas'!$B$9)+C53*(('🎛️ Premissas'!$B$21*('🎛️ Premissas'!$B$19*('🎛️ Premissas'!$B$10/1000000)+'🎛️ Premissas'!$B$20*('🎛️ Premissas'!$B$11/1000000))*(1-'🎛️ Premissas'!$B$12)*'🎛️ Premissas'!$B$9)+('🎛️ Premissas'!$B$22*('🎛️ Premissas'!$B$23*('🎛️ Premissas'!$B$10/1000000)+'🎛️ Premissas'!$B$24*('🎛️ Premissas'!$B$11/1000000))*(1-'🎛️ Premissas'!$B$12)*'🎛️ Premissas'!$B$9))+C54*(('🎛️ Premissas'!$B$25*('🎛️ Premissas'!$B$19*('🎛️ Premissas'!$B$10/1000000)+'🎛️ Premissas'!$B$20*('🎛️ Premissas'!$B$11/1000000))*(1-'🎛️ Premissas'!$B$12)*'🎛️ Premissas'!$B$9)+('🎛️ Premissas'!$B$26*('🎛️ Premissas'!$B$23*('🎛️ Premissas'!$B$10/1000000)+'🎛️ Premissas'!$B$24*('🎛️ Premissas'!$B$11/1000000))*(1-'🎛️ Premissas'!$B$12)*'🎛️ Premissas'!$B$9)) | D57: =D51*('🎛️ Premissas'!$B$14*('🎛️ Premissas'!$B$15*('🎛️ Premissas'!$B$10/1000000)+'🎛️ Premissas'!$B$16*('🎛️ Premissas'!$B$11/1000000))*(1-'🎛️ Premissas'!$B$12)*'🎛️ Premissas'!$B$9*'🎛️ Premissas'!$B$17)+D52*('🎛️ Premissas'!$B$18*('🎛️ Premissas'!$B$19*('🎛️ Premissas'!$B$10/1000000)+'🎛️ Premissas'!$B$20*('🎛️ Premissas'!$B$11/1000000))*(1-'🎛️ Premissas'!$B$12)*'🎛️ Premissas'!$B$9)+D53*(('🎛️ Premissas'!$B$21*('🎛️ Premissas'!$B$19*('🎛️ Premissas'!$B$10/1000000)+'🎛️ Premissas'!$B$20*('🎛️ Premissas'!$B$11/1000000))*(1-'🎛️ Premissas'!$B$12)*'🎛️ Premissas'!$B$9)+('🎛️ Premissas'!$B$22*('🎛️ Premissas'!$B$23*('🎛️ Premissas'!$B$10/1000000)+'🎛️ Premissas'!$B$24*('🎛️ Premissas'!$B$11/1000000))*(1-'🎛️ Premissas'!$B$12)*'🎛️ Premissas'!$B$9))+D54*(('🎛️ Premissas'!$B$25*('🎛️ Premissas'!$B$19*('🎛️ Premissas'!$B$10/1000000)+'🎛️ Premissas'!$B$20*('🎛️ Premissas'!$B$11/1000000))*(1-'🎛️ Premissas'!$B$12)*'🎛️ Premissas'!$B$9)+('🎛️ Premissas'!$B$26*('🎛️ Premissas'!$B$23*('🎛️ Premissas'!$B$10/1000000)+'🎛️ Premissas'!$B$24*('🎛️ Premissas'!$B$11/1000000))*(1-'🎛️ Premissas'!$B$12)*'🎛️ Premissas'!$B$9)) | E57: =E51*('🎛️ Premissas'!$B$14*('🎛️ Premissas'!$B$15*('🎛️ Premissas'!$B$10/1000000)+'🎛️ Premissas'!$B$16*('🎛️ Premissas'!$B$11/1000000))*(1-'🎛️ Premissas'!$B$12)*'🎛️ Premissas'!$B$9*'🎛️ Premissas'!$B$17)+E52*('🎛️ Premissas'!$B$18*('🎛️ Premissas'!$B$19*('🎛️ Premissas'!$B$10/1000000)+'🎛️ Premissas'!$B$20*('🎛️ Premissas'!$B$11/1000000))*(1-'🎛️ Premissas'!$B$12)*'🎛️ Premissas'!$B$9)+E53*(('🎛️ Premissas'!$B$21*('🎛️ Premissas'!$B$19*('🎛️ Premissas'!$B$10/1000000)+'🎛️ Premissas'!$B$20*('🎛️ Premissas'!$B$11/1000000))*(1-'🎛️ Premissas'!$B$12)*'🎛️ Premissas'!$B$9)+('🎛️ Premissas'!$B$22*('🎛️ Premissas'!$B$23*('🎛️ Premissas'!$B$10/1000000)+'🎛️ Premissas'!$B$24*('🎛️ Premissas'!$B$11/1000000))*(1-'🎛️ Premissas'!$B$12)*'🎛️ Premissas'!$B$9))+E54*(('🎛️ Premissas'!$B$25*('🎛️ Premissas'!$B$19*('🎛️ Premissas'!$B$10/1000000)+'🎛️ Premissas'!$B$20*('🎛️ Premissas'!$B$11/1000000))*(1-'🎛️ Premissas'!$B$12)*'🎛️ Premissas'!$B$9)+('🎛️ Premissas'!$B$26*('🎛️ Premissas'!$B$23*('🎛️ Premissas'!$B$10/1000000)+'🎛️ Premissas'!$B$24*('🎛️ Premissas'!$B$11/1000000))*(1-'🎛️ Premissas'!$B$12)*'🎛️ Premissas'!$B$9)) | F57: =F51*('🎛️ Premissas'!$B$14*('🎛️ Premissas'!$B$15*('🎛️ Premissas'!$B$10/1000000)+'🎛️ Premissas'!$B$16*('🎛️ Premissas'!$B$11/1000000))*(1-'🎛️ Premissas'!$B$12)*'🎛️ Premissas'!$B$9*'🎛️ Premissas'!$B$17)+F52*('🎛️ Premissas'!$B$18*('🎛️ Premissas'!$B$19*('🎛️ Premissas'!$B$10/1000000)+'🎛️ Premissas'!$B$20*('🎛️ Premissas'!$B$11/1000000))*(1-'🎛️ Premissas'!$B$12)*'🎛️ Premissas'!$B$9)+F53*(('🎛️ Premissas'!$B$21*('🎛️ Premissas'!$B$19*('🎛️ Premissas'!$B$10/1000000)+'🎛️ Premissas'!$B$20*('🎛️ Premissas'!$B$11/1000000))*(1-'🎛️ Premissas'!$B$12)*'🎛️ Premissas'!$B$9)+('🎛️ Premissas'!$B$22*('🎛️ Premissas'!$B$23*('🎛️ Premissas'!$B$10/1000000)+'🎛️ Premissas'!$B$24*('🎛️ Premissas'!$B$11/1000000))*(1-'🎛️ Premissas'!$B$12)*'🎛️ Premissas'!$B$9))+F54*(('🎛️ Premissas'!$B$25*('🎛️ Premissas'!$B$19*('🎛️ Premissas'!$B$10/1000000)+'🎛️ Premissas'!$B$20*('🎛️ Premissas'!$B$11/1000000))*(1-'🎛️ Premissas'!$B$12)*'🎛️ Premissas'!$B$9)+('🎛️ Premissas'!$B$26*('🎛️ Premissas'!$B$23*('🎛️ Premissas'!$B$10/1000000)+'🎛️ Premissas'!$B$24*('🎛️ Premissas'!$B$11/1000000))*(1-'🎛️ Premissas'!$B$12)*'🎛️ Premissas'!$B$9)) | G57: =G51*('🎛️ Premissas'!$B$14*('🎛️ Premissas'!$B$15*('🎛️ Premissas'!$B$10/1000000)+'🎛️ Premissas'!$B$16*('🎛️ Premissas'!$B$11/1000000))*(1-'🎛️ Premissas'!$B$12)*'🎛️ Premissas'!$B$9*'🎛️ Premissas'!$B$17)+G52*('🎛️ Premissas'!$B$18*('🎛️ Premissas'!$B$19*('🎛️ Premissas'!$B$10/1000000)+'🎛️ Premissas'!$B$20*('🎛️ Premissas'!$B$11/1000000))*(1-'🎛️ Premissas'!$B$12)*'🎛️ Premissas'!$B$9)+G53*(('🎛️ Premissas'!$B$21*('🎛️ Premissas'!$B$19*('🎛️ Premissas'!$B$10/1000000)+'🎛️ Premissas'!$B$20*('🎛️ Premissas'!$B$11/1000000))*(1-'🎛️ Premissas'!$B$12)*'🎛️ Premissas'!$B$9)+('🎛️ Premissas'!$B$22*('🎛️ Premissas'!$B$23*('🎛️ Premissas'!$B$10/1000000)+'🎛️ Premissas'!$B$24*('🎛️ Premissas'!$B$11/1000000))*(1-'🎛️ Premissas'!$B$12)*'🎛️ Premissas'!$B$9))+G54*(('🎛️ Premissas'!$B$25*('🎛️ Premissas'!$B$19*('🎛️ Premissas'!$B$10/1000000)+'🎛️ Premissas'!$B$20*('🎛️ Premissas'!$B$11/1000000))*(1-'🎛️ Premissas'!$B$12)*'🎛️ Premissas'!$B$9)+('🎛️ Premissas'!$B$26*('🎛️ Premissas'!$B$23*('🎛️ Premissas'!$B$10/1000000)+'🎛️ Premissas'!$B$24*('🎛️ Premissas'!$B$11/1000000))*(1-'🎛️ Premissas'!$B$12)*'🎛️ Premissas'!$B$9)) | H57: =H51*('🎛️ Premissas'!$B$14*('🎛️ Premissas'!$B$15*('🎛️ Premissas'!$B$10/1000000)+'🎛️ Premissas'!$B$16*('🎛️ Premissas'!$B$11/1000000))*(1-'🎛️ Premissas'!$B$12)*'🎛️ Premissas'!$B$9*'🎛️ Premissas'!$B$17)+H52*('🎛️ Premissas'!$B$18*('🎛️ Premissas'!$B$19*('🎛️ Premissas'!$B$10/1000000)+'🎛️ Premissas'!$B$20*('🎛️ Premissas'!$B$11/1000000))*(1-'🎛️ Premissas'!$B$12)*'🎛️ Premissas'!$B$9)+H53*(('🎛️ Premissas'!$B$21*('🎛️ Premissas'!$B$19*('🎛️ Premissas'!$B$10/1000000)+'🎛️ Premissas'!$B$20*('🎛️ Premissas'!$B$11/1000000))*(1-'🎛️ Premissas'!$B$12)*'🎛️ Premissas'!$B$9)+('🎛️ Premissas'!$B$22*('🎛️ Premissas'!$B$23*('🎛️ Premissas'!$B$10/1000000)+'🎛️ Premissas'!$B$24*('🎛️ Premissas'!$B$11/1000000))*(1-'🎛️ Premissas'!$B$12)*'🎛️ Premissas'!$B$9))+H54*(('🎛️ Premissas'!$B$25*('🎛️ Premissas'!$B$19*('🎛️ Premissas'!$B$10/1000000)+'🎛️ Premissas'!$B$20*('🎛️ Premissas'!$B$11/1000000))*(1-'🎛️ Premissas'!$B$12)*'🎛️ Premissas'!$B$9)+('🎛️ Premissas'!$B$26*('🎛️ Premissas'!$B$23*('🎛️ Premissas'!$B$10/1000000)+'🎛️ Premissas'!$B$24*('🎛️ Premissas'!$B$11/1000000))*(1-'🎛️ Premissas'!$B$12)*'🎛️ Premissas'!$B$9)) | I57: =I51*('🎛️ Premissas'!$B$14*('🎛️ Premissas'!$B$15*('🎛️ Premissas'!$B$10/1000000)+'🎛️ Premissas'!$B$16*('🎛️ Premissas'!$B$11/1000000))*(1-'🎛️ Premissas'!$B$12)*'🎛️ Premissas'!$B$9*'🎛️ Premissas'!$B$17)+I52*('🎛️ Premissas'!$B$18*('🎛️ Premissas'!$B$19*('🎛️ Premissas'!$B$10/1000000)+'🎛️ Premissas'!$B$20*('🎛️ Premissas'!$B$11/1000000))*(1-'🎛️ Premissas'!$B$12)*'🎛️ Premissas'!$B$9)+I53*(('🎛️ Premissas'!$B$21*('🎛️ Premissas'!$B$19*('🎛️ Premissas'!$B$10/1000000)+'🎛️ Premissas'!$B$20*('🎛️ Premissas'!$B$11/1000000))*(1-'🎛️ Premissas'!$B$12)*'🎛️ Premissas'!$B$9)+('🎛️ Premissas'!$B$22*('🎛️ Premissas'!$B$23*('🎛️ Premissas'!$B$10/1000000)+'🎛️ Premissas'!$B$24*('🎛️ Premissas'!$B$11/1000000))*(1-'🎛️ Premissas'!$B$12)*'🎛️ Premissas'!$B$9))+I54*(('🎛️ Premissas'!$B$25*('🎛️ Premissas'!$B$19*('🎛️ Premissas'!$B$10/1000000)+'🎛️ Premissas'!$B$20*('🎛️ Premissas'!$B$11/1000000))*(1-'🎛️ Premissas'!$B$12)*'🎛️ Premissas'!$B$9)+('🎛️ Premissas'!$B$26*('🎛️ Premissas'!$B$23*('🎛️ Premissas'!$B$10/1000000)+'🎛️ Premissas'!$B$24*('🎛️ Premissas'!$B$11/1000000))*(1-'🎛️ Premissas'!$B$12)*'🎛️ Premissas'!$B$9)) | ... Y57: =Y51*('🎛️ Premissas'!$B$14*('🎛️ Premissas'!$B$15*('🎛️ Premissas'!$B$10/1000000)+'🎛️ Premissas'!$B$16*('🎛️ Premissas'!$B$11/1000000))*(1-'🎛️ Premissas'!$B$12)*'🎛️ Premissas'!$B$9*'🎛️ Premissas'!$B$17)+Y52*('🎛️ Premissas'!$B$18*('🎛️ Premissas'!$B$19*('🎛️ Premissas'!$B$10/1000000)+'🎛️ Premissas'!$B$20*('🎛️ Premissas'!$B$11/1000000))*(1-'🎛️ Premissas'!$B$12)*'🎛️ Premissas'!$B$9)+Y53*(('🎛️ Premissas'!$B$21*('🎛️ Premissas'!$B$19*('🎛️ Premissas'!$B$10/1000000)+'🎛️ Premissas'!$B$20*('🎛️ Premissas'!$B$11/1000000))*(1-'🎛️ Premissas'!$B$12)*'🎛️ Premissas'!$B$9)+('🎛️ Premissas'!$B$22*('🎛️ Premissas'!$B$23*('🎛️ Premissas'!$B$10/1000000)+'🎛️ Premissas'!$B$24*('🎛️ Premissas'!$B$11/1000000))*(1-'🎛️ Premissas'!$B$12)*'🎛️ Premissas'!$B$9))+Y54*(('🎛️ Premissas'!$B$25*('🎛️ Premissas'!$B$19*('🎛️ Premissas'!$B$10/1000000)+'🎛️ Premissas'!$B$20*('🎛️ Premissas'!$B$11/1000000))*(1-'🎛️ Premissas'!$B$12)*'🎛️ Premissas'!$B$9)+('🎛️ Premissas'!$B$26*('🎛️ Premissas'!$B$23*('🎛️ Premissas'!$B$10/1000000)+'🎛️ Premissas'!$B$24*('🎛️ Premissas'!$B$11/1000000))*(1-'🎛️ Premissas'!$B$12)*'🎛️ Premissas'!$B$9))
A58: Custo Fixo | B58: ='🎛️ Premissas'!$B$37+'🎛️ Premissas'!$B$39+'🎛️ Premissas'!$B$41+'🎛️ Premissas'!$B$43 | C58: ='🎛️ Premissas'!$B$37+'🎛️ Premissas'!$B$39+'🎛️ Premissas'!$B$41+'🎛️ Premissas'!$B$43 | D58: ='🎛️ Premissas'!$B$37+'🎛️ Premissas'!$B$39+'🎛️ Premissas'!$B$41+'🎛️ Premissas'!$B$43 | E58: ='🎛️ Premissas'!$B$37+'🎛️ Premissas'!$B$39+'🎛️ Premissas'!$B$41+'🎛️ Premissas'!$B$43 | F58: ='🎛️ Premissas'!$B$37+'🎛️ Premissas'!$B$39+'🎛️ Premissas'!$B$41+'🎛️ Premissas'!$B$43 | G58: ='🎛️ Premissas'!$B$37+'🎛️ Premissas'!$B$39+'🎛️ Premissas'!$B$41+'🎛️ Premissas'!$B$43 | H58: ='🎛️ Premissas'!$B$37+'🎛️ Premissas'!$B$39+'🎛️ Premissas'!$B$41+'🎛️ Premissas'!$B$43 | I58: ='🎛️ Premissas'!$B$37+'🎛️ Premissas'!$B$39+'🎛️ Premissas'!$B$41+'🎛️ Premissas'!$B$43 | ... M58: ='🎛️ Premissas'!$B$37+'🎛️ Premissas'!$B$39+'🎛️ Premissas'!$B$41+'🎛️ Premissas'!$B$43 | N58: ='🎛️ Premissas'!$B$38+'🎛️ Premissas'!$B$40+'🎛️ Premissas'!$B$42+'🎛️ Premissas'!$B$43 | O58: ='🎛️ Premissas'!$B$38+'🎛️ Premissas'!$B$40+'🎛️ Premissas'!$B$42+'🎛️ Premissas'!$B$43 | P58: ='🎛️ Premissas'!$B$38+'🎛️ Premissas'!$B$40+'🎛️ Premissas'!$B$42+'🎛️ Premissas'!$B$43 | Q58: ='🎛️ Premissas'!$B$38+'🎛️ Premissas'!$B$40+'🎛️ Premissas'!$B$42+'🎛️ Premissas'!$B$43 | R58: ='🎛️ Premissas'!$B$38+'🎛️ Premissas'!$B$40+'🎛️ Premissas'!$B$42+'🎛️ Premissas'!$B$43 | S58: ='🎛️ Premissas'!$B$38+'🎛️ Premissas'!$B$40+'🎛️ Premissas'!$B$42+'🎛️ Premissas'!$B$43 | T58: ='🎛️ Premissas'!$B$38+'🎛️ Premissas'!$B$40+'🎛️ Premissas'!$B$42+'🎛️ Premissas'!$B$43 | U58: ='🎛️ Premissas'!$B$38+'🎛️ Premissas'!$B$40+'🎛️ Premissas'!$B$42+'🎛️ Premissas'!$B$43 | ... Y58: ='🎛️ Premissas'!$B$38+'🎛️ Premissas'!$B$40+'🎛️ Premissas'!$B$42+'🎛️ Premissas'!$B$43
A59: Impostos | B59: =B56*'🎛️ Premissas'!$B$67 | C59: =C56*'🎛️ Premissas'!$B$67 | D59: =D56*'🎛️ Premissas'!$B$67 | E59: =E56*'🎛️ Premissas'!$B$67 | F59: =F56*'🎛️ Premissas'!$B$67 | G59: =G56*'🎛️ Premissas'!$B$67 | H59: =H56*'🎛️ Premissas'!$B$67 | I59: =I56*'🎛️ Premissas'!$B$67 | ... Y59: =Y56*'🎛️ Premissas'!$B$67
A60: Resultado Mensal | B60: =B56-B57-B58-B59 | C60: =C56-C57-C58-C59 | D60: =D56-D57-D58-D59 | E60: =E56-E57-E58-E59 | F60: =F56-F57-F58-F59 | G60: =G56-G57-G58-G59 | H60: =H56-H57-H58-H59 | I60: =I56-I57-I58-I59 | ... Y60: =Y56-Y57-Y58-Y59
A62: BASE
A63: Free Cadastros | B63: ='🎛️ Premissas'!$B$61 | C63: =B63+'🎛️ Premissas'!$C$28 | D63: =C63+'🎛️ Premissas'!$C$28 | E63: =D63+'🎛️ Premissas'!$C$28 | F63: =E63+'🎛️ Premissas'!$C$28 | G63: =F63+'🎛️ Premissas'!$C$28 | H63: =G63+'🎛️ Premissas'!$C$28 | I63: =H63+'🎛️ Premissas'!$C$28 | J63: =I63+'🎛️ Premissas'!$C$28 | ... M63: =L63+'🎛️ Premissas'!$C$28 | N63: =M63+'🎛️ Premissas'!$C$29 | O63: =N63+'🎛️ Premissas'!$C$29 | P63: =O63+'🎛️ Premissas'!$C$29 | Q63: =P63+'🎛️ Premissas'!$C$29 | R63: =Q63+'🎛️ Premissas'!$C$29 | S63: =R63+'🎛️ Premissas'!$C$29 | T63: =S63+'🎛️ Premissas'!$C$29 | U63: =T63+'🎛️ Premissas'!$C$29 | ... Y63: =X63+'🎛️ Premissas'!$C$29
A64: Essencial | B64: =ROUND(B63*'🎛️ Premissas'!$C$30,0) | C64: =ROUND(C63*'🎛️ Premissas'!$C$30,0) | D64: =ROUND(D63*'🎛️ Premissas'!$C$30,0) | E64: =ROUND(E63*'🎛️ Premissas'!$C$30,0) | F64: =ROUND(F63*'🎛️ Premissas'!$C$30,0) | G64: =ROUND(G63*'🎛️ Premissas'!$C$30,0) | H64: =ROUND(H63*'🎛️ Premissas'!$C$30,0) | I64: =ROUND(I63*'🎛️ Premissas'!$C$30,0) | ... M64: =ROUND(M63*'🎛️ Premissas'!$C$30,0) | N64: =ROUND(M64*(1-'🎛️ Premissas'!$C$33)+MAX(0,N63-M67)*'🎛️ Premissas'!$C$30,0) | O64: =ROUND(N64*(1-'🎛️ Premissas'!$C$33)+MAX(0,O63-N67)*'🎛️ Premissas'!$C$30,0) | P64: =ROUND(O64*(1-'🎛️ Premissas'!$C$33)+MAX(0,P63-O67)*'🎛️ Premissas'!$C$30,0) | Q64: =ROUND(P64*(1-'🎛️ Premissas'!$C$33)+MAX(0,Q63-P67)*'🎛️ Premissas'!$C$30,0) | R64: =ROUND(Q64*(1-'🎛️ Premissas'!$C$33)+MAX(0,R63-Q67)*'🎛️ Premissas'!$C$30,0) | S64: =ROUND(R64*(1-'🎛️ Premissas'!$C$33)+MAX(0,S63-R67)*'🎛️ Premissas'!$C$30,0) | T64: =ROUND(S64*(1-'🎛️ Premissas'!$C$33)+MAX(0,T63-S67)*'🎛️ Premissas'!$C$30,0) | U64: =ROUND(T64*(1-'🎛️ Premissas'!$C$33)+MAX(0,U63-T67)*'🎛️ Premissas'!$C$30,0) | ... Y64: =ROUND(X64*(1-'🎛️ Premissas'!$C$33)+MAX(0,Y63-X67)*'🎛️ Premissas'!$C$30,0)
A65: Autônoma | B65: =ROUND(B63*'🎛️ Premissas'!$C$31,0) | C65: =ROUND(C63*'🎛️ Premissas'!$C$31,0) | D65: =ROUND(D63*'🎛️ Premissas'!$C$31,0) | E65: =ROUND(E63*'🎛️ Premissas'!$C$31,0) | F65: =ROUND(F63*'🎛️ Premissas'!$C$31,0) | G65: =ROUND(G63*'🎛️ Premissas'!$C$31,0) | H65: =ROUND(H63*'🎛️ Premissas'!$C$31,0) | I65: =ROUND(I63*'🎛️ Premissas'!$C$31,0) | ... M65: =ROUND(M63*'🎛️ Premissas'!$C$31,0) | N65: =ROUND(M65*(1-'🎛️ Premissas'!$C$34)+MAX(0,N64-M64-M65)*'🎛️ Premissas'!$C$31,0) | O65: =ROUND(N65*(1-'🎛️ Premissas'!$C$34)+MAX(0,O64-N64-N65)*'🎛️ Premissas'!$C$31,0) | P65: =ROUND(O65*(1-'🎛️ Premissas'!$C$34)+MAX(0,P64-O64-O65)*'🎛️ Premissas'!$C$31,0) | Q65: =ROUND(P65*(1-'🎛️ Premissas'!$C$34)+MAX(0,Q64-P64-P65)*'🎛️ Premissas'!$C$31,0) | R65: =ROUND(Q65*(1-'🎛️ Premissas'!$C$34)+MAX(0,R64-Q64-Q65)*'🎛️ Premissas'!$C$31,0) | S65: =ROUND(R65*(1-'🎛️ Premissas'!$C$34)+MAX(0,S64-R64-R65)*'🎛️ Premissas'!$C$31,0) | T65: =ROUND(S65*(1-'🎛️ Premissas'!$C$34)+MAX(0,T64-S64-S65)*'🎛️ Premissas'!$C$31,0) | U65: =ROUND(T65*(1-'🎛️ Premissas'!$C$34)+MAX(0,U64-T64-T65)*'🎛️ Premissas'!$C$31,0) | ... Y65: =ROUND(X65*(1-'🎛️ Premissas'!$C$34)+MAX(0,Y64-X64-X65)*'🎛️ Premissas'!$C$31,0)
A66: Livre | B66: =ROUND(B63*'🎛️ Premissas'!$C$32,0) | C66: =ROUND(C63*'🎛️ Premissas'!$C$32,0) | D66: =ROUND(D63*'🎛️ Premissas'!$C$32,0) | E66: =ROUND(E63*'🎛️ Premissas'!$C$32,0) | F66: =ROUND(F63*'🎛️ Premissas'!$C$32,0) | G66: =ROUND(G63*'🎛️ Premissas'!$C$32,0) | H66: =ROUND(H63*'🎛️ Premissas'!$C$32,0) | I66: =ROUND(I63*'🎛️ Premissas'!$C$32,0) | ... M66: =ROUND(M63*'🎛️ Premissas'!$C$32,0) | N66: =ROUND(M66*(1-'🎛️ Premissas'!$C$35)+MAX(0,N65-M65)*'🎛️ Premissas'!$C$32,0) | O66: =ROUND(N66*(1-'🎛️ Premissas'!$C$35)+MAX(0,O65-N65)*'🎛️ Premissas'!$C$32,0) | P66: =ROUND(O66*(1-'🎛️ Premissas'!$C$35)+MAX(0,P65-O65)*'🎛️ Premissas'!$C$32,0) | Q66: =ROUND(P66*(1-'🎛️ Premissas'!$C$35)+MAX(0,Q65-P65)*'🎛️ Premissas'!$C$32,0) | R66: =ROUND(Q66*(1-'🎛️ Premissas'!$C$35)+MAX(0,R65-Q65)*'🎛️ Premissas'!$C$32,0) | S66: =ROUND(R66*(1-'🎛️ Premissas'!$C$35)+MAX(0,S65-R65)*'🎛️ Premissas'!$C$32,0) | T66: =ROUND(S66*(1-'🎛️ Premissas'!$C$35)+MAX(0,T65-S65)*'🎛️ Premissas'!$C$32,0) | U66: =ROUND(T66*(1-'🎛️ Premissas'!$C$35)+MAX(0,U65-T65)*'🎛️ Premissas'!$C$32,0) | ... Y66: =ROUND(X66*(1-'🎛️ Premissas'!$C$35)+MAX(0,Y65-X65)*'🎛️ Premissas'!$C$32,0)
A67: Total Pagantes | B67: =SUM(B64:B66) | C67: =SUM(C64:C66) | D67: =SUM(D64:D66) | E67: =SUM(E64:E66) | F67: =SUM(F64:F66) | G67: =SUM(G64:G66) | H67: =SUM(H64:H66) | I67: =SUM(I64:I66) | ... Y67: =SUM(Y64:Y66)
A68: MRR | B68: =B64*'🎛️ Premissas'!$C$5+B65*'🎛️ Premissas'!$C$6+B66*'🎛️ Premissas'!$C$7 | C68: =C64*'🎛️ Premissas'!$C$5+C65*'🎛️ Premissas'!$C$6+C66*'🎛️ Premissas'!$C$7 | D68: =D64*'🎛️ Premissas'!$C$5+D65*'🎛️ Premissas'!$C$6+D66*'🎛️ Premissas'!$C$7 | E68: =E64*'🎛️ Premissas'!$C$5+E65*'🎛️ Premissas'!$C$6+E66*'🎛️ Premissas'!$C$7 | F68: =F64*'🎛️ Premissas'!$C$5+F65*'🎛️ Premissas'!$C$6+F66*'🎛️ Premissas'!$C$7 | G68: =G64*'🎛️ Premissas'!$C$5+G65*'🎛️ Premissas'!$C$6+G66*'🎛️ Premissas'!$C$7 | H68: =H64*'🎛️ Premissas'!$C$5+H65*'🎛️ Premissas'!$C$6+H66*'🎛️ Premissas'!$C$7 | I68: =I64*'🎛️ Premissas'!$C$5+I65*'🎛️ Premissas'!$C$6+I66*'🎛️ Premissas'!$C$7 | ... Y68: =Y64*'🎛️ Premissas'!$C$5+Y65*'🎛️ Premissas'!$C$6+Y66*'🎛️ Premissas'!$C$7
A69: API Total | B69: =B63*('🎛️ Premissas'!$C$14*('🎛️ Premissas'!$C$15*('🎛️ Premissas'!$C$10/1000000)+'🎛️ Premissas'!$C$16*('🎛️ Premissas'!$C$11/1000000))*(1-'🎛️ Premissas'!$C$12)*'🎛️ Premissas'!$C$9*'🎛️ Premissas'!$C$17)+B64*('🎛️ Premissas'!$C$18*('🎛️ Premissas'!$C$19*('🎛️ Premissas'!$C$10/1000000)+'🎛️ Premissas'!$C$20*('🎛️ Premissas'!$C$11/1000000))*(1-'🎛️ Premissas'!$C$12)*'🎛️ Premissas'!$C$9)+B65*(('🎛️ Premissas'!$C$21*('🎛️ Premissas'!$C$19*('🎛️ Premissas'!$C$10/1000000)+'🎛️ Premissas'!$C$20*('🎛️ Premissas'!$C$11/1000000))*(1-'🎛️ Premissas'!$C$12)*'🎛️ Premissas'!$C$9)+('🎛️ Premissas'!$C$22*('🎛️ Premissas'!$C$23*('🎛️ Premissas'!$C$10/1000000)+'🎛️ Premissas'!$C$24*('🎛️ Premissas'!$C$11/1000000))*(1-'🎛️ Premissas'!$C$12)*'🎛️ Premissas'!$C$9))+B66*(('🎛️ Premissas'!$C$25*('🎛️ Premissas'!$C$19*('🎛️ Premissas'!$C$10/1000000)+'🎛️ Premissas'!$C$20*('🎛️ Premissas'!$C$11/1000000))*(1-'🎛️ Premissas'!$C$12)*'🎛️ Premissas'!$C$9)+('🎛️ Premissas'!$C$26*('🎛️ Premissas'!$C$23*('🎛️ Premissas'!$C$10/1000000)+'🎛️ Premissas'!$C$24*('🎛️ Premissas'!$C$11/1000000))*(1-'🎛️ Premissas'!$C$12)*'🎛️ Premissas'!$C$9)) | C69: =C63*('🎛️ Premissas'!$C$14*('🎛️ Premissas'!$C$15*('🎛️ Premissas'!$C$10/1000000)+'🎛️ Premissas'!$C$16*('🎛️ Premissas'!$C$11/1000000))*(1-'🎛️ Premissas'!$C$12)*'🎛️ Premissas'!$C$9*'🎛️ Premissas'!$C$17)+C64*('🎛️ Premissas'!$C$18*('🎛️ Premissas'!$C$19*('🎛️ Premissas'!$C$10/1000000)+'🎛️ Premissas'!$C$20*('🎛️ Premissas'!$C$11/1000000))*(1-'🎛️ Premissas'!$C$12)*'🎛️ Premissas'!$C$9)+C65*(('🎛️ Premissas'!$C$21*('🎛️ Premissas'!$C$19*('🎛️ Premissas'!$C$10/1000000)+'🎛️ Premissas'!$C$20*('🎛️ Premissas'!$C$11/1000000))*(1-'🎛️ Premissas'!$C$12)*'🎛️ Premissas'!$C$9)+('🎛️ Premissas'!$C$22*('🎛️ Premissas'!$C$23*('🎛️ Premissas'!$C$10/1000000)+'🎛️ Premissas'!$C$24*('🎛️ Premissas'!$C$11/1000000))*(1-'🎛️ Premissas'!$C$12)*'🎛️ Premissas'!$C$9))+C66*(('🎛️ Premissas'!$C$25*('🎛️ Premissas'!$C$19*('🎛️ Premissas'!$C$10/1000000)+'🎛️ Premissas'!$C$20*('🎛️ Premissas'!$C$11/1000000))*(1-'🎛️ Premissas'!$C$12)*'🎛️ Premissas'!$C$9)+('🎛️ Premissas'!$C$26*('🎛️ Premissas'!$C$23*('🎛️ Premissas'!$C$10/1000000)+'🎛️ Premissas'!$C$24*('🎛️ Premissas'!$C$11/1000000))*(1-'🎛️ Premissas'!$C$12)*'🎛️ Premissas'!$C$9)) | D69: =D63*('🎛️ Premissas'!$C$14*('🎛️ Premissas'!$C$15*('🎛️ Premissas'!$C$10/1000000)+'🎛️ Premissas'!$C$16*('🎛️ Premissas'!$C$11/1000000))*(1-'🎛️ Premissas'!$C$12)*'🎛️ Premissas'!$C$9*'🎛️ Premissas'!$C$17)+D64*('🎛️ Premissas'!$C$18*('🎛️ Premissas'!$C$19*('🎛️ Premissas'!$C$10/1000000)+'🎛️ Premissas'!$C$20*('🎛️ Premissas'!$C$11/1000000))*(1-'🎛️ Premissas'!$C$12)*'🎛️ Premissas'!$C$9)+D65*(('🎛️ Premissas'!$C$21*('🎛️ Premissas'!$C$19*('🎛️ Premissas'!$C$10/1000000)+'🎛️ Premissas'!$C$20*('🎛️ Premissas'!$C$11/1000000))*(1-'🎛️ Premissas'!$C$12)*'🎛️ Premissas'!$C$9)+('🎛️ Premissas'!$C$22*('🎛️ Premissas'!$C$23*('🎛️ Premissas'!$C$10/1000000)+'🎛️ Premissas'!$C$24*('🎛️ Premissas'!$C$11/1000000))*(1-'🎛️ Premissas'!$C$12)*'🎛️ Premissas'!$C$9))+D66*(('🎛️ Premissas'!$C$25*('🎛️ Premissas'!$C$19*('🎛️ Premissas'!$C$10/1000000)+'🎛️ Premissas'!$C$20*('🎛️ Premissas'!$C$11/1000000))*(1-'🎛️ Premissas'!$C$12)*'🎛️ Premissas'!$C$9)+('🎛️ Premissas'!$C$26*('🎛️ Premissas'!$C$23*('🎛️ Premissas'!$C$10/1000000)+'🎛️ Premissas'!$C$24*('🎛️ Premissas'!$C$11/1000000))*(1-'🎛️ Premissas'!$C$12)*'🎛️ Premissas'!$C$9)) | E69: =E63*('🎛️ Premissas'!$C$14*('🎛️ Premissas'!$C$15*('🎛️ Premissas'!$C$10/1000000)+'🎛️ Premissas'!$C$16*('🎛️ Premissas'!$C$11/1000000))*(1-'🎛️ Premissas'!$C$12)*'🎛️ Premissas'!$C$9*'🎛️ Premissas'!$C$17)+E64*('🎛️ Premissas'!$C$18*('🎛️ Premissas'!$C$19*('🎛️ Premissas'!$C$10/1000000)+'🎛️ Premissas'!$C$20*('🎛️ Premissas'!$C$11/1000000))*(1-'🎛️ Premissas'!$C$12)*'🎛️ Premissas'!$C$9)+E65*(('🎛️ Premissas'!$C$21*('🎛️ Premissas'!$C$19*('🎛️ Premissas'!$C$10/1000000)+'🎛️ Premissas'!$C$20*('🎛️ Premissas'!$C$11/1000000))*(1-'🎛️ Premissas'!$C$12)*'🎛️ Premissas'!$C$9)+('🎛️ Premissas'!$C$22*('🎛️ Premissas'!$C$23*('🎛️ Premissas'!$C$10/1000000)+'🎛️ Premissas'!$C$24*('🎛️ Premissas'!$C$11/1000000))*(1-'🎛️ Premissas'!$C$12)*'🎛️ Premissas'!$C$9))+E66*(('🎛️ Premissas'!$C$25*('🎛️ Premissas'!$C$19*('🎛️ Premissas'!$C$10/1000000)+'🎛️ Premissas'!$C$20*('🎛️ Premissas'!$C$11/1000000))*(1-'🎛️ Premissas'!$C$12)*'🎛️ Premissas'!$C$9)+('🎛️ Premissas'!$C$26*('🎛️ Premissas'!$C$23*('🎛️ Premissas'!$C$10/1000000)+'🎛️ Premissas'!$C$24*('🎛️ Premissas'!$C$11/1000000))*(1-'🎛️ Premissas'!$C$12)*'🎛️ Premissas'!$C$9)) | F69: =F63*('🎛️ Premissas'!$C$14*('🎛️ Premissas'!$C$15*('🎛️ Premissas'!$C$10/1000000)+'🎛️ Premissas'!$C$16*('🎛️ Premissas'!$C$11/1000000))*(1-'🎛️ Premissas'!$C$12)*'🎛️ Premissas'!$C$9*'🎛️ Premissas'!$C$17)+F64*('🎛️ Premissas'!$C$18*('🎛️ Premissas'!$C$19*('🎛️ Premissas'!$C$10/1000000)+'🎛️ Premissas'!$C$20*('🎛️ Premissas'!$C$11/1000000))*(1-'🎛️ Premissas'!$C$12)*'🎛️ Premissas'!$C$9)+F65*(('🎛️ Premissas'!$C$21*('🎛️ Premissas'!$C$19*('🎛️ Premissas'!$C$10/1000000)+'🎛️ Premissas'!$C$20*('🎛️ Premissas'!$C$11/1000000))*(1-'🎛️ Premissas'!$C$12)*'🎛️ Premissas'!$C$9)+('🎛️ Premissas'!$C$22*('🎛️ Premissas'!$C$23*('🎛️ Premissas'!$C$10/1000000)+'🎛️ Premissas'!$C$24*('🎛️ Premissas'!$C$11/1000000))*(1-'🎛️ Premissas'!$C$12)*'🎛️ Premissas'!$C$9))+F66*(('🎛️ Premissas'!$C$25*('🎛️ Premissas'!$C$19*('🎛️ Premissas'!$C$10/1000000)+'🎛️ Premissas'!$C$20*('🎛️ Premissas'!$C$11/1000000))*(1-'🎛️ Premissas'!$C$12)*'🎛️ Premissas'!$C$9)+('🎛️ Premissas'!$C$26*('🎛️ Premissas'!$C$23*('🎛️ Premissas'!$C$10/1000000)+'🎛️ Premissas'!$C$24*('🎛️ Premissas'!$C$11/1000000))*(1-'🎛️ Premissas'!$C$12)*'🎛️ Premissas'!$C$9)) | G69: =G63*('🎛️ Premissas'!$C$14*('🎛️ Premissas'!$C$15*('🎛️ Premissas'!$C$10/1000000)+'🎛️ Premissas'!$C$16*('🎛️ Premissas'!$C$11/1000000))*(1-'🎛️ Premissas'!$C$12)*'🎛️ Premissas'!$C$9*'🎛️ Premissas'!$C$17)+G64*('🎛️ Premissas'!$C$18*('🎛️ Premissas'!$C$19*('🎛️ Premissas'!$C$10/1000000)+'🎛️ Premissas'!$C$20*('🎛️ Premissas'!$C$11/1000000))*(1-'🎛️ Premissas'!$C$12)*'🎛️ Premissas'!$C$9)+G65*(('🎛️ Premissas'!$C$21*('🎛️ Premissas'!$C$19*('🎛️ Premissas'!$C$10/1000000)+'🎛️ Premissas'!$C$20*('🎛️ Premissas'!$C$11/1000000))*(1-'🎛️ Premissas'!$C$12)*'🎛️ Premissas'!$C$9)+('🎛️ Premissas'!$C$22*('🎛️ Premissas'!$C$23*('🎛️ Premissas'!$C$10/1000000)+'🎛️ Premissas'!$C$24*('🎛️ Premissas'!$C$11/1000000))*(1-'🎛️ Premissas'!$C$12)*'🎛️ Premissas'!$C$9))+G66*(('🎛️ Premissas'!$C$25*('🎛️ Premissas'!$C$19*('🎛️ Premissas'!$C$10/1000000)+'🎛️ Premissas'!$C$20*('🎛️ Premissas'!$C$11/1000000))*(1-'🎛️ Premissas'!$C$12)*'🎛️ Premissas'!$C$9)+('🎛️ Premissas'!$C$26*('🎛️ Premissas'!$C$23*('🎛️ Premissas'!$C$10/1000000)+'🎛️ Premissas'!$C$24*('🎛️ Premissas'!$C$11/1000000))*(1-'🎛️ Premissas'!$C$12)*'🎛️ Premissas'!$C$9)) | H69: =H63*('🎛️ Premissas'!$C$14*('🎛️ Premissas'!$C$15*('🎛️ Premissas'!$C$10/1000000)+'🎛️ Premissas'!$C$16*('🎛️ Premissas'!$C$11/1000000))*(1-'🎛️ Premissas'!$C$12)*'🎛️ Premissas'!$C$9*'🎛️ Premissas'!$C$17)+H64*('🎛️ Premissas'!$C$18*('🎛️ Premissas'!$C$19*('🎛️ Premissas'!$C$10/1000000)+'🎛️ Premissas'!$C$20*('🎛️ Premissas'!$C$11/1000000))*(1-'🎛️ Premissas'!$C$12)*'🎛️ Premissas'!$C$9)+H65*(('🎛️ Premissas'!$C$21*('🎛️ Premissas'!$C$19*('🎛️ Premissas'!$C$10/1000000)+'🎛️ Premissas'!$C$20*('🎛️ Premissas'!$C$11/1000000))*(1-'🎛️ Premissas'!$C$12)*'🎛️ Premissas'!$C$9)+('🎛️ Premissas'!$C$22*('🎛️ Premissas'!$C$23*('🎛️ Premissas'!$C$10/1000000)+'🎛️ Premissas'!$C$24*('🎛️ Premissas'!$C$11/1000000))*(1-'🎛️ Premissas'!$C$12)*'🎛️ Premissas'!$C$9))+H66*(('🎛️ Premissas'!$C$25*('🎛️ Premissas'!$C$19*('🎛️ Premissas'!$C$10/1000000)+'🎛️ Premissas'!$C$20*('🎛️ Premissas'!$C$11/1000000))*(1-'🎛️ Premissas'!$C$12)*'🎛️ Premissas'!$C$9)+('🎛️ Premissas'!$C$26*('🎛️ Premissas'!$C$23*('🎛️ Premissas'!$C$10/1000000)+'🎛️ Premissas'!$C$24*('🎛️ Premissas'!$C$11/1000000))*(1-'🎛️ Premissas'!$C$12)*'🎛️ Premissas'!$C$9)) | I69: =I63*('🎛️ Premissas'!$C$14*('🎛️ Premissas'!$C$15*('🎛️ Premissas'!$C$10/1000000)+'🎛️ Premissas'!$C$16*('🎛️ Premissas'!$C$11/1000000))*(1-'🎛️ Premissas'!$C$12)*'🎛️ Premissas'!$C$9*'🎛️ Premissas'!$C$17)+I64*('🎛️ Premissas'!$C$18*('🎛️ Premissas'!$C$19*('🎛️ Premissas'!$C$10/1000000)+'🎛️ Premissas'!$C$20*('🎛️ Premissas'!$C$11/1000000))*(1-'🎛️ Premissas'!$C$12)*'🎛️ Premissas'!$C$9)+I65*(('🎛️ Premissas'!$C$21*('🎛️ Premissas'!$C$19*('🎛️ Premissas'!$C$10/1000000)+'🎛️ Premissas'!$C$20*('🎛️ Premissas'!$C$11/1000000))*(1-'🎛️ Premissas'!$C$12)*'🎛️ Premissas'!$C$9)+('🎛️ Premissas'!$C$22*('🎛️ Premissas'!$C$23*('🎛️ Premissas'!$C$10/1000000)+'🎛️ Premissas'!$C$24*('🎛️ Premissas'!$C$11/1000000))*(1-'🎛️ Premissas'!$C$12)*'🎛️ Premissas'!$C$9))+I66*(('🎛️ Premissas'!$C$25*('🎛️ Premissas'!$C$19*('🎛️ Premissas'!$C$10/1000000)+'🎛️ Premissas'!$C$20*('🎛️ Premissas'!$C$11/1000000))*(1-'🎛️ Premissas'!$C$12)*'🎛️ Premissas'!$C$9)+('🎛️ Premissas'!$C$26*('🎛️ Premissas'!$C$23*('🎛️ Premissas'!$C$10/1000000)+'🎛️ Premissas'!$C$24*('🎛️ Premissas'!$C$11/1000000))*(1-'🎛️ Premissas'!$C$12)*'🎛️ Premissas'!$C$9)) | ... Y69: =Y63*('🎛️ Premissas'!$C$14*('🎛️ Premissas'!$C$15*('🎛️ Premissas'!$C$10/1000000)+'🎛️ Premissas'!$C$16*('🎛️ Premissas'!$C$11/1000000))*(1-'🎛️ Premissas'!$C$12)*'🎛️ Premissas'!$C$9*'🎛️ Premissas'!$C$17)+Y64*('🎛️ Premissas'!$C$18*('🎛️ Premissas'!$C$19*('🎛️ Premissas'!$C$10/1000000)+'🎛️ Premissas'!$C$20*('🎛️ Premissas'!$C$11/1000000))*(1-'🎛️ Premissas'!$C$12)*'🎛️ Premissas'!$C$9)+Y65*(('🎛️ Premissas'!$C$21*('🎛️ Premissas'!$C$19*('🎛️ Premissas'!$C$10/1000000)+'🎛️ Premissas'!$C$20*('🎛️ Premissas'!$C$11/1000000))*(1-'🎛️ Premissas'!$C$12)*'🎛️ Premissas'!$C$9)+('🎛️ Premissas'!$C$22*('🎛️ Premissas'!$C$23*('🎛️ Premissas'!$C$10/1000000)+'🎛️ Premissas'!$C$24*('🎛️ Premissas'!$C$11/1000000))*(1-'🎛️ Premissas'!$C$12)*'🎛️ Premissas'!$C$9))+Y66*(('🎛️ Premissas'!$C$25*('🎛️ Premissas'!$C$19*('🎛️ Premissas'!$C$10/1000000)+'🎛️ Premissas'!$C$20*('🎛️ Premissas'!$C$11/1000000))*(1-'🎛️ Premissas'!$C$12)*'🎛️ Premissas'!$C$9)+('🎛️ Premissas'!$C$26*('🎛️ Premissas'!$C$23*('🎛️ Premissas'!$C$10/1000000)+'🎛️ Premissas'!$C$24*('🎛️ Premissas'!$C$11/1000000))*(1-'🎛️ Premissas'!$C$12)*'🎛️ Premissas'!$C$9))
A70: Custo Fixo | B70: ='🎛️ Premissas'!$C$37+'🎛️ Premissas'!$C$39+'🎛️ Premissas'!$C$41+'🎛️ Premissas'!$C$43 | C70: ='🎛️ Premissas'!$C$37+'🎛️ Premissas'!$C$39+'🎛️ Premissas'!$C$41+'🎛️ Premissas'!$C$43 | D70: ='🎛️ Premissas'!$C$37+'🎛️ Premissas'!$C$39+'🎛️ Premissas'!$C$41+'🎛️ Premissas'!$C$43 | E70: ='🎛️ Premissas'!$C$37+'🎛️ Premissas'!$C$39+'🎛️ Premissas'!$C$41+'🎛️ Premissas'!$C$43 | F70: ='🎛️ Premissas'!$C$37+'🎛️ Premissas'!$C$39+'🎛️ Premissas'!$C$41+'🎛️ Premissas'!$C$43 | G70: ='🎛️ Premissas'!$C$37+'🎛️ Premissas'!$C$39+'🎛️ Premissas'!$C$41+'🎛️ Premissas'!$C$43 | H70: ='🎛️ Premissas'!$C$37+'🎛️ Premissas'!$C$39+'🎛️ Premissas'!$C$41+'🎛️ Premissas'!$C$43 | I70: ='🎛️ Premissas'!$C$37+'🎛️ Premissas'!$C$39+'🎛️ Premissas'!$C$41+'🎛️ Premissas'!$C$43 | ... M70: ='🎛️ Premissas'!$C$37+'🎛️ Premissas'!$C$39+'🎛️ Premissas'!$C$41+'🎛️ Premissas'!$C$43 | N70: ='🎛️ Premissas'!$C$38+'🎛️ Premissas'!$C$40+'🎛️ Premissas'!$C$42+'🎛️ Premissas'!$C$43 | O70: ='🎛️ Premissas'!$C$38+'🎛️ Premissas'!$C$40+'🎛️ Premissas'!$C$42+'🎛️ Premissas'!$C$43 | P70: ='🎛️ Premissas'!$C$38+'🎛️ Premissas'!$C$40+'🎛️ Premissas'!$C$42+'🎛️ Premissas'!$C$43 | Q70: ='🎛️ Premissas'!$C$38+'🎛️ Premissas'!$C$40+'🎛️ Premissas'!$C$42+'🎛️ Premissas'!$C$43 | R70: ='🎛️ Premissas'!$C$38+'🎛️ Premissas'!$C$40+'🎛️ Premissas'!$C$42+'🎛️ Premissas'!$C$43 | S70: ='🎛️ Premissas'!$C$38+'🎛️ Premissas'!$C$40+'🎛️ Premissas'!$C$42+'🎛️ Premissas'!$C$43 | T70: ='🎛️ Premissas'!$C$38+'🎛️ Premissas'!$C$40+'🎛️ Premissas'!$C$42+'🎛️ Premissas'!$C$43 | U70: ='🎛️ Premissas'!$C$38+'🎛️ Premissas'!$C$40+'🎛️ Premissas'!$C$42+'🎛️ Premissas'!$C$43 | ... Y70: ='🎛️ Premissas'!$C$38+'🎛️ Premissas'!$C$40+'🎛️ Premissas'!$C$42+'🎛️ Premissas'!$C$43
A71: Impostos | B71: =B68*'🎛️ Premissas'!$C$67 | C71: =C68*'🎛️ Premissas'!$C$67 | D71: =D68*'🎛️ Premissas'!$C$67 | E71: =E68*'🎛️ Premissas'!$C$67 | F71: =F68*'🎛️ Premissas'!$C$67 | G71: =G68*'🎛️ Premissas'!$C$67 | H71: =H68*'🎛️ Premissas'!$C$67 | I71: =I68*'🎛️ Premissas'!$C$67 | ... Y71: =Y68*'🎛️ Premissas'!$C$67
A72: Resultado Mensal | B72: =B68-B69-B70-B71 | C72: =C68-C69-C70-C71 | D72: =D68-D69-D70-D71 | E72: =E68-E69-E70-E71 | F72: =F68-F69-F70-F71 | G72: =G68-G69-G70-G71 | H72: =H68-H69-H70-H71 | I72: =I68-I69-I70-I71 | ... Y72: =Y68-Y69-Y70-Y71
A74: OTIMISTA
A75: Free Cadastros | B75: ='🎛️ Premissas'!$B$61 | C75: =B75+'🎛️ Premissas'!$D$28 | D75: =C75+'🎛️ Premissas'!$D$28 | E75: =D75+'🎛️ Premissas'!$D$28 | F75: =E75+'🎛️ Premissas'!$D$28 | G75: =F75+'🎛️ Premissas'!$D$28 | H75: =G75+'🎛️ Premissas'!$D$28 | I75: =H75+'🎛️ Premissas'!$D$28 | J75: =I75+'🎛️ Premissas'!$D$28 | ... M75: =L75+'🎛️ Premissas'!$D$28 | N75: =M75+'🎛️ Premissas'!$D$29 | O75: =N75+'🎛️ Premissas'!$D$29 | P75: =O75+'🎛️ Premissas'!$D$29 | Q75: =P75+'🎛️ Premissas'!$D$29 | R75: =Q75+'🎛️ Premissas'!$D$29 | S75: =R75+'🎛️ Premissas'!$D$29 | T75: =S75+'🎛️ Premissas'!$D$29 | U75: =T75+'🎛️ Premissas'!$D$29 | ... Y75: =X75+'🎛️ Premissas'!$D$29
A76: Essencial | B76: =ROUND(B75*'🎛️ Premissas'!$D$30,0) | C76: =ROUND(C75*'🎛️ Premissas'!$D$30,0) | D76: =ROUND(D75*'🎛️ Premissas'!$D$30,0) | E76: =ROUND(E75*'🎛️ Premissas'!$D$30,0) | F76: =ROUND(F75*'🎛️ Premissas'!$D$30,0) | G76: =ROUND(G75*'🎛️ Premissas'!$D$30,0) | H76: =ROUND(H75*'🎛️ Premissas'!$D$30,0) | I76: =ROUND(I75*'🎛️ Premissas'!$D$30,0) | ... M76: =ROUND(M75*'🎛️ Premissas'!$D$30,0) | N76: =ROUND(M76*(1-'🎛️ Premissas'!$D$33)+MAX(0,N75-M79)*'🎛️ Premissas'!$D$30,0) | O76: =ROUND(N76*(1-'🎛️ Premissas'!$D$33)+MAX(0,O75-N79)*'🎛️ Premissas'!$D$30,0) | P76: =ROUND(O76*(1-'🎛️ Premissas'!$D$33)+MAX(0,P75-O79)*'🎛️ Premissas'!$D$30,0) | Q76: =ROUND(P76*(1-'🎛️ Premissas'!$D$33)+MAX(0,Q75-P79)*'🎛️ Premissas'!$D$30,0) | R76: =ROUND(Q76*(1-'🎛️ Premissas'!$D$33)+MAX(0,R75-Q79)*'🎛️ Premissas'!$D$30,0) | S76: =ROUND(R76*(1-'🎛️ Premissas'!$D$33)+MAX(0,S75-R79)*'🎛️ Premissas'!$D$30,0) | T76: =ROUND(S76*(1-'🎛️ Premissas'!$D$33)+MAX(0,T75-S79)*'🎛️ Premissas'!$D$30,0) | U76: =ROUND(T76*(1-'🎛️ Premissas'!$D$33)+MAX(0,U75-T79)*'🎛️ Premissas'!$D$30,0) | ... Y76: =ROUND(X76*(1-'🎛️ Premissas'!$D$33)+MAX(0,Y75-X79)*'🎛️ Premissas'!$D$30,0)
A77: Autônoma | B77: =ROUND(B75*'🎛️ Premissas'!$D$31,0) | C77: =ROUND(C75*'🎛️ Premissas'!$D$31,0) | D77: =ROUND(D75*'🎛️ Premissas'!$D$31,0) | E77: =ROUND(E75*'🎛️ Premissas'!$D$31,0) | F77: =ROUND(F75*'🎛️ Premissas'!$D$31,0) | G77: =ROUND(G75*'🎛️ Premissas'!$D$31,0) | H77: =ROUND(H75*'🎛️ Premissas'!$D$31,0) | I77: =ROUND(I75*'🎛️ Premissas'!$D$31,0) | ... M77: =ROUND(M75*'🎛️ Premissas'!$D$31,0) | N77: =ROUND(M77*(1-'🎛️ Premissas'!$D$34)+MAX(0,N76-M76-M77)*'🎛️ Premissas'!$D$31,0) | O77: =ROUND(N77*(1-'🎛️ Premissas'!$D$34)+MAX(0,O76-N76-N77)*'🎛️ Premissas'!$D$31,0) | P77: =ROUND(O77*(1-'🎛️ Premissas'!$D$34)+MAX(0,P76-O76-O77)*'🎛️ Premissas'!$D$31,0) | Q77: =ROUND(P77*(1-'🎛️ Premissas'!$D$34)+MAX(0,Q76-P76-P77)*'🎛️ Premissas'!$D$31,0) | R77: =ROUND(Q77*(1-'🎛️ Premissas'!$D$34)+MAX(0,R76-Q76-Q77)*'🎛️ Premissas'!$D$31,0) | S77: =ROUND(R77*(1-'🎛️ Premissas'!$D$34)+MAX(0,S76-R76-R77)*'🎛️ Premissas'!$D$31,0) | T77: =ROUND(S77*(1-'🎛️ Premissas'!$D$34)+MAX(0,T76-S76-S77)*'🎛️ Premissas'!$D$31,0) | U77: =ROUND(T77*(1-'🎛️ Premissas'!$D$34)+MAX(0,U76-T76-T77)*'🎛️ Premissas'!$D$31,0) | ... Y77: =ROUND(X77*(1-'🎛️ Premissas'!$D$34)+MAX(0,Y76-X76-X77)*'🎛️ Premissas'!$D$31,0)
A78: Livre | B78: =ROUND(B75*'🎛️ Premissas'!$D$32,0) | C78: =ROUND(C75*'🎛️ Premissas'!$D$32,0) | D78: =ROUND(D75*'🎛️ Premissas'!$D$32,0) | E78: =ROUND(E75*'🎛️ Premissas'!$D$32,0) | F78: =ROUND(F75*'🎛️ Premissas'!$D$32,0) | G78: =ROUND(G75*'🎛️ Premissas'!$D$32,0) | H78: =ROUND(H75*'🎛️ Premissas'!$D$32,0) | I78: =ROUND(I75*'🎛️ Premissas'!$D$32,0) | ... M78: =ROUND(M75*'🎛️ Premissas'!$D$32,0) | N78: =ROUND(M78*(1-'🎛️ Premissas'!$D$35)+MAX(0,N77-M77)*'🎛️ Premissas'!$D$32,0) | O78: =ROUND(N78*(1-'🎛️ Premissas'!$D$35)+MAX(0,O77-N77)*'🎛️ Premissas'!$D$32,0) | P78: =ROUND(O78*(1-'🎛️ Premissas'!$D$35)+MAX(0,P77-O77)*'🎛️ Premissas'!$D$32,0) | Q78: =ROUND(P78*(1-'🎛️ Premissas'!$D$35)+MAX(0,Q77-P77)*'🎛️ Premissas'!$D$32,0) | R78: =ROUND(Q78*(1-'🎛️ Premissas'!$D$35)+MAX(0,R77-Q77)*'🎛️ Premissas'!$D$32,0) | S78: =ROUND(R78*(1-'🎛️ Premissas'!$D$35)+MAX(0,S77-R77)*'🎛️ Premissas'!$D$32,0) | T78: =ROUND(S78*(1-'🎛️ Premissas'!$D$35)+MAX(0,T77-S77)*'🎛️ Premissas'!$D$32,0) | U78: =ROUND(T78*(1-'🎛️ Premissas'!$D$35)+MAX(0,U77-T77)*'🎛️ Premissas'!$D$32,0) | ... Y78: =ROUND(X78*(1-'🎛️ Premissas'!$D$35)+MAX(0,Y77-X77)*'🎛️ Premissas'!$D$32,0)
A79: Total Pagantes | B79: =SUM(B76:B78) | C79: =SUM(C76:C78) | D79: =SUM(D76:D78) | E79: =SUM(E76:E78) | F79: =SUM(F76:F78) | G79: =SUM(G76:G78) | H79: =SUM(H76:H78) | I79: =SUM(I76:I78) | ... Y79: =SUM(Y76:Y78)
A80: MRR | B80: =B76*'🎛️ Premissas'!$D$5+B77*'🎛️ Premissas'!$D$6+B78*'🎛️ Premissas'!$D$7 | C80: =C76*'🎛️ Premissas'!$D$5+C77*'🎛️ Premissas'!$D$6+C78*'🎛️ Premissas'!$D$7 | D80: =D76*'🎛️ Premissas'!$D$5+D77*'🎛️ Premissas'!$D$6+D78*'🎛️ Premissas'!$D$7 | E80: =E76*'🎛️ Premissas'!$D$5+E77*'🎛️ Premissas'!$D$6+E78*'🎛️ Premissas'!$D$7 | F80: =F76*'🎛️ Premissas'!$D$5+F77*'🎛️ Premissas'!$D$6+F78*'🎛️ Premissas'!$D$7 | G80: =G76*'🎛️ Premissas'!$D$5+G77*'🎛️ Premissas'!$D$6+G78*'🎛️ Premissas'!$D$7 | H80: =H76*'🎛️ Premissas'!$D$5+H77*'🎛️ Premissas'!$D$6+H78*'🎛️ Premissas'!$D$7 | I80: =I76*'🎛️ Premissas'!$D$5+I77*'🎛️ Premissas'!$D$6+I78*'🎛️ Premissas'!$D$7 | ... Y80: =Y76*'🎛️ Premissas'!$D$5+Y77*'🎛️ Premissas'!$D$6+Y78*'🎛️ Premissas'!$D$7
A81: API Total | B81: =B75*('🎛️ Premissas'!$D$14*('🎛️ Premissas'!$D$15*('🎛️ Premissas'!$D$10/1000000)+'🎛️ Premissas'!$D$16*('🎛️ Premissas'!$D$11/1000000))*(1-'🎛️ Premissas'!$D$12)*'🎛️ Premissas'!$D$9*'🎛️ Premissas'!$D$17)+B76*('🎛️ Premissas'!$D$18*('🎛️ Premissas'!$D$19*('🎛️ Premissas'!$D$10/1000000)+'🎛️ Premissas'!$D$20*('🎛️ Premissas'!$D$11/1000000))*(1-'🎛️ Premissas'!$D$12)*'🎛️ Premissas'!$D$9)+B77*(('🎛️ Premissas'!$D$21*('🎛️ Premissas'!$D$19*('🎛️ Premissas'!$D$10/1000000)+'🎛️ Premissas'!$D$20*('🎛️ Premissas'!$D$11/1000000))*(1-'🎛️ Premissas'!$D$12)*'🎛️ Premissas'!$D$9)+('🎛️ Premissas'!$D$22*('🎛️ Premissas'!$D$23*('🎛️ Premissas'!$D$10/1000000)+'🎛️ Premissas'!$D$24*('🎛️ Premissas'!$D$11/1000000))*(1-'🎛️ Premissas'!$D$12)*'🎛️ Premissas'!$D$9))+B78*(('🎛️ Premissas'!$D$25*('🎛️ Premissas'!$D$19*('🎛️ Premissas'!$D$10/1000000)+'🎛️ Premissas'!$D$20*('🎛️ Premissas'!$D$11/1000000))*(1-'🎛️ Premissas'!$D$12)*'🎛️ Premissas'!$D$9)+('🎛️ Premissas'!$D$26*('🎛️ Premissas'!$D$23*('🎛️ Premissas'!$D$10/1000000)+'🎛️ Premissas'!$D$24*('🎛️ Premissas'!$D$11/1000000))*(1-'🎛️ Premissas'!$D$12)*'🎛️ Premissas'!$D$9)) | C81: =C75*('🎛️ Premissas'!$D$14*('🎛️ Premissas'!$D$15*('🎛️ Premissas'!$D$10/1000000)+'🎛️ Premissas'!$D$16*('🎛️ Premissas'!$D$11/1000000))*(1-'🎛️ Premissas'!$D$12)*'🎛️ Premissas'!$D$9*'🎛️ Premissas'!$D$17)+C76*('🎛️ Premissas'!$D$18*('🎛️ Premissas'!$D$19*('🎛️ Premissas'!$D$10/1000000)+'🎛️ Premissas'!$D$20*('🎛️ Premissas'!$D$11/1000000))*(1-'🎛️ Premissas'!$D$12)*'🎛️ Premissas'!$D$9)+C77*(('🎛️ Premissas'!$D$21*('🎛️ Premissas'!$D$19*('🎛️ Premissas'!$D$10/1000000)+'🎛️ Premissas'!$D$20*('🎛️ Premissas'!$D$11/1000000))*(1-'🎛️ Premissas'!$D$12)*'🎛️ Premissas'!$D$9)+('🎛️ Premissas'!$D$22*('🎛️ Premissas'!$D$23*('🎛️ Premissas'!$D$10/1000000)+'🎛️ Premissas'!$D$24*('🎛️ Premissas'!$D$11/1000000))*(1-'🎛️ Premissas'!$D$12)*'🎛️ Premissas'!$D$9))+C78*(('🎛️ Premissas'!$D$25*('🎛️ Premissas'!$D$19*('🎛️ Premissas'!$D$10/1000000)+'🎛️ Premissas'!$D$20*('🎛️ Premissas'!$D$11/1000000))*(1-'🎛️ Premissas'!$D$12)*'🎛️ Premissas'!$D$9)+('🎛️ Premissas'!$D$26*('🎛️ Premissas'!$D$23*('🎛️ Premissas'!$D$10/1000000)+'🎛️ Premissas'!$D$24*('🎛️ Premissas'!$D$11/1000000))*(1-'🎛️ Premissas'!$D$12)*'🎛️ Premissas'!$D$9)) | D81: =D75*('🎛️ Premissas'!$D$14*('🎛️ Premissas'!$D$15*('🎛️ Premissas'!$D$10/1000000)+'🎛️ Premissas'!$D$16*('🎛️ Premissas'!$D$11/1000000))*(1-'🎛️ Premissas'!$D$12)*'🎛️ Premissas'!$D$9*'🎛️ Premissas'!$D$17)+D76*('🎛️ Premissas'!$D$18*('🎛️ Premissas'!$D$19*('🎛️ Premissas'!$D$10/1000000)+'🎛️ Premissas'!$D$20*('🎛️ Premissas'!$D$11/1000000))*(1-'🎛️ Premissas'!$D$12)*'🎛️ Premissas'!$D$9)+D77*(('🎛️ Premissas'!$D$21*('🎛️ Premissas'!$D$19*('🎛️ Premissas'!$D$10/1000000)+'🎛️ Premissas'!$D$20*('🎛️ Premissas'!$D$11/1000000))*(1-'🎛️ Premissas'!$D$12)*'🎛️ Premissas'!$D$9)+('🎛️ Premissas'!$D$22*('🎛️ Premissas'!$D$23*('🎛️ Premissas'!$D$10/1000000)+'🎛️ Premissas'!$D$24*('🎛️ Premissas'!$D$11/1000000))*(1-'🎛️ Premissas'!$D$12)*'🎛️ Premissas'!$D$9))+D78*(('🎛️ Premissas'!$D$25*('🎛️ Premissas'!$D$19*('🎛️ Premissas'!$D$10/1000000)+'🎛️ Premissas'!$D$20*('🎛️ Premissas'!$D$11/1000000))*(1-'🎛️ Premissas'!$D$12)*'🎛️ Premissas'!$D$9)+('🎛️ Premissas'!$D$26*('🎛️ Premissas'!$D$23*('🎛️ Premissas'!$D$10/1000000)+'🎛️ Premissas'!$D$24*('🎛️ Premissas'!$D$11/1000000))*(1-'🎛️ Premissas'!$D$12)*'🎛️ Premissas'!$D$9)) | E81: =E75*('🎛️ Premissas'!$D$14*('🎛️ Premissas'!$D$15*('🎛️ Premissas'!$D$10/1000000)+'🎛️ Premissas'!$D$16*('🎛️ Premissas'!$D$11/1000000))*(1-'🎛️ Premissas'!$D$12)*'🎛️ Premissas'!$D$9*'🎛️ Premissas'!$D$17)+E76*('🎛️ Premissas'!$D$18*('🎛️ Premissas'!$D$19*('🎛️ Premissas'!$D$10/1000000)+'🎛️ Premissas'!$D$20*('🎛️ Premissas'!$D$11/1000000))*(1-'🎛️ Premissas'!$D$12)*'🎛️ Premissas'!$D$9)+E77*(('🎛️ Premissas'!$D$21*('🎛️ Premissas'!$D$19*('🎛️ Premissas'!$D$10/1000000)+'🎛️ Premissas'!$D$20*('🎛️ Premissas'!$D$11/1000000))*(1-'🎛️ Premissas'!$D$12)*'🎛️ Premissas'!$D$9)+('🎛️ Premissas'!$D$22*('🎛️ Premissas'!$D$23*('🎛️ Premissas'!$D$10/1000000)+'🎛️ Premissas'!$D$24*('🎛️ Premissas'!$D$11/1000000))*(1-'🎛️ Premissas'!$D$12)*'🎛️ Premissas'!$D$9))+E78*(('🎛️ Premissas'!$D$25*('🎛️ Premissas'!$D$19*('🎛️ Premissas'!$D$10/1000000)+'🎛️ Premissas'!$D$20*('🎛️ Premissas'!$D$11/1000000))*(1-'🎛️ Premissas'!$D$12)*'🎛️ Premissas'!$D$9)+('🎛️ Premissas'!$D$26*('🎛️ Premissas'!$D$23*('🎛️ Premissas'!$D$10/1000000)+'🎛️ Premissas'!$D$24*('🎛️ Premissas'!$D$11/1000000))*(1-'🎛️ Premissas'!$D$12)*'🎛️ Premissas'!$D$9)) | F81: =F75*('🎛️ Premissas'!$D$14*('🎛️ Premissas'!$D$15*('🎛️ Premissas'!$D$10/1000000)+'🎛️ Premissas'!$D$16*('🎛️ Premissas'!$D$11/1000000))*(1-'🎛️ Premissas'!$D$12)*'🎛️ Premissas'!$D$9*'🎛️ Premissas'!$D$17)+F76*('🎛️ Premissas'!$D$18*('🎛️ Premissas'!$D$19*('🎛️ Premissas'!$D$10/1000000)+'🎛️ Premissas'!$D$20*('🎛️ Premissas'!$D$11/1000000))*(1-'🎛️ Premissas'!$D$12)*'🎛️ Premissas'!$D$9)+F77*(('🎛️ Premissas'!$D$21*('🎛️ Premissas'!$D$19*('🎛️ Premissas'!$D$10/1000000)+'🎛️ Premissas'!$D$20*('🎛️ Premissas'!$D$11/1000000))*(1-'🎛️ Premissas'!$D$12)*'🎛️ Premissas'!$D$9)+('🎛️ Premissas'!$D$22*('🎛️ Premissas'!$D$23*('🎛️ Premissas'!$D$10/1000000)+'🎛️ Premissas'!$D$24*('🎛️ Premissas'!$D$11/1000000))*(1-'🎛️ Premissas'!$D$12)*'🎛️ Premissas'!$D$9))+F78*(('🎛️ Premissas'!$D$25*('🎛️ Premissas'!$D$19*('🎛️ Premissas'!$D$10/1000000)+'🎛️ Premissas'!$D$20*('🎛️ Premissas'!$D$11/1000000))*(1-'🎛️ Premissas'!$D$12)*'🎛️ Premissas'!$D$9)+('🎛️ Premissas'!$D$26*('🎛️ Premissas'!$D$23*('🎛️ Premissas'!$D$10/1000000)+'🎛️ Premissas'!$D$24*('🎛️ Premissas'!$D$11/1000000))*(1-'🎛️ Premissas'!$D$12)*'🎛️ Premissas'!$D$9)) | G81: =G75*('🎛️ Premissas'!$D$14*('🎛️ Premissas'!$D$15*('🎛️ Premissas'!$D$10/1000000)+'🎛️ Premissas'!$D$16*('🎛️ Premissas'!$D$11/1000000))*(1-'🎛️ Premissas'!$D$12)*'🎛️ Premissas'!$D$9*'🎛️ Premissas'!$D$17)+G76*('🎛️ Premissas'!$D$18*('🎛️ Premissas'!$D$19*('🎛️ Premissas'!$D$10/1000000)+'🎛️ Premissas'!$D$20*('🎛️ Premissas'!$D$11/1000000))*(1-'🎛️ Premissas'!$D$12)*'🎛️ Premissas'!$D$9)+G77*(('🎛️ Premissas'!$D$21*('🎛️ Premissas'!$D$19*('🎛️ Premissas'!$D$10/1000000)+'🎛️ Premissas'!$D$20*('🎛️ Premissas'!$D$11/1000000))*(1-'🎛️ Premissas'!$D$12)*'🎛️ Premissas'!$D$9)+('🎛️ Premissas'!$D$22*('🎛️ Premissas'!$D$23*('🎛️ Premissas'!$D$10/1000000)+'🎛️ Premissas'!$D$24*('🎛️ Premissas'!$D$11/1000000))*(1-'🎛️ Premissas'!$D$12)*'🎛️ Premissas'!$D$9))+G78*(('🎛️ Premissas'!$D$25*('🎛️ Premissas'!$D$19*('🎛️ Premissas'!$D$10/1000000)+'🎛️ Premissas'!$D$20*('🎛️ Premissas'!$D$11/1000000))*(1-'🎛️ Premissas'!$D$12)*'🎛️ Premissas'!$D$9)+('🎛️ Premissas'!$D$26*('🎛️ Premissas'!$D$23*('🎛️ Premissas'!$D$10/1000000)+'🎛️ Premissas'!$D$24*('🎛️ Premissas'!$D$11/1000000))*(1-'🎛️ Premissas'!$D$12)*'🎛️ Premissas'!$D$9)) | H81: =H75*('🎛️ Premissas'!$D$14*('🎛️ Premissas'!$D$15*('🎛️ Premissas'!$D$10/1000000)+'🎛️ Premissas'!$D$16*('🎛️ Premissas'!$D$11/1000000))*(1-'🎛️ Premissas'!$D$12)*'🎛️ Premissas'!$D$9*'🎛️ Premissas'!$D$17)+H76*('🎛️ Premissas'!$D$18*('🎛️ Premissas'!$D$19*('🎛️ Premissas'!$D$10/1000000)+'🎛️ Premissas'!$D$20*('🎛️ Premissas'!$D$11/1000000))*(1-'🎛️ Premissas'!$D$12)*'🎛️ Premissas'!$D$9)+H77*(('🎛️ Premissas'!$D$21*('🎛️ Premissas'!$D$19*('🎛️ Premissas'!$D$10/1000000)+'🎛️ Premissas'!$D$20*('🎛️ Premissas'!$D$11/1000000))*(1-'🎛️ Premissas'!$D$12)*'🎛️ Premissas'!$D$9)+('🎛️ Premissas'!$D$22*('🎛️ Premissas'!$D$23*('🎛️ Premissas'!$D$10/1000000)+'🎛️ Premissas'!$D$24*('🎛️ Premissas'!$D$11/1000000))*(1-'🎛️ Premissas'!$D$12)*'🎛️ Premissas'!$D$9))+H78*(('🎛️ Premissas'!$D$25*('🎛️ Premissas'!$D$19*('🎛️ Premissas'!$D$10/1000000)+'🎛️ Premissas'!$D$20*('🎛️ Premissas'!$D$11/1000000))*(1-'🎛️ Premissas'!$D$12)*'🎛️ Premissas'!$D$9)+('🎛️ Premissas'!$D$26*('🎛️ Premissas'!$D$23*('🎛️ Premissas'!$D$10/1000000)+'🎛️ Premissas'!$D$24*('🎛️ Premissas'!$D$11/1000000))*(1-'🎛️ Premissas'!$D$12)*'🎛️ Premissas'!$D$9)) | I81: =I75*('🎛️ Premissas'!$D$14*('🎛️ Premissas'!$D$15*('🎛️ Premissas'!$D$10/1000000)+'🎛️ Premissas'!$D$16*('🎛️ Premissas'!$D$11/1000000))*(1-'🎛️ Premissas'!$D$12)*'🎛️ Premissas'!$D$9*'🎛️ Premissas'!$D$17)+I76*('🎛️ Premissas'!$D$18*('🎛️ Premissas'!$D$19*('🎛️ Premissas'!$D$10/1000000)+'🎛️ Premissas'!$D$20*('🎛️ Premissas'!$D$11/1000000))*(1-'🎛️ Premissas'!$D$12)*'🎛️ Premissas'!$D$9)+I77*(('🎛️ Premissas'!$D$21*('🎛️ Premissas'!$D$19*('🎛️ Premissas'!$D$10/1000000)+'🎛️ Premissas'!$D$20*('🎛️ Premissas'!$D$11/1000000))*(1-'🎛️ Premissas'!$D$12)*'🎛️ Premissas'!$D$9)+('🎛️ Premissas'!$D$22*('🎛️ Premissas'!$D$23*('🎛️ Premissas'!$D$10/1000000)+'🎛️ Premissas'!$D$24*('🎛️ Premissas'!$D$11/1000000))*(1-'🎛️ Premissas'!$D$12)*'🎛️ Premissas'!$D$9))+I78*(('🎛️ Premissas'!$D$25*('🎛️ Premissas'!$D$19*('🎛️ Premissas'!$D$10/1000000)+'🎛️ Premissas'!$D$20*('🎛️ Premissas'!$D$11/1000000))*(1-'🎛️ Premissas'!$D$12)*'🎛️ Premissas'!$D$9)+('🎛️ Premissas'!$D$26*('🎛️ Premissas'!$D$23*('🎛️ Premissas'!$D$10/1000000)+'🎛️ Premissas'!$D$24*('🎛️ Premissas'!$D$11/1000000))*(1-'🎛️ Premissas'!$D$12)*'🎛️ Premissas'!$D$9)) | ... Y81: =Y75*('🎛️ Premissas'!$D$14*('🎛️ Premissas'!$D$15*('🎛️ Premissas'!$D$10/1000000)+'🎛️ Premissas'!$D$16*('🎛️ Premissas'!$D$11/1000000))*(1-'🎛️ Premissas'!$D$12)*'🎛️ Premissas'!$D$9*'🎛️ Premissas'!$D$17)+Y76*('🎛️ Premissas'!$D$18*('🎛️ Premissas'!$D$19*('🎛️ Premissas'!$D$10/1000000)+'🎛️ Premissas'!$D$20*('🎛️ Premissas'!$D$11/1000000))*(1-'🎛️ Premissas'!$D$12)*'🎛️ Premissas'!$D$9)+Y77*(('🎛️ Premissas'!$D$21*('🎛️ Premissas'!$D$19*('🎛️ Premissas'!$D$10/1000000)+'🎛️ Premissas'!$D$20*('🎛️ Premissas'!$D$11/1000000))*(1-'🎛️ Premissas'!$D$12)*'🎛️ Premissas'!$D$9)+('🎛️ Premissas'!$D$22*('🎛️ Premissas'!$D$23*('🎛️ Premissas'!$D$10/1000000)+'🎛️ Premissas'!$D$24*('🎛️ Premissas'!$D$11/1000000))*(1-'🎛️ Premissas'!$D$12)*'🎛️ Premissas'!$D$9))+Y78*(('🎛️ Premissas'!$D$25*('🎛️ Premissas'!$D$19*('🎛️ Premissas'!$D$10/1000000)+'🎛️ Premissas'!$D$20*('🎛️ Premissas'!$D$11/1000000))*(1-'🎛️ Premissas'!$D$12)*'🎛️ Premissas'!$D$9)+('🎛️ Premissas'!$D$26*('🎛️ Premissas'!$D$23*('🎛️ Premissas'!$D$10/1000000)+'🎛️ Premissas'!$D$24*('🎛️ Premissas'!$D$11/1000000))*(1-'🎛️ Premissas'!$D$12)*'🎛️ Premissas'!$D$9))
A82: Custo Fixo | B82: ='🎛️ Premissas'!$D$37+'🎛️ Premissas'!$D$39+'🎛️ Premissas'!$D$41+'🎛️ Premissas'!$D$43 | C82: ='🎛️ Premissas'!$D$37+'🎛️ Premissas'!$D$39+'🎛️ Premissas'!$D$41+'🎛️ Premissas'!$D$43 | D82: ='🎛️ Premissas'!$D$37+'🎛️ Premissas'!$D$39+'🎛️ Premissas'!$D$41+'🎛️ Premissas'!$D$43 | E82: ='🎛️ Premissas'!$D$37+'🎛️ Premissas'!$D$39+'🎛️ Premissas'!$D$41+'🎛️ Premissas'!$D$43 | F82: ='🎛️ Premissas'!$D$37+'🎛️ Premissas'!$D$39+'🎛️ Premissas'!$D$41+'🎛️ Premissas'!$D$43 | G82: ='🎛️ Premissas'!$D$37+'🎛️ Premissas'!$D$39+'🎛️ Premissas'!$D$41+'🎛️ Premissas'!$D$43 | H82: ='🎛️ Premissas'!$D$37+'🎛️ Premissas'!$D$39+'🎛️ Premissas'!$D$41+'🎛️ Premissas'!$D$43 | I82: ='🎛️ Premissas'!$D$37+'🎛️ Premissas'!$D$39+'🎛️ Premissas'!$D$41+'🎛️ Premissas'!$D$43 | ... M82: ='🎛️ Premissas'!$D$37+'🎛️ Premissas'!$D$39+'🎛️ Premissas'!$D$41+'🎛️ Premissas'!$D$43 | N82: ='🎛️ Premissas'!$D$38+'🎛️ Premissas'!$D$40+'🎛️ Premissas'!$D$42+'🎛️ Premissas'!$D$43 | O82: ='🎛️ Premissas'!$D$38+'🎛️ Premissas'!$D$40+'🎛️ Premissas'!$D$42+'🎛️ Premissas'!$D$43 | P82: ='🎛️ Premissas'!$D$38+'🎛️ Premissas'!$D$40+'🎛️ Premissas'!$D$42+'🎛️ Premissas'!$D$43 | Q82: ='🎛️ Premissas'!$D$38+'🎛️ Premissas'!$D$40+'🎛️ Premissas'!$D$42+'🎛️ Premissas'!$D$43 | R82: ='🎛️ Premissas'!$D$38+'🎛️ Premissas'!$D$40+'🎛️ Premissas'!$D$42+'🎛️ Premissas'!$D$43 | S82: ='🎛️ Premissas'!$D$38+'🎛️ Premissas'!$D$40+'🎛️ Premissas'!$D$42+'🎛️ Premissas'!$D$43 | T82: ='🎛️ Premissas'!$D$38+'🎛️ Premissas'!$D$40+'🎛️ Premissas'!$D$42+'🎛️ Premissas'!$D$43 | U82: ='🎛️ Premissas'!$D$38+'🎛️ Premissas'!$D$40+'🎛️ Premissas'!$D$42+'🎛️ Premissas'!$D$43 | ... Y82: ='🎛️ Premissas'!$D$38+'🎛️ Premissas'!$D$40+'🎛️ Premissas'!$D$42+'🎛️ Premissas'!$D$43
A83: Impostos | B83: =B80*'🎛️ Premissas'!$D$67 | C83: =C80*'🎛️ Premissas'!$D$67 | D83: =D80*'🎛️ Premissas'!$D$67 | E83: =E80*'🎛️ Premissas'!$D$67 | F83: =F80*'🎛️ Premissas'!$D$67 | G83: =G80*'🎛️ Premissas'!$D$67 | H83: =H80*'🎛️ Premissas'!$D$67 | I83: =I80*'🎛️ Premissas'!$D$67 | ... Y83: =Y80*'🎛️ Premissas'!$D$67
A84: Resultado Mensal | B84: =B80-B81-B82-B83 | C84: =C80-C81-C82-C83 | D84: =D80-D81-D82-D83 | E84: =E80-E81-E82-E83 | F84: =F80-F81-F82-F83 | G84: =G80-G81-G82-G83 | H84: =H80-H81-H82-H83 | I84: =I80-I81-I82-I83 | ... Y84: =Y80-Y81-Y82-Y83
A86: Cons CF (helper TIR) | B86: =-'🎛️ Premissas'!$B$55 | C86: =B60 | D86: =C60 | E86: =D60 | F86: =E60 | G86: =F60 | H86: =G60 | I86: =H60 | J86: =I60 | ... Z86: =Y60
A87: Base CF (helper TIR) | B87: =-'🎛️ Premissas'!$B$55 | C87: =B72 | D87: =C72 | E87: =D72 | F87: =E72 | G87: =F72 | H87: =G72 | I87: =H72 | J87: =I72 | ... Z87: =Y72
A88: Otim CF (helper TIR) | B88: =-'🎛️ Premissas'!$B$55 | C88: =B84 | D88: =C84 | E88: =D84 | F88: =E84 | G88: =F84 | H88: =G84 | I88: =H84 | J88: =I84 | ... Z88: =Y84
