Workbook

Sheet 🚀 Dashboard Investidor
A2: AUTONOMA · DASHBOARD
A3: Asset Light SaaS · Brasil → LATAM · Sonnet 4.6 (pagos) + Haiku 4.5 (Free) · Projeto de 24 meses com valuation M24
A5: CENÁRIO ATIVO: | B5: ='🔧 Cenário Ativo'!B2 -> Conservador | C5: ← altere em '🔧 Cenário Ativo'!B2 · Opções: Conservador / Base / Otimista
A7: PAYBACK CAC | C7: VALUATION M24 | E7: RECEITA ACUM 24m | G7: BREAKEVEN | I7: RETORNO ANJO
A8: ='🔧 Cenário Ativo'!B54*30 -> 70.441014 | C8: =IF('🔧 Cenário Ativo'!B2="Conservador",'📊 Resumo Cenários'!B21,IF('🔧 Cenário Ativo'!B2="Base",'📊 Resumo Cenários'!C21,'📊 Resumo Cenários'!D21)) -> 27698813 | E8: =IF('🔧 Cenário Ativo'!B2="Conservador",'📊 Resumo Cenários'!B19,IF('🔧 Cenário Ativo'!B2="Base",'📊 Resumo Cenários'!C19,'📊 Resumo Cenários'!D19)) -> 9232937.7 | G8: {=IFERROR("M"&MATCH(TRUE,INDEX('📊 Base Mensal'!C25:Z25>0,0),0),">24m")} -> M10 | I8: =C8*'🎛️ Premissas'!$B$56 -> 4154822
A9: tempo p/ recuperar CAC (dias) | C9: Receita acum 24m × múltiplo cenário | E9: soma MRR M1–M24 | G9: resultado acum. > 0 | I9: valor da fatia % sobre aporte
A11: FLUXO DE CAIXA ACUMULADO | F11: BREAKEVEN
A29: MRR & ASSINANTES | F29: VALUATION 3 CENARIOS
A47: UNIT ECONOMICS · CENARIO ATIVO
A49: CAC | C49: LTV Essencial | E49: LTV / CAC | G49: CHURN MENSAL | I49: MARGEM M24
A50: ='🔧 Cenário Ativo'!B44 -> 80 | C50: ='🔧 Cenário Ativo'!B52 -> 425.88825 | E50: ='🔧 Cenário Ativo'!B53 -> 5.3236031 | G50: ='🔧 Cenário Ativo'!B32 -> 0.08 | I50: ='📊 Base Mensal'!Z26 -> 0.8315493
A51: full-loaded | C51: margem × vida média | E51: =IF(E50>=8,"✅ top quartile",IF(E50>=3,"✅ saudável","⚠️ rever CAC")) -> ✅ saudável | G51: anual ~46% | I51: bruta sobre MRR
A52: Obs.: Este estudo não configura convite ou promessa de investimento. Valores projetados com base em premissas controláveis em 🎛️ Premissas e 🔧 Cenário Ativo.
A53: AutoNoma © 2025 · Dashboard dinâmico · Todos os valores recalculam ao mudar o cenário em '🔧 Cenário Ativo'!B2
L76: Mês | M76: MRR | N76: Pagantes | O76: Free | P76: Resultado | Q76: Acumulado | R76: Essencial | S76: Autônoma | T76: Livre | U76: API Total | V76: Custo Fixo | W76: Margem%
L77: M01 | M77: ='📊 Base Mensal'!C11 -> 16167 | N77: ='📊 Base Mensal'!C9 -> 330 | O77: ='📊 Base Mensal'!C5 -> 3000 | P77: ='📊 Base Mensal'!C24 -> -44124.37 | Q77: ='📊 Base Mensal'!C25 -> -44124.37 | R77: ='📊 Base Mensal'!C6 -> 210 | S77: ='📊 Base Mensal'!C7 -> 90 | T77: ='📊 Base Mensal'!C8 -> 30 | U77: ='📊 Base Mensal'!C18 -> 3351.3305 | V77: ='📊 Base Mensal'!C20 -> 55000 | W77: ='📊 Base Mensal'!C26 -> 0.79270548
L78: M02 | M78: ='📊 Base Mensal'!D11 -> 32334 | N78: ='📊 Base Mensal'!D9 -> 660 | O78: ='📊 Base Mensal'!D5 -> 6000 | P78: ='📊 Base Mensal'!D24 -> -33248.741 | Q78: ='📊 Base Mensal'!D25 -> -77373.111 | R78: ='📊 Base Mensal'!D6 -> 420 | S78: ='📊 Base Mensal'!D7 -> 180 | T78: ='📊 Base Mensal'!D8 -> 60 | U78: ='📊 Base Mensal'!D18 -> 6702.6609 | V78: ='📊 Base Mensal'!D20 -> 55000 | W78: ='📊 Base Mensal'!D26 -> 0.79270548
L79: M03 | M79: ='📊 Base Mensal'!E11 -> 48501 | N79: ='📊 Base Mensal'!E9 -> 990 | O79: ='📊 Base Mensal'!E5 -> 9000 | P79: ='📊 Base Mensal'!E24 -> -22373.111 | Q79: ='📊 Base Mensal'!E25 -> -99746.223 | R79: ='📊 Base Mensal'!E6 -> 630 | S79: ='📊 Base Mensal'!E7 -> 270 | T79: ='📊 Base Mensal'!E8 -> 90 | U79: ='📊 Base Mensal'!E18 -> 10053.991 | V79: ='📊 Base Mensal'!E20 -> 55000 | W79: ='📊 Base Mensal'!E26 -> 0.79270548
L80: M04 | M80: ='📊 Base Mensal'!F11 -> 64668 | N80: ='📊 Base Mensal'!F9 -> 1320 | O80: ='📊 Base Mensal'!F5 -> 12000 | P80: ='📊 Base Mensal'!F24 -> -11497.482 | Q80: ='📊 Base Mensal'!F25 -> -111243.7 | R80: ='📊 Base Mensal'!F6 -> 840 | S80: ='📊 Base Mensal'!F7 -> 360 | T80: ='📊 Base Mensal'!F8 -> 120 | U80: ='📊 Base Mensal'!F18 -> 13405.322 | V80: ='📊 Base Mensal'!F20 -> 55000 | W80: ='📊 Base Mensal'!F26 -> 0.79270548
L81: M05 | M81: ='📊 Base Mensal'!G11 -> 80835 | N81: ='📊 Base Mensal'!G9 -> 1650 | O81: ='📊 Base Mensal'!G5 -> 15000 | P81: ='📊 Base Mensal'!G24 -> -621.85225 | Q81: ='📊 Base Mensal'!G25 -> -111865.56 | R81: ='📊 Base Mensal'!G6 -> 1050 | S81: ='📊 Base Mensal'!G7 -> 450 | T81: ='📊 Base Mensal'!G8 -> 150 | U81: ='📊 Base Mensal'!G18 -> 16756.652 | V81: ='📊 Base Mensal'!G20 -> 55000 | W81: ='📊 Base Mensal'!G26 -> 0.79270548
L82: M06 | M82: ='📊 Base Mensal'!H11 -> 97002 | N82: ='📊 Base Mensal'!H9 -> 1980 | O82: ='📊 Base Mensal'!H5 -> 18000 | P82: ='📊 Base Mensal'!H24 -> 10253.777 | Q82: ='📊 Base Mensal'!H25 -> -101611.78 | R82: ='📊 Base Mensal'!H6 -> 1260 | S82: ='📊 Base Mensal'!H7 -> 540 | T82: ='📊 Base Mensal'!H8 -> 180 | U82: ='📊 Base Mensal'!H18 -> 20107.983 | V82: ='📊 Base Mensal'!H20 -> 55000 | W82: ='📊 Base Mensal'!H26 -> 0.79270548
L83: M07 | M83: ='📊 Base Mensal'!I11 -> 113169 | N83: ='📊 Base Mensal'!I9 -> 2310 | O83: ='📊 Base Mensal'!I5 -> 21000 | P83: ='📊 Base Mensal'!I24 -> 21129.407 | Q83: ='📊 Base Mensal'!I25 -> -80482.373 | R83: ='📊 Base Mensal'!I6 -> 1470 | S83: ='📊 Base Mensal'!I7 -> 630 | T83: ='📊 Base Mensal'!I8 -> 210 | U83: ='📊 Base Mensal'!I18 -> 23459.313 | V83: ='📊 Base Mensal'!I20 -> 55000 | W83: ='📊 Base Mensal'!I26 -> 0.79270548
L84: M08 | M84: ='📊 Base Mensal'!J11 -> 129336 | N84: ='📊 Base Mensal'!J9 -> 2640 | O84: ='📊 Base Mensal'!J5 -> 24000 | P84: ='📊 Base Mensal'!J24 -> 32005.036 | Q84: ='📊 Base Mensal'!J25 -> -48477.336 | R84: ='📊 Base Mensal'!J6 -> 1680 | S84: ='📊 Base Mensal'!J7 -> 720 | T84: ='📊 Base Mensal'!J8 -> 240 | U84: ='📊 Base Mensal'!J18 -> 26810.644 | V84: ='📊 Base Mensal'!J20 -> 55000 | W84: ='📊 Base Mensal'!J26 -> 0.79270548
L85: M09 | M85: ='📊 Base Mensal'!K11 -> 145503 | N85: ='📊 Base Mensal'!K9 -> 2970 | O85: ='📊 Base Mensal'!K5 -> 27000 | P85: ='📊 Base Mensal'!K24 -> 42880.666 | Q85: ='📊 Base Mensal'!K25 -> -5596.6703 | R85: ='📊 Base Mensal'!K6 -> 1890 | S85: ='📊 Base Mensal'!K7 -> 810 | T85: ='📊 Base Mensal'!K8 -> 270 | U85: ='📊 Base Mensal'!K18 -> 30161.974 | V85: ='📊 Base Mensal'!K20 -> 55000 | W85: ='📊 Base Mensal'!K26 -> 0.79270548
L86: M10 | M86: ='📊 Base Mensal'!L11 -> 161670 | N86: ='📊 Base Mensal'!L9 -> 3300 | O86: ='📊 Base Mensal'!L5 -> 30000 | P86: ='📊 Base Mensal'!L24 -> 53756.296 | Q86: ='📊 Base Mensal'!L25 -> 48159.625 | R86: ='📊 Base Mensal'!L6 -> 2100 | S86: ='📊 Base Mensal'!L7 -> 900 | T86: ='📊 Base Mensal'!L8 -> 300 | U86: ='📊 Base Mensal'!L18 -> 33513.305 | V86: ='📊 Base Mensal'!L20 -> 55000 | W86: ='📊 Base Mensal'!L26 -> 0.79270548
L87: M11 | M87: ='📊 Base Mensal'!M11 -> 177837 | N87: ='📊 Base Mensal'!M9 -> 3630 | O87: ='📊 Base Mensal'!M5 -> 33000 | P87: ='📊 Base Mensal'!M24 -> 64631.925 | Q87: ='📊 Base Mensal'!M25 -> 112791.55 | R87: ='📊 Base Mensal'!M6 -> 2310 | S87: ='📊 Base Mensal'!M7 -> 990 | T87: ='📊 Base Mensal'!M8 -> 330 | U87: ='📊 Base Mensal'!M18 -> 36864.635 | V87: ='📊 Base Mensal'!M20 -> 55000 | W87: ='📊 Base Mensal'!M26 -> 0.79270548
L88: M12 | M88: ='📊 Base Mensal'!N11 -> 194004 | N88: ='📊 Base Mensal'!N9 -> 3960 | O88: ='📊 Base Mensal'!N5 -> 36000 | P88: ='📊 Base Mensal'!N24 -> 75507.555 | Q88: ='📊 Base Mensal'!N25 -> 188299.1 | R88: ='📊 Base Mensal'!N6 -> 2520 | S88: ='📊 Base Mensal'!N7 -> 1080 | T88: ='📊 Base Mensal'!N8 -> 360 | U88: ='📊 Base Mensal'!N18 -> 40215.965 | V88: ='📊 Base Mensal'!N20 -> 55000 | W88: ='📊 Base Mensal'!N26 -> 0.79270548
L89: M13 | M89: ='📊 Base Mensal'!O11 -> 212865.5 | N89: ='📊 Base Mensal'!O9 -> 4345 | O89: ='📊 Base Mensal'!O5 -> 39500 | P89: ='📊 Base Mensal'!O24 -> 73195.789 | Q89: ='📊 Base Mensal'!O25 -> 261494.89 | R89: ='📊 Base Mensal'!O6 -> 2765 | S89: ='📊 Base Mensal'!O7 -> 1185 | T89: ='📊 Base Mensal'!O8 -> 395 | U89: ='📊 Base Mensal'!O18 -> 44125.851 | V89: ='📊 Base Mensal'!O20 -> 70000 | W89: ='📊 Base Mensal'!O26 -> 0.79270548
L90: M14 | M90: ='📊 Base Mensal'!P11 -> 231727 | N90: ='📊 Base Mensal'!P9 -> 4730 | O90: ='📊 Base Mensal'!P5 -> 43000 | P90: ='📊 Base Mensal'!P24 -> 85884.024 | Q90: ='📊 Base Mensal'!P25 -> 347378.92 | R90: ='📊 Base Mensal'!P6 -> 3010 | S90: ='📊 Base Mensal'!P7 -> 1290 | T90: ='📊 Base Mensal'!P8 -> 430 | U90: ='📊 Base Mensal'!P18 -> 48035.736 | V90: ='📊 Base Mensal'!P20 -> 70000 | W90: ='📊 Base Mensal'!P26 -> 0.79270548
L91: M15 | M91: ='📊 Base Mensal'!Q11 -> 250588.5 | N91: ='📊 Base Mensal'!Q9 -> 5115 | O91: ='📊 Base Mensal'!Q5 -> 46500 | P91: ='📊 Base Mensal'!Q24 -> 98572.258 | Q91: ='📊 Base Mensal'!Q25 -> 445951.18 | R91: ='📊 Base Mensal'!Q6 -> 3255 | S91: ='📊 Base Mensal'!Q7 -> 1395 | T91: ='📊 Base Mensal'!Q8 -> 465 | U91: ='📊 Base Mensal'!Q18 -> 51945.622 | V91: ='📊 Base Mensal'!Q20 -> 70000 | W91: ='📊 Base Mensal'!Q26 -> 0.79270548
L92: M16 | M92: ='📊 Base Mensal'!R11 -> 368794.8 | N92: ='📊 Base Mensal'!R9 -> 8052 | O92: ='📊 Base Mensal'!R5 -> 50000 | P92: ='📊 Base Mensal'!R24 -> 184298.34 | Q92: ='📊 Base Mensal'!R25 -> 630249.52 | R92: ='📊 Base Mensal'!R6 -> 6137 | S92: ='📊 Base Mensal'!R7 -> 1454 | T92: ='📊 Base Mensal'!R8 -> 461 | U92: ='📊 Base Mensal'!R18 -> 70241.083 | V92: ='📊 Base Mensal'!R20 -> 70000 | W92: ='📊 Base Mensal'!R26 -> 0.80953885
L93: M17 | M93: ='📊 Base Mensal'!S11 -> 483972.6 | N93: ='📊 Base Mensal'!S9 -> 10874 | O93: ='📊 Base Mensal'!S5 -> 53500 | P93: ='📊 Base Mensal'!S24 -> 267692.34 | Q93: ='📊 Base Mensal'!S25 -> 897941.85 | R93: ='📊 Base Mensal'!S6 -> 8827 | S93: ='📊 Base Mensal'!S7 -> 1589 | T93: ='📊 Base Mensal'!S8 -> 458 | U93: ='📊 Base Mensal'!S18 -> 88203.551 | V93: ='📊 Base Mensal'!S20 -> 70000 | W93: ='📊 Base Mensal'!S26 -> 0.81775094
L94: M18 | M94: ='📊 Base Mensal'!T11 -> 596620.3 | N94: ='📊 Base Mensal'!T9 -> 13597 | O94: ='📊 Base Mensal'!T5 -> 57000 | P94: ='📊 Base Mensal'!T24 -> 349132.44 | Q94: ='📊 Base Mensal'!T25 -> 1247074.3 | R94: ='📊 Base Mensal'!T6 -> 11350 | S94: ='📊 Base Mensal'!T7 -> 1789 | T94: ='📊 Base Mensal'!T8 -> 458 | U94: ='📊 Base Mensal'!T18 -> 105893.42 | V94: ='📊 Base Mensal'!T20 -> 70000 | W94: ='📊 Base Mensal'!T26 -> 0.8225112
L95: M19 | M95: ='📊 Base Mensal'!U11 -> 706817.1 | N95: ='📊 Base Mensal'!U9 -> 16229 | O95: ='📊 Base Mensal'!U5 -> 60500 | P95: ='📊 Base Mensal'!U24 -> 428692.57 | Q95: ='📊 Base Mensal'!U25 -> 1675766.9 | R95: ='📊 Base Mensal'!U6 -> 13725 | S95: ='📊 Base Mensal'!U7 -> 2044 | T95: ='📊 Base Mensal'!U8 -> 460 | U95: ='📊 Base Mensal'!U18 -> 123306.48 | V95: ='📊 Base Mensal'!U20 -> 70000 | W95: ='📊 Base Mensal'!U26 -> 0.82554683
L96: M20 | M96: ='📊 Base Mensal'!V11 -> 814921.8 | N96: ='📊 Base Mensal'!V9 -> 18782 | O96: ='📊 Base Mensal'!V5 -> 64000 | P96: ='📊 Base Mensal'!V24 -> 506645.79 | Q96: ='📊 Base Mensal'!V25 -> 2182412.7 | R96: ='📊 Base Mensal'!V6 -> 15971 | S96: ='📊 Base Mensal'!V7 -> 2346 | T96: ='📊 Base Mensal'!V8 -> 465 | U96: ='📊 Base Mensal'!V18 -> 140485.39 | V96: ='📊 Base Mensal'!V20 -> 70000 | W96: ='📊 Base Mensal'!V26 -> 0.82760875
L97: M21 | M97: ='📊 Base Mensal'!W11 -> 921093.6 | N97: ='📊 Base Mensal'!W9 -> 21264 | O97: ='📊 Base Mensal'!W5 -> 67500 | P97: ='📊 Base Mensal'!W24 -> 583120.31 | Q97: ='📊 Base Mensal'!W25 -> 2765533 | R97: ='📊 Base Mensal'!W6 -> 18104 | S97: ='📊 Base Mensal'!W7 -> 2687 | T97: ='📊 Base Mensal'!W8 -> 473 | U97: ='📊 Base Mensal'!W18 -> 157442.06 | V97: ='📊 Base Mensal'!W20 -> 70000 | W97: ='📊 Base Mensal'!W26 -> 0.82907051
L98: M22 | M98: ='📊 Base Mensal'!X11 -> 1025631.6 | N98: ='📊 Base Mensal'!X9 -> 23684 | O98: ='📊 Base Mensal'!X5 -> 71000 | P98: ='📊 Base Mensal'!X24 -> 658341.13 | Q98: ='📊 Base Mensal'!X25 -> 3423874.1 | R98: ='📊 Base Mensal'!X6 -> 20137 | S98: ='📊 Base Mensal'!X7 -> 3062 | T98: ='📊 Base Mensal'!X8 -> 485 | U98: ='📊 Base Mensal'!X18 -> 174214.68 | V98: ='📊 Base Mensal'!X20 -> 70000 | W98: ='📊 Base Mensal'!X26 -> 0.83013913
L99: M23 | M99: ='📊 Base Mensal'!Y11 -> 1128615.2 | N99: ='📊 Base Mensal'!Y9 -> 26048 | O99: ='📊 Base Mensal'!Y5 -> 74500 | P99: ='📊 Base Mensal'!Y24 -> 732376.64 | Q99: ='📊 Base Mensal'!Y25 -> 4156250.7 | R99: ='📊 Base Mensal'!Y6 -> 22083 | S99: ='📊 Base Mensal'!Y7 -> 3465 | T99: ='📊 Base Mensal'!Y8 -> 500 | U99: ='📊 Base Mensal'!Y18 -> 190804.74 | V99: ='📊 Base Mensal'!Y20 -> 70000 | W99: ='📊 Base Mensal'!Y26 -> 0.83093907
L100: M24 | M100: ='📊 Base Mensal'!Z11 -> 1230263.7 | N100: ='📊 Base Mensal'!Z9 -> 28363 | O100: ='📊 Base Mensal'!Z5 -> 78000 | P100: ='📊 Base Mensal'!Z24 -> 805393.27 | Q100: ='📊 Base Mensal'!Z25 -> 4961644 | R100: ='📊 Base Mensal'!Z6 -> 23953 | S100: ='📊 Base Mensal'!Z7 -> 3891 | T100: ='📊 Base Mensal'!Z8 -> 519 | U100: ='📊 Base Mensal'!Z18 -> 207238.78 | V100: ='📊 Base Mensal'!Z20 -> 70000 | W100: ='📊 Base Mensal'!Z26 -> 0.8315493
L102: Cenário | M102: Aporte R$1M | N102: Valuation 100% M24 | O102: ="Retorno Anjo ("&TEXT('🎛️ Premissas'!$B$56,"0%")&")" -> Retorno Anjo (15%)
L103: Conservador | M103: ='🎛️ Premissas'!$B$55/1000000 -> 1 | N103: ='📊 Resumo Cenários'!B21/1000000 -> 27.698813 | O103: ='📊 Resumo Cenários'!B22/1000000 -> 4.154822
L104: Base | M104: ='🎛️ Premissas'!$B$55/1000000 -> 1 | N104: ='📊 Resumo Cenários'!C21/1000000 -> 75.044719 | O104: ='📊 Resumo Cenários'!C22/1000000 -> 11.256708
L105: Otimista | M105: ='🎛️ Premissas'!$B$55/1000000 -> 1 | N105: ='📊 Resumo Cenários'!D21/1000000 -> 148.72558 | O105: ='📊 Resumo Cenários'!D22/1000000 -> 22.308836

Sheet 💎 Resumo Anjo
B2: AUTONOMA · RESUMO PARA INVESTIDOR ANJO
B3: Asset-Light SaaS · Brasil → LATAM · Sonnet 4.6 (planos pagos) + Haiku 4.5 (Free) · Horizonte 24 meses
B5: 1 · A OFERTA
B6: Aporte | C6: ='🎛️ Premissas'!B55 -> 1000000 | D6: ← entrada do anjo
B7: Equity oferecido | C7: ='🎛️ Premissas'!B56 -> 0.15 | D7: ← fatia adquirida
B8: Valuation post-money | C8: ='🎛️ Premissas'!B58 -> 6666666.7 | D8: = aporte ÷ equity
B9: Valuation pre-money | C9: ='🎛️ Premissas'!B57 -> 5666666.7
B11: 2 · MARCOS ATÉ A SÉRIE A (cenário Base)
B12: Indicador | C12: M12 | D12: M24
B13: Assinantes pagantes | C13: ='📊 Base Mensal'!N9 -> 3960 | D13: ='📊 Base Mensal'!Z9 -> 28363
B14: MRR (R$/mês) | C14: ='📊 Base Mensal'!N11 -> 194004 | D14: ='📊 Base Mensal'!Z11 -> 1230263.7
B15: Receita acumulada | C15: ='📊 Base Mensal'!N12 -> 1261026 | D15: ='📊 Base Mensal'!Z12 -> 9232937.7
B16: Margem bruta | C16: ='📊 Base Mensal'!N26 -> 0.79270548 | D16: ='📊 Base Mensal'!Z26 -> 0.8315493
B17: Resultado mensal | C17: ='📊 Base Mensal'!N24 -> 75507.555 | D17: ='📊 Base Mensal'!Z24 -> 805393.27
B19: 3 · RETORNO DO ANJO (fatia de 15%)
B20: Cenário | C20: Valuation M24 | D20: Valor da fatia 15% | E20: Múltiplo s/ aporte
B21: Conservador | C21: ='📊 Resumo Cenários'!B21 -> 27698813 | D21: =C21*'🎛️ Premissas'!$B$56 -> 4154822 | E21: =D21/'🎛️ Premissas'!$B$55 -> 4.154822
B22: Base | C22: ='📊 Resumo Cenários'!C21 -> 75044719 | D22: =C22*'🎛️ Premissas'!$B$56 -> 11256708 | E22: =D22/'🎛️ Premissas'!$B$55 -> 11.256708
B23: Otimista | C23: ='📊 Resumo Cenários'!D21 -> 1.4872558e+08 | D23: =C23*'🎛️ Premissas'!$B$56 -> 22308836 | E23: =D23/'🎛️ Premissas'!$B$55 -> 22.308836
B25: 4 · USO DO CAPITAL (R$1M · ~runway 18 meses)
B26: Produto & Engenharia (Sonnet/Haiku, dev) | C26: 0.4 | D26: =C26*'🎛️ Premissas'!$B$55 -> 400000
B27: Aquisição & Marketing (CAC, growth) | C27: 0.3 | D27: =C27*'🎛️ Premissas'!$B$55 -> 300000
B28: Equipe & Operação (CS, pró-labore) | C28: 0.2 | D28: =C28*'🎛️ Premissas'!$B$55 -> 200000
B29: Reserva & Jurídico/Contab. | C29: 0.1 | D29: =C29*'🎛️ Premissas'!$B$55 -> 100000
B30: Total | C30: =SUM(C26:C29) -> 1 | D30: =SUM(D26:D29) -> 1000000
B32: 5 · TESTE DE STRESS / DOWNSIDE (honestidade ao anjo)
B33: • Mesmo no cenário Conservador, o aporte retorna ~4,2× em 24 meses (fatia 15% = R$4,2M).
B34: • Churn diferenciado por plano: Essencial 8%, Autônoma 5%, Livre 3% — lock-in cresce com o agente.
B35: • Break-even de caixa no M6; margem bruta >80% sustentada por rodar o Free em Haiku (só custo).
B36: • Sensível a: CAC real (hoje R$60 full-loaded) e conversão Free→pago. Ambos controláveis em 🎛️ Premissas.
B37: • Próximo marco: Receita acum. R$15M no M24 sustenta conversão Série A a 5× receita (≈R$75M).
B39: Obs.: Este resumo não configura convite ou promessa de investimento. Todos os valores recalculam ao alterar o cenário em 🔧 Cenário Ativo e as premissas em 🎛️ Premissas. AutoNoma © 2025.
B42: 6 · SENSIBILIDADE: CHURN × LTV/CAC (plano Essencial, cenário Base)
B43: Churn/mês | C43: Vida média (m) | D43: LTV (R$) | E43: LTV / CAC | F43: Leitura
B44: 0.05 | C44: =1/B44 -> 20 | D44: ='📊 Resumo Cenários'!$C$13*C44 -> 867.1112 | E44: =D44/'🎛️ Premissas'!$C$45 -> 14.451853 | F44: =IF(E44>=8,"✅ top quartile",IF(E44>=3,"✅ saudável","⚠️ rever CAC")) -> ✅ top quartile
B45: 0.06 | C45: =1/B45 -> 16.666667 | D45: ='📊 Resumo Cenários'!$C$13*C45 -> 722.59267 | E45: =D45/'🎛️ Premissas'!$C$45 -> 12.043211 | F45: =IF(E45>=8,"✅ top quartile",IF(E45>=3,"✅ saudável","⚠️ rever CAC")) -> ✅ top quartile
B46: 0.07 | C46: =1/B46 -> 14.285714 | D46: ='📊 Resumo Cenários'!$C$13*C46 -> 619.36514 | E46: =D46/'🎛️ Premissas'!$C$45 -> 10.322752 | F46: =IF(E46>=8,"✅ top quartile",IF(E46>=3,"✅ saudável","⚠️ rever CAC")) -> ✅ top quartile
B47: 0.08 | C47: =1/B47 -> 12.5 | D47: ='📊 Resumo Cenários'!$C$13*C47 -> 541.9445 | E47: =D47/'🎛️ Premissas'!$C$45 -> 9.0324083 | F47: =IF(E47>=8,"✅ top quartile",IF(E47>=3,"✅ saudável","⚠️ rever CAC")) -> ✅ top quartile
B48: 0.1 | C48: =1/B48 -> 10 | D48: ='📊 Resumo Cenários'!$C$13*C48 -> 433.5556 | E48: =D48/'🎛️ Premissas'!$C$45 -> 7.2259267 | F48: =IF(E48>=8,"✅ top quartile",IF(E48>=3,"✅ saudável","⚠️ rever CAC")) -> ✅ saudável
B49: 0.12 | C49: =1/B49 -> 8.3333333 | D49: ='📊 Resumo Cenários'!$C$13*C49 -> 361.29633 | E49: =D49/'🎛️ Premissas'!$C$45 -> 6.0216056 | F49: =IF(E49>=8,"✅ top quartile",IF(E49>=3,"✅ saudável","⚠️ rever CAC")) -> ✅ saudável
B50: 0.15 | C50: =1/B50 -> 6.6666667 | D50: ='📊 Resumo Cenários'!$C$13*C50 -> 289.03707 | E50: =D50/'🎛️ Premissas'!$C$45 -> 4.8172844 | F50: =IF(E50>=8,"✅ top quartile",IF(E50>=3,"✅ saudável","⚠️ rever CAC")) -> ✅ saudável
B51: Leitura: mesmo dobrando o churn para 15%/mês (vida ~7m), o LTV/CAC continua saudável em 4,8×. O modelo não depende de retenção otimista — sobrevive ao downside.

Sheet 🔧 Cenário Ativo
A1: AutoNoma · Seletor de Cenário · Controler
A2: ▶ CENÁRIO ATIVO ◀ (altere aqui o modelo) | B2: Conservador | C2: ← Selecione: Conservador / Base / Otimista
A3: Coluna das premissas (uso interno — não edite) | B3: =MATCH(B2,{"Conservador","Base","Otimista"},0)+1 -> 2
A4: Premissas resolvidas para o cenário selecionado
A5: ── PREÇOS ──
A6: Preço Essencial | B6: =INDEX('🎛️ Premissas'!B5:D5,1,MATCH($B$2,{"Conservador","Base","Otimista"},0)) -> 39.9 | C6: ← Premissas!Preço Essencial (linha 5)
A7: Preço Autônoma | B7: =INDEX('🎛️ Premissas'!B6:D6,1,MATCH($B$2,{"Conservador","Base","Otimista"},0)) -> 59.9 | C7: ← Premissas!Preço Autônoma (linha 6)
A8: Preço Livre | B8: =INDEX('🎛️ Premissas'!B7:D7,1,MATCH($B$2,{"Conservador","Base","Otimista"},0)) -> 79.9 | C8: ← Premissas!Preço Livre (linha 7)
A9: ── API ──
A10: Câmbio USD/BRL | B10: =INDEX('🎛️ Premissas'!B9:D9,1,MATCH($B$2,{"Conservador","Base","Otimista"},0)) -> 5.3 | C10: ← Premissas!Câmbio USD/BRL (linha 9)
A11: Sonnet Input $/MTok | B11: =INDEX('🎛️ Premissas'!B10:D10,1,MATCH($B$2,{"Conservador","Base","Otimista"},0)) -> 3 | C11: ← Premissas!Sonnet 4.6 Input ($/MTok) (linha 10)
A12: Sonnet Output $/MTok | B12: =INDEX('🎛️ Premissas'!B11:D11,1,MATCH($B$2,{"Conservador","Base","Otimista"},0)) -> 15 | C12: ← Premissas!Sonnet 4.6 Output ($/MTok) (linha 11)
A13: Desconto Caching | B13: =INDEX('🎛️ Premissas'!B12:D12,1,MATCH($B$2,{"Conservador","Base","Otimista"},0)) -> 0.35 | C13: ← Premissas!Desconto Prompt Caching (%) (linha 12)
A14: ── USO ──
A15: Free: interações/mês | B15: =INDEX('🎛️ Premissas'!B14:D14,1,MATCH($B$2,{"Conservador","Base","Otimista"},0)) -> 50 | C15: ← Premissas!Free: interações/mês (LIMITE) (linha 14)
A16: Free: tokens input | B16: =INDEX('🎛️ Premissas'!B15:D15,1,MATCH($B$2,{"Conservador","Base","Otimista"},0)) -> 900 | C16: ← Premissas!Free: tokens input/interação (linha 15)
A17: Free: tokens output | B17: =INDEX('🎛️ Premissas'!B16:D16,1,MATCH($B$2,{"Conservador","Base","Otimista"},0)) -> 450 | C17: ← Premissas!Free: tokens output/interação (linha 16)
A18: Free: % ativas/mês | B18: =INDEX('🎛️ Premissas'!B17:D17,1,MATCH($B$2,{"Conservador","Base","Otimista"},0)) -> 0.5 | C18: ← Premissas!Free: % usuárias ativas/mês (linha 17)
A19: Essencial: interações/mês | B19: =INDEX('🎛️ Premissas'!B18:D18,1,MATCH($B$2,{"Conservador","Base","Otimista"},0)) -> 120 | C19: ← Premissas!Essencial: interações chat/mês (linha 18)
A20: Essencial: tokens input | B20: =INDEX('🎛️ Premissas'!B19:D19,1,MATCH($B$2,{"Conservador","Base","Otimista"},0)) -> 1200 | C20: ← Premissas!Essencial: tokens input/interação (linha 19)
A21: Essencial: tokens output | B21: =INDEX('🎛️ Premissas'!B20:D20,1,MATCH($B$2,{"Conservador","Base","Otimista"},0)) -> 700 | C21: ← Premissas!Essencial: tokens output/interação (linha 20)
A22: Autônoma: sessões agente/mês | B22: =INDEX('🎛️ Premissas'!B22:D22,1,MATCH($B$2,{"Conservador","Base","Otimista"},0)) -> 35 | C22: ← Premissas!Autônoma: sessões agente/mês (linha 22)
A23: Autônoma: tokens input/sessão | B23: =INDEX('🎛️ Premissas'!B23:D23,1,MATCH($B$2,{"Conservador","Base","Otimista"},0)) -> 3000 | C23: ← Premissas!Autônoma: tokens input/sessão agente (linha 23)
A24: Autônoma: tokens output/sessão | B24: =INDEX('🎛️ Premissas'!B24:D24,1,MATCH($B$2,{"Conservador","Base","Otimista"},0)) -> 1800 | C24: ← Premissas!Autônoma: tokens output/sessão agente (linha 24)
A25: Livre: sessões totais/mês | B25: =INDEX('🎛️ Premissas'!B26:D26,1,MATCH($B$2,{"Conservador","Base","Otimista"},0)) -> 60 | C25: ← Premissas!Livre: sessões totais agentes/mês (linha 26)
A26: ── CRESCIMENTO ──
A27: Free leads M1–12 | B27: =INDEX('🎛️ Premissas'!B28:D28,1,MATCH($B$2,{"Conservador","Base","Otimista"},0)) -> 3000 | C27: ← Premissas!Crescimento Free M1–12 (leads/mês) (linha 28)
A28: Free leads M13–24 | B28: =INDEX('🎛️ Premissas'!B29:D29,1,MATCH($B$2,{"Conservador","Base","Otimista"},0)) -> 3500 | C28: ← Premissas!Crescimento Free M13–24 (leads/mês) (linha 29)
A29: Conv. Free→Essencial | B29: =INDEX('🎛️ Premissas'!B30:D30,1,MATCH($B$2,{"Conservador","Base","Otimista"},0)) -> 0.07 | C29: ← Premissas!Conversão Free → Essencial (%) (linha 31)
A30: Conv. Free→Autônoma | B30: =INDEX('🎛️ Premissas'!B31:D31,1,MATCH($B$2,{"Conservador","Base","Otimista"},0)) -> 0.03 | C30: ← Premissas!Conversão Free → Autônoma (%) (linha 32)
A31: Conv. Free→Livre | B31: =INDEX('🎛️ Premissas'!B32:D32,1,MATCH($B$2,{"Conservador","Base","Otimista"},0)) -> 0.01 | C31: ← Premissas!Conversão Free → Livre (%) (linha 33)
A32: Churn Essencial/mês | B32: =INDEX('🎛️ Premissas'!B33:D33,1,MATCH($B$2,{"Conservador","Base","Otimista"},0)) -> 0.08 | C32: ← Premissas!Churn mensal Essencial (linha 34)
A33: Churn Autônoma/mês | B33: =INDEX('🎛️ Premissas'!B34:D34,1,MATCH($B$2,{"Conservador","Base","Otimista"},0)) -> 0.05 | C33: ← Premissas!Churn mensal Autônoma (linha 35)
A34: Churn Livre/mês | B34: =INDEX('🎛️ Premissas'!B35:D35,1,MATCH($B$2,{"Conservador","Base","Otimista"},0)) -> 0.03 | C34: ← Premissas!Churn mensal Livre (linha 36)
A35: ── CUSTO FIXO ──
A36: Equipe Ano 1 | B36: =INDEX('🎛️ Premissas'!B37:D37,1,MATCH($B$2,{"Conservador","Base","Otimista"},0)) -> 40000 | C36: ← Premissas!Equipe Ano 1 (média/mês) (linha 38)
A37: Equipe Ano 2 | B37: =INDEX('🎛️ Premissas'!B38:D38,1,MATCH($B$2,{"Conservador","Base","Otimista"},0)) -> 50000 | C37: ← Premissas!Equipe Ano 2 (média/mês) (linha 39)
A38: Infra Ano 1 | B38: =INDEX('🎛️ Premissas'!B39:D39,1,MATCH($B$2,{"Conservador","Base","Otimista"},0)) -> 5000 | C38: ← Premissas!Infraestrutura Ano 1 (linha 41)
A39: Infra Ano 2 | B39: =INDEX('🎛️ Premissas'!B40:D40,1,MATCH($B$2,{"Conservador","Base","Otimista"},0)) -> 7000 | C39: ← Premissas!Infraestrutura Ano 2 (linha 42)
A40: Marketing Ano 1 | B40: =INDEX('🎛️ Premissas'!B41:D41,1,MATCH($B$2,{"Conservador","Base","Otimista"},0)) -> 5000 | C40: ← Premissas!Marketing base Ano 1 (linha 44)
A41: Marketing Ano 2 | B41: =INDEX('🎛️ Premissas'!B42:D42,1,MATCH($B$2,{"Conservador","Base","Otimista"},0)) -> 8000 | C41: ← Premissas!Marketing base Ano 2 (linha 45)
A42: Outros | B42: =INDEX('🎛️ Premissas'!B43:D43,1,MATCH($B$2,{"Conservador","Base","Otimista"},0)) -> 5000 | C42: ← Premissas!Outros (jurídico, contab, misc.) (linha 47)
A43: ── UNIT ECONOMICS ──
A44: CAC full-loaded | B44: =INDEX('🎛️ Premissas'!B45:D45,1,MATCH($B$2,{"Conservador","Base","Otimista"},0)) -> 80 | C44: ← Premissas!CAC real full-loaded (R$) (linha 49)
A45: % aquisição via paid | B45: =INDEX('🎛️ Premissas'!B47:D47,1,MATCH($B$2,{"Conservador","Base","Otimista"},0)) -> 0.5 | C45: ← Premissas!% aquisição via paid (linha 51)
A46: ── VALUATION ──
A47: Múltiplo ARR M18 | B47: =INDEX('🎛️ Premissas'!B49:D49,1,MATCH($B$2,{"Conservador","Base","Otimista"},0)) -> 3 | C47: ← Premissas!Múltiplo ARR Série A (× ARR) (linha 53)
A48: UNIT ECONOMICS CALCULADOS (helpers)
A49: Custo API por Essencial / mês | B49: =B19*(B20/1000000*B11+B21/1000000*B12)*(1-B13)*B10 -> 5.82894 | C49: ARPU cobre custo API?
A50: Margem Unitária Essencial / mês | B50: =B6-B49 -> 34.07106 | C50: Preço − Custo API (contribuição)
A51: Vida média Essencial (meses) | B51: =1/B32 -> 12.5 | C51: 1 ÷ churn mensal
A52: LTV Essencial | B52: =B50*B51 -> 425.88825 | C52: Margem × vida média
A53: LTV / CAC | B53: =IFERROR(B52/B44,0) -> 5.3236031 | C53: ≥3× ok · ≥8× top quartile
A54: Payback CAC (meses) | B54: =IFERROR(B44/B50,0) -> 2.3480338 | C54: CAC ÷ margem mensal · <12m = excelente
A55: IMPOSTOS
A56: Alíquota imposto/receita | B56: =IF($B$2="Conservador",'🎛️ Premissas'!B67,IF($B$2="Base",'🎛️ Premissas'!C67,'🎛️ Premissas'!D67)) -> 0.12 | C56: ← Premissas!Alíquota (linha 67)

Sheet 🎛️ Premissas
A1: AutoNoma · Premissas · Fonte Única de Verdade · 100% Sonnet 4.6
A2: Azul = Input editável | B2: Preto = Fórmula | C2: Malva = Link cross-sheet
A3: PARAMETRO | B3: Conservador | C3: Base (padrão) | D3: Otimista | E3: UNIDADE/NOTA
A4: 1 · PREÇOS DOS PLANOS (R$/mês)
A5: Preço Essencial | B5: 39.9 | C5: 49.9 | D5: 49.9 | E5: R$/mês · + uso esporadico agente
A6: Preço Autônoma | B6: 59.9 | C6: 59.9 | D6: 62.9 | E6: R$/mês · chat + 1 agente
A7: Preço Livre | B7: 79.9 | C7: 79.9 | D7: 79.9 | E7: R$/mês · chat + 2 agentes
A8: 2 · CUSTO API ANTHROPIC (1 semestre 2026) | F8: 2b · CUSTO API HAIKU (plano Free)
A9: Câmbio USD/BRL | B9: 5.3 | C9: 5.3 | D9: 5.3 | E9: R$ por USD | F9: Haiku 4.5 Input ($/MTok) | G9: 1
A10: Sonnet 4.6 Input ($/MTok) | B10: 3 | C10: 3 | D10: 3 | E10: USD — oficial Anthropic | F10: Haiku 4.5 Output ($/MTok) | G10: 5
A11: Sonnet 4.6 Output ($/MTok) | B11: 15 | C11: 15 | D11: 15 | E11: USD — oficial Anthropic | F11: ← Free roda em Haiku (só custo)
A12: Desconto Prompt Caching (%) | B12: 0.35 | C12: 0.4 | D12: 0.45 | E12: % redução no bloco fixo
A13: 3 · USO POR PLANO — 100% SONNET 4.6
A14: Free: interações/mês (LIMITE) | B14: 50 | C14: 50 | D14: 50 | E14: Sonnet · teto produto
A15: Free: tokens input/interação | B15: 900 | C15: 900 | D15: 900 | E15: inclui system prompt cacheado
A16: Free: tokens output/interação | B16: 450 | C16: 450 | D16: 450 | E16: resposta orientada
A17: Free: % usuárias ativas/mês | B17: 0.5 | C17: 0.5 | D17: 0.5 | E17: % do cadastro que usa no mês
A18: Essencial: interações chat/mês | B18: 120 | C18: 140 | D18: 180 | E18: ilimitado prático · 20 dias × uso
A19: Essencial: tokens input/interação | B19: 1200 | C19: 1400 | D19: 1800 | E19: contexto Noma + memória
A20: Essencial: tokens output/interação | B20: 700 | C20: 700 | D20: 700 | E20: resposta + ação autônoma
A21: Autônoma: chat (= Essencial) | B21: 140 | C21: 140 | D21: 140 | E21: chat ilimitado Sonnet
A22: Autônoma: sessões agente/mês | B22: 35 | C22: 45 | D22: 60 | E22: sessões profundas com 1 agente
A23: Autônoma: tokens input/sessão agente | B23: 3000 | C23: 3000 | D23: 3000 | E23: contexto resolução + memória
A24: Autônoma: tokens output/sessão agente | B24: 1800 | C24: 1800 | D24: 1800 | E24: resolução completa + confirmação
A25: Livre: chat (= Essencial) | B25: 140 | C25: 140 | D25: 140 | E25: chat ilimitado Sonnet
A26: Livre: sessões totais agentes/mês | B26: 60 | C26: 80 | D26: 100 | E26: 2 agentes · mais que Autônoma
A27: 4 · CRESCIMENTO DA BASE
A28: Crescimento Free M1–12 (leads/mês) | B28: 3000 | C28: 3500 | D28: 4000 | E28: cadastros orgânicos+viral+paid
A29: Crescimento Free M13–24 (leads/mês) | B29: 3500 | C29: 4000 | D29: 4500 | E29: escala Brasil
A30: Conversão Free → Essencial (%) | B30: 0.07 | C30: 0.08 | D30: 0.1 | E30: % base Free que vira assinante
A31: Conversão Free → Autônoma (%) | B31: 0.03 | C31: 0.04 | D31: 0.05 | E31: % Essenciais que sobem
A32: Conversão Free → Livre (%) | B32: 0.01 | C32: 0.02 | D32: 0.03 | E32: % Autônomas que sobem
A33: Churn mensal Essencial | B33: 0.08 | C33: 0.08 | D33: 0.08 | E33: % cancela por mês
A34: Churn mensal Autônoma | B34: 0.05 | C34: 0.05 | D34: 0.05 | E34: % cancela por mês · agente = lock-in
A35: Churn mensal Livre | B35: 0.03 | C35: 0.03 | D35: 0.03 | E35: % cancela · 2 agentes = máximo lock-in
A36: 5 · CUSTO FIXO MENSAL (R$)
A37: Equipe Ano 1 (média/mês) | B37: 40000 | C37: 45000 | D37: 50000 | E37: devs+CS+pró-labore fundadores
A38: Equipe Ano 2 (média/mês) | B38: 50000 | C38: 60000 | D38: 70000 | E38: expansão de time
A39: Infraestrutura Ano 1 | B39: 5000 | C39: 6000 | D39: 8000 | E39: servidores, DB, CDN
A40: Infraestrutura Ano 2 | B40: 7000 | C40: 8000 | D40: 10000 | E40: escala com base
A41: Marketing base Ano 1 | B41: 5000 | C41: 6000 | D41: 8000 | E41: além do paid do pre-seed
A42: Marketing base Ano 2 | B42: 8000 | C42: 10000 | D42: 15000 | E42: crescimento + paid
A43: Outros (jurídico, contab, misc.) | B43: 5000 | C43: 6000 | D43: 8000 | E43: fixo administrativo
A44: 6 · UNIT ECONOMICS (CAC full-loaded)
A45: CAC real full-loaded (R$) | B45: 80 | C45: 60 | D45: 50 | E45: inclui mkt+CS+onboarding
A46: CAC via paid apenas (R$) | B46: 27 | C46: 25 | D46: 20 | E46: referência apenas
A47: % aquisição via paid | B47: 0.5 | C47: 0.45 | D47: 0.4 | E47: % novos pagantes via ads
A48: 7 · VALUATION M24 (sobre Receita Acumulada 24m)
A49: Múltiplo × Receita Acumulada 24m | B49: 3 | C49: 5 | D49: 7 | E49: × sobre 'Base Mensal'!Z12 (R$ 12,8M)
A50: 📐 Nota modelo: Conversão aplica-se ao pool elegível mensal (Free - já pagantes). Taxa ≠ '% dos leads mensais' mas '% da base elegível acumulada que converte por mês'. Calibrado para reproduzir ~4.400 pagantes no M12 (cenário Base).
A54: 8 · CAPTAÇÃO ANJO (R$1M = 15% equity)
A55: Aporte máximo (R$) | B55: 1000000 | C55: ← editável (simule aqui)
A56: % Equity oferecido | B56: 0.15 | C56: = 15% fixo (R$1M = 15%)
A57: Valuation pre-money implícito | B57: =B55/B56-B55 -> 5666666.7 | C57: = Aporte/%Equity - Aporte
A58: Valuation post-money implícito | B58: =B55/B56 -> 6666666.7 | C58: = Aporte / %Equity
A60: 9 · PARÂMETROS DO MODELO
A61: Free cadastradas no M1 (semente) | B61: 3000 | C61: ← lista de espera M1
A62: Floor YoY · Conservador | B62: 0.3 | C62: ← piso ajuste valuation
A63: Floor YoY · Base | B63: 0.4 | C63: ← piso ajuste valuation
A64: Floor YoY · Otimista | B64: 0.6 | C64: ← piso ajuste valuation
A65: Divisor YoY (suavização) | B65: 20 | C65: ← maior = ajuste mais suave
A66: Taxa de desconto mensal (NPV/IRR) | B66: 0.018 | C66: =(1+B66)^12-1 -> 0.23872053 | D66: ← anualizada
A67: Alíquota imposto sobre receita | B67: 0.12 | C67: 0.12 | D67: 0.15 | E67: ← Simples Nacional

Sheet 📊 Base Mensal
A1: AutoNoma · Base Mensal · 24 Meses · Fórmulas Dinâmicas · Cenário Controlado por 🔧 Cenário Ativo
A2: Cenário ativo: | C2: ='🔧 Cenário Ativo'!B2 -> Conservador
A3: Indicador | B3: Unid. | C3: M01 | D3: M02 | E3: M03 | F3: M04 | G3: M05 | H3: M06 | I3: M07 | J3: M08 | K3: M09 | L3: M10 | M3: M11 | N3: M12 ★ | O3: M13 | P3: M14 | Q3: M15 | R3: M16 | S3: M17 | T3: M18 | U3: M19 | V3: M20 | W3: M21 | X3: M22 | Y3: M23 | Z3: M24 ★
A4: USUÁRIOS
A5: Free · Cadastros (Sonnet 40 int/mês) | B5: usr | C5: ='🎛️ Premissas'!B61 -> 3000 | D5: =C5+'🔧 Cenário Ativo'!$B$27 -> 6000 | E5: =D5+'🔧 Cenário Ativo'!$B$27 -> 9000 | F5: =E5+'🔧 Cenário Ativo'!$B$27 -> 12000 | G5: =F5+'🔧 Cenário Ativo'!$B$27 -> 15000 | H5: =G5+'🔧 Cenário Ativo'!$B$27 -> 18000 | I5: =H5+'🔧 Cenário Ativo'!$B$27 -> 21000 | J5: =I5+'🔧 Cenário Ativo'!$B$27 -> 24000 | K5: =J5+'🔧 Cenário Ativo'!$B$27 -> 27000 | ... N5: =M5+'🔧 Cenário Ativo'!$B$27 -> 36000 | O5: =N5+'🔧 Cenário Ativo'!$B$28 -> 39500 | P5: =O5+'🔧 Cenário Ativo'!$B$28 -> 43000 | Q5: =P5+'🔧 Cenário Ativo'!$B$28 -> 46500 | R5: =Q5+'🔧 Cenário Ativo'!$B$28 -> 50000 | S5: =R5+'🔧 Cenário Ativo'!$B$28 -> 53500 | T5: =S5+'🔧 Cenário Ativo'!$B$28 -> 57000 | U5: =T5+'🔧 Cenário Ativo'!$B$28 -> 60500 | V5: =U5+'🔧 Cenário Ativo'!$B$28 -> 64000 | ... Z5: =Y5+'🔧 Cenário Ativo'!$B$28 -> 78000
A6: Essencial · Assinantes | B6: ass. | C6: =ROUND(C5*'🔧 Cenário Ativo'!$B$29,0) -> 210 | D6: =ROUND(D5*'🔧 Cenário Ativo'!$B$29,0) -> 420 | E6: =ROUND(E5*'🔧 Cenário Ativo'!$B$29,0) -> 630 | F6: =ROUND(F5*'🔧 Cenário Ativo'!$B$29,0) -> 840 | G6: =ROUND(G5*'🔧 Cenário Ativo'!$B$29,0) -> 1050 | H6: =ROUND(H5*'🔧 Cenário Ativo'!$B$29,0) -> 1260 | I6: =ROUND(I5*'🔧 Cenário Ativo'!$B$29,0) -> 1470 | J6: =ROUND(J5*'🔧 Cenário Ativo'!$B$29,0) -> 1680 | ... Q6: =ROUND(Q5*'🔧 Cenário Ativo'!$B$29,0) -> 3255 | R6: =ROUND(Q6*(1-'🔧 Cenário Ativo'!B32)+MAX(0,R5-Q9)*'🔧 Cenário Ativo'!B29,0) -> 6137 | S6: =ROUND(R6*(1-'🔧 Cenário Ativo'!B32)+MAX(0,S5-R9)*'🔧 Cenário Ativo'!B29,0) -> 8827 | T6: =ROUND(S6*(1-'🔧 Cenário Ativo'!B32)+MAX(0,T5-S9)*'🔧 Cenário Ativo'!B29,0) -> 11350 | U6: =ROUND(T6*(1-'🔧 Cenário Ativo'!B32)+MAX(0,U5-T9)*'🔧 Cenário Ativo'!B29,0) -> 13725 | V6: =ROUND(U6*(1-'🔧 Cenário Ativo'!B32)+MAX(0,V5-U9)*'🔧 Cenário Ativo'!B29,0) -> 15971 | W6: =ROUND(V6*(1-'🔧 Cenário Ativo'!B32)+MAX(0,W5-V9)*'🔧 Cenário Ativo'!B29,0) -> 18104 | X6: =ROUND(W6*(1-'🔧 Cenário Ativo'!B32)+MAX(0,X5-W9)*'🔧 Cenário Ativo'!B29,0) -> 20137 | Y6: =ROUND(X6*(1-'🔧 Cenário Ativo'!B32)+MAX(0,Y5-X9)*'🔧 Cenário Ativo'!B29,0) -> 22083 | Z6: =ROUND(Y6*(1-'🔧 Cenário Ativo'!B32)+MAX(0,Z5-Y9)*'🔧 Cenário Ativo'!B29,0) -> 23953
A7: Autônoma · Assinantes | B7: ass. | C7: =ROUND(C5*'🔧 Cenário Ativo'!$B$30,0) -> 90 | D7: =ROUND(D5*'🔧 Cenário Ativo'!$B$30,0) -> 180 | E7: =ROUND(E5*'🔧 Cenário Ativo'!$B$30,0) -> 270 | F7: =ROUND(F5*'🔧 Cenário Ativo'!$B$30,0) -> 360 | G7: =ROUND(G5*'🔧 Cenário Ativo'!$B$30,0) -> 450 | H7: =ROUND(H5*'🔧 Cenário Ativo'!$B$30,0) -> 540 | I7: =ROUND(I5*'🔧 Cenário Ativo'!$B$30,0) -> 630 | J7: =ROUND(J5*'🔧 Cenário Ativo'!$B$30,0) -> 720 | ... Q7: =ROUND(Q5*'🔧 Cenário Ativo'!$B$30,0) -> 1395 | R7: =ROUND(Q7*(1-'🔧 Cenário Ativo'!B33)+MAX(0,R6-Q7-Q8)*'🔧 Cenário Ativo'!B30,0) -> 1454 | S7: =ROUND(R7*(1-'🔧 Cenário Ativo'!B33)+MAX(0,S6-R7-R8)*'🔧 Cenário Ativo'!B30,0) -> 1589 | T7: =ROUND(S7*(1-'🔧 Cenário Ativo'!B33)+MAX(0,T6-S7-S8)*'🔧 Cenário Ativo'!B30,0) -> 1789 | U7: =ROUND(T7*(1-'🔧 Cenário Ativo'!B33)+MAX(0,U6-T7-T8)*'🔧 Cenário Ativo'!B30,0) -> 2044 | V7: =ROUND(U7*(1-'🔧 Cenário Ativo'!B33)+MAX(0,V6-U7-U8)*'🔧 Cenário Ativo'!B30,0) -> 2346 | W7: =ROUND(V7*(1-'🔧 Cenário Ativo'!B33)+MAX(0,W6-V7-V8)*'🔧 Cenário Ativo'!B30,0) -> 2687 | X7: =ROUND(W7*(1-'🔧 Cenário Ativo'!B33)+MAX(0,X6-W7-W8)*'🔧 Cenário Ativo'!B30,0) -> 3062 | Y7: =ROUND(X7*(1-'🔧 Cenário Ativo'!B33)+MAX(0,Y6-X7-X8)*'🔧 Cenário Ativo'!B30,0) -> 3465 | Z7: =ROUND(Y7*(1-'🔧 Cenário Ativo'!B33)+MAX(0,Z6-Y7-Y8)*'🔧 Cenário Ativo'!B30,0) -> 3891
A8: Livre · Assinantes | B8: ass. | C8: =ROUND(C5*'🔧 Cenário Ativo'!$B$31,0) -> 30 | D8: =ROUND(D5*'🔧 Cenário Ativo'!$B$31,0) -> 60 | E8: =ROUND(E5*'🔧 Cenário Ativo'!$B$31,0) -> 90 | F8: =ROUND(F5*'🔧 Cenário Ativo'!$B$31,0) -> 120 | G8: =ROUND(G5*'🔧 Cenário Ativo'!$B$31,0) -> 150 | H8: =ROUND(H5*'🔧 Cenário Ativo'!$B$31,0) -> 180 | I8: =ROUND(I5*'🔧 Cenário Ativo'!$B$31,0) -> 210 | J8: =ROUND(J5*'🔧 Cenário Ativo'!$B$31,0) -> 240 | ... Q8: =ROUND(Q5*'🔧 Cenário Ativo'!$B$31,0) -> 465 | R8: =ROUND(Q8*(1-'🔧 Cenário Ativo'!B34)+MAX(0,R7-Q8)*'🔧 Cenário Ativo'!B31,0) -> 461 | S8: =ROUND(R8*(1-'🔧 Cenário Ativo'!B34)+MAX(0,S7-R8)*'🔧 Cenário Ativo'!B31,0) -> 458 | T8: =ROUND(S8*(1-'🔧 Cenário Ativo'!B34)+MAX(0,T7-S8)*'🔧 Cenário Ativo'!B31,0) -> 458 | U8: =ROUND(T8*(1-'🔧 Cenário Ativo'!B34)+MAX(0,U7-T8)*'🔧 Cenário Ativo'!B31,0) -> 460 | V8: =ROUND(U8*(1-'🔧 Cenário Ativo'!B34)+MAX(0,V7-U8)*'🔧 Cenário Ativo'!B31,0) -> 465 | W8: =ROUND(V8*(1-'🔧 Cenário Ativo'!B34)+MAX(0,W7-V8)*'🔧 Cenário Ativo'!B31,0) -> 473 | X8: =ROUND(W8*(1-'🔧 Cenário Ativo'!B34)+MAX(0,X7-W8)*'🔧 Cenário Ativo'!B31,0) -> 485 | Y8: =ROUND(X8*(1-'🔧 Cenário Ativo'!B34)+MAX(0,Y7-X8)*'🔧 Cenário Ativo'!B31,0) -> 500 | Z8: =ROUND(Y8*(1-'🔧 Cenário Ativo'!B34)+MAX(0,Z7-Y8)*'🔧 Cenário Ativo'!B31,0) -> 519
A9: TOTAL PAGANTES | B9: ass. | C9: =SUM(C6:C8) -> 330 | D9: =SUM(D6:D8) -> 660 | E9: =SUM(E6:E8) -> 990 | F9: =SUM(F6:F8) -> 1320 | G9: =SUM(G6:G8) -> 1650 | H9: =SUM(H6:H8) -> 1980 | I9: =SUM(I6:I8) -> 2310 | J9: =SUM(J6:J8) -> 2640 | ... Z9: =SUM(Z6:Z8) -> 28363
A10: RECEITA
A11: MRR MENSAL | B11: R$ | C11: =C6*'🔧 Cenário Ativo'!B6+C7*'🔧 Cenário Ativo'!B7+C8*'🔧 Cenário Ativo'!B8 -> 16167 | D11: =D6*'🔧 Cenário Ativo'!B6+D7*'🔧 Cenário Ativo'!B7+D8*'🔧 Cenário Ativo'!B8 -> 32334 | E11: =E6*'🔧 Cenário Ativo'!B6+E7*'🔧 Cenário Ativo'!B7+E8*'🔧 Cenário Ativo'!B8 -> 48501 | F11: =F6*'🔧 Cenário Ativo'!B6+F7*'🔧 Cenário Ativo'!B7+F8*'🔧 Cenário Ativo'!B8 -> 64668 | G11: =G6*'🔧 Cenário Ativo'!B6+G7*'🔧 Cenário Ativo'!B7+G8*'🔧 Cenário Ativo'!B8 -> 80835 | H11: =H6*'🔧 Cenário Ativo'!B6+H7*'🔧 Cenário Ativo'!B7+H8*'🔧 Cenário Ativo'!B8 -> 97002 | I11: =I6*'🔧 Cenário Ativo'!B6+I7*'🔧 Cenário Ativo'!B7+I8*'🔧 Cenário Ativo'!B8 -> 113169 | J11: =J6*'🔧 Cenário Ativo'!B6+J7*'🔧 Cenário Ativo'!B7+J8*'🔧 Cenário Ativo'!B8 -> 129336 | K11: =K6*'🔧 Cenário Ativo'!B6+K7*'🔧 Cenário Ativo'!B7+K8*'🔧 Cenário Ativo'!B8 -> 145503 | L11: =L6*'🔧 Cenário Ativo'!B6+L7*'🔧 Cenário Ativo'!B7+L8*'🔧 Cenário Ativo'!B8 -> 161670 | M11: =M6*'🔧 Cenário Ativo'!B6+M7*'🔧 Cenário Ativo'!B7+M8*'🔧 Cenário Ativo'!B8 -> 177837 | N11: =N6*'🔧 Cenário Ativo'!B6+N7*'🔧 Cenário Ativo'!B7+N8*'🔧 Cenário Ativo'!B8 -> 194004 | O11: =O6*'🔧 Cenário Ativo'!B6+O7*'🔧 Cenário Ativo'!B7+O8*'🔧 Cenário Ativo'!B8 -> 212865.5 | P11: =P6*'🔧 Cenário Ativo'!B6+P7*'🔧 Cenário Ativo'!B7+P8*'🔧 Cenário Ativo'!B8 -> 231727 | Q11: =Q6*'🔧 Cenário Ativo'!B6+Q7*'🔧 Cenário Ativo'!B7+Q8*'🔧 Cenário Ativo'!B8 -> 250588.5 | R11: =R6*'🔧 Cenário Ativo'!B6+R7*'🔧 Cenário Ativo'!B7+R8*'🔧 Cenário Ativo'!B8 -> 368794.8 | S11: =S6*'🔧 Cenário Ativo'!B6+S7*'🔧 Cenário Ativo'!B7+S8*'🔧 Cenário Ativo'!B8 -> 483972.6 | T11: =T6*'🔧 Cenário Ativo'!B6+T7*'🔧 Cenário Ativo'!B7+T8*'🔧 Cenário Ativo'!B8 -> 596620.3 | U11: =U6*'🔧 Cenário Ativo'!B6+U7*'🔧 Cenário Ativo'!B7+U8*'🔧 Cenário Ativo'!B8 -> 706817.1 | V11: =V6*'🔧 Cenário Ativo'!B6+V7*'🔧 Cenário Ativo'!B7+V8*'🔧 Cenário Ativo'!B8 -> 814921.8 | W11: =W6*'🔧 Cenário Ativo'!B6+W7*'🔧 Cenário Ativo'!B7+W8*'🔧 Cenário Ativo'!B8 -> 921093.6 | X11: =X6*'🔧 Cenário Ativo'!B6+X7*'🔧 Cenário Ativo'!B7+X8*'🔧 Cenário Ativo'!B8 -> 1025631.6 | Y11: =Y6*'🔧 Cenário Ativo'!B6+Y7*'🔧 Cenário Ativo'!B7+Y8*'🔧 Cenário Ativo'!B8 -> 1128615.2 | Z11: =Z6*'🔧 Cenário Ativo'!B6+Z7*'🔧 Cenário Ativo'!B7+Z8*'🔧 Cenário Ativo'!B8 -> 1230263.7
A12: MRR ACUMULADO | B12: R$ | C12: =C11 -> 16167 | D12: =C12+D11 -> 48501 | E12: =D12+E11 -> 97002 | F12: =E12+F11 -> 161670 | G12: =F12+G11 -> 242505 | H12: =G12+H11 -> 339507 | I12: =H12+I11 -> 452676 | J12: =I12+J11 -> 582012 | K12: =J12+K11 -> 727515 | ... Z12: =Y12+Z11 -> 9232937.7
A13: CUSTO API · 100% Sonnet 4.6 · Caching ativo
A14: API Free (Sonnet · 40 int/mês) | B14: R$ | C14: =C5*'🔧 Cenário Ativo'!$B$18*('🔧 Cenário Ativo'!$B$15*('🔧 Cenário Ativo'!$B$16/1000000*'🎛️ Premissas'!$G$9+'🔧 Cenário Ativo'!$B$17/1000000*'🎛️ Premissas'!$G$10)*(1-'🔧 Cenário Ativo'!$B$13)*'🔧 Cenário Ativo'!$B$10) -> 813.88125 | D14: =D5*'🔧 Cenário Ativo'!$B$18*('🔧 Cenário Ativo'!$B$15*('🔧 Cenário Ativo'!$B$16/1000000*'🎛️ Premissas'!$G$9+'🔧 Cenário Ativo'!$B$17/1000000*'🎛️ Premissas'!$G$10)*(1-'🔧 Cenário Ativo'!$B$13)*'🔧 Cenário Ativo'!$B$10) -> 1627.7625 | E14: =E5*'🔧 Cenário Ativo'!$B$18*('🔧 Cenário Ativo'!$B$15*('🔧 Cenário Ativo'!$B$16/1000000*'🎛️ Premissas'!$G$9+'🔧 Cenário Ativo'!$B$17/1000000*'🎛️ Premissas'!$G$10)*(1-'🔧 Cenário Ativo'!$B$13)*'🔧 Cenário Ativo'!$B$10) -> 2441.6438 | F14: =F5*'🔧 Cenário Ativo'!$B$18*('🔧 Cenário Ativo'!$B$15*('🔧 Cenário Ativo'!$B$16/1000000*'🎛️ Premissas'!$G$9+'🔧 Cenário Ativo'!$B$17/1000000*'🎛️ Premissas'!$G$10)*(1-'🔧 Cenário Ativo'!$B$13)*'🔧 Cenário Ativo'!$B$10) -> 3255.525 | G14: =G5*'🔧 Cenário Ativo'!$B$18*('🔧 Cenário Ativo'!$B$15*('🔧 Cenário Ativo'!$B$16/1000000*'🎛️ Premissas'!$G$9+'🔧 Cenário Ativo'!$B$17/1000000*'🎛️ Premissas'!$G$10)*(1-'🔧 Cenário Ativo'!$B$13)*'🔧 Cenário Ativo'!$B$10) -> 4069.4062 | H14: =H5*'🔧 Cenário Ativo'!$B$18*('🔧 Cenário Ativo'!$B$15*('🔧 Cenário Ativo'!$B$16/1000000*'🎛️ Premissas'!$G$9+'🔧 Cenário Ativo'!$B$17/1000000*'🎛️ Premissas'!$G$10)*(1-'🔧 Cenário Ativo'!$B$13)*'🔧 Cenário Ativo'!$B$10) -> 4883.2875 | I14: =I5*'🔧 Cenário Ativo'!$B$18*('🔧 Cenário Ativo'!$B$15*('🔧 Cenário Ativo'!$B$16/1000000*'🎛️ Premissas'!$G$9+'🔧 Cenário Ativo'!$B$17/1000000*'🎛️ Premissas'!$G$10)*(1-'🔧 Cenário Ativo'!$B$13)*'🔧 Cenário Ativo'!$B$10) -> 5697.1687 | J14: =J5*'🔧 Cenário Ativo'!$B$18*('🔧 Cenário Ativo'!$B$15*('🔧 Cenário Ativo'!$B$16/1000000*'🎛️ Premissas'!$G$9+'🔧 Cenário Ativo'!$B$17/1000000*'🎛️ Premissas'!$G$10)*(1-'🔧 Cenário Ativo'!$B$13)*'🔧 Cenário Ativo'!$B$10) -> 6511.05 | ... Z14: =Z5*'🔧 Cenário Ativo'!$B$18*('🔧 Cenário Ativo'!$B$15*('🔧 Cenário Ativo'!$B$16/1000000*'🎛️ Premissas'!$G$9+'🔧 Cenário Ativo'!$B$17/1000000*'🎛️ Premissas'!$G$10)*(1-'🔧 Cenário Ativo'!$B$13)*'🔧 Cenário Ativo'!$B$10) -> 21160.912
A15: API Essencial (chat ilimitado) | B15: R$ | C15: =C6*'🔧 Cenário Ativo'!B19*('🔧 Cenário Ativo'!B20/1000000*'🔧 Cenário Ativo'!B11+'🔧 Cenário Ativo'!B21/1000000*'🔧 Cenário Ativo'!B12)*(1-'🔧 Cenário Ativo'!B13)*'🔧 Cenário Ativo'!B10 -> 1224.0774 | D15: =D6*'🔧 Cenário Ativo'!B19*('🔧 Cenário Ativo'!B20/1000000*'🔧 Cenário Ativo'!B11+'🔧 Cenário Ativo'!B21/1000000*'🔧 Cenário Ativo'!B12)*(1-'🔧 Cenário Ativo'!B13)*'🔧 Cenário Ativo'!B10 -> 2448.1548 | E15: =E6*'🔧 Cenário Ativo'!B19*('🔧 Cenário Ativo'!B20/1000000*'🔧 Cenário Ativo'!B11+'🔧 Cenário Ativo'!B21/1000000*'🔧 Cenário Ativo'!B12)*(1-'🔧 Cenário Ativo'!B13)*'🔧 Cenário Ativo'!B10 -> 3672.2322 | F15: =F6*'🔧 Cenário Ativo'!B19*('🔧 Cenário Ativo'!B20/1000000*'🔧 Cenário Ativo'!B11+'🔧 Cenário Ativo'!B21/1000000*'🔧 Cenário Ativo'!B12)*(1-'🔧 Cenário Ativo'!B13)*'🔧 Cenário Ativo'!B10 -> 4896.3096 | G15: =G6*'🔧 Cenário Ativo'!B19*('🔧 Cenário Ativo'!B20/1000000*'🔧 Cenário Ativo'!B11+'🔧 Cenário Ativo'!B21/1000000*'🔧 Cenário Ativo'!B12)*(1-'🔧 Cenário Ativo'!B13)*'🔧 Cenário Ativo'!B10 -> 6120.387 | H15: =H6*'🔧 Cenário Ativo'!B19*('🔧 Cenário Ativo'!B20/1000000*'🔧 Cenário Ativo'!B11+'🔧 Cenário Ativo'!B21/1000000*'🔧 Cenário Ativo'!B12)*(1-'🔧 Cenário Ativo'!B13)*'🔧 Cenário Ativo'!B10 -> 7344.4644 | I15: =I6*'🔧 Cenário Ativo'!B19*('🔧 Cenário Ativo'!B20/1000000*'🔧 Cenário Ativo'!B11+'🔧 Cenário Ativo'!B21/1000000*'🔧 Cenário Ativo'!B12)*(1-'🔧 Cenário Ativo'!B13)*'🔧 Cenário Ativo'!B10 -> 8568.5418 | J15: =J6*'🔧 Cenário Ativo'!B19*('🔧 Cenário Ativo'!B20/1000000*'🔧 Cenário Ativo'!B11+'🔧 Cenário Ativo'!B21/1000000*'🔧 Cenário Ativo'!B12)*(1-'🔧 Cenário Ativo'!B13)*'🔧 Cenário Ativo'!B10 -> 9792.6192 | K15: =K6*'🔧 Cenário Ativo'!B19*('🔧 Cenário Ativo'!B20/1000000*'🔧 Cenário Ativo'!B11+'🔧 Cenário Ativo'!B21/1000000*'🔧 Cenário Ativo'!B12)*(1-'🔧 Cenário Ativo'!B13)*'🔧 Cenário Ativo'!B10 -> 11016.697 | L15: =L6*'🔧 Cenário Ativo'!B19*('🔧 Cenário Ativo'!B20/1000000*'🔧 Cenário Ativo'!B11+'🔧 Cenário Ativo'!B21/1000000*'🔧 Cenário Ativo'!B12)*(1-'🔧 Cenário Ativo'!B13)*'🔧 Cenário Ativo'!B10 -> 12240.774 | M15: =M6*'🔧 Cenário Ativo'!B19*('🔧 Cenário Ativo'!B20/1000000*'🔧 Cenário Ativo'!B11+'🔧 Cenário Ativo'!B21/1000000*'🔧 Cenário Ativo'!B12)*(1-'🔧 Cenário Ativo'!B13)*'🔧 Cenário Ativo'!B10 -> 13464.851 | N15: =N6*'🔧 Cenário Ativo'!B19*('🔧 Cenário Ativo'!B20/1000000*'🔧 Cenário Ativo'!B11+'🔧 Cenário Ativo'!B21/1000000*'🔧 Cenário Ativo'!B12)*(1-'🔧 Cenário Ativo'!B13)*'🔧 Cenário Ativo'!B10 -> 14688.929 | O15: =O6*'🔧 Cenário Ativo'!B19*('🔧 Cenário Ativo'!B20/1000000*'🔧 Cenário Ativo'!B11+'🔧 Cenário Ativo'!B21/1000000*'🔧 Cenário Ativo'!B12)*(1-'🔧 Cenário Ativo'!B13)*'🔧 Cenário Ativo'!B10 -> 16117.019 | P15: =P6*'🔧 Cenário Ativo'!B19*('🔧 Cenário Ativo'!B20/1000000*'🔧 Cenário Ativo'!B11+'🔧 Cenário Ativo'!B21/1000000*'🔧 Cenário Ativo'!B12)*(1-'🔧 Cenário Ativo'!B13)*'🔧 Cenário Ativo'!B10 -> 17545.109 | Q15: =Q6*'🔧 Cenário Ativo'!B19*('🔧 Cenário Ativo'!B20/1000000*'🔧 Cenário Ativo'!B11+'🔧 Cenário Ativo'!B21/1000000*'🔧 Cenário Ativo'!B12)*(1-'🔧 Cenário Ativo'!B13)*'🔧 Cenário Ativo'!B10 -> 18973.2 | R15: =R6*'🔧 Cenário Ativo'!B19*('🔧 Cenário Ativo'!B20/1000000*'🔧 Cenário Ativo'!B11+'🔧 Cenário Ativo'!B21/1000000*'🔧 Cenário Ativo'!B12)*(1-'🔧 Cenário Ativo'!B13)*'🔧 Cenário Ativo'!B10 -> 35772.205 | S15: =S6*'🔧 Cenário Ativo'!B19*('🔧 Cenário Ativo'!B20/1000000*'🔧 Cenário Ativo'!B11+'🔧 Cenário Ativo'!B21/1000000*'🔧 Cenário Ativo'!B12)*(1-'🔧 Cenário Ativo'!B13)*'🔧 Cenário Ativo'!B10 -> 51452.053 | T15: =T6*'🔧 Cenário Ativo'!B19*('🔧 Cenário Ativo'!B20/1000000*'🔧 Cenário Ativo'!B11+'🔧 Cenário Ativo'!B21/1000000*'🔧 Cenário Ativo'!B12)*(1-'🔧 Cenário Ativo'!B13)*'🔧 Cenário Ativo'!B10 -> 66158.469 | U15: =U6*'🔧 Cenário Ativo'!B19*('🔧 Cenário Ativo'!B20/1000000*'🔧 Cenário Ativo'!B11+'🔧 Cenário Ativo'!B21/1000000*'🔧 Cenário Ativo'!B12)*(1-'🔧 Cenário Ativo'!B13)*'🔧 Cenário Ativo'!B10 -> 80002.201 | V15: =V6*'🔧 Cenário Ativo'!B19*('🔧 Cenário Ativo'!B20/1000000*'🔧 Cenário Ativo'!B11+'🔧 Cenário Ativo'!B21/1000000*'🔧 Cenário Ativo'!B12)*(1-'🔧 Cenário Ativo'!B13)*'🔧 Cenário Ativo'!B10 -> 93094.001 | W15: =W6*'🔧 Cenário Ativo'!B19*('🔧 Cenário Ativo'!B20/1000000*'🔧 Cenário Ativo'!B11+'🔧 Cenário Ativo'!B21/1000000*'🔧 Cenário Ativo'!B12)*(1-'🔧 Cenário Ativo'!B13)*'🔧 Cenário Ativo'!B10 -> 105527.13 | X15: =X6*'🔧 Cenário Ativo'!B19*('🔧 Cenário Ativo'!B20/1000000*'🔧 Cenário Ativo'!B11+'🔧 Cenário Ativo'!B21/1000000*'🔧 Cenário Ativo'!B12)*(1-'🔧 Cenário Ativo'!B13)*'🔧 Cenário Ativo'!B10 -> 117377.36 | Y15: =Y6*'🔧 Cenário Ativo'!B19*('🔧 Cenário Ativo'!B20/1000000*'🔧 Cenário Ativo'!B11+'🔧 Cenário Ativo'!B21/1000000*'🔧 Cenário Ativo'!B12)*(1-'🔧 Cenário Ativo'!B13)*'🔧 Cenário Ativo'!B10 -> 128720.48 | Z15: =Z6*'🔧 Cenário Ativo'!B19*('🔧 Cenário Ativo'!B20/1000000*'🔧 Cenário Ativo'!B11+'🔧 Cenário Ativo'!B21/1000000*'🔧 Cenário Ativo'!B12)*(1-'🔧 Cenário Ativo'!B13)*'🔧 Cenário Ativo'!B10 -> 139620.6
A16: API Autônoma (+1 agente) | B16: R$ | C16: =C7*('🔧 Cenário Ativo'!B19*('🔧 Cenário Ativo'!B20/1000000*'🔧 Cenário Ativo'!B11+'🔧 Cenário Ativo'!B21/1000000*'🔧 Cenário Ativo'!B12)*(1-'🔧 Cenário Ativo'!B13)*'🔧 Cenário Ativo'!B10+'🔧 Cenário Ativo'!B22*('🔧 Cenário Ativo'!B23/1000000*'🔧 Cenário Ativo'!B11+'🔧 Cenário Ativo'!B24/1000000*'🔧 Cenário Ativo'!B12)*(1-'🔧 Cenário Ativo'!B13)*'🔧 Cenário Ativo'!B10) -> 915.2676 | D16: =D7*('🔧 Cenário Ativo'!B19*('🔧 Cenário Ativo'!B20/1000000*'🔧 Cenário Ativo'!B11+'🔧 Cenário Ativo'!B21/1000000*'🔧 Cenário Ativo'!B12)*(1-'🔧 Cenário Ativo'!B13)*'🔧 Cenário Ativo'!B10+'🔧 Cenário Ativo'!B22*('🔧 Cenário Ativo'!B23/1000000*'🔧 Cenário Ativo'!B11+'🔧 Cenário Ativo'!B24/1000000*'🔧 Cenário Ativo'!B12)*(1-'🔧 Cenário Ativo'!B13)*'🔧 Cenário Ativo'!B10) -> 1830.5352 | E16: =E7*('🔧 Cenário Ativo'!B19*('🔧 Cenário Ativo'!B20/1000000*'🔧 Cenário Ativo'!B11+'🔧 Cenário Ativo'!B21/1000000*'🔧 Cenário Ativo'!B12)*(1-'🔧 Cenário Ativo'!B13)*'🔧 Cenário Ativo'!B10+'🔧 Cenário Ativo'!B22*('🔧 Cenário Ativo'!B23/1000000*'🔧 Cenário Ativo'!B11+'🔧 Cenário Ativo'!B24/1000000*'🔧 Cenário Ativo'!B12)*(1-'🔧 Cenário Ativo'!B13)*'🔧 Cenário Ativo'!B10) -> 2745.8028 | F16: =F7*('🔧 Cenário Ativo'!B19*('🔧 Cenário Ativo'!B20/1000000*'🔧 Cenário Ativo'!B11+'🔧 Cenário Ativo'!B21/1000000*'🔧 Cenário Ativo'!B12)*(1-'🔧 Cenário Ativo'!B13)*'🔧 Cenário Ativo'!B10+'🔧 Cenário Ativo'!B22*('🔧 Cenário Ativo'!B23/1000000*'🔧 Cenário Ativo'!B11+'🔧 Cenário Ativo'!B24/1000000*'🔧 Cenário Ativo'!B12)*(1-'🔧 Cenário Ativo'!B13)*'🔧 Cenário Ativo'!B10) -> 3661.0704 | G16: =G7*('🔧 Cenário Ativo'!B19*('🔧 Cenário Ativo'!B20/1000000*'🔧 Cenário Ativo'!B11+'🔧 Cenário Ativo'!B21/1000000*'🔧 Cenário Ativo'!B12)*(1-'🔧 Cenário Ativo'!B13)*'🔧 Cenário Ativo'!B10+'🔧 Cenário Ativo'!B22*('🔧 Cenário Ativo'!B23/1000000*'🔧 Cenário Ativo'!B11+'🔧 Cenário Ativo'!B24/1000000*'🔧 Cenário Ativo'!B12)*(1-'🔧 Cenário Ativo'!B13)*'🔧 Cenário Ativo'!B10) -> 4576.338 | H16: =H7*('🔧 Cenário Ativo'!B19*('🔧 Cenário Ativo'!B20/1000000*'🔧 Cenário Ativo'!B11+'🔧 Cenário Ativo'!B21/1000000*'🔧 Cenário Ativo'!B12)*(1-'🔧 Cenário Ativo'!B13)*'🔧 Cenário Ativo'!B10+'🔧 Cenário Ativo'!B22*('🔧 Cenário Ativo'!B23/1000000*'🔧 Cenário Ativo'!B11+'🔧 Cenário Ativo'!B24/1000000*'🔧 Cenário Ativo'!B12)*(1-'🔧 Cenário Ativo'!B13)*'🔧 Cenário Ativo'!B10) -> 5491.6056 | I16: =I7*('🔧 Cenário Ativo'!B19*('🔧 Cenário Ativo'!B20/1000000*'🔧 Cenário Ativo'!B11+'🔧 Cenário Ativo'!B21/1000000*'🔧 Cenário Ativo'!B12)*(1-'🔧 Cenário Ativo'!B13)*'🔧 Cenário Ativo'!B10+'🔧 Cenário Ativo'!B22*('🔧 Cenário Ativo'!B23/1000000*'🔧 Cenário Ativo'!B11+'🔧 Cenário Ativo'!B24/1000000*'🔧 Cenário Ativo'!B12)*(1-'🔧 Cenário Ativo'!B13)*'🔧 Cenário Ativo'!B10) -> 6406.8732 | J16: =J7*('🔧 Cenário Ativo'!B19*('🔧 Cenário Ativo'!B20/1000000*'🔧 Cenário Ativo'!B11+'🔧 Cenário Ativo'!B21/1000000*'🔧 Cenário Ativo'!B12)*(1-'🔧 Cenário Ativo'!B13)*'🔧 Cenário Ativo'!B10+'🔧 Cenário Ativo'!B22*('🔧 Cenário Ativo'!B23/1000000*'🔧 Cenário Ativo'!B11+'🔧 Cenário Ativo'!B24/1000000*'🔧 Cenário Ativo'!B12)*(1-'🔧 Cenário Ativo'!B13)*'🔧 Cenário Ativo'!B10) -> 7322.1408 | K16: =K7*('🔧 Cenário Ativo'!B19*('🔧 Cenário Ativo'!B20/1000000*'🔧 Cenário Ativo'!B11+'🔧 Cenário Ativo'!B21/1000000*'🔧 Cenário Ativo'!B12)*(1-'🔧 Cenário Ativo'!B13)*'🔧 Cenário Ativo'!B10+'🔧 Cenário Ativo'!B22*('🔧 Cenário Ativo'!B23/1000000*'🔧 Cenário Ativo'!B11+'🔧 Cenário Ativo'!B24/1000000*'🔧 Cenário Ativo'!B12)*(1-'🔧 Cenário Ativo'!B13)*'🔧 Cenário Ativo'!B10) -> 8237.4084 | L16: =L7*('🔧 Cenário Ativo'!B19*('🔧 Cenário Ativo'!B20/1000000*'🔧 Cenário Ativo'!B11+'🔧 Cenário Ativo'!B21/1000000*'🔧 Cenário Ativo'!B12)*(1-'🔧 Cenário Ativo'!B13)*'🔧 Cenário Ativo'!B10+'🔧 Cenário Ativo'!B22*('🔧 Cenário Ativo'!B23/1000000*'🔧 Cenário Ativo'!B11+'🔧 Cenário Ativo'!B24/1000000*'🔧 Cenário Ativo'!B12)*(1-'🔧 Cenário Ativo'!B13)*'🔧 Cenário Ativo'!B10) -> 9152.676 | M16: =M7*('🔧 Cenário Ativo'!B19*('🔧 Cenário Ativo'!B20/1000000*'🔧 Cenário Ativo'!B11+'🔧 Cenário Ativo'!B21/1000000*'🔧 Cenário Ativo'!B12)*(1-'🔧 Cenário Ativo'!B13)*'🔧 Cenário Ativo'!B10+'🔧 Cenário Ativo'!B22*('🔧 Cenário Ativo'!B23/1000000*'🔧 Cenário Ativo'!B11+'🔧 Cenário Ativo'!B24/1000000*'🔧 Cenário Ativo'!B12)*(1-'🔧 Cenário Ativo'!B13)*'🔧 Cenário Ativo'!B10) -> 10067.944 | N16: =N7*('🔧 Cenário Ativo'!B19*('🔧 Cenário Ativo'!B20/1000000*'🔧 Cenário Ativo'!B11+'🔧 Cenário Ativo'!B21/1000000*'🔧 Cenário Ativo'!B12)*(1-'🔧 Cenário Ativo'!B13)*'🔧 Cenário Ativo'!B10+'🔧 Cenário Ativo'!B22*('🔧 Cenário Ativo'!B23/1000000*'🔧 Cenário Ativo'!B11+'🔧 Cenário Ativo'!B24/1000000*'🔧 Cenário Ativo'!B12)*(1-'🔧 Cenário Ativo'!B13)*'🔧 Cenário Ativo'!B10) -> 10983.211 | O16: =O7*('🔧 Cenário Ativo'!B19*('🔧 Cenário Ativo'!B20/1000000*'🔧 Cenário Ativo'!B11+'🔧 Cenário Ativo'!B21/1000000*'🔧 Cenário Ativo'!B12)*(1-'🔧 Cenário Ativo'!B13)*'🔧 Cenário Ativo'!B10+'🔧 Cenário Ativo'!B22*('🔧 Cenário Ativo'!B23/1000000*'🔧 Cenário Ativo'!B11+'🔧 Cenário Ativo'!B24/1000000*'🔧 Cenário Ativo'!B12)*(1-'🔧 Cenário Ativo'!B13)*'🔧 Cenário Ativo'!B10) -> 12051.023 | P16: =P7*('🔧 Cenário Ativo'!B19*('🔧 Cenário Ativo'!B20/1000000*'🔧 Cenário Ativo'!B11+'🔧 Cenário Ativo'!B21/1000000*'🔧 Cenário Ativo'!B12)*(1-'🔧 Cenário Ativo'!B13)*'🔧 Cenário Ativo'!B10+'🔧 Cenário Ativo'!B22*('🔧 Cenário Ativo'!B23/1000000*'🔧 Cenário Ativo'!B11+'🔧 Cenário Ativo'!B24/1000000*'🔧 Cenário Ativo'!B12)*(1-'🔧 Cenário Ativo'!B13)*'🔧 Cenário Ativo'!B10) -> 13118.836 | Q16: =Q7*('🔧 Cenário Ativo'!B19*('🔧 Cenário Ativo'!B20/1000000*'🔧 Cenário Ativo'!B11+'🔧 Cenário Ativo'!B21/1000000*'🔧 Cenário Ativo'!B12)*(1-'🔧 Cenário Ativo'!B13)*'🔧 Cenário Ativo'!B10+'🔧 Cenário Ativo'!B22*('🔧 Cenário Ativo'!B23/1000000*'🔧 Cenário Ativo'!B11+'🔧 Cenário Ativo'!B24/1000000*'🔧 Cenário Ativo'!B12)*(1-'🔧 Cenário Ativo'!B13)*'🔧 Cenário Ativo'!B10) -> 14186.648 | R16: =R7*('🔧 Cenário Ativo'!B19*('🔧 Cenário Ativo'!B20/1000000*'🔧 Cenário Ativo'!B11+'🔧 Cenário Ativo'!B21/1000000*'🔧 Cenário Ativo'!B12)*(1-'🔧 Cenário Ativo'!B13)*'🔧 Cenário Ativo'!B10+'🔧 Cenário Ativo'!B22*('🔧 Cenário Ativo'!B23/1000000*'🔧 Cenário Ativo'!B11+'🔧 Cenário Ativo'!B24/1000000*'🔧 Cenário Ativo'!B12)*(1-'🔧 Cenário Ativo'!B13)*'🔧 Cenário Ativo'!B10) -> 14786.657 | S16: =S7*('🔧 Cenário Ativo'!B19*('🔧 Cenário Ativo'!B20/1000000*'🔧 Cenário Ativo'!B11+'🔧 Cenário Ativo'!B21/1000000*'🔧 Cenário Ativo'!B12)*(1-'🔧 Cenário Ativo'!B13)*'🔧 Cenário Ativo'!B10+'🔧 Cenário Ativo'!B22*('🔧 Cenário Ativo'!B23/1000000*'🔧 Cenário Ativo'!B11+'🔧 Cenário Ativo'!B24/1000000*'🔧 Cenário Ativo'!B12)*(1-'🔧 Cenário Ativo'!B13)*'🔧 Cenário Ativo'!B10) -> 16159.558 | T16: =T7*('🔧 Cenário Ativo'!B19*('🔧 Cenário Ativo'!B20/1000000*'🔧 Cenário Ativo'!B11+'🔧 Cenário Ativo'!B21/1000000*'🔧 Cenário Ativo'!B12)*(1-'🔧 Cenário Ativo'!B13)*'🔧 Cenário Ativo'!B10+'🔧 Cenário Ativo'!B22*('🔧 Cenário Ativo'!B23/1000000*'🔧 Cenário Ativo'!B11+'🔧 Cenário Ativo'!B24/1000000*'🔧 Cenário Ativo'!B12)*(1-'🔧 Cenário Ativo'!B13)*'🔧 Cenário Ativo'!B10) -> 18193.486 | U16: =U7*('🔧 Cenário Ativo'!B19*('🔧 Cenário Ativo'!B20/1000000*'🔧 Cenário Ativo'!B11+'🔧 Cenário Ativo'!B21/1000000*'🔧 Cenário Ativo'!B12)*(1-'🔧 Cenário Ativo'!B13)*'🔧 Cenário Ativo'!B10+'🔧 Cenário Ativo'!B22*('🔧 Cenário Ativo'!B23/1000000*'🔧 Cenário Ativo'!B11+'🔧 Cenário Ativo'!B24/1000000*'🔧 Cenário Ativo'!B12)*(1-'🔧 Cenário Ativo'!B13)*'🔧 Cenário Ativo'!B10) -> 20786.744 | V16: =V7*('🔧 Cenário Ativo'!B19*('🔧 Cenário Ativo'!B20/1000000*'🔧 Cenário Ativo'!B11+'🔧 Cenário Ativo'!B21/1000000*'🔧 Cenário Ativo'!B12)*(1-'🔧 Cenário Ativo'!B13)*'🔧 Cenário Ativo'!B10+'🔧 Cenário Ativo'!B22*('🔧 Cenário Ativo'!B23/1000000*'🔧 Cenário Ativo'!B11+'🔧 Cenário Ativo'!B24/1000000*'🔧 Cenário Ativo'!B12)*(1-'🔧 Cenário Ativo'!B13)*'🔧 Cenário Ativo'!B10) -> 23857.975 | W16: =W7*('🔧 Cenário Ativo'!B19*('🔧 Cenário Ativo'!B20/1000000*'🔧 Cenário Ativo'!B11+'🔧 Cenário Ativo'!B21/1000000*'🔧 Cenário Ativo'!B12)*(1-'🔧 Cenário Ativo'!B13)*'🔧 Cenário Ativo'!B10+'🔧 Cenário Ativo'!B22*('🔧 Cenário Ativo'!B23/1000000*'🔧 Cenário Ativo'!B11+'🔧 Cenário Ativo'!B24/1000000*'🔧 Cenário Ativo'!B12)*(1-'🔧 Cenário Ativo'!B13)*'🔧 Cenário Ativo'!B10) -> 27325.823 | X16: =X7*('🔧 Cenário Ativo'!B19*('🔧 Cenário Ativo'!B20/1000000*'🔧 Cenário Ativo'!B11+'🔧 Cenário Ativo'!B21/1000000*'🔧 Cenário Ativo'!B12)*(1-'🔧 Cenário Ativo'!B13)*'🔧 Cenário Ativo'!B10+'🔧 Cenário Ativo'!B22*('🔧 Cenário Ativo'!B23/1000000*'🔧 Cenário Ativo'!B11+'🔧 Cenário Ativo'!B24/1000000*'🔧 Cenário Ativo'!B12)*(1-'🔧 Cenário Ativo'!B13)*'🔧 Cenário Ativo'!B10) -> 31139.438 | Y16: =Y7*('🔧 Cenário Ativo'!B19*('🔧 Cenário Ativo'!B20/1000000*'🔧 Cenário Ativo'!B11+'🔧 Cenário Ativo'!B21/1000000*'🔧 Cenário Ativo'!B12)*(1-'🔧 Cenário Ativo'!B13)*'🔧 Cenário Ativo'!B10+'🔧 Cenário Ativo'!B22*('🔧 Cenário Ativo'!B23/1000000*'🔧 Cenário Ativo'!B11+'🔧 Cenário Ativo'!B24/1000000*'🔧 Cenário Ativo'!B12)*(1-'🔧 Cenário Ativo'!B13)*'🔧 Cenário Ativo'!B10) -> 35237.803 | Z16: =Z7*('🔧 Cenário Ativo'!B19*('🔧 Cenário Ativo'!B20/1000000*'🔧 Cenário Ativo'!B11+'🔧 Cenário Ativo'!B21/1000000*'🔧 Cenário Ativo'!B12)*(1-'🔧 Cenário Ativo'!B13)*'🔧 Cenário Ativo'!B10+'🔧 Cenário Ativo'!B22*('🔧 Cenário Ativo'!B23/1000000*'🔧 Cenário Ativo'!B11+'🔧 Cenário Ativo'!B24/1000000*'🔧 Cenário Ativo'!B12)*(1-'🔧 Cenário Ativo'!B13)*'🔧 Cenário Ativo'!B10) -> 39570.069
A17: API Livre (+2 agentes) | B17: R$ | C17: =C8*('🔧 Cenário Ativo'!B19*('🔧 Cenário Ativo'!B20/1000000*'🔧 Cenário Ativo'!B11+'🔧 Cenário Ativo'!B21/1000000*'🔧 Cenário Ativo'!B12)*(1-'🔧 Cenário Ativo'!B13)*'🔧 Cenário Ativo'!B10+'🔧 Cenário Ativo'!B25*('🔧 Cenário Ativo'!B23/1000000*'🔧 Cenário Ativo'!B11+'🔧 Cenário Ativo'!B24/1000000*'🔧 Cenário Ativo'!B12)*(1-'🔧 Cenário Ativo'!B13)*'🔧 Cenário Ativo'!B10) -> 398.1042 | D17: =D8*('🔧 Cenário Ativo'!B19*('🔧 Cenário Ativo'!B20/1000000*'🔧 Cenário Ativo'!B11+'🔧 Cenário Ativo'!B21/1000000*'🔧 Cenário Ativo'!B12)*(1-'🔧 Cenário Ativo'!B13)*'🔧 Cenário Ativo'!B10+'🔧 Cenário Ativo'!B25*('🔧 Cenário Ativo'!B23/1000000*'🔧 Cenário Ativo'!B11+'🔧 Cenário Ativo'!B24/1000000*'🔧 Cenário Ativo'!B12)*(1-'🔧 Cenário Ativo'!B13)*'🔧 Cenário Ativo'!B10) -> 796.2084 | E17: =E8*('🔧 Cenário Ativo'!B19*('🔧 Cenário Ativo'!B20/1000000*'🔧 Cenário Ativo'!B11+'🔧 Cenário Ativo'!B21/1000000*'🔧 Cenário Ativo'!B12)*(1-'🔧 Cenário Ativo'!B13)*'🔧 Cenário Ativo'!B10+'🔧 Cenário Ativo'!B25*('🔧 Cenário Ativo'!B23/1000000*'🔧 Cenário Ativo'!B11+'🔧 Cenário Ativo'!B24/1000000*'🔧 Cenário Ativo'!B12)*(1-'🔧 Cenário Ativo'!B13)*'🔧 Cenário Ativo'!B10) -> 1194.3126 | F17: =F8*('🔧 Cenário Ativo'!B19*('🔧 Cenário Ativo'!B20/1000000*'🔧 Cenário Ativo'!B11+'🔧 Cenário Ativo'!B21/1000000*'🔧 Cenário Ativo'!B12)*(1-'🔧 Cenário Ativo'!B13)*'🔧 Cenário Ativo'!B10+'🔧 Cenário Ativo'!B25*('🔧 Cenário Ativo'!B23/1000000*'🔧 Cenário Ativo'!B11+'🔧 Cenário Ativo'!B24/1000000*'🔧 Cenário Ativo'!B12)*(1-'🔧 Cenário Ativo'!B13)*'🔧 Cenário Ativo'!B10) -> 1592.4168 | G17: =G8*('🔧 Cenário Ativo'!B19*('🔧 Cenário Ativo'!B20/1000000*'🔧 Cenário Ativo'!B11+'🔧 Cenário Ativo'!B21/1000000*'🔧 Cenário Ativo'!B12)*(1-'🔧 Cenário Ativo'!B13)*'🔧 Cenário Ativo'!B10+'🔧 Cenário Ativo'!B25*('🔧 Cenário Ativo'!B23/1000000*'🔧 Cenário Ativo'!B11+'🔧 Cenário Ativo'!B24/1000000*'🔧 Cenário Ativo'!B12)*(1-'🔧 Cenário Ativo'!B13)*'🔧 Cenário Ativo'!B10) -> 1990.521 | H17: =H8*('🔧 Cenário Ativo'!B19*('🔧 Cenário Ativo'!B20/1000000*'🔧 Cenário Ativo'!B11+'🔧 Cenário Ativo'!B21/1000000*'🔧 Cenário Ativo'!B12)*(1-'🔧 Cenário Ativo'!B13)*'🔧 Cenário Ativo'!B10+'🔧 Cenário Ativo'!B25*('🔧 Cenário Ativo'!B23/1000000*'🔧 Cenário Ativo'!B11+'🔧 Cenário Ativo'!B24/1000000*'🔧 Cenário Ativo'!B12)*(1-'🔧 Cenário Ativo'!B13)*'🔧 Cenário Ativo'!B10) -> 2388.6252 | I17: =I8*('🔧 Cenário Ativo'!B19*('🔧 Cenário Ativo'!B20/1000000*'🔧 Cenário Ativo'!B11+'🔧 Cenário Ativo'!B21/1000000*'🔧 Cenário Ativo'!B12)*(1-'🔧 Cenário Ativo'!B13)*'🔧 Cenário Ativo'!B10+'🔧 Cenário Ativo'!B25*('🔧 Cenário Ativo'!B23/1000000*'🔧 Cenário Ativo'!B11+'🔧 Cenário Ativo'!B24/1000000*'🔧 Cenário Ativo'!B12)*(1-'🔧 Cenário Ativo'!B13)*'🔧 Cenário Ativo'!B10) -> 2786.7294 | J17: =J8*('🔧 Cenário Ativo'!B19*('🔧 Cenário Ativo'!B20/1000000*'🔧 Cenário Ativo'!B11+'🔧 Cenário Ativo'!B21/1000000*'🔧 Cenário Ativo'!B12)*(1-'🔧 Cenário Ativo'!B13)*'🔧 Cenário Ativo'!B10+'🔧 Cenário Ativo'!B25*('🔧 Cenário Ativo'!B23/1000000*'🔧 Cenário Ativo'!B11+'🔧 Cenário Ativo'!B24/1000000*'🔧 Cenário Ativo'!B12)*(1-'🔧 Cenário Ativo'!B13)*'🔧 Cenário Ativo'!B10) -> 3184.8336 | K17: =K8*('🔧 Cenário Ativo'!B19*('🔧 Cenário Ativo'!B20/1000000*'🔧 Cenário Ativo'!B11+'🔧 Cenário Ativo'!B21/1000000*'🔧 Cenário Ativo'!B12)*(1-'🔧 Cenário Ativo'!B13)*'🔧 Cenário Ativo'!B10+'🔧 Cenário Ativo'!B25*('🔧 Cenário Ativo'!B23/1000000*'🔧 Cenário Ativo'!B11+'🔧 Cenário Ativo'!B24/1000000*'🔧 Cenário Ativo'!B12)*(1-'🔧 Cenário Ativo'!B13)*'🔧 Cenário Ativo'!B10) -> 3582.9378 | L17: =L8*('🔧 Cenário Ativo'!B19*('🔧 Cenário Ativo'!B20/1000000*'🔧 Cenário Ativo'!B11+'🔧 Cenário Ativo'!B21/1000000*'🔧 Cenário Ativo'!B12)*(1-'🔧 Cenário Ativo'!B13)*'🔧 Cenário Ativo'!B10+'🔧 Cenário Ativo'!B25*('🔧 Cenário Ativo'!B23/1000000*'🔧 Cenário Ativo'!B11+'🔧 Cenário Ativo'!B24/1000000*'🔧 Cenário Ativo'!B12)*(1-'🔧 Cenário Ativo'!B13)*'🔧 Cenário Ativo'!B10) -> 3981.042 | M17: =M8*('🔧 Cenário Ativo'!B19*('🔧 Cenário Ativo'!B20/1000000*'🔧 Cenário Ativo'!B11+'🔧 Cenário Ativo'!B21/1000000*'🔧 Cenário Ativo'!B12)*(1-'🔧 Cenário Ativo'!B13)*'🔧 Cenário Ativo'!B10+'🔧 Cenário Ativo'!B25*('🔧 Cenário Ativo'!B23/1000000*'🔧 Cenário Ativo'!B11+'🔧 Cenário Ativo'!B24/1000000*'🔧 Cenário Ativo'!B12)*(1-'🔧 Cenário Ativo'!B13)*'🔧 Cenário Ativo'!B10) -> 4379.1462 | N17: =N8*('🔧 Cenário Ativo'!B19*('🔧 Cenário Ativo'!B20/1000000*'🔧 Cenário Ativo'!B11+'🔧 Cenário Ativo'!B21/1000000*'🔧 Cenário Ativo'!B12)*(1-'🔧 Cenário Ativo'!B13)*'🔧 Cenário Ativo'!B10+'🔧 Cenário Ativo'!B25*('🔧 Cenário Ativo'!B23/1000000*'🔧 Cenário Ativo'!B11+'🔧 Cenário Ativo'!B24/1000000*'🔧 Cenário Ativo'!B12)*(1-'🔧 Cenário Ativo'!B13)*'🔧 Cenário Ativo'!B10) -> 4777.2504 | O17: =O8*('🔧 Cenário Ativo'!B19*('🔧 Cenário Ativo'!B20/1000000*'🔧 Cenário Ativo'!B11+'🔧 Cenário Ativo'!B21/1000000*'🔧 Cenário Ativo'!B12)*(1-'🔧 Cenário Ativo'!B13)*'🔧 Cenário Ativo'!B10+'🔧 Cenário Ativo'!B25*('🔧 Cenário Ativo'!B23/1000000*'🔧 Cenário Ativo'!B11+'🔧 Cenário Ativo'!B24/1000000*'🔧 Cenário Ativo'!B12)*(1-'🔧 Cenário Ativo'!B13)*'🔧 Cenário Ativo'!B10) -> 5241.7053 | P17: =P8*('🔧 Cenário Ativo'!B19*('🔧 Cenário Ativo'!B20/1000000*'🔧 Cenário Ativo'!B11+'🔧 Cenário Ativo'!B21/1000000*'🔧 Cenário Ativo'!B12)*(1-'🔧 Cenário Ativo'!B13)*'🔧 Cenário Ativo'!B10+'🔧 Cenário Ativo'!B25*('🔧 Cenário Ativo'!B23/1000000*'🔧 Cenário Ativo'!B11+'🔧 Cenário Ativo'!B24/1000000*'🔧 Cenário Ativo'!B12)*(1-'🔧 Cenário Ativo'!B13)*'🔧 Cenário Ativo'!B10) -> 5706.1602 | Q17: =Q8*('🔧 Cenário Ativo'!B19*('🔧 Cenário Ativo'!B20/1000000*'🔧 Cenário Ativo'!B11+'🔧 Cenário Ativo'!B21/1000000*'🔧 Cenário Ativo'!B12)*(1-'🔧 Cenário Ativo'!B13)*'🔧 Cenário Ativo'!B10+'🔧 Cenário Ativo'!B25*('🔧 Cenário Ativo'!B23/1000000*'🔧 Cenário Ativo'!B11+'🔧 Cenário Ativo'!B24/1000000*'🔧 Cenário Ativo'!B12)*(1-'🔧 Cenário Ativo'!B13)*'🔧 Cenário Ativo'!B10) -> 6170.6151 | R17: =R8*('🔧 Cenário Ativo'!B19*('🔧 Cenário Ativo'!B20/1000000*'🔧 Cenário Ativo'!B11+'🔧 Cenário Ativo'!B21/1000000*'🔧 Cenário Ativo'!B12)*(1-'🔧 Cenário Ativo'!B13)*'🔧 Cenário Ativo'!B10+'🔧 Cenário Ativo'!B25*('🔧 Cenário Ativo'!B23/1000000*'🔧 Cenário Ativo'!B11+'🔧 Cenário Ativo'!B24/1000000*'🔧 Cenário Ativo'!B12)*(1-'🔧 Cenário Ativo'!B13)*'🔧 Cenário Ativo'!B10) -> 6117.5345 | S17: =S8*('🔧 Cenário Ativo'!B19*('🔧 Cenário Ativo'!B20/1000000*'🔧 Cenário Ativo'!B11+'🔧 Cenário Ativo'!B21/1000000*'🔧 Cenário Ativo'!B12)*(1-'🔧 Cenário Ativo'!B13)*'🔧 Cenário Ativo'!B10+'🔧 Cenário Ativo'!B25*('🔧 Cenário Ativo'!B23/1000000*'🔧 Cenário Ativo'!B11+'🔧 Cenário Ativo'!B24/1000000*'🔧 Cenário Ativo'!B12)*(1-'🔧 Cenário Ativo'!B13)*'🔧 Cenário Ativo'!B10) -> 6077.7241 | T17: =T8*('🔧 Cenário Ativo'!B19*('🔧 Cenário Ativo'!B20/1000000*'🔧 Cenário Ativo'!B11+'🔧 Cenário Ativo'!B21/1000000*'🔧 Cenário Ativo'!B12)*(1-'🔧 Cenário Ativo'!B13)*'🔧 Cenário Ativo'!B10+'🔧 Cenário Ativo'!B25*('🔧 Cenário Ativo'!B23/1000000*'🔧 Cenário Ativo'!B11+'🔧 Cenário Ativo'!B24/1000000*'🔧 Cenário Ativo'!B12)*(1-'🔧 Cenário Ativo'!B13)*'🔧 Cenário Ativo'!B10) -> 6077.7241 | U17: =U8*('🔧 Cenário Ativo'!B19*('🔧 Cenário Ativo'!B20/1000000*'🔧 Cenário Ativo'!B11+'🔧 Cenário Ativo'!B21/1000000*'🔧 Cenário Ativo'!B12)*(1-'🔧 Cenário Ativo'!B13)*'🔧 Cenário Ativo'!B10+'🔧 Cenário Ativo'!B25*('🔧 Cenário Ativo'!B23/1000000*'🔧 Cenário Ativo'!B11+'🔧 Cenário Ativo'!B24/1000000*'🔧 Cenário Ativo'!B12)*(1-'🔧 Cenário Ativo'!B13)*'🔧 Cenário Ativo'!B10) -> 6104.2644 | V17: =V8*('🔧 Cenário Ativo'!B19*('🔧 Cenário Ativo'!B20/1000000*'🔧 Cenário Ativo'!B11+'🔧 Cenário Ativo'!B21/1000000*'🔧 Cenário Ativo'!B12)*(1-'🔧 Cenário Ativo'!B13)*'🔧 Cenário Ativo'!B10+'🔧 Cenário Ativo'!B25*('🔧 Cenário Ativo'!B23/1000000*'🔧 Cenário Ativo'!B11+'🔧 Cenário Ativo'!B24/1000000*'🔧 Cenário Ativo'!B12)*(1-'🔧 Cenário Ativo'!B13)*'🔧 Cenário Ativo'!B10) -> 6170.6151 | W17: =W8*('🔧 Cenário Ativo'!B19*('🔧 Cenário Ativo'!B20/1000000*'🔧 Cenário Ativo'!B11+'🔧 Cenário Ativo'!B21/1000000*'🔧 Cenário Ativo'!B12)*(1-'🔧 Cenário Ativo'!B13)*'🔧 Cenário Ativo'!B10+'🔧 Cenário Ativo'!B25*('🔧 Cenário Ativo'!B23/1000000*'🔧 Cenário Ativo'!B11+'🔧 Cenário Ativo'!B24/1000000*'🔧 Cenário Ativo'!B12)*(1-'🔧 Cenário Ativo'!B13)*'🔧 Cenário Ativo'!B10) -> 6276.7762 | X17: =X8*('🔧 Cenário Ativo'!B19*('🔧 Cenário Ativo'!B20/1000000*'🔧 Cenário Ativo'!B11+'🔧 Cenário Ativo'!B21/1000000*'🔧 Cenário Ativo'!B12)*(1-'🔧 Cenário Ativo'!B13)*'🔧 Cenário Ativo'!B10+'🔧 Cenário Ativo'!B25*('🔧 Cenário Ativo'!B23/1000000*'🔧 Cenário Ativo'!B11+'🔧 Cenário Ativo'!B24/1000000*'🔧 Cenário Ativo'!B12)*(1-'🔧 Cenário Ativo'!B13)*'🔧 Cenário Ativo'!B10) -> 6436.0179 | Y17: =Y8*('🔧 Cenário Ativo'!B19*('🔧 Cenário Ativo'!B20/1000000*'🔧 Cenário Ativo'!B11+'🔧 Cenário Ativo'!B21/1000000*'🔧 Cenário Ativo'!B12)*(1-'🔧 Cenário Ativo'!B13)*'🔧 Cenário Ativo'!B10+'🔧 Cenário Ativo'!B25*('🔧 Cenário Ativo'!B23/1000000*'🔧 Cenário Ativo'!B11+'🔧 Cenário Ativo'!B24/1000000*'🔧 Cenário Ativo'!B12)*(1-'🔧 Cenário Ativo'!B13)*'🔧 Cenário Ativo'!B10) -> 6635.07 | Z17: =Z8*('🔧 Cenário Ativo'!B19*('🔧 Cenário Ativo'!B20/1000000*'🔧 Cenário Ativo'!B11+'🔧 Cenário Ativo'!B21/1000000*'🔧 Cenário Ativo'!B12)*(1-'🔧 Cenário Ativo'!B13)*'🔧 Cenário Ativo'!B10+'🔧 Cenário Ativo'!B25*('🔧 Cenário Ativo'!B23/1000000*'🔧 Cenário Ativo'!B11+'🔧 Cenário Ativo'!B24/1000000*'🔧 Cenário Ativo'!B12)*(1-'🔧 Cenário Ativo'!B13)*'🔧 Cenário Ativo'!B10) -> 6887.2027
A18: TOTAL API | B18: R$ | C18: =SUM(C14:C17) -> 3351.3305 | D18: =SUM(D14:D17) -> 6702.6609 | E18: =SUM(E14:E17) -> 10053.991 | F18: =SUM(F14:F17) -> 13405.322 | G18: =SUM(G14:G17) -> 16756.652 | H18: =SUM(H14:H17) -> 20107.983 | I18: =SUM(I14:I17) -> 23459.313 | J18: =SUM(J14:J17) -> 26810.644 | ... Z18: =SUM(Z14:Z17) -> 207238.78
A19: CUSTO FIXO
A20: Custo Fixo (equipe+infra+mkt) | B20: R$ | C20: ='🔧 Cenário Ativo'!B36+'🔧 Cenário Ativo'!B38+'🔧 Cenário Ativo'!B40+'🔧 Cenário Ativo'!B42 -> 55000 | D20: ='🔧 Cenário Ativo'!B36+'🔧 Cenário Ativo'!B38+'🔧 Cenário Ativo'!B40+'🔧 Cenário Ativo'!B42 -> 55000 | E20: ='🔧 Cenário Ativo'!B36+'🔧 Cenário Ativo'!B38+'🔧 Cenário Ativo'!B40+'🔧 Cenário Ativo'!B42 -> 55000 | F20: ='🔧 Cenário Ativo'!B36+'🔧 Cenário Ativo'!B38+'🔧 Cenário Ativo'!B40+'🔧 Cenário Ativo'!B42 -> 55000 | G20: ='🔧 Cenário Ativo'!B36+'🔧 Cenário Ativo'!B38+'🔧 Cenário Ativo'!B40+'🔧 Cenário Ativo'!B42 -> 55000 | H20: ='🔧 Cenário Ativo'!B36+'🔧 Cenário Ativo'!B38+'🔧 Cenário Ativo'!B40+'🔧 Cenário Ativo'!B42 -> 55000 | I20: ='🔧 Cenário Ativo'!B36+'🔧 Cenário Ativo'!B38+'🔧 Cenário Ativo'!B40+'🔧 Cenário Ativo'!B42 -> 55000 | J20: ='🔧 Cenário Ativo'!B36+'🔧 Cenário Ativo'!B38+'🔧 Cenário Ativo'!B40+'🔧 Cenário Ativo'!B42 -> 55000 | K20: ='🔧 Cenário Ativo'!B36+'🔧 Cenário Ativo'!B38+'🔧 Cenário Ativo'!B40+'🔧 Cenário Ativo'!B42 -> 55000 | L20: ='🔧 Cenário Ativo'!B36+'🔧 Cenário Ativo'!B38+'🔧 Cenário Ativo'!B40+'🔧 Cenário Ativo'!B42 -> 55000 | M20: ='🔧 Cenário Ativo'!B36+'🔧 Cenário Ativo'!B38+'🔧 Cenário Ativo'!B40+'🔧 Cenário Ativo'!B42 -> 55000 | N20: ='🔧 Cenário Ativo'!B36+'🔧 Cenário Ativo'!B38+'🔧 Cenário Ativo'!B40+'🔧 Cenário Ativo'!B42 -> 55000 | O20: ='🔧 Cenário Ativo'!B37+'🔧 Cenário Ativo'!B39+'🔧 Cenário Ativo'!B41+'🔧 Cenário Ativo'!B42 -> 70000 | P20: ='🔧 Cenário Ativo'!B37+'🔧 Cenário Ativo'!B39+'🔧 Cenário Ativo'!B41+'🔧 Cenário Ativo'!B42 -> 70000 | Q20: ='🔧 Cenário Ativo'!B37+'🔧 Cenário Ativo'!B39+'🔧 Cenário Ativo'!B41+'🔧 Cenário Ativo'!B42 -> 70000 | R20: ='🔧 Cenário Ativo'!B37+'🔧 Cenário Ativo'!B39+'🔧 Cenário Ativo'!B41+'🔧 Cenário Ativo'!B42 -> 70000 | S20: ='🔧 Cenário Ativo'!B37+'🔧 Cenário Ativo'!B39+'🔧 Cenário Ativo'!B41+'🔧 Cenário Ativo'!B42 -> 70000 | T20: ='🔧 Cenário Ativo'!B37+'🔧 Cenário Ativo'!B39+'🔧 Cenário Ativo'!B41+'🔧 Cenário Ativo'!B42 -> 70000 | U20: ='🔧 Cenário Ativo'!B37+'🔧 Cenário Ativo'!B39+'🔧 Cenário Ativo'!B41+'🔧 Cenário Ativo'!B42 -> 70000 | V20: ='🔧 Cenário Ativo'!B37+'🔧 Cenário Ativo'!B39+'🔧 Cenário Ativo'!B41+'🔧 Cenário Ativo'!B42 -> 70000 | W20: ='🔧 Cenário Ativo'!B37+'🔧 Cenário Ativo'!B39+'🔧 Cenário Ativo'!B41+'🔧 Cenário Ativo'!B42 -> 70000 | X20: ='🔧 Cenário Ativo'!B37+'🔧 Cenário Ativo'!B39+'🔧 Cenário Ativo'!B41+'🔧 Cenário Ativo'!B42 -> 70000 | Y20: ='🔧 Cenário Ativo'!B37+'🔧 Cenário Ativo'!B39+'🔧 Cenário Ativo'!B41+'🔧 Cenário Ativo'!B42 -> 70000 | Z20: ='🔧 Cenário Ativo'!B37+'🔧 Cenário Ativo'!B39+'🔧 Cenário Ativo'!B41+'🔧 Cenário Ativo'!B42 -> 70000
A21: IMPOSTOS | B21: R$ | C21: =C11*'🔧 Cenário Ativo'!$B$56 -> 1940.04 | D21: =D11*'🔧 Cenário Ativo'!$B$56 -> 3880.08 | E21: =E11*'🔧 Cenário Ativo'!$B$56 -> 5820.12 | F21: =F11*'🔧 Cenário Ativo'!$B$56 -> 7760.16 | G21: =G11*'🔧 Cenário Ativo'!$B$56 -> 9700.2 | H21: =H11*'🔧 Cenário Ativo'!$B$56 -> 11640.24 | I21: =I11*'🔧 Cenário Ativo'!$B$56 -> 13580.28 | J21: =J11*'🔧 Cenário Ativo'!$B$56 -> 15520.32 | ... Z21: =Z11*'🔧 Cenário Ativo'!$B$56 -> 147631.64
A22: RESULTADO
A23: Custo Total (API + Fixo + Impostos) | B23: R$ | C23: =C18+C20+C21 -> 60291.37 | D23: =D18+D20+D21 -> 65582.741 | E23: =E18+E20+E21 -> 70874.111 | F23: =F18+F20+F21 -> 76165.482 | G23: =G18+G20+G21 -> 81456.852 | H23: =H18+H20+H21 -> 86748.223 | I23: =I18+I20+I21 -> 92039.593 | J23: =J18+J20+J21 -> 97330.964 | ... Z23: =Z18+Z20+Z21 -> 424870.43
A24: RESULTADO MENSAL | B24: R$ | C24: =C11-C23 -> -44124.37 | D24: =D11-D23 -> -33248.741 | E24: =E11-E23 -> -22373.111 | F24: =F11-F23 -> -11497.482 | G24: =G11-G23 -> -621.85225 | H24: =H11-H23 -> 10253.777 | I24: =I11-I23 -> 21129.407 | J24: =J11-J23 -> 32005.036 | ... Z24: =Z11-Z23 -> 805393.27
A25: RESULTADO ACUMULADO | B25: R$ | C25: =C24 -> -44124.37 | D25: =C25+D24 -> -77373.111 | E25: =D25+E24 -> -99746.223 | F25: =E25+F24 -> -111243.7 | G25: =F25+G24 -> -111865.56 | H25: =G25+H24 -> -101611.78 | I25: =H25+I24 -> -80482.373 | J25: =I25+J24 -> -48477.336 | K25: =J25+K24 -> -5596.6703 | ... Z25: =Y25+Z24 -> 4961644
A26: Margem Bruta API (% MRR) | B26: % | C26: =IF(C11=0,0,1-C18/C11) -> 0.79270548 | D26: =IF(D11=0,0,1-D18/D11) -> 0.79270548 | E26: =IF(E11=0,0,1-E18/E11) -> 0.79270548 | F26: =IF(F11=0,0,1-F18/F11) -> 0.79270548 | G26: =IF(G11=0,0,1-G18/G11) -> 0.79270548 | H26: =IF(H11=0,0,1-H18/H11) -> 0.79270548 | I26: =IF(I11=0,0,1-I18/I11) -> 0.79270548 | J26: =IF(J11=0,0,1-J18/J11) -> 0.79270548 | ... Z26: =IF(Z11=0,0,1-Z18/Z11) -> 0.8315493

Sheet 📊 Resumo Cenários
A1: AutoNoma · Comparativo Real de Cenários · 3 Anos · Fórmulas Dinâmicas
A2: Comparativo dos 3 cenários · Premissas / Unit Economics / Valuation / Operacional · Independentes
A3: INDICADOR | B3: Conservador | C3: Base (padrão) | D3: Otimista | E3: UNIDADE
A4: PREMISSAS DIFERENCIADORAS POR CENÁRIO
A5: CAC Real (full-loaded) | B5: ='🎛️ Premissas'!B45 -> 80 | C5: ='🎛️ Premissas'!C45 -> 60 | D5: ='🎛️ Premissas'!D45 -> 50 | E5: R$/assinante
A6: Churn mensal Essencial | B6: ='🎛️ Premissas'!B33 -> 0.08 | C6: ='🎛️ Premissas'!C33 -> 0.08 | D6: ='🎛️ Premissas'!D33 -> 0.08 | E6: %/mês
A7: Churn anual implícito | B7: =1-(1-'🎛️ Premissas'!B33)^12 -> 0.63233361 | C7: =1-(1-'🎛️ Premissas'!C33)^12 -> 0.63233361 | D7: =1-(1-'🎛️ Premissas'!D33)^12 -> 0.63233361 | E7: %/ano
A8: Múltiplo valuation M24 | B8: ='🎛️ Premissas'!B49 -> 3 | C8: ='🎛️ Premissas'!C49 -> 5 | D8: ='🎛️ Premissas'!D49 -> 7 | E8: × ARR (SaaS LATAM)
A9: Free: % usuárias ativas | B9: ='🎛️ Premissas'!B17 -> 0.5 | C9: ='🎛️ Premissas'!C17 -> 0.5 | D9: ='🎛️ Premissas'!D17 -> 0.5 | E9: % do cadastro
A10: Conversão Free→Essencial | B10: ='🎛️ Premissas'!B30 -> 0.07 | C10: ='🎛️ Premissas'!C30 -> 0.08 | D10: ='🎛️ Premissas'!D30 -> 0.1 | E10: % base Free
A11: UNIT ECONOMICS (calculado das premissas)
A12: Custo API Essencial/mês | B12: =('🎛️ Premissas'!B18*('🎛️ Premissas'!B19/1000000*'🎛️ Premissas'!B10+'🎛️ Premissas'!B20/1000000*'🎛️ Premissas'!B11)*(1-'🎛️ Premissas'!B12)*'🎛️ Premissas'!B9) -> 5.82894 | C12: =('🎛️ Premissas'!C18*('🎛️ Premissas'!C19/1000000*'🎛️ Premissas'!C10+'🎛️ Premissas'!C20/1000000*'🎛️ Premissas'!C11)*(1-'🎛️ Premissas'!C12)*'🎛️ Premissas'!C9) -> 6.54444 | D12: =('🎛️ Premissas'!D18*('🎛️ Premissas'!D19/1000000*'🎛️ Premissas'!D10+'🎛️ Premissas'!D20/1000000*'🎛️ Premissas'!D11)*(1-'🎛️ Premissas'!D12)*'🎛️ Premissas'!D9) -> 8.34273 | E12: R$/assinante/mês
A13: Margem Unitária Essencial/mês | B13: =('🎛️ Premissas'!B5-('🎛️ Premissas'!B18*('🎛️ Premissas'!B19/1000000*'🎛️ Premissas'!B10+'🎛️ Premissas'!B20/1000000*'🎛️ Premissas'!B11)*(1-'🎛️ Premissas'!B12)*'🎛️ Premissas'!B9)) -> 34.07106 | C13: =('🎛️ Premissas'!C5-('🎛️ Premissas'!C18*('🎛️ Premissas'!C19/1000000*'🎛️ Premissas'!C10+'🎛️ Premissas'!C20/1000000*'🎛️ Premissas'!C11)*(1-'🎛️ Premissas'!C12)*'🎛️ Premissas'!C9)) -> 43.35556 | D13: =('🎛️ Premissas'!D5-('🎛️ Premissas'!D18*('🎛️ Premissas'!D19/1000000*'🎛️ Premissas'!D10+'🎛️ Premissas'!D20/1000000*'🎛️ Premissas'!D11)*(1-'🎛️ Premissas'!D12)*'🎛️ Premissas'!D9)) -> 41.55727 | E13: R$/mês
A14: Vida média (meses) | B14: =1/'🎛️ Premissas'!B33 -> 12.5 | C14: =1/'🎛️ Premissas'!C33 -> 12.5 | D14: =1/'🎛️ Premissas'!D33 -> 12.5 | E14: 1 ÷ churn
A15: LTV Essencial | B15: =B13*B14 -> 425.88825 | C15: =C13*C14 -> 541.9445 | D15: =D13*D14 -> 519.46587 | E15: R$ vida útil
A16: LTV / CAC | B16: =IFERROR(B15/B5,0) -> 5.3236031 | C16: =IFERROR(C15/C5,0) -> 9.0324083 | D16: =IFERROR(D15/D5,0) -> 10.389317 | E16: ≥3× ok · ≥8× top quartile
A17: Payback CAC (meses) | B17: =IFERROR(B5/B13,0) -> 2.3480338 | C17: =IFERROR(C5/C13,0) -> 1.3839055 | D17: =IFERROR(D5/D13,0) -> 1.2031589 | E17: meses
A18: VALUATION · MÊS 24 (Receita Acum × múltiplo)
A19: Receita Acumulada 24m (Z12) | B19: =SUM(B56:Y56) -> 9232937.7 | C19: =SUM(B68:Y68) -> 15008944 | D19: =SUM(B80:Y80) -> 21246511 | E19: R$ acumulado 24m
A20: Múltiplo aplicado | B20: ='🎛️ Premissas'!B49 -> 3 | C20: ='🎛️ Premissas'!C49 -> 5 | D20: ='🎛️ Premissas'!D49 -> 7 | E20: × Receita acum
A21: VALUATION SUGERIDO M24 | B21: =B19*B20 -> 27698813 | C21: =C19*C20 -> 75044719 | D21: =D19*D20 -> 1.4872558e+08 | E21: R$
A22: Equity anjo (% Premissas) | B22: =B21*'🎛️ Premissas'!$B$56 -> 4154822 | C22: =C21*'🎛️ Premissas'!$B$56 -> 11256708 | D22: =D21*'🎛️ Premissas'!$B$56 -> 22308836 | E22: R$
A23: Retorno sobre aporte (×) | B23: =B22/'🎛️ Premissas'!$B$55 -> 4.154822 | C23: =C22/'🎛️ Premissas'!$B$55 -> 11.256708 | D23: =D22/'🎛️ Premissas'!$B$55 -> 22.308836 | E23: × sobre aporte
A24: ANO 1 · Resultados
A25: MRR Dezembro M12 | B25: =M56 -> 194004 | C25: =M68 -> 331419 | D25: =M80 -> 495004 | E25: R$/mês
A26: ARR Ano 1 (MRR×12) | B26: =M56*12 -> 2328048 | C26: =M68*12 -> 3977028 | D26: =M80*12 -> 5940048 | E26: R$/ano
A27: Resultado Líquido no Ano | B27: =SUM(B60:M60) -> 179205.96 | C27: =SUM(B72:M72) -> 704970.97 | D27: =SUM(B84:M84) -> 1133888.3 | E27: R$
A28: Pagantes M12 | B28: =M55 -> 3960 | C28: =M67 -> 5810 | D28: =M79 -> 8460 | E28: assinantes
A29: ANO 2 · Resultados
A30: MRR Dezembro M24 | B30: =Y56 -> 1230263.7 | C30: =Y68 -> 1949301 | D30: =Y80 -> 2679324.5 | E30: R$/mês
A31: ARR Ano 2 (MRR×12) | B31: =Y56*12 -> 14763164 | C31: =Y68*12 -> 23391612 | D31: =Y80*12 -> 32151894 | E31: R$/ano
A32: Resultado Líquido no Ano | B32: =SUM(N60:Y60) -> 4742484.5 | C32: =SUM(N72:Y72) -> 8208038.3 | D32: =SUM(N84:Y84) -> 10683891 | E32: R$
A33: Pagantes M24 | B33: =Y55 -> 28363 | C33: =Y67 -> 37090 | D33: =Y79 -> 49885 | E33: assinantes
A34: RESUMO
A35: VPL (Valor Presente Líquido) | B35: =-'🎛️ Premissas'!$B$55+NPV('🎛️ Premissas'!$B$66,C86:Z86) -> 2419822 | C35: =-'🎛️ Premissas'!$B$55+NPV('🎛️ Premissas'!$B$66,C87:Z87) -> 5288430.2 | D35: =-'🎛️ Premissas'!$B$55+NPV('🎛️ Premissas'!$B$66,C88:Z88) -> 7387811.6 | E35: R$ · taxa B66 mensal
A36: TIR (anualizada) | B36: =IFERROR((1+IRR(B86:Z86,'🎛️ Premissas'!$B$66))^12-1,"n/a") -> 1.561834 | C36: =IFERROR((1+IRR(B87:Z87,'🎛️ Premissas'!$B$66))^12-1,"n/a") -> 3.0554598 | D36: =IFERROR((1+IRR(B88:Z88,'🎛️ Premissas'!$B$66))^12-1,"n/a") -> 4.1864214 | E36: % a.a.
A37: ✅ Todos os indicadores acima são calculados independentemente por cenário. Helpers de simulação ocultos linhas 50-89.
A49: ── HELPERS · 3 CENÁRIOS · 24 MESES (oculto) ── | B49: M1 | C49: M2 | D49: M3 | E49: M4 | F49: M5 | G49: M6 | H49: M7 | I49: M8 | J49: M9 | K49: M10 | L49: M11 | M49: M12 | N49: M13 | O49: M14 | P49: M15 | Q49: M16 | R49: M17 | S49: M18 | T49: M19 | U49: M20 | V49: M21 | W49: M22 | X49: M23 | Y49: M24
A50: CONSERVADOR
A51: Free Cadastros | B51: ='🎛️ Premissas'!$B$61 -> 3000 | C51: =B51+'🎛️ Premissas'!$B$28 -> 6000 | D51: =C51+'🎛️ Premissas'!$B$28 -> 9000 | E51: =D51+'🎛️ Premissas'!$B$28 -> 12000 | F51: =E51+'🎛️ Premissas'!$B$28 -> 15000 | G51: =F51+'🎛️ Premissas'!$B$28 -> 18000 | H51: =G51+'🎛️ Premissas'!$B$28 -> 21000 | I51: =H51+'🎛️ Premissas'!$B$28 -> 24000 | J51: =I51+'🎛️ Premissas'!$B$28 -> 27000 | ... M51: =L51+'🎛️ Premissas'!$B$28 -> 36000 | N51: =M51+'🎛️ Premissas'!$B$29 -> 39500 | O51: =N51+'🎛️ Premissas'!$B$29 -> 43000 | P51: =O51+'🎛️ Premissas'!$B$29 -> 46500 | Q51: =P51+'🎛️ Premissas'!$B$29 -> 50000 | R51: =Q51+'🎛️ Premissas'!$B$29 -> 53500 | S51: =R51+'🎛️ Premissas'!$B$29 -> 57000 | T51: =S51+'🎛️ Premissas'!$B$29 -> 60500 | U51: =T51+'🎛️ Premissas'!$B$29 -> 64000 | ... Y51: =X51+'🎛️ Premissas'!$B$29 -> 78000
A52: Essencial | B52: =ROUND(B51*'🎛️ Premissas'!$B$30,0) -> 210 | C52: =ROUND(C51*'🎛️ Premissas'!$B$30,0) -> 420 | D52: =ROUND(D51*'🎛️ Premissas'!$B$30,0) -> 630 | E52: =ROUND(E51*'🎛️ Premissas'!$B$30,0) -> 840 | F52: =ROUND(F51*'🎛️ Premissas'!$B$30,0) -> 1050 | G52: =ROUND(G51*'🎛️ Premissas'!$B$30,0) -> 1260 | H52: =ROUND(H51*'🎛️ Premissas'!$B$30,0) -> 1470 | I52: =ROUND(I51*'🎛️ Premissas'!$B$30,0) -> 1680 | ... P52: =ROUND(P51*'🎛️ Premissas'!$B$30,0) -> 3255 | Q52: =ROUND(P52*(1-'🎛️ Premissas'!$B$33)+MAX(0,Q51-P55)*'🎛️ Premissas'!$B$30,0) -> 6137 | R52: =ROUND(Q52*(1-'🎛️ Premissas'!$B$33)+MAX(0,R51-Q55)*'🎛️ Premissas'!$B$30,0) -> 8827 | S52: =ROUND(R52*(1-'🎛️ Premissas'!$B$33)+MAX(0,S51-R55)*'🎛️ Premissas'!$B$30,0) -> 11350 | T52: =ROUND(S52*(1-'🎛️ Premissas'!$B$33)+MAX(0,T51-S55)*'🎛️ Premissas'!$B$30,0) -> 13725 | U52: =ROUND(T52*(1-'🎛️ Premissas'!$B$33)+MAX(0,U51-T55)*'🎛️ Premissas'!$B$30,0) -> 15971 | V52: =ROUND(U52*(1-'🎛️ Premissas'!$B$33)+MAX(0,V51-U55)*'🎛️ Premissas'!$B$30,0) -> 18104 | W52: =ROUND(V52*(1-'🎛️ Premissas'!$B$33)+MAX(0,W51-V55)*'🎛️ Premissas'!$B$30,0) -> 20137 | X52: =ROUND(W52*(1-'🎛️ Premissas'!$B$33)+MAX(0,X51-W55)*'🎛️ Premissas'!$B$30,0) -> 22083 | Y52: =ROUND(X52*(1-'🎛️ Premissas'!$B$33)+MAX(0,Y51-X55)*'🎛️ Premissas'!$B$30,0) -> 23953
A53: Autônoma | B53: =ROUND(B51*'🎛️ Premissas'!$B$31,0) -> 90 | C53: =ROUND(C51*'🎛️ Premissas'!$B$31,0) -> 180 | D53: =ROUND(D51*'🎛️ Premissas'!$B$31,0) -> 270 | E53: =ROUND(E51*'🎛️ Premissas'!$B$31,0) -> 360 | F53: =ROUND(F51*'🎛️ Premissas'!$B$31,0) -> 450 | G53: =ROUND(G51*'🎛️ Premissas'!$B$31,0) -> 540 | H53: =ROUND(H51*'🎛️ Premissas'!$B$31,0) -> 630 | I53: =ROUND(I51*'🎛️ Premissas'!$B$31,0) -> 720 | ... P53: =ROUND(P51*'🎛️ Premissas'!$B$31,0) -> 1395 | Q53: =ROUND(P53*(1-'🎛️ Premissas'!$B$34)+MAX(0,Q52-P53-P54)*'🎛️ Premissas'!$B$31,0) -> 1454 | R53: =ROUND(Q53*(1-'🎛️ Premissas'!$B$34)+MAX(0,R52-Q53-Q54)*'🎛️ Premissas'!$B$31,0) -> 1589 | S53: =ROUND(R53*(1-'🎛️ Premissas'!$B$34)+MAX(0,S52-R53-R54)*'🎛️ Premissas'!$B$31,0) -> 1789 | T53: =ROUND(S53*(1-'🎛️ Premissas'!$B$34)+MAX(0,T52-S53-S54)*'🎛️ Premissas'!$B$31,0) -> 2044 | U53: =ROUND(T53*(1-'🎛️ Premissas'!$B$34)+MAX(0,U52-T53-T54)*'🎛️ Premissas'!$B$31,0) -> 2346 | V53: =ROUND(U53*(1-'🎛️ Premissas'!$B$34)+MAX(0,V52-U53-U54)*'🎛️ Premissas'!$B$31,0) -> 2687 | W53: =ROUND(V53*(1-'🎛️ Premissas'!$B$34)+MAX(0,W52-V53-V54)*'🎛️ Premissas'!$B$31,0) -> 3062 | X53: =ROUND(W53*(1-'🎛️ Premissas'!$B$34)+MAX(0,X52-W53-W54)*'🎛️ Premissas'!$B$31,0) -> 3465 | Y53: =ROUND(X53*(1-'🎛️ Premissas'!$B$34)+MAX(0,Y52-X53-X54)*'🎛️ Premissas'!$B$31,0) -> 3891
A54: Livre | B54: =ROUND(B51*'🎛️ Premissas'!$B$32,0) -> 30 | C54: =ROUND(C51*'🎛️ Premissas'!$B$32,0) -> 60 | D54: =ROUND(D51*'🎛️ Premissas'!$B$32,0) -> 90 | E54: =ROUND(E51*'🎛️ Premissas'!$B$32,0) -> 120 | F54: =ROUND(F51*'🎛️ Premissas'!$B$32,0) -> 150 | G54: =ROUND(G51*'🎛️ Premissas'!$B$32,0) -> 180 | H54: =ROUND(H51*'🎛️ Premissas'!$B$32,0) -> 210 | I54: =ROUND(I51*'🎛️ Premissas'!$B$32,0) -> 240 | ... P54: =ROUND(P51*'🎛️ Premissas'!$B$32,0) -> 465 | Q54: =ROUND(P54*(1-'🎛️ Premissas'!$B$35)+MAX(0,Q53-P54)*'🎛️ Premissas'!$B$32,0) -> 461 | R54: =ROUND(Q54*(1-'🎛️ Premissas'!$B$35)+MAX(0,R53-Q54)*'🎛️ Premissas'!$B$32,0) -> 458 | S54: =ROUND(R54*(1-'🎛️ Premissas'!$B$35)+MAX(0,S53-R54)*'🎛️ Premissas'!$B$32,0) -> 458 | T54: =ROUND(S54*(1-'🎛️ Premissas'!$B$35)+MAX(0,T53-S54)*'🎛️ Premissas'!$B$32,0) -> 460 | U54: =ROUND(T54*(1-'🎛️ Premissas'!$B$35)+MAX(0,U53-T54)*'🎛️ Premissas'!$B$32,0) -> 465 | V54: =ROUND(U54*(1-'🎛️ Premissas'!$B$35)+MAX(0,V53-U54)*'🎛️ Premissas'!$B$32,0) -> 473 | W54: =ROUND(V54*(1-'🎛️ Premissas'!$B$35)+MAX(0,W53-V54)*'🎛️ Premissas'!$B$32,0) -> 485 | X54: =ROUND(W54*(1-'🎛️ Premissas'!$B$35)+MAX(0,X53-W54)*'🎛️ Premissas'!$B$32,0) -> 500 | Y54: =ROUND(X54*(1-'🎛️ Premissas'!$B$35)+MAX(0,Y53-X54)*'🎛️ Premissas'!$B$32,0) -> 519
A55: Total Pagantes | B55: =SUM(B52:B54) -> 330 | C55: =SUM(C52:C54) -> 660 | D55: =SUM(D52:D54) -> 990 | E55: =SUM(E52:E54) -> 1320 | F55: =SUM(F52:F54) -> 1650 | G55: =SUM(G52:G54) -> 1980 | H55: =SUM(H52:H54) -> 2310 | I55: =SUM(I52:I54) -> 2640 | ... Y55: =SUM(Y52:Y54) -> 28363
A56: MRR | B56: =B52*'🎛️ Premissas'!$B$5+B53*'🎛️ Premissas'!$B$6+B54*'🎛️ Premissas'!$B$7 -> 16167 | C56: =C52*'🎛️ Premissas'!$B$5+C53*'🎛️ Premissas'!$B$6+C54*'🎛️ Premissas'!$B$7 -> 32334 | D56: =D52*'🎛️ Premissas'!$B$5+D53*'🎛️ Premissas'!$B$6+D54*'🎛️ Premissas'!$B$7 -> 48501 | E56: =E52*'🎛️ Premissas'!$B$5+E53*'🎛️ Premissas'!$B$6+E54*'🎛️ Premissas'!$B$7 -> 64668 | F56: =F52*'🎛️ Premissas'!$B$5+F53*'🎛️ Premissas'!$B$6+F54*'🎛️ Premissas'!$B$7 -> 80835 | G56: =G52*'🎛️ Premissas'!$B$5+G53*'🎛️ Premissas'!$B$6+G54*'🎛️ Premissas'!$B$7 -> 97002 | H56: =H52*'🎛️ Premissas'!$B$5+H53*'🎛️ Premissas'!$B$6+H54*'🎛️ Premissas'!$B$7 -> 113169 | I56: =I52*'🎛️ Premissas'!$B$5+I53*'🎛️ Premissas'!$B$6+I54*'🎛️ Premissas'!$B$7 -> 129336 | ... Y56: =Y52*'🎛️ Premissas'!$B$5+Y53*'🎛️ Premissas'!$B$6+Y54*'🎛️ Premissas'!$B$7 -> 1230263.7
A57: API Total | B57: =B51*('🎛️ Premissas'!$B$14*('🎛️ Premissas'!$B$15*('🎛️ Premissas'!$G$9/1000000)+'🎛️ Premissas'!$B$16*('🎛️ Premissas'!$G$10/1000000))*(1-'🎛️ Premissas'!$B$12)*'🎛️ Premissas'!$B$9*'🎛️ Premissas'!$B$17)+B52*('🎛️ Premissas'!$B$18*('🎛️ Premissas'!$B$19*('🎛️ Premissas'!$B$10/1000000)+'🎛️ Premissas'!$B$20*('🎛️ Premissas'!$B$11/1000000))*(1-'🎛️ Premissas'!$B$12)*'🎛️ Premissas'!$B$9)+B53*(('🎛️ Premissas'!$B$21*('🎛️ Premissas'!$B$19*('🎛️ Premissas'!$B$10/1000000)+'🎛️ Premissas'!$B$20*('🎛️ Premissas'!$B$11/1000000))*(1-'🎛️ Premissas'!$B$12)*'🎛️ Premissas'!$B$9)+('🎛️ Premissas'!$B$22*('🎛️ Premissas'!$B$23*('🎛️ Premissas'!$B$10/1000000)+'🎛️ Premissas'!$B$24*('🎛️ Premissas'!$B$11/1000000))*(1-'🎛️ Premissas'!$B$12)*'🎛️ Premissas'!$B$9))+B54*(('🎛️ Premissas'!$B$25*('🎛️ Premissas'!$B$19*('🎛️ Premissas'!$B$10/1000000)+'🎛️ Premissas'!$B$20*('🎛️ Premissas'!$B$11/1000000))*(1-'🎛️ Premissas'!$B$12)*'🎛️ Premissas'!$B$9)+('🎛️ Premissas'!$B$26*('🎛️ Premissas'!$B$23*('🎛️ Premissas'!$B$10/1000000)+'🎛️ Premissas'!$B$24*('🎛️ Premissas'!$B$11/1000000))*(1-'🎛️ Premissas'!$B$12)*'🎛️ Premissas'!$B$9)) -> 3467.9093 | C57: =C51*('🎛️ Premissas'!$B$14*('🎛️ Premissas'!$B$15*('🎛️ Premissas'!$G$9/1000000)+'🎛️ Premissas'!$B$16*('🎛️ Premissas'!$G$10/1000000))*(1-'🎛️ Premissas'!$B$12)*'🎛️ Premissas'!$B$9*'🎛️ Premissas'!$B$17)+C52*('🎛️ Premissas'!$B$18*('🎛️ Premissas'!$B$19*('🎛️ Premissas'!$B$10/1000000)+'🎛️ Premissas'!$B$20*('🎛️ Premissas'!$B$11/1000000))*(1-'🎛️ Premissas'!$B$12)*'🎛️ Premissas'!$B$9)+C53*(('🎛️ Premissas'!$B$21*('🎛️ Premissas'!$B$19*('🎛️ Premissas'!$B$10/1000000)+'🎛️ Premissas'!$B$20*('🎛️ Premissas'!$B$11/1000000))*(1-'🎛️ Premissas'!$B$12)*'🎛️ Premissas'!$B$9)+('🎛️ Premissas'!$B$22*('🎛️ Premissas'!$B$23*('🎛️ Premissas'!$B$10/1000000)+'🎛️ Premissas'!$B$24*('🎛️ Premissas'!$B$11/1000000))*(1-'🎛️ Premissas'!$B$12)*'🎛️ Premissas'!$B$9))+C54*(('🎛️ Premissas'!$B$25*('🎛️ Premissas'!$B$19*('🎛️ Premissas'!$B$10/1000000)+'🎛️ Premissas'!$B$20*('🎛️ Premissas'!$B$11/1000000))*(1-'🎛️ Premissas'!$B$12)*'🎛️ Premissas'!$B$9)+('🎛️ Premissas'!$B$26*('🎛️ Premissas'!$B$23*('🎛️ Premissas'!$B$10/1000000)+'🎛️ Premissas'!$B$24*('🎛️ Premissas'!$B$11/1000000))*(1-'🎛️ Premissas'!$B$12)*'🎛️ Premissas'!$B$9)) -> 6935.8185 | D57: =D51*('🎛️ Premissas'!$B$14*('🎛️ Premissas'!$B$15*('🎛️ Premissas'!$G$9/1000000)+'🎛️ Premissas'!$B$16*('🎛️ Premissas'!$G$10/1000000))*(1-'🎛️ Premissas'!$B$12)*'🎛️ Premissas'!$B$9*'🎛️ Premissas'!$B$17)+D52*('🎛️ Premissas'!$B$18*('🎛️ Premissas'!$B$19*('🎛️ Premissas'!$B$10/1000000)+'🎛️ Premissas'!$B$20*('🎛️ Premissas'!$B$11/1000000))*(1-'🎛️ Premissas'!$B$12)*'🎛️ Premissas'!$B$9)+D53*(('🎛️ Premissas'!$B$21*('🎛️ Premissas'!$B$19*('🎛️ Premissas'!$B$10/1000000)+'🎛️ Premissas'!$B$20*('🎛️ Premissas'!$B$11/1000000))*(1-'🎛️ Premissas'!$B$12)*'🎛️ Premissas'!$B$9)+('🎛️ Premissas'!$B$22*('🎛️ Premissas'!$B$23*('🎛️ Premissas'!$B$10/1000000)+'🎛️ Premissas'!$B$24*('🎛️ Premissas'!$B$11/1000000))*(1-'🎛️ Premissas'!$B$12)*'🎛️ Premissas'!$B$9))+D54*(('🎛️ Premissas'!$B$25*('🎛️ Premissas'!$B$19*('🎛️ Premissas'!$B$10/1000000)+'🎛️ Premissas'!$B$20*('🎛️ Premissas'!$B$11/1000000))*(1-'🎛️ Premissas'!$B$12)*'🎛️ Premissas'!$B$9)+('🎛️ Premissas'!$B$26*('🎛️ Premissas'!$B$23*('🎛️ Premissas'!$B$10/1000000)+'🎛️ Premissas'!$B$24*('🎛️ Premissas'!$B$11/1000000))*(1-'🎛️ Premissas'!$B$12)*'🎛️ Premissas'!$B$9)) -> 10403.728 | E57: =E51*('🎛️ Premissas'!$B$14*('🎛️ Premissas'!$B$15*('🎛️ Premissas'!$G$9/1000000)+'🎛️ Premissas'!$B$16*('🎛️ Premissas'!$G$10/1000000))*(1-'🎛️ Premissas'!$B$12)*'🎛️ Premissas'!$B$9*'🎛️ Premissas'!$B$17)+E52*('🎛️ Premissas'!$B$18*('🎛️ Premissas'!$B$19*('🎛️ Premissas'!$B$10/1000000)+'🎛️ Premissas'!$B$20*('🎛️ Premissas'!$B$11/1000000))*(1-'🎛️ Premissas'!$B$12)*'🎛️ Premissas'!$B$9)+E53*(('🎛️ Premissas'!$B$21*('🎛️ Premissas'!$B$19*('🎛️ Premissas'!$B$10/1000000)+'🎛️ Premissas'!$B$20*('🎛️ Premissas'!$B$11/1000000))*(1-'🎛️ Premissas'!$B$12)*'🎛️ Premissas'!$B$9)+('🎛️ Premissas'!$B$22*('🎛️ Premissas'!$B$23*('🎛️ Premissas'!$B$10/1000000)+'🎛️ Premissas'!$B$24*('🎛️ Premissas'!$B$11/1000000))*(1-'🎛️ Premissas'!$B$12)*'🎛️ Premissas'!$B$9))+E54*(('🎛️ Premissas'!$B$25*('🎛️ Premissas'!$B$19*('🎛️ Premissas'!$B$10/1000000)+'🎛️ Premissas'!$B$20*('🎛️ Premissas'!$B$11/1000000))*(1-'🎛️ Premissas'!$B$12)*'🎛️ Premissas'!$B$9)+('🎛️ Premissas'!$B$26*('🎛️ Premissas'!$B$23*('🎛️ Premissas'!$B$10/1000000)+'🎛️ Premissas'!$B$24*('🎛️ Premissas'!$B$11/1000000))*(1-'🎛️ Premissas'!$B$12)*'🎛️ Premissas'!$B$9)) -> 13871.637 | F57: =F51*('🎛️ Premissas'!$B$14*('🎛️ Premissas'!$B$15*('🎛️ Premissas'!$G$9/1000000)+'🎛️ Premissas'!$B$16*('🎛️ Premissas'!$G$10/1000000))*(1-'🎛️ Premissas'!$B$12)*'🎛️ Premissas'!$B$9*'🎛️ Premissas'!$B$17)+F52*('🎛️ Premissas'!$B$18*('🎛️ Premissas'!$B$19*('🎛️ Premissas'!$B$10/1000000)+'🎛️ Premissas'!$B$20*('🎛️ Premissas'!$B$11/1000000))*(1-'🎛️ Premissas'!$B$12)*'🎛️ Premissas'!$B$9)+F53*(('🎛️ Premissas'!$B$21*('🎛️ Premissas'!$B$19*('🎛️ Premissas'!$B$10/1000000)+'🎛️ Premissas'!$B$20*('🎛️ Premissas'!$B$11/1000000))*(1-'🎛️ Premissas'!$B$12)*'🎛️ Premissas'!$B$9)+('🎛️ Premissas'!$B$22*('🎛️ Premissas'!$B$23*('🎛️ Premissas'!$B$10/1000000)+'🎛️ Premissas'!$B$24*('🎛️ Premissas'!$B$11/1000000))*(1-'🎛️ Premissas'!$B$12)*'🎛️ Premissas'!$B$9))+F54*(('🎛️ Premissas'!$B$25*('🎛️ Premissas'!$B$19*('🎛️ Premissas'!$B$10/1000000)+'🎛️ Premissas'!$B$20*('🎛️ Premissas'!$B$11/1000000))*(1-'🎛️ Premissas'!$B$12)*'🎛️ Premissas'!$B$9)+('🎛️ Premissas'!$B$26*('🎛️ Premissas'!$B$23*('🎛️ Premissas'!$B$10/1000000)+'🎛️ Premissas'!$B$24*('🎛️ Premissas'!$B$11/1000000))*(1-'🎛️ Premissas'!$B$12)*'🎛️ Premissas'!$B$9)) -> 17339.546 | G57: =G51*('🎛️ Premissas'!$B$14*('🎛️ Premissas'!$B$15*('🎛️ Premissas'!$G$9/1000000)+'🎛️ Premissas'!$B$16*('🎛️ Premissas'!$G$10/1000000))*(1-'🎛️ Premissas'!$B$12)*'🎛️ Premissas'!$B$9*'🎛️ Premissas'!$B$17)+G52*('🎛️ Premissas'!$B$18*('🎛️ Premissas'!$B$19*('🎛️ Premissas'!$B$10/1000000)+'🎛️ Premissas'!$B$20*('🎛️ Premissas'!$B$11/1000000))*(1-'🎛️ Premissas'!$B$12)*'🎛️ Premissas'!$B$9)+G53*(('🎛️ Premissas'!$B$21*('🎛️ Premissas'!$B$19*('🎛️ Premissas'!$B$10/1000000)+'🎛️ Premissas'!$B$20*('🎛️ Premissas'!$B$11/1000000))*(1-'🎛️ Premissas'!$B$12)*'🎛️ Premissas'!$B$9)+('🎛️ Premissas'!$B$22*('🎛️ Premissas'!$B$23*('🎛️ Premissas'!$B$10/1000000)+'🎛️ Premissas'!$B$24*('🎛️ Premissas'!$B$11/1000000))*(1-'🎛️ Premissas'!$B$12)*'🎛️ Premissas'!$B$9))+G54*(('🎛️ Premissas'!$B$25*('🎛️ Premissas'!$B$19*('🎛️ Premissas'!$B$10/1000000)+'🎛️ Premissas'!$B$20*('🎛️ Premissas'!$B$11/1000000))*(1-'🎛️ Premissas'!$B$12)*'🎛️ Premissas'!$B$9)+('🎛️ Premissas'!$B$26*('🎛️ Premissas'!$B$23*('🎛️ Premissas'!$B$10/1000000)+'🎛️ Premissas'!$B$24*('🎛️ Premissas'!$B$11/1000000))*(1-'🎛️ Premissas'!$B$12)*'🎛️ Premissas'!$B$9)) -> 20807.456 | H57: =H51*('🎛️ Premissas'!$B$14*('🎛️ Premissas'!$B$15*('🎛️ Premissas'!$G$9/1000000)+'🎛️ Premissas'!$B$16*('🎛️ Premissas'!$G$10/1000000))*(1-'🎛️ Premissas'!$B$12)*'🎛️ Premissas'!$B$9*'🎛️ Premissas'!$B$17)+H52*('🎛️ Premissas'!$B$18*('🎛️ Premissas'!$B$19*('🎛️ Premissas'!$B$10/1000000)+'🎛️ Premissas'!$B$20*('🎛️ Premissas'!$B$11/1000000))*(1-'🎛️ Premissas'!$B$12)*'🎛️ Premissas'!$B$9)+H53*(('🎛️ Premissas'!$B$21*('🎛️ Premissas'!$B$19*('🎛️ Premissas'!$B$10/1000000)+'🎛️ Premissas'!$B$20*('🎛️ Premissas'!$B$11/1000000))*(1-'🎛️ Premissas'!$B$12)*'🎛️ Premissas'!$B$9)+('🎛️ Premissas'!$B$22*('🎛️ Premissas'!$B$23*('🎛️ Premissas'!$B$10/1000000)+'🎛️ Premissas'!$B$24*('🎛️ Premissas'!$B$11/1000000))*(1-'🎛️ Premissas'!$B$12)*'🎛️ Premissas'!$B$9))+H54*(('🎛️ Premissas'!$B$25*('🎛️ Premissas'!$B$19*('🎛️ Premissas'!$B$10/1000000)+'🎛️ Premissas'!$B$20*('🎛️ Premissas'!$B$11/1000000))*(1-'🎛️ Premissas'!$B$12)*'🎛️ Premissas'!$B$9)+('🎛️ Premissas'!$B$26*('🎛️ Premissas'!$B$23*('🎛️ Premissas'!$B$10/1000000)+'🎛️ Premissas'!$B$24*('🎛️ Premissas'!$B$11/1000000))*(1-'🎛️ Premissas'!$B$12)*'🎛️ Premissas'!$B$9)) -> 24275.365 | I57: =I51*('🎛️ Premissas'!$B$14*('🎛️ Premissas'!$B$15*('🎛️ Premissas'!$G$9/1000000)+'🎛️ Premissas'!$B$16*('🎛️ Premissas'!$G$10/1000000))*(1-'🎛️ Premissas'!$B$12)*'🎛️ Premissas'!$B$9*'🎛️ Premissas'!$B$17)+I52*('🎛️ Premissas'!$B$18*('🎛️ Premissas'!$B$19*('🎛️ Premissas'!$B$10/1000000)+'🎛️ Premissas'!$B$20*('🎛️ Premissas'!$B$11/1000000))*(1-'🎛️ Premissas'!$B$12)*'🎛️ Premissas'!$B$9)+I53*(('🎛️ Premissas'!$B$21*('🎛️ Premissas'!$B$19*('🎛️ Premissas'!$B$10/1000000)+'🎛️ Premissas'!$B$20*('🎛️ Premissas'!$B$11/1000000))*(1-'🎛️ Premissas'!$B$12)*'🎛️ Premissas'!$B$9)+('🎛️ Premissas'!$B$22*('🎛️ Premissas'!$B$23*('🎛️ Premissas'!$B$10/1000000)+'🎛️ Premissas'!$B$24*('🎛️ Premissas'!$B$11/1000000))*(1-'🎛️ Premissas'!$B$12)*'🎛️ Premissas'!$B$9))+I54*(('🎛️ Premissas'!$B$25*('🎛️ Premissas'!$B$19*('🎛️ Premissas'!$B$10/1000000)+'🎛️ Premissas'!$B$20*('🎛️ Premissas'!$B$11/1000000))*(1-'🎛️ Premissas'!$B$12)*'🎛️ Premissas'!$B$9)+('🎛️ Premissas'!$B$26*('🎛️ Premissas'!$B$23*('🎛️ Premissas'!$B$10/1000000)+'🎛️ Premissas'!$B$24*('🎛️ Premissas'!$B$11/1000000))*(1-'🎛️ Premissas'!$B$12)*'🎛️ Premissas'!$B$9)) -> 27743.274 | ... Y57: =Y51*('🎛️ Premissas'!$B$14*('🎛️ Premissas'!$B$15*('🎛️ Premissas'!$G$9/1000000)+'🎛️ Premissas'!$B$16*('🎛️ Premissas'!$G$10/1000000))*(1-'🎛️ Premissas'!$B$12)*'🎛️ Premissas'!$B$9*'🎛️ Premissas'!$B$17)+Y52*('🎛️ Premissas'!$B$18*('🎛️ Premissas'!$B$19*('🎛️ Premissas'!$B$10/1000000)+'🎛️ Premissas'!$B$20*('🎛️ Premissas'!$B$11/1000000))*(1-'🎛️ Premissas'!$B$12)*'🎛️ Premissas'!$B$9)+Y53*(('🎛️ Premissas'!$B$21*('🎛️ Premissas'!$B$19*('🎛️ Premissas'!$B$10/1000000)+'🎛️ Premissas'!$B$20*('🎛️ Premissas'!$B$11/1000000))*(1-'🎛️ Premissas'!$B$12)*'🎛️ Premissas'!$B$9)+('🎛️ Premissas'!$B$22*('🎛️ Premissas'!$B$23*('🎛️ Premissas'!$B$10/1000000)+'🎛️ Premissas'!$B$24*('🎛️ Premissas'!$B$11/1000000))*(1-'🎛️ Premissas'!$B$12)*'🎛️ Premissas'!$B$9))+Y54*(('🎛️ Premissas'!$B$25*('🎛️ Premissas'!$B$19*('🎛️ Premissas'!$B$10/1000000)+'🎛️ Premissas'!$B$20*('🎛️ Premissas'!$B$11/1000000))*(1-'🎛️ Premissas'!$B$12)*'🎛️ Premissas'!$B$9)+('🎛️ Premissas'!$B$26*('🎛️ Premissas'!$B$23*('🎛️ Premissas'!$B$10/1000000)+'🎛️ Premissas'!$B$24*('🎛️ Premissas'!$B$11/1000000))*(1-'🎛️ Premissas'!$B$12)*'🎛️ Premissas'!$B$9)) -> 211523.06
A58: Custo Fixo | B58: ='🎛️ Premissas'!$B$37+'🎛️ Premissas'!$B$39+'🎛️ Premissas'!$B$41+'🎛️ Premissas'!$B$43 -> 55000 | C58: ='🎛️ Premissas'!$B$37+'🎛️ Premissas'!$B$39+'🎛️ Premissas'!$B$41+'🎛️ Premissas'!$B$43 -> 55000 | D58: ='🎛️ Premissas'!$B$37+'🎛️ Premissas'!$B$39+'🎛️ Premissas'!$B$41+'🎛️ Premissas'!$B$43 -> 55000 | E58: ='🎛️ Premissas'!$B$37+'🎛️ Premissas'!$B$39+'🎛️ Premissas'!$B$41+'🎛️ Premissas'!$B$43 -> 55000 | F58: ='🎛️ Premissas'!$B$37+'🎛️ Premissas'!$B$39+'🎛️ Premissas'!$B$41+'🎛️ Premissas'!$B$43 -> 55000 | G58: ='🎛️ Premissas'!$B$37+'🎛️ Premissas'!$B$39+'🎛️ Premissas'!$B$41+'🎛️ Premissas'!$B$43 -> 55000 | H58: ='🎛️ Premissas'!$B$37+'🎛️ Premissas'!$B$39+'🎛️ Premissas'!$B$41+'🎛️ Premissas'!$B$43 -> 55000 | I58: ='🎛️ Premissas'!$B$37+'🎛️ Premissas'!$B$39+'🎛️ Premissas'!$B$41+'🎛️ Premissas'!$B$43 -> 55000 | ... M58: ='🎛️ Premissas'!$B$37+'🎛️ Premissas'!$B$39+'🎛️ Premissas'!$B$41+'🎛️ Premissas'!$B$43 -> 55000 | N58: ='🎛️ Premissas'!$B$38+'🎛️ Premissas'!$B$40+'🎛️ Premissas'!$B$42+'🎛️ Premissas'!$B$43 -> 70000 | O58: ='🎛️ Premissas'!$B$38+'🎛️ Premissas'!$B$40+'🎛️ Premissas'!$B$42+'🎛️ Premissas'!$B$43 -> 70000 | P58: ='🎛️ Premissas'!$B$38+'🎛️ Premissas'!$B$40+'🎛️ Premissas'!$B$42+'🎛️ Premissas'!$B$43 -> 70000 | Q58: ='🎛️ Premissas'!$B$38+'🎛️ Premissas'!$B$40+'🎛️ Premissas'!$B$42+'🎛️ Premissas'!$B$43 -> 70000 | R58: ='🎛️ Premissas'!$B$38+'🎛️ Premissas'!$B$40+'🎛️ Premissas'!$B$42+'🎛️ Premissas'!$B$43 -> 70000 | S58: ='🎛️ Premissas'!$B$38+'🎛️ Premissas'!$B$40+'🎛️ Premissas'!$B$42+'🎛️ Premissas'!$B$43 -> 70000 | T58: ='🎛️ Premissas'!$B$38+'🎛️ Premissas'!$B$40+'🎛️ Premissas'!$B$42+'🎛️ Premissas'!$B$43 -> 70000 | U58: ='🎛️ Premissas'!$B$38+'🎛️ Premissas'!$B$40+'🎛️ Premissas'!$B$42+'🎛️ Premissas'!$B$43 -> 70000 | ... Y58: ='🎛️ Premissas'!$B$38+'🎛️ Premissas'!$B$40+'🎛️ Premissas'!$B$42+'🎛️ Premissas'!$B$43 -> 70000
A59: Impostos | B59: =B56*'🎛️ Premissas'!$B$67 -> 1940.04 | C59: =C56*'🎛️ Premissas'!$B$67 -> 3880.08 | D59: =D56*'🎛️ Premissas'!$B$67 -> 5820.12 | E59: =E56*'🎛️ Premissas'!$B$67 -> 7760.16 | F59: =F56*'🎛️ Premissas'!$B$67 -> 9700.2 | G59: =G56*'🎛️ Premissas'!$B$67 -> 11640.24 | H59: =H56*'🎛️ Premissas'!$B$67 -> 13580.28 | I59: =I56*'🎛️ Premissas'!$B$67 -> 15520.32 | ... Y59: =Y56*'🎛️ Premissas'!$B$67 -> 147631.64
A60: Resultado Mensal | B60: =B56-B57-B58-B59 -> -44240.949 | C60: =C56-C57-C58-C59 -> -33481.899 | D60: =D56-D57-D58-D59 -> -22722.848 | E60: =E56-E57-E58-E59 -> -11963.797 | F60: =F56-F57-F58-F59 -> -1204.7462 | G60: =G56-G57-G58-G59 -> 9554.3045 | H60: =H56-H57-H58-H59 -> 20313.355 | I60: =I56-I57-I58-I59 -> 31072.406 | ... Y60: =Y56-Y57-Y58-Y59 -> 801109
A62: BASE
A63: Free Cadastros | B63: ='🎛️ Premissas'!$B$61 -> 3000 | C63: =B63+'🎛️ Premissas'!$C$28 -> 6500 | D63: =C63+'🎛️ Premissas'!$C$28 -> 10000 | E63: =D63+'🎛️ Premissas'!$C$28 -> 13500 | F63: =E63+'🎛️ Premissas'!$C$28 -> 17000 | G63: =F63+'🎛️ Premissas'!$C$28 -> 20500 | H63: =G63+'🎛️ Premissas'!$C$28 -> 24000 | I63: =H63+'🎛️ Premissas'!$C$28 -> 27500 | J63: =I63+'🎛️ Premissas'!$C$28 -> 31000 | ... M63: =L63+'🎛️ Premissas'!$C$28 -> 41500 | N63: =M63+'🎛️ Premissas'!$C$29 -> 45500 | O63: =N63+'🎛️ Premissas'!$C$29 -> 49500 | P63: =O63+'🎛️ Premissas'!$C$29 -> 53500 | Q63: =P63+'🎛️ Premissas'!$C$29 -> 57500 | R63: =Q63+'🎛️ Premissas'!$C$29 -> 61500 | S63: =R63+'🎛️ Premissas'!$C$29 -> 65500 | T63: =S63+'🎛️ Premissas'!$C$29 -> 69500 | U63: =T63+'🎛️ Premissas'!$C$29 -> 73500 | ... Y63: =X63+'🎛️ Premissas'!$C$29 -> 89500
A64: Essencial | B64: =ROUND(B63*'🎛️ Premissas'!$C$30,0) -> 240 | C64: =ROUND(C63*'🎛️ Premissas'!$C$30,0) -> 520 | D64: =ROUND(D63*'🎛️ Premissas'!$C$30,0) -> 800 | E64: =ROUND(E63*'🎛️ Premissas'!$C$30,0) -> 1080 | F64: =ROUND(F63*'🎛️ Premissas'!$C$30,0) -> 1360 | G64: =ROUND(G63*'🎛️ Premissas'!$C$30,0) -> 1640 | H64: =ROUND(H63*'🎛️ Premissas'!$C$30,0) -> 1920 | I64: =ROUND(I63*'🎛️ Premissas'!$C$30,0) -> 2200 | ... P64: =ROUND(P63*'🎛️ Premissas'!$C$30,0) -> 4280 | Q64: =ROUND(P64*(1-'🎛️ Premissas'!$C$33)+MAX(0,Q63-P67)*'🎛️ Premissas'!$C$30,0) -> 7938 | R64: =ROUND(Q64*(1-'🎛️ Premissas'!$C$33)+MAX(0,R63-Q67)*'🎛️ Premissas'!$C$30,0) -> 11325 | S64: =ROUND(R64*(1-'🎛️ Premissas'!$C$33)+MAX(0,S63-R67)*'🎛️ Premissas'!$C$30,0) -> 14474 | T64: =ROUND(S64*(1-'🎛️ Premissas'!$C$33)+MAX(0,T63-S67)*'🎛️ Premissas'!$C$30,0) -> 17413 | U64: =ROUND(T64*(1-'🎛️ Premissas'!$C$33)+MAX(0,U63-T67)*'🎛️ Premissas'!$C$30,0) -> 20169 | V64: =ROUND(U64*(1-'🎛️ Premissas'!$C$33)+MAX(0,V63-U67)*'🎛️ Premissas'!$C$30,0) -> 22764 | W64: =ROUND(V64*(1-'🎛️ Premissas'!$C$33)+MAX(0,W63-V67)*'🎛️ Premissas'!$C$30,0) -> 25218 | X64: =ROUND(W64*(1-'🎛️ Premissas'!$C$33)+MAX(0,X63-W67)*'🎛️ Premissas'!$C$30,0) -> 27549 | Y64: =ROUND(X64*(1-'🎛️ Premissas'!$C$33)+MAX(0,Y63-X67)*'🎛️ Premissas'!$C$30,0) -> 29773
A65: Autônoma | B65: =ROUND(B63*'🎛️ Premissas'!$C$31,0) -> 120 | C65: =ROUND(C63*'🎛️ Premissas'!$C$31,0) -> 260 | D65: =ROUND(D63*'🎛️ Premissas'!$C$31,0) -> 400 | E65: =ROUND(E63*'🎛️ Premissas'!$C$31,0) -> 540 | F65: =ROUND(F63*'🎛️ Premissas'!$C$31,0) -> 680 | G65: =ROUND(G63*'🎛️ Premissas'!$C$31,0) -> 820 | H65: =ROUND(H63*'🎛️ Premissas'!$C$31,0) -> 960 | I65: =ROUND(I63*'🎛️ Premissas'!$C$31,0) -> 1100 | ... P65: =ROUND(P63*'🎛️ Premissas'!$C$31,0) -> 2140 | Q65: =ROUND(P65*(1-'🎛️ Premissas'!$C$34)+MAX(0,Q64-P65-P66)*'🎛️ Premissas'!$C$31,0) -> 2222 | R65: =ROUND(Q65*(1-'🎛️ Premissas'!$C$34)+MAX(0,R64-Q65-Q66)*'🎛️ Premissas'!$C$31,0) -> 2433 | S65: =ROUND(R65*(1-'🎛️ Premissas'!$C$34)+MAX(0,S64-R65-R66)*'🎛️ Premissas'!$C$31,0) -> 2751 | T65: =ROUND(S65*(1-'🎛️ Premissas'!$C$34)+MAX(0,T64-S65-S66)*'🎛️ Premissas'!$C$31,0) -> 3158 | U65: =ROUND(T65*(1-'🎛️ Premissas'!$C$34)+MAX(0,U64-T65-T66)*'🎛️ Premissas'!$C$31,0) -> 3638 | V65: =ROUND(U65*(1-'🎛️ Premissas'!$C$34)+MAX(0,V64-U65-U66)*'🎛️ Premissas'!$C$31,0) -> 4178 | W65: =ROUND(V65*(1-'🎛️ Premissas'!$C$34)+MAX(0,W64-V65-V66)*'🎛️ Premissas'!$C$31,0) -> 4766 | X65: =ROUND(W65*(1-'🎛️ Premissas'!$C$34)+MAX(0,X64-W65-W66)*'🎛️ Premissas'!$C$31,0) -> 5393 | Y65: =ROUND(X65*(1-'🎛️ Premissas'!$C$34)+MAX(0,Y64-X65-X66)*'🎛️ Premissas'!$C$31,0) -> 6050
A66: Livre | B66: =ROUND(B63*'🎛️ Premissas'!$C$32,0) -> 60 | C66: =ROUND(C63*'🎛️ Premissas'!$C$32,0) -> 130 | D66: =ROUND(D63*'🎛️ Premissas'!$C$32,0) -> 200 | E66: =ROUND(E63*'🎛️ Premissas'!$C$32,0) -> 270 | F66: =ROUND(F63*'🎛️ Premissas'!$C$32,0) -> 340 | G66: =ROUND(G63*'🎛️ Premissas'!$C$32,0) -> 410 | H66: =ROUND(H63*'🎛️ Premissas'!$C$32,0) -> 480 | I66: =ROUND(I63*'🎛️ Premissas'!$C$32,0) -> 550 | ... P66: =ROUND(P63*'🎛️ Premissas'!$C$32,0) -> 1070 | Q66: =ROUND(P66*(1-'🎛️ Premissas'!$C$35)+MAX(0,Q65-P66)*'🎛️ Premissas'!$C$32,0) -> 1061 | R66: =ROUND(Q66*(1-'🎛️ Premissas'!$C$35)+MAX(0,R65-Q66)*'🎛️ Premissas'!$C$32,0) -> 1057 | S66: =ROUND(R66*(1-'🎛️ Premissas'!$C$35)+MAX(0,S65-R66)*'🎛️ Premissas'!$C$32,0) -> 1059 | T66: =ROUND(S66*(1-'🎛️ Premissas'!$C$35)+MAX(0,T65-S66)*'🎛️ Premissas'!$C$32,0) -> 1069 | U66: =ROUND(T66*(1-'🎛️ Premissas'!$C$35)+MAX(0,U65-T66)*'🎛️ Premissas'!$C$32,0) -> 1088 | V66: =ROUND(U66*(1-'🎛️ Premissas'!$C$35)+MAX(0,V65-U66)*'🎛️ Premissas'!$C$32,0) -> 1117 | W66: =ROUND(V66*(1-'🎛️ Premissas'!$C$35)+MAX(0,W65-V66)*'🎛️ Premissas'!$C$32,0) -> 1156 | X66: =ROUND(W66*(1-'🎛️ Premissas'!$C$35)+MAX(0,X65-W66)*'🎛️ Premissas'!$C$32,0) -> 1206 | Y66: =ROUND(X66*(1-'🎛️ Premissas'!$C$35)+MAX(0,Y65-X66)*'🎛️ Premissas'!$C$32,0) -> 1267
A67: Total Pagantes | B67: =SUM(B64:B66) -> 420 | C67: =SUM(C64:C66) -> 910 | D67: =SUM(D64:D66) -> 1400 | E67: =SUM(E64:E66) -> 1890 | F67: =SUM(F64:F66) -> 2380 | G67: =SUM(G64:G66) -> 2870 | H67: =SUM(H64:H66) -> 3360 | I67: =SUM(I64:I66) -> 3850 | ... Y67: =SUM(Y64:Y66) -> 37090
A68: MRR | B68: =B64*'🎛️ Premissas'!$C$5+B65*'🎛️ Premissas'!$C$6+B66*'🎛️ Premissas'!$C$7 -> 23958 | C68: =C64*'🎛️ Premissas'!$C$5+C65*'🎛️ Premissas'!$C$6+C66*'🎛️ Premissas'!$C$7 -> 51909 | D68: =D64*'🎛️ Premissas'!$C$5+D65*'🎛️ Premissas'!$C$6+D66*'🎛️ Premissas'!$C$7 -> 79860 | E68: =E64*'🎛️ Premissas'!$C$5+E65*'🎛️ Premissas'!$C$6+E66*'🎛️ Premissas'!$C$7 -> 107811 | F68: =F64*'🎛️ Premissas'!$C$5+F65*'🎛️ Premissas'!$C$6+F66*'🎛️ Premissas'!$C$7 -> 135762 | G68: =G64*'🎛️ Premissas'!$C$5+G65*'🎛️ Premissas'!$C$6+G66*'🎛️ Premissas'!$C$7 -> 163713 | H68: =H64*'🎛️ Premissas'!$C$5+H65*'🎛️ Premissas'!$C$6+H66*'🎛️ Premissas'!$C$7 -> 191664 | I68: =I64*'🎛️ Premissas'!$C$5+I65*'🎛️ Premissas'!$C$6+I66*'🎛️ Premissas'!$C$7 -> 219615 | ... Y68: =Y64*'🎛️ Premissas'!$C$5+Y65*'🎛️ Premissas'!$C$6+Y66*'🎛️ Premissas'!$C$7 -> 1949301
A69: API Total | B69: =B63*('🎛️ Premissas'!$C$14*('🎛️ Premissas'!$C$15*('🎛️ Premissas'!$G$9/1000000)+'🎛️ Premissas'!$C$16*('🎛️ Premissas'!$G$10/1000000))*(1-'🎛️ Premissas'!$C$12)*'🎛️ Premissas'!$C$9*'🎛️ Premissas'!$C$17)+B64*('🎛️ Premissas'!$C$18*('🎛️ Premissas'!$C$19*('🎛️ Premissas'!$C$10/1000000)+'🎛️ Premissas'!$C$20*('🎛️ Premissas'!$C$11/1000000))*(1-'🎛️ Premissas'!$C$12)*'🎛️ Premissas'!$C$9)+B65*(('🎛️ Premissas'!$C$21*('🎛️ Premissas'!$C$19*('🎛️ Premissas'!$C$10/1000000)+'🎛️ Premissas'!$C$20*('🎛️ Premissas'!$C$11/1000000))*(1-'🎛️ Premissas'!$C$12)*'🎛️ Premissas'!$C$9)+('🎛️ Premissas'!$C$22*('🎛️ Premissas'!$C$23*('🎛️ Premissas'!$C$10/1000000)+'🎛️ Premissas'!$C$24*('🎛️ Premissas'!$C$11/1000000))*(1-'🎛️ Premissas'!$C$12)*'🎛️ Premissas'!$C$9))+B66*(('🎛️ Premissas'!$C$25*('🎛️ Premissas'!$C$19*('🎛️ Premissas'!$C$10/1000000)+'🎛️ Premissas'!$C$20*('🎛️ Premissas'!$C$11/1000000))*(1-'🎛️ Premissas'!$C$12)*'🎛️ Premissas'!$C$9)+('🎛️ Premissas'!$C$26*('🎛️ Premissas'!$C$23*('🎛️ Premissas'!$C$10/1000000)+'🎛️ Premissas'!$C$24*('🎛️ Premissas'!$C$11/1000000))*(1-'🎛️ Premissas'!$C$12)*'🎛️ Premissas'!$C$9)) -> 4667.6358 | C69: =C63*('🎛️ Premissas'!$C$14*('🎛️ Premissas'!$C$15*('🎛️ Premissas'!$G$9/1000000)+'🎛️ Premissas'!$C$16*('🎛️ Premissas'!$G$10/1000000))*(1-'🎛️ Premissas'!$C$12)*'🎛️ Premissas'!$C$9*'🎛️ Premissas'!$C$17)+C64*('🎛️ Premissas'!$C$18*('🎛️ Premissas'!$C$19*('🎛️ Premissas'!$C$10/1000000)+'🎛️ Premissas'!$C$20*('🎛️ Premissas'!$C$11/1000000))*(1-'🎛️ Premissas'!$C$12)*'🎛️ Premissas'!$C$9)+C65*(('🎛️ Premissas'!$C$21*('🎛️ Premissas'!$C$19*('🎛️ Premissas'!$C$10/1000000)+'🎛️ Premissas'!$C$20*('🎛️ Premissas'!$C$11/1000000))*(1-'🎛️ Premissas'!$C$12)*'🎛️ Premissas'!$C$9)+('🎛️ Premissas'!$C$22*('🎛️ Premissas'!$C$23*('🎛️ Premissas'!$C$10/1000000)+'🎛️ Premissas'!$C$24*('🎛️ Premissas'!$C$11/1000000))*(1-'🎛️ Premissas'!$C$12)*'🎛️ Premissas'!$C$9))+C66*(('🎛️ Premissas'!$C$25*('🎛️ Premissas'!$C$19*('🎛️ Premissas'!$C$10/1000000)+'🎛️ Premissas'!$C$20*('🎛️ Premissas'!$C$11/1000000))*(1-'🎛️ Premissas'!$C$12)*'🎛️ Premissas'!$C$9)+('🎛️ Premissas'!$C$26*('🎛️ Premissas'!$C$23*('🎛️ Premissas'!$C$10/1000000)+'🎛️ Premissas'!$C$24*('🎛️ Premissas'!$C$11/1000000))*(1-'🎛️ Premissas'!$C$12)*'🎛️ Premissas'!$C$9)) -> 10113.211 | D69: =D63*('🎛️ Premissas'!$C$14*('🎛️ Premissas'!$C$15*('🎛️ Premissas'!$G$9/1000000)+'🎛️ Premissas'!$C$16*('🎛️ Premissas'!$G$10/1000000))*(1-'🎛️ Premissas'!$C$12)*'🎛️ Premissas'!$C$9*'🎛️ Premissas'!$C$17)+D64*('🎛️ Premissas'!$C$18*('🎛️ Premissas'!$C$19*('🎛️ Premissas'!$C$10/1000000)+'🎛️ Premissas'!$C$20*('🎛️ Premissas'!$C$11/1000000))*(1-'🎛️ Premissas'!$C$12)*'🎛️ Premissas'!$C$9)+D65*(('🎛️ Premissas'!$C$21*('🎛️ Premissas'!$C$19*('🎛️ Premissas'!$C$10/1000000)+'🎛️ Premissas'!$C$20*('🎛️ Premissas'!$C$11/1000000))*(1-'🎛️ Premissas'!$C$12)*'🎛️ Premissas'!$C$9)+('🎛️ Premissas'!$C$22*('🎛️ Premissas'!$C$23*('🎛️ Premissas'!$C$10/1000000)+'🎛️ Premissas'!$C$24*('🎛️ Premissas'!$C$11/1000000))*(1-'🎛️ Premissas'!$C$12)*'🎛️ Premissas'!$C$9))+D66*(('🎛️ Premissas'!$C$25*('🎛️ Premissas'!$C$19*('🎛️ Premissas'!$C$10/1000000)+'🎛️ Premissas'!$C$20*('🎛️ Premissas'!$C$11/1000000))*(1-'🎛️ Premissas'!$C$12)*'🎛️ Premissas'!$C$9)+('🎛️ Premissas'!$C$26*('🎛️ Premissas'!$C$23*('🎛️ Premissas'!$C$10/1000000)+'🎛️ Premissas'!$C$24*('🎛️ Premissas'!$C$11/1000000))*(1-'🎛️ Premissas'!$C$12)*'🎛️ Premissas'!$C$9)) -> 15558.786 | E69: =E63*('🎛️ Premissas'!$C$14*('🎛️ Premissas'!$C$15*('🎛️ Premissas'!$G$9/1000000)+'🎛️ Premissas'!$C$16*('🎛️ Premissas'!$G$10/1000000))*(1-'🎛️ Premissas'!$C$12)*'🎛️ Premissas'!$C$9*'🎛️ Premissas'!$C$17)+E64*('🎛️ Premissas'!$C$18*('🎛️ Premissas'!$C$19*('🎛️ Premissas'!$C$10/1000000)+'🎛️ Premissas'!$C$20*('🎛️ Premissas'!$C$11/1000000))*(1-'🎛️ Premissas'!$C$12)*'🎛️ Premissas'!$C$9)+E65*(('🎛️ Premissas'!$C$21*('🎛️ Premissas'!$C$19*('🎛️ Premissas'!$C$10/1000000)+'🎛️ Premissas'!$C$20*('🎛️ Premissas'!$C$11/1000000))*(1-'🎛️ Premissas'!$C$12)*'🎛️ Premissas'!$C$9)+('🎛️ Premissas'!$C$22*('🎛️ Premissas'!$C$23*('🎛️ Premissas'!$C$10/1000000)+'🎛️ Premissas'!$C$24*('🎛️ Premissas'!$C$11/1000000))*(1-'🎛️ Premissas'!$C$12)*'🎛️ Premissas'!$C$9))+E66*(('🎛️ Premissas'!$C$25*('🎛️ Premissas'!$C$19*('🎛️ Premissas'!$C$10/1000000)+'🎛️ Premissas'!$C$20*('🎛️ Premissas'!$C$11/1000000))*(1-'🎛️ Premissas'!$C$12)*'🎛️ Premissas'!$C$9)+('🎛️ Premissas'!$C$26*('🎛️ Premissas'!$C$23*('🎛️ Premissas'!$C$10/1000000)+'🎛️ Premissas'!$C$24*('🎛️ Premissas'!$C$11/1000000))*(1-'🎛️ Premissas'!$C$12)*'🎛️ Premissas'!$C$9)) -> 21004.361 | F69: =F63*('🎛️ Premissas'!$C$14*('🎛️ Premissas'!$C$15*('🎛️ Premissas'!$G$9/1000000)+'🎛️ Premissas'!$C$16*('🎛️ Premissas'!$G$10/1000000))*(1-'🎛️ Premissas'!$C$12)*'🎛️ Premissas'!$C$9*'🎛️ Premissas'!$C$17)+F64*('🎛️ Premissas'!$C$18*('🎛️ Premissas'!$C$19*('🎛️ Premissas'!$C$10/1000000)+'🎛️ Premissas'!$C$20*('🎛️ Premissas'!$C$11/1000000))*(1-'🎛️ Premissas'!$C$12)*'🎛️ Premissas'!$C$9)+F65*(('🎛️ Premissas'!$C$21*('🎛️ Premissas'!$C$19*('🎛️ Premissas'!$C$10/1000000)+'🎛️ Premissas'!$C$20*('🎛️ Premissas'!$C$11/1000000))*(1-'🎛️ Premissas'!$C$12)*'🎛️ Premissas'!$C$9)+('🎛️ Premissas'!$C$22*('🎛️ Premissas'!$C$23*('🎛️ Premissas'!$C$10/1000000)+'🎛️ Premissas'!$C$24*('🎛️ Premissas'!$C$11/1000000))*(1-'🎛️ Premissas'!$C$12)*'🎛️ Premissas'!$C$9))+F66*(('🎛️ Premissas'!$C$25*('🎛️ Premissas'!$C$19*('🎛️ Premissas'!$C$10/1000000)+'🎛️ Premissas'!$C$20*('🎛️ Premissas'!$C$11/1000000))*(1-'🎛️ Premissas'!$C$12)*'🎛️ Premissas'!$C$9)+('🎛️ Premissas'!$C$26*('🎛️ Premissas'!$C$23*('🎛️ Premissas'!$C$10/1000000)+'🎛️ Premissas'!$C$24*('🎛️ Premissas'!$C$11/1000000))*(1-'🎛️ Premissas'!$C$12)*'🎛️ Premissas'!$C$9)) -> 26449.936 | G69: =G63*('🎛️ Premissas'!$C$14*('🎛️ Premissas'!$C$15*('🎛️ Premissas'!$G$9/1000000)+'🎛️ Premissas'!$C$16*('🎛️ Premissas'!$G$10/1000000))*(1-'🎛️ Premissas'!$C$12)*'🎛️ Premissas'!$C$9*'🎛️ Premissas'!$C$17)+G64*('🎛️ Premissas'!$C$18*('🎛️ Premissas'!$C$19*('🎛️ Premissas'!$C$10/1000000)+'🎛️ Premissas'!$C$20*('🎛️ Premissas'!$C$11/1000000))*(1-'🎛️ Premissas'!$C$12)*'🎛️ Premissas'!$C$9)+G65*(('🎛️ Premissas'!$C$21*('🎛️ Premissas'!$C$19*('🎛️ Premissas'!$C$10/1000000)+'🎛️ Premissas'!$C$20*('🎛️ Premissas'!$C$11/1000000))*(1-'🎛️ Premissas'!$C$12)*'🎛️ Premissas'!$C$9)+('🎛️ Premissas'!$C$22*('🎛️ Premissas'!$C$23*('🎛️ Premissas'!$C$10/1000000)+'🎛️ Premissas'!$C$24*('🎛️ Premissas'!$C$11/1000000))*(1-'🎛️ Premissas'!$C$12)*'🎛️ Premissas'!$C$9))+G66*(('🎛️ Premissas'!$C$25*('🎛️ Premissas'!$C$19*('🎛️ Premissas'!$C$10/1000000)+'🎛️ Premissas'!$C$20*('🎛️ Premissas'!$C$11/1000000))*(1-'🎛️ Premissas'!$C$12)*'🎛️ Premissas'!$C$9)+('🎛️ Premissas'!$C$26*('🎛️ Premissas'!$C$23*('🎛️ Premissas'!$C$10/1000000)+'🎛️ Premissas'!$C$24*('🎛️ Premissas'!$C$11/1000000))*(1-'🎛️ Premissas'!$C$12)*'🎛️ Premissas'!$C$9)) -> 31895.511 | H69: =H63*('🎛️ Premissas'!$C$14*('🎛️ Premissas'!$C$15*('🎛️ Premissas'!$G$9/1000000)+'🎛️ Premissas'!$C$16*('🎛️ Premissas'!$G$10/1000000))*(1-'🎛️ Premissas'!$C$12)*'🎛️ Premissas'!$C$9*'🎛️ Premissas'!$C$17)+H64*('🎛️ Premissas'!$C$18*('🎛️ Premissas'!$C$19*('🎛️ Premissas'!$C$10/1000000)+'🎛️ Premissas'!$C$20*('🎛️ Premissas'!$C$11/1000000))*(1-'🎛️ Premissas'!$C$12)*'🎛️ Premissas'!$C$9)+H65*(('🎛️ Premissas'!$C$21*('🎛️ Premissas'!$C$19*('🎛️ Premissas'!$C$10/1000000)+'🎛️ Premissas'!$C$20*('🎛️ Premissas'!$C$11/1000000))*(1-'🎛️ Premissas'!$C$12)*'🎛️ Premissas'!$C$9)+('🎛️ Premissas'!$C$22*('🎛️ Premissas'!$C$23*('🎛️ Premissas'!$C$10/1000000)+'🎛️ Premissas'!$C$24*('🎛️ Premissas'!$C$11/1000000))*(1-'🎛️ Premissas'!$C$12)*'🎛️ Premissas'!$C$9))+H66*(('🎛️ Premissas'!$C$25*('🎛️ Premissas'!$C$19*('🎛️ Premissas'!$C$10/1000000)+'🎛️ Premissas'!$C$20*('🎛️ Premissas'!$C$11/1000000))*(1-'🎛️ Premissas'!$C$12)*'🎛️ Premissas'!$C$9)+('🎛️ Premissas'!$C$26*('🎛️ Premissas'!$C$23*('🎛️ Premissas'!$C$10/1000000)+'🎛️ Premissas'!$C$24*('🎛️ Premissas'!$C$11/1000000))*(1-'🎛️ Premissas'!$C$12)*'🎛️ Premissas'!$C$9)) -> 37341.086 | I69: =I63*('🎛️ Premissas'!$C$14*('🎛️ Premissas'!$C$15*('🎛️ Premissas'!$G$9/1000000)+'🎛️ Premissas'!$C$16*('🎛️ Premissas'!$G$10/1000000))*(1-'🎛️ Premissas'!$C$12)*'🎛️ Premissas'!$C$9*'🎛️ Premissas'!$C$17)+I64*('🎛️ Premissas'!$C$18*('🎛️ Premissas'!$C$19*('🎛️ Premissas'!$C$10/1000000)+'🎛️ Premissas'!$C$20*('🎛️ Premissas'!$C$11/1000000))*(1-'🎛️ Premissas'!$C$12)*'🎛️ Premissas'!$C$9)+I65*(('🎛️ Premissas'!$C$21*('🎛️ Premissas'!$C$19*('🎛️ Premissas'!$C$10/1000000)+'🎛️ Premissas'!$C$20*('🎛️ Premissas'!$C$11/1000000))*(1-'🎛️ Premissas'!$C$12)*'🎛️ Premissas'!$C$9)+('🎛️ Premissas'!$C$22*('🎛️ Premissas'!$C$23*('🎛️ Premissas'!$C$10/1000000)+'🎛️ Premissas'!$C$24*('🎛️ Premissas'!$C$11/1000000))*(1-'🎛️ Premissas'!$C$12)*'🎛️ Premissas'!$C$9))+I66*(('🎛️ Premissas'!$C$25*('🎛️ Premissas'!$C$19*('🎛️ Premissas'!$C$10/1000000)+'🎛️ Premissas'!$C$20*('🎛️ Premissas'!$C$11/1000000))*(1-'🎛️ Premissas'!$C$12)*'🎛️ Premissas'!$C$9)+('🎛️ Premissas'!$C$26*('🎛️ Premissas'!$C$23*('🎛️ Premissas'!$C$10/1000000)+'🎛️ Premissas'!$C$24*('🎛️ Premissas'!$C$11/1000000))*(1-'🎛️ Premissas'!$C$12)*'🎛️ Premissas'!$C$9)) -> 42786.662 | ... Y69: =Y63*('🎛️ Premissas'!$C$14*('🎛️ Premissas'!$C$15*('🎛️ Premissas'!$G$9/1000000)+'🎛️ Premissas'!$C$16*('🎛️ Premissas'!$G$10/1000000))*(1-'🎛️ Premissas'!$C$12)*'🎛️ Premissas'!$C$9*'🎛️ Premissas'!$C$17)+Y64*('🎛️ Premissas'!$C$18*('🎛️ Premissas'!$C$19*('🎛️ Premissas'!$C$10/1000000)+'🎛️ Premissas'!$C$20*('🎛️ Premissas'!$C$11/1000000))*(1-'🎛️ Premissas'!$C$12)*'🎛️ Premissas'!$C$9)+Y65*(('🎛️ Premissas'!$C$21*('🎛️ Premissas'!$C$19*('🎛️ Premissas'!$C$10/1000000)+'🎛️ Premissas'!$C$20*('🎛️ Premissas'!$C$11/1000000))*(1-'🎛️ Premissas'!$C$12)*'🎛️ Premissas'!$C$9)+('🎛️ Premissas'!$C$22*('🎛️ Premissas'!$C$23*('🎛️ Premissas'!$C$10/1000000)+'🎛️ Premissas'!$C$24*('🎛️ Premissas'!$C$11/1000000))*(1-'🎛️ Premissas'!$C$12)*'🎛️ Premissas'!$C$9))+Y66*(('🎛️ Premissas'!$C$25*('🎛️ Premissas'!$C$19*('🎛️ Premissas'!$C$10/1000000)+'🎛️ Premissas'!$C$20*('🎛️ Premissas'!$C$11/1000000))*(1-'🎛️ Premissas'!$C$12)*'🎛️ Premissas'!$C$9)+('🎛️ Premissas'!$C$26*('🎛️ Premissas'!$C$23*('🎛️ Premissas'!$C$10/1000000)+'🎛️ Premissas'!$C$24*('🎛️ Premissas'!$C$11/1000000))*(1-'🎛️ Premissas'!$C$12)*'🎛️ Premissas'!$C$9)) -> 307917.19
A70: Custo Fixo | B70: ='🎛️ Premissas'!$C$37+'🎛️ Premissas'!$C$39+'🎛️ Premissas'!$C$41+'🎛️ Premissas'!$C$43 -> 63000 | C70: ='🎛️ Premissas'!$C$37+'🎛️ Premissas'!$C$39+'🎛️ Premissas'!$C$41+'🎛️ Premissas'!$C$43 -> 63000 | D70: ='🎛️ Premissas'!$C$37+'🎛️ Premissas'!$C$39+'🎛️ Premissas'!$C$41+'🎛️ Premissas'!$C$43 -> 63000 | E70: ='🎛️ Premissas'!$C$37+'🎛️ Premissas'!$C$39+'🎛️ Premissas'!$C$41+'🎛️ Premissas'!$C$43 -> 63000 | F70: ='🎛️ Premissas'!$C$37+'🎛️ Premissas'!$C$39+'🎛️ Premissas'!$C$41+'🎛️ Premissas'!$C$43 -> 63000 | G70: ='🎛️ Premissas'!$C$37+'🎛️ Premissas'!$C$39+'🎛️ Premissas'!$C$41+'🎛️ Premissas'!$C$43 -> 63000 | H70: ='🎛️ Premissas'!$C$37+'🎛️ Premissas'!$C$39+'🎛️ Premissas'!$C$41+'🎛️ Premissas'!$C$43 -> 63000 | I70: ='🎛️ Premissas'!$C$37+'🎛️ Premissas'!$C$39+'🎛️ Premissas'!$C$41+'🎛️ Premissas'!$C$43 -> 63000 | ... M70: ='🎛️ Premissas'!$C$37+'🎛️ Premissas'!$C$39+'🎛️ Premissas'!$C$41+'🎛️ Premissas'!$C$43 -> 63000 | N70: ='🎛️ Premissas'!$C$38+'🎛️ Premissas'!$C$40+'🎛️ Premissas'!$C$42+'🎛️ Premissas'!$C$43 -> 84000 | O70: ='🎛️ Premissas'!$C$38+'🎛️ Premissas'!$C$40+'🎛️ Premissas'!$C$42+'🎛️ Premissas'!$C$43 -> 84000 | P70: ='🎛️ Premissas'!$C$38+'🎛️ Premissas'!$C$40+'🎛️ Premissas'!$C$42+'🎛️ Premissas'!$C$43 -> 84000 | Q70: ='🎛️ Premissas'!$C$38+'🎛️ Premissas'!$C$40+'🎛️ Premissas'!$C$42+'🎛️ Premissas'!$C$43 -> 84000 | R70: ='🎛️ Premissas'!$C$38+'🎛️ Premissas'!$C$40+'🎛️ Premissas'!$C$42+'🎛️ Premissas'!$C$43 -> 84000 | S70: ='🎛️ Premissas'!$C$38+'🎛️ Premissas'!$C$40+'🎛️ Premissas'!$C$42+'🎛️ Premissas'!$C$43 -> 84000 | T70: ='🎛️ Premissas'!$C$38+'🎛️ Premissas'!$C$40+'🎛️ Premissas'!$C$42+'🎛️ Premissas'!$C$43 -> 84000 | U70: ='🎛️ Premissas'!$C$38+'🎛️ Premissas'!$C$40+'🎛️ Premissas'!$C$42+'🎛️ Premissas'!$C$43 -> 84000 | ... Y70: ='🎛️ Premissas'!$C$38+'🎛️ Premissas'!$C$40+'🎛️ Premissas'!$C$42+'🎛️ Premissas'!$C$43 -> 84000
A71: Impostos | B71: =B68*'🎛️ Premissas'!$C$67 -> 2874.96 | C71: =C68*'🎛️ Premissas'!$C$67 -> 6229.08 | D71: =D68*'🎛️ Premissas'!$C$67 -> 9583.2 | E71: =E68*'🎛️ Premissas'!$C$67 -> 12937.32 | F71: =F68*'🎛️ Premissas'!$C$67 -> 16291.44 | G71: =G68*'🎛️ Premissas'!$C$67 -> 19645.56 | H71: =H68*'🎛️ Premissas'!$C$67 -> 22999.68 | I71: =I68*'🎛️ Premissas'!$C$67 -> 26353.8 | ... Y71: =Y68*'🎛️ Premissas'!$C$67 -> 233916.12
A72: Resultado Mensal | B72: =B68-B69-B70-B71 -> -46584.596 | C72: =C68-C69-C70-C71 -> -27433.291 | D72: =D68-D69-D70-D71 -> -8281.986 | E72: =E68-E69-E70-E71 -> 10869.319 | F72: =F68-F69-F70-F71 -> 30020.624 | G72: =G68-G69-G70-G71 -> 49171.929 | H72: =H68-H69-H70-H71 -> 68323.234 | I72: =I68-I69-I70-I71 -> 87474.539 | ... Y72: =Y68-Y69-Y70-Y71 -> 1323467.7
A74: OTIMISTA
A75: Free Cadastros | B75: ='🎛️ Premissas'!$B$61 -> 3000 | C75: =B75+'🎛️ Premissas'!$D$28 -> 7000 | D75: =C75+'🎛️ Premissas'!$D$28 -> 11000 | E75: =D75+'🎛️ Premissas'!$D$28 -> 15000 | F75: =E75+'🎛️ Premissas'!$D$28 -> 19000 | G75: =F75+'🎛️ Premissas'!$D$28 -> 23000 | H75: =G75+'🎛️ Premissas'!$D$28 -> 27000 | I75: =H75+'🎛️ Premissas'!$D$28 -> 31000 | J75: =I75+'🎛️ Premissas'!$D$28 -> 35000 | ... M75: =L75+'🎛️ Premissas'!$D$28 -> 47000 | N75: =M75+'🎛️ Premissas'!$D$29 -> 51500 | O75: =N75+'🎛️ Premissas'!$D$29 -> 56000 | P75: =O75+'🎛️ Premissas'!$D$29 -> 60500 | Q75: =P75+'🎛️ Premissas'!$D$29 -> 65000 | R75: =Q75+'🎛️ Premissas'!$D$29 -> 69500 | S75: =R75+'🎛️ Premissas'!$D$29 -> 74000 | T75: =S75+'🎛️ Premissas'!$D$29 -> 78500 | U75: =T75+'🎛️ Premissas'!$D$29 -> 83000 | ... Y75: =X75+'🎛️ Premissas'!$D$29 -> 101000
A76: Essencial | B76: =ROUND(B75*'🎛️ Premissas'!$D$30,0) -> 300 | C76: =ROUND(C75*'🎛️ Premissas'!$D$30,0) -> 700 | D76: =ROUND(D75*'🎛️ Premissas'!$D$30,0) -> 1100 | E76: =ROUND(E75*'🎛️ Premissas'!$D$30,0) -> 1500 | F76: =ROUND(F75*'🎛️ Premissas'!$D$30,0) -> 1900 | G76: =ROUND(G75*'🎛️ Premissas'!$D$30,0) -> 2300 | H76: =ROUND(H75*'🎛️ Premissas'!$D$30,0) -> 2700 | I76: =ROUND(I75*'🎛️ Premissas'!$D$30,0) -> 3100 | ... P76: =ROUND(P75*'🎛️ Premissas'!$D$30,0) -> 6050 | Q76: =ROUND(P76*(1-'🎛️ Premissas'!$D$33)+MAX(0,Q75-P79)*'🎛️ Premissas'!$D$30,0) -> 10977 | R76: =ROUND(Q76*(1-'🎛️ Premissas'!$D$33)+MAX(0,R75-Q79)*'🎛️ Premissas'!$D$30,0) -> 15453 | S76: =ROUND(R76*(1-'🎛️ Premissas'!$D$33)+MAX(0,S75-R79)*'🎛️ Premissas'!$D$30,0) -> 19537 | T76: =ROUND(S76*(1-'🎛️ Premissas'!$D$33)+MAX(0,T75-S79)*'🎛️ Premissas'!$D$30,0) -> 23281 | U76: =ROUND(T76*(1-'🎛️ Premissas'!$D$33)+MAX(0,U75-T79)*'🎛️ Premissas'!$D$30,0) -> 26731 | V76: =ROUND(U76*(1-'🎛️ Premissas'!$D$33)+MAX(0,V75-U79)*'🎛️ Premissas'!$D$30,0) -> 29928 | W76: =ROUND(V76*(1-'🎛️ Premissas'!$D$33)+MAX(0,W75-V79)*'🎛️ Premissas'!$D$30,0) -> 32907 | X76: =ROUND(W76*(1-'🎛️ Premissas'!$D$33)+MAX(0,X75-W79)*'🎛️ Premissas'!$D$30,0) -> 35699 | Y76: =ROUND(X76*(1-'🎛️ Premissas'!$D$33)+MAX(0,Y75-X79)*'🎛️ Premissas'!$D$30,0) -> 38330
A77: Autônoma | B77: =ROUND(B75*'🎛️ Premissas'!$D$31,0) -> 150 | C77: =ROUND(C75*'🎛️ Premissas'!$D$31,0) -> 350 | D77: =ROUND(D75*'🎛️ Premissas'!$D$31,0) -> 550 | E77: =ROUND(E75*'🎛️ Premissas'!$D$31,0) -> 750 | F77: =ROUND(F75*'🎛️ Premissas'!$D$31,0) -> 950 | G77: =ROUND(G75*'🎛️ Premissas'!$D$31,0) -> 1150 | H77: =ROUND(H75*'🎛️ Premissas'!$D$31,0) -> 1350 | I77: =ROUND(I75*'🎛️ Premissas'!$D$31,0) -> 1550 | ... P77: =ROUND(P75*'🎛️ Premissas'!$D$31,0) -> 3025 | Q77: =ROUND(P77*(1-'🎛️ Premissas'!$D$34)+MAX(0,Q76-P77-P78)*'🎛️ Premissas'!$D$31,0) -> 3181 | R77: =ROUND(Q77*(1-'🎛️ Premissas'!$D$34)+MAX(0,R76-Q77-Q78)*'🎛️ Premissas'!$D$31,0) -> 3545 | S77: =ROUND(R77*(1-'🎛️ Premissas'!$D$34)+MAX(0,S76-R77-R78)*'🎛️ Premissas'!$D$31,0) -> 4077 | T77: =ROUND(S77*(1-'🎛️ Premissas'!$D$34)+MAX(0,T76-S77-S78)*'🎛️ Premissas'!$D$31,0) -> 4743 | U77: =ROUND(T77*(1-'🎛️ Premissas'!$D$34)+MAX(0,U76-T77-T78)*'🎛️ Premissas'!$D$31,0) -> 5513 | V77: =ROUND(U77*(1-'🎛️ Premissas'!$D$34)+MAX(0,V76-U77-U78)*'🎛️ Premissas'!$D$31,0) -> 6363 | W77: =ROUND(V77*(1-'🎛️ Premissas'!$D$34)+MAX(0,W76-V77-V78)*'🎛️ Premissas'!$D$31,0) -> 7273 | X77: =ROUND(W77*(1-'🎛️ Premissas'!$D$34)+MAX(0,X76-W77-W78)*'🎛️ Premissas'!$D$31,0) -> 8227 | Y77: =ROUND(X77*(1-'🎛️ Premissas'!$D$34)+MAX(0,Y76-X77-X78)*'🎛️ Premissas'!$D$31,0) -> 9211
A78: Livre | B78: =ROUND(B75*'🎛️ Premissas'!$D$32,0) -> 90 | C78: =ROUND(C75*'🎛️ Premissas'!$D$32,0) -> 210 | D78: =ROUND(D75*'🎛️ Premissas'!$D$32,0) -> 330 | E78: =ROUND(E75*'🎛️ Premissas'!$D$32,0) -> 450 | F78: =ROUND(F75*'🎛️ Premissas'!$D$32,0) -> 570 | G78: =ROUND(G75*'🎛️ Premissas'!$D$32,0) -> 690 | H78: =ROUND(H75*'🎛️ Premissas'!$D$32,0) -> 810 | I78: =ROUND(I75*'🎛️ Premissas'!$D$32,0) -> 930 | ... P78: =ROUND(P75*'🎛️ Premissas'!$D$32,0) -> 1815 | Q78: =ROUND(P78*(1-'🎛️ Premissas'!$D$35)+MAX(0,Q77-P78)*'🎛️ Premissas'!$D$32,0) -> 1802 | R78: =ROUND(Q78*(1-'🎛️ Premissas'!$D$35)+MAX(0,R77-Q78)*'🎛️ Premissas'!$D$32,0) -> 1800 | S78: =ROUND(R78*(1-'🎛️ Premissas'!$D$35)+MAX(0,S77-R78)*'🎛️ Premissas'!$D$32,0) -> 1814 | T78: =ROUND(S78*(1-'🎛️ Premissas'!$D$35)+MAX(0,T77-S78)*'🎛️ Premissas'!$D$32,0) -> 1847 | U78: =ROUND(T78*(1-'🎛️ Premissas'!$D$35)+MAX(0,U77-T78)*'🎛️ Premissas'!$D$32,0) -> 1902 | V78: =ROUND(U78*(1-'🎛️ Premissas'!$D$35)+MAX(0,V77-U78)*'🎛️ Premissas'!$D$32,0) -> 1979 | W78: =ROUND(V78*(1-'🎛️ Premissas'!$D$35)+MAX(0,W77-V78)*'🎛️ Premissas'!$D$32,0) -> 2078 | X78: =ROUND(W78*(1-'🎛️ Premissas'!$D$35)+MAX(0,X77-W78)*'🎛️ Premissas'!$D$32,0) -> 2200 | Y78: =ROUND(X78*(1-'🎛️ Premissas'!$D$35)+MAX(0,Y77-X78)*'🎛️ Premissas'!$D$32,0) -> 2344
A79: Total Pagantes | B79: =SUM(B76:B78) -> 540 | C79: =SUM(C76:C78) -> 1260 | D79: =SUM(D76:D78) -> 1980 | E79: =SUM(E76:E78) -> 2700 | F79: =SUM(F76:F78) -> 3420 | G79: =SUM(G76:G78) -> 4140 | H79: =SUM(H76:H78) -> 4860 | I79: =SUM(I76:I78) -> 5580 | ... Y79: =SUM(Y76:Y78) -> 49885
A80: MRR | B80: =B76*'🎛️ Premissas'!$D$5+B77*'🎛️ Premissas'!$D$6+B78*'🎛️ Premissas'!$D$7 -> 31596 | C80: =C76*'🎛️ Premissas'!$D$5+C77*'🎛️ Premissas'!$D$6+C78*'🎛️ Premissas'!$D$7 -> 73724 | D80: =D76*'🎛️ Premissas'!$D$5+D77*'🎛️ Premissas'!$D$6+D78*'🎛️ Premissas'!$D$7 -> 115852 | E80: =E76*'🎛️ Premissas'!$D$5+E77*'🎛️ Premissas'!$D$6+E78*'🎛️ Premissas'!$D$7 -> 157980 | F80: =F76*'🎛️ Premissas'!$D$5+F77*'🎛️ Premissas'!$D$6+F78*'🎛️ Premissas'!$D$7 -> 200108 | G80: =G76*'🎛️ Premissas'!$D$5+G77*'🎛️ Premissas'!$D$6+G78*'🎛️ Premissas'!$D$7 -> 242236 | H80: =H76*'🎛️ Premissas'!$D$5+H77*'🎛️ Premissas'!$D$6+H78*'🎛️ Premissas'!$D$7 -> 284364 | I80: =I76*'🎛️ Premissas'!$D$5+I77*'🎛️ Premissas'!$D$6+I78*'🎛️ Premissas'!$D$7 -> 326492 | ... Y80: =Y76*'🎛️ Premissas'!$D$5+Y77*'🎛️ Premissas'!$D$6+Y78*'🎛️ Premissas'!$D$7 -> 2679324.5
A81: API Total | B81: =B75*('🎛️ Premissas'!$D$14*('🎛️ Premissas'!$D$15*('🎛️ Premissas'!$G$9/1000000)+'🎛️ Premissas'!$D$16*('🎛️ Premissas'!$G$10/1000000))*(1-'🎛️ Premissas'!$D$12)*'🎛️ Premissas'!$D$9*'🎛️ Premissas'!$D$17)+B76*('🎛️ Premissas'!$D$18*('🎛️ Premissas'!$D$19*('🎛️ Premissas'!$D$10/1000000)+'🎛️ Premissas'!$D$20*('🎛️ Premissas'!$D$11/1000000))*(1-'🎛️ Premissas'!$D$12)*'🎛️ Premissas'!$D$9)+B77*(('🎛️ Premissas'!$D$21*('🎛️ Premissas'!$D$19*('🎛️ Premissas'!$D$10/1000000)+'🎛️ Premissas'!$D$20*('🎛️ Premissas'!$D$11/1000000))*(1-'🎛️ Premissas'!$D$12)*'🎛️ Premissas'!$D$9)+('🎛️ Premissas'!$D$22*('🎛️ Premissas'!$D$23*('🎛️ Premissas'!$D$10/1000000)+'🎛️ Premissas'!$D$24*('🎛️ Premissas'!$D$11/1000000))*(1-'🎛️ Premissas'!$D$12)*'🎛️ Premissas'!$D$9))+B78*(('🎛️ Premissas'!$D$25*('🎛️ Premissas'!$D$19*('🎛️ Premissas'!$D$10/1000000)+'🎛️ Premissas'!$D$20*('🎛️ Premissas'!$D$11/1000000))*(1-'🎛️ Premissas'!$D$12)*'🎛️ Premissas'!$D$9)+('🎛️ Premissas'!$D$26*('🎛️ Premissas'!$D$23*('🎛️ Premissas'!$D$10/1000000)+'🎛️ Premissas'!$D$24*('🎛️ Premissas'!$D$11/1000000))*(1-'🎛️ Premissas'!$D$12)*'🎛️ Premissas'!$D$9)) -> 6637.7174 | C81: =C75*('🎛️ Premissas'!$D$14*('🎛️ Premissas'!$D$15*('🎛️ Premissas'!$G$9/1000000)+'🎛️ Premissas'!$D$16*('🎛️ Premissas'!$G$10/1000000))*(1-'🎛️ Premissas'!$D$12)*'🎛️ Premissas'!$D$9*'🎛️ Premissas'!$D$17)+C76*('🎛️ Premissas'!$D$18*('🎛️ Premissas'!$D$19*('🎛️ Premissas'!$D$10/1000000)+'🎛️ Premissas'!$D$20*('🎛️ Premissas'!$D$11/1000000))*(1-'🎛️ Premissas'!$D$12)*'🎛️ Premissas'!$D$9)+C77*(('🎛️ Premissas'!$D$21*('🎛️ Premissas'!$D$19*('🎛️ Premissas'!$D$10/1000000)+'🎛️ Premissas'!$D$20*('🎛️ Premissas'!$D$11/1000000))*(1-'🎛️ Premissas'!$D$12)*'🎛️ Premissas'!$D$9)+('🎛️ Premissas'!$D$22*('🎛️ Premissas'!$D$23*('🎛️ Premissas'!$D$10/1000000)+'🎛️ Premissas'!$D$24*('🎛️ Premissas'!$D$11/1000000))*(1-'🎛️ Premissas'!$D$12)*'🎛️ Premissas'!$D$9))+C78*(('🎛️ Premissas'!$D$25*('🎛️ Premissas'!$D$19*('🎛️ Premissas'!$D$10/1000000)+'🎛️ Premissas'!$D$20*('🎛️ Premissas'!$D$11/1000000))*(1-'🎛️ Premissas'!$D$12)*'🎛️ Premissas'!$D$9)+('🎛️ Premissas'!$D$26*('🎛️ Premissas'!$D$23*('🎛️ Premissas'!$D$10/1000000)+'🎛️ Premissas'!$D$24*('🎛️ Premissas'!$D$11/1000000))*(1-'🎛️ Premissas'!$D$12)*'🎛️ Premissas'!$D$9)) -> 15488.007 | D81: =D75*('🎛️ Premissas'!$D$14*('🎛️ Premissas'!$D$15*('🎛️ Premissas'!$G$9/1000000)+'🎛️ Premissas'!$D$16*('🎛️ Premissas'!$G$10/1000000))*(1-'🎛️ Premissas'!$D$12)*'🎛️ Premissas'!$D$9*'🎛️ Premissas'!$D$17)+D76*('🎛️ Premissas'!$D$18*('🎛️ Premissas'!$D$19*('🎛️ Premissas'!$D$10/1000000)+'🎛️ Premissas'!$D$20*('🎛️ Premissas'!$D$11/1000000))*(1-'🎛️ Premissas'!$D$12)*'🎛️ Premissas'!$D$9)+D77*(('🎛️ Premissas'!$D$21*('🎛️ Premissas'!$D$19*('🎛️ Premissas'!$D$10/1000000)+'🎛️ Premissas'!$D$20*('🎛️ Premissas'!$D$11/1000000))*(1-'🎛️ Premissas'!$D$12)*'🎛️ Premissas'!$D$9)+('🎛️ Premissas'!$D$22*('🎛️ Premissas'!$D$23*('🎛️ Premissas'!$D$10/1000000)+'🎛️ Premissas'!$D$24*('🎛️ Premissas'!$D$11/1000000))*(1-'🎛️ Premissas'!$D$12)*'🎛️ Premissas'!$D$9))+D78*(('🎛️ Premissas'!$D$25*('🎛️ Premissas'!$D$19*('🎛️ Premissas'!$D$10/1000000)+'🎛️ Premissas'!$D$20*('🎛️ Premissas'!$D$11/1000000))*(1-'🎛️ Premissas'!$D$12)*'🎛️ Premissas'!$D$9)+('🎛️ Premissas'!$D$26*('🎛️ Premissas'!$D$23*('🎛️ Premissas'!$D$10/1000000)+'🎛️ Premissas'!$D$24*('🎛️ Premissas'!$D$11/1000000))*(1-'🎛️ Premissas'!$D$12)*'🎛️ Premissas'!$D$9)) -> 24338.297 | E81: =E75*('🎛️ Premissas'!$D$14*('🎛️ Premissas'!$D$15*('🎛️ Premissas'!$G$9/1000000)+'🎛️ Premissas'!$D$16*('🎛️ Premissas'!$G$10/1000000))*(1-'🎛️ Premissas'!$D$12)*'🎛️ Premissas'!$D$9*'🎛️ Premissas'!$D$17)+E76*('🎛️ Premissas'!$D$18*('🎛️ Premissas'!$D$19*('🎛️ Premissas'!$D$10/1000000)+'🎛️ Premissas'!$D$20*('🎛️ Premissas'!$D$11/1000000))*(1-'🎛️ Premissas'!$D$12)*'🎛️ Premissas'!$D$9)+E77*(('🎛️ Premissas'!$D$21*('🎛️ Premissas'!$D$19*('🎛️ Premissas'!$D$10/1000000)+'🎛️ Premissas'!$D$20*('🎛️ Premissas'!$D$11/1000000))*(1-'🎛️ Premissas'!$D$12)*'🎛️ Premissas'!$D$9)+('🎛️ Premissas'!$D$22*('🎛️ Premissas'!$D$23*('🎛️ Premissas'!$D$10/1000000)+'🎛️ Premissas'!$D$24*('🎛️ Premissas'!$D$11/1000000))*(1-'🎛️ Premissas'!$D$12)*'🎛️ Premissas'!$D$9))+E78*(('🎛️ Premissas'!$D$25*('🎛️ Premissas'!$D$19*('🎛️ Premissas'!$D$10/1000000)+'🎛️ Premissas'!$D$20*('🎛️ Premissas'!$D$11/1000000))*(1-'🎛️ Premissas'!$D$12)*'🎛️ Premissas'!$D$9)+('🎛️ Premissas'!$D$26*('🎛️ Premissas'!$D$23*('🎛️ Premissas'!$D$10/1000000)+'🎛️ Premissas'!$D$24*('🎛️ Premissas'!$D$11/1000000))*(1-'🎛️ Premissas'!$D$12)*'🎛️ Premissas'!$D$9)) -> 33188.587 | F81: =F75*('🎛️ Premissas'!$D$14*('🎛️ Premissas'!$D$15*('🎛️ Premissas'!$G$9/1000000)+'🎛️ Premissas'!$D$16*('🎛️ Premissas'!$G$10/1000000))*(1-'🎛️ Premissas'!$D$12)*'🎛️ Premissas'!$D$9*'🎛️ Premissas'!$D$17)+F76*('🎛️ Premissas'!$D$18*('🎛️ Premissas'!$D$19*('🎛️ Premissas'!$D$10/1000000)+'🎛️ Premissas'!$D$20*('🎛️ Premissas'!$D$11/1000000))*(1-'🎛️ Premissas'!$D$12)*'🎛️ Premissas'!$D$9)+F77*(('🎛️ Premissas'!$D$21*('🎛️ Premissas'!$D$19*('🎛️ Premissas'!$D$10/1000000)+'🎛️ Premissas'!$D$20*('🎛️ Premissas'!$D$11/1000000))*(1-'🎛️ Premissas'!$D$12)*'🎛️ Premissas'!$D$9)+('🎛️ Premissas'!$D$22*('🎛️ Premissas'!$D$23*('🎛️ Premissas'!$D$10/1000000)+'🎛️ Premissas'!$D$24*('🎛️ Premissas'!$D$11/1000000))*(1-'🎛️ Premissas'!$D$12)*'🎛️ Premissas'!$D$9))+F78*(('🎛️ Premissas'!$D$25*('🎛️ Premissas'!$D$19*('🎛️ Premissas'!$D$10/1000000)+'🎛️ Premissas'!$D$20*('🎛️ Premissas'!$D$11/1000000))*(1-'🎛️ Premissas'!$D$12)*'🎛️ Premissas'!$D$9)+('🎛️ Premissas'!$D$26*('🎛️ Premissas'!$D$23*('🎛️ Premissas'!$D$10/1000000)+'🎛️ Premissas'!$D$24*('🎛️ Premissas'!$D$11/1000000))*(1-'🎛️ Premissas'!$D$12)*'🎛️ Premissas'!$D$9)) -> 42038.877 | G81: =G75*('🎛️ Premissas'!$D$14*('🎛️ Premissas'!$D$15*('🎛️ Premissas'!$G$9/1000000)+'🎛️ Premissas'!$D$16*('🎛️ Premissas'!$G$10/1000000))*(1-'🎛️ Premissas'!$D$12)*'🎛️ Premissas'!$D$9*'🎛️ Premissas'!$D$17)+G76*('🎛️ Premissas'!$D$18*('🎛️ Premissas'!$D$19*('🎛️ Premissas'!$D$10/1000000)+'🎛️ Premissas'!$D$20*('🎛️ Premissas'!$D$11/1000000))*(1-'🎛️ Premissas'!$D$12)*'🎛️ Premissas'!$D$9)+G77*(('🎛️ Premissas'!$D$21*('🎛️ Premissas'!$D$19*('🎛️ Premissas'!$D$10/1000000)+'🎛️ Premissas'!$D$20*('🎛️ Premissas'!$D$11/1000000))*(1-'🎛️ Premissas'!$D$12)*'🎛️ Premissas'!$D$9)+('🎛️ Premissas'!$D$22*('🎛️ Premissas'!$D$23*('🎛️ Premissas'!$D$10/1000000)+'🎛️ Premissas'!$D$24*('🎛️ Premissas'!$D$11/1000000))*(1-'🎛️ Premissas'!$D$12)*'🎛️ Premissas'!$D$9))+G78*(('🎛️ Premissas'!$D$25*('🎛️ Premissas'!$D$19*('🎛️ Premissas'!$D$10/1000000)+'🎛️ Premissas'!$D$20*('🎛️ Premissas'!$D$11/1000000))*(1-'🎛️ Premissas'!$D$12)*'🎛️ Premissas'!$D$9)+('🎛️ Premissas'!$D$26*('🎛️ Premissas'!$D$23*('🎛️ Premissas'!$D$10/1000000)+'🎛️ Premissas'!$D$24*('🎛️ Premissas'!$D$11/1000000))*(1-'🎛️ Premissas'!$D$12)*'🎛️ Premissas'!$D$9)) -> 50889.166 | H81: =H75*('🎛️ Premissas'!$D$14*('🎛️ Premissas'!$D$15*('🎛️ Premissas'!$G$9/1000000)+'🎛️ Premissas'!$D$16*('🎛️ Premissas'!$G$10/1000000))*(1-'🎛️ Premissas'!$D$12)*'🎛️ Premissas'!$D$9*'🎛️ Premissas'!$D$17)+H76*('🎛️ Premissas'!$D$18*('🎛️ Premissas'!$D$19*('🎛️ Premissas'!$D$10/1000000)+'🎛️ Premissas'!$D$20*('🎛️ Premissas'!$D$11/1000000))*(1-'🎛️ Premissas'!$D$12)*'🎛️ Premissas'!$D$9)+H77*(('🎛️ Premissas'!$D$21*('🎛️ Premissas'!$D$19*('🎛️ Premissas'!$D$10/1000000)+'🎛️ Premissas'!$D$20*('🎛️ Premissas'!$D$11/1000000))*(1-'🎛️ Premissas'!$D$12)*'🎛️ Premissas'!$D$9)+('🎛️ Premissas'!$D$22*('🎛️ Premissas'!$D$23*('🎛️ Premissas'!$D$10/1000000)+'🎛️ Premissas'!$D$24*('🎛️ Premissas'!$D$11/1000000))*(1-'🎛️ Premissas'!$D$12)*'🎛️ Premissas'!$D$9))+H78*(('🎛️ Premissas'!$D$25*('🎛️ Premissas'!$D$19*('🎛️ Premissas'!$D$10/1000000)+'🎛️ Premissas'!$D$20*('🎛️ Premissas'!$D$11/1000000))*(1-'🎛️ Premissas'!$D$12)*'🎛️ Premissas'!$D$9)+('🎛️ Premissas'!$D$26*('🎛️ Premissas'!$D$23*('🎛️ Premissas'!$D$10/1000000)+'🎛️ Premissas'!$D$24*('🎛️ Premissas'!$D$11/1000000))*(1-'🎛️ Premissas'!$D$12)*'🎛️ Premissas'!$D$9)) -> 59739.456 | I81: =I75*('🎛️ Premissas'!$D$14*('🎛️ Premissas'!$D$15*('🎛️ Premissas'!$G$9/1000000)+'🎛️ Premissas'!$D$16*('🎛️ Premissas'!$G$10/1000000))*(1-'🎛️ Premissas'!$D$12)*'🎛️ Premissas'!$D$9*'🎛️ Premissas'!$D$17)+I76*('🎛️ Premissas'!$D$18*('🎛️ Premissas'!$D$19*('🎛️ Premissas'!$D$10/1000000)+'🎛️ Premissas'!$D$20*('🎛️ Premissas'!$D$11/1000000))*(1-'🎛️ Premissas'!$D$12)*'🎛️ Premissas'!$D$9)+I77*(('🎛️ Premissas'!$D$21*('🎛️ Premissas'!$D$19*('🎛️ Premissas'!$D$10/1000000)+'🎛️ Premissas'!$D$20*('🎛️ Premissas'!$D$11/1000000))*(1-'🎛️ Premissas'!$D$12)*'🎛️ Premissas'!$D$9)+('🎛️ Premissas'!$D$22*('🎛️ Premissas'!$D$23*('🎛️ Premissas'!$D$10/1000000)+'🎛️ Premissas'!$D$24*('🎛️ Premissas'!$D$11/1000000))*(1-'🎛️ Premissas'!$D$12)*'🎛️ Premissas'!$D$9))+I78*(('🎛️ Premissas'!$D$25*('🎛️ Premissas'!$D$19*('🎛️ Premissas'!$D$10/1000000)+'🎛️ Premissas'!$D$20*('🎛️ Premissas'!$D$11/1000000))*(1-'🎛️ Premissas'!$D$12)*'🎛️ Premissas'!$D$9)+('🎛️ Premissas'!$D$26*('🎛️ Premissas'!$D$23*('🎛️ Premissas'!$D$10/1000000)+'🎛️ Premissas'!$D$24*('🎛️ Premissas'!$D$11/1000000))*(1-'🎛️ Premissas'!$D$12)*'🎛️ Premissas'!$D$9)) -> 68589.746 | ... Y81: =Y75*('🎛️ Premissas'!$D$14*('🎛️ Premissas'!$D$15*('🎛️ Premissas'!$G$9/1000000)+'🎛️ Premissas'!$D$16*('🎛️ Premissas'!$G$10/1000000))*(1-'🎛️ Premissas'!$D$12)*'🎛️ Premissas'!$D$9*'🎛️ Premissas'!$D$17)+Y76*('🎛️ Premissas'!$D$18*('🎛️ Premissas'!$D$19*('🎛️ Premissas'!$D$10/1000000)+'🎛️ Premissas'!$D$20*('🎛️ Premissas'!$D$11/1000000))*(1-'🎛️ Premissas'!$D$12)*'🎛️ Premissas'!$D$9)+Y77*(('🎛️ Premissas'!$D$21*('🎛️ Premissas'!$D$19*('🎛️ Premissas'!$D$10/1000000)+'🎛️ Premissas'!$D$20*('🎛️ Premissas'!$D$11/1000000))*(1-'🎛️ Premissas'!$D$12)*'🎛️ Premissas'!$D$9)+('🎛️ Premissas'!$D$22*('🎛️ Premissas'!$D$23*('🎛️ Premissas'!$D$10/1000000)+'🎛️ Premissas'!$D$24*('🎛️ Premissas'!$D$11/1000000))*(1-'🎛️ Premissas'!$D$12)*'🎛️ Premissas'!$D$9))+Y78*(('🎛️ Premissas'!$D$25*('🎛️ Premissas'!$D$19*('🎛️ Premissas'!$D$10/1000000)+'🎛️ Premissas'!$D$20*('🎛️ Premissas'!$D$11/1000000))*(1-'🎛️ Premissas'!$D$12)*'🎛️ Premissas'!$D$9)+('🎛️ Premissas'!$D$26*('🎛️ Premissas'!$D$23*('🎛️ Premissas'!$D$10/1000000)+'🎛️ Premissas'!$D$24*('🎛️ Premissas'!$D$11/1000000))*(1-'🎛️ Premissas'!$D$12)*'🎛️ Premissas'!$D$9)) -> 500534.07
A82: Custo Fixo | B82: ='🎛️ Premissas'!$D$37+'🎛️ Premissas'!$D$39+'🎛️ Premissas'!$D$41+'🎛️ Premissas'!$D$43 -> 74000 | C82: ='🎛️ Premissas'!$D$37+'🎛️ Premissas'!$D$39+'🎛️ Premissas'!$D$41+'🎛️ Premissas'!$D$43 -> 74000 | D82: ='🎛️ Premissas'!$D$37+'🎛️ Premissas'!$D$39+'🎛️ Premissas'!$D$41+'🎛️ Premissas'!$D$43 -> 74000 | E82: ='🎛️ Premissas'!$D$37+'🎛️ Premissas'!$D$39+'🎛️ Premissas'!$D$41+'🎛️ Premissas'!$D$43 -> 74000 | F82: ='🎛️ Premissas'!$D$37+'🎛️ Premissas'!$D$39+'🎛️ Premissas'!$D$41+'🎛️ Premissas'!$D$43 -> 74000 | G82: ='🎛️ Premissas'!$D$37+'🎛️ Premissas'!$D$39+'🎛️ Premissas'!$D$41+'🎛️ Premissas'!$D$43 -> 74000 | H82: ='🎛️ Premissas'!$D$37+'🎛️ Premissas'!$D$39+'🎛️ Premissas'!$D$41+'🎛️ Premissas'!$D$43 -> 74000 | I82: ='🎛️ Premissas'!$D$37+'🎛️ Premissas'!$D$39+'🎛️ Premissas'!$D$41+'🎛️ Premissas'!$D$43 -> 74000 | ... M82: ='🎛️ Premissas'!$D$37+'🎛️ Premissas'!$D$39+'🎛️ Premissas'!$D$41+'🎛️ Premissas'!$D$43 -> 74000 | N82: ='🎛️ Premissas'!$D$38+'🎛️ Premissas'!$D$40+'🎛️ Premissas'!$D$42+'🎛️ Premissas'!$D$43 -> 103000 | O82: ='🎛️ Premissas'!$D$38+'🎛️ Premissas'!$D$40+'🎛️ Premissas'!$D$42+'🎛️ Premissas'!$D$43 -> 103000 | P82: ='🎛️ Premissas'!$D$38+'🎛️ Premissas'!$D$40+'🎛️ Premissas'!$D$42+'🎛️ Premissas'!$D$43 -> 103000 | Q82: ='🎛️ Premissas'!$D$38+'🎛️ Premissas'!$D$40+'🎛️ Premissas'!$D$42+'🎛️ Premissas'!$D$43 -> 103000 | R82: ='🎛️ Premissas'!$D$38+'🎛️ Premissas'!$D$40+'🎛️ Premissas'!$D$42+'🎛️ Premissas'!$D$43 -> 103000 | S82: ='🎛️ Premissas'!$D$38+'🎛️ Premissas'!$D$40+'🎛️ Premissas'!$D$42+'🎛️ Premissas'!$D$43 -> 103000 | T82: ='🎛️ Premissas'!$D$38+'🎛️ Premissas'!$D$40+'🎛️ Premissas'!$D$42+'🎛️ Premissas'!$D$43 -> 103000 | U82: ='🎛️ Premissas'!$D$38+'🎛️ Premissas'!$D$40+'🎛️ Premissas'!$D$42+'🎛️ Premissas'!$D$43 -> 103000 | ... Y82: ='🎛️ Premissas'!$D$38+'🎛️ Premissas'!$D$40+'🎛️ Premissas'!$D$42+'🎛️ Premissas'!$D$43 -> 103000
A83: Impostos | B83: =B80*'🎛️ Premissas'!$D$67 -> 4739.4 | C83: =C80*'🎛️ Premissas'!$D$67 -> 11058.6 | D83: =D80*'🎛️ Premissas'!$D$67 -> 17377.8 | E83: =E80*'🎛️ Premissas'!$D$67 -> 23697 | F83: =F80*'🎛️ Premissas'!$D$67 -> 30016.2 | G83: =G80*'🎛️ Premissas'!$D$67 -> 36335.4 | H83: =H80*'🎛️ Premissas'!$D$67 -> 42654.6 | I83: =I80*'🎛️ Premissas'!$D$67 -> 48973.8 | ... Y83: =Y80*'🎛️ Premissas'!$D$67 -> 401898.67
A84: Resultado Mensal | B84: =B80-B81-B82-B83 -> -53781.117 | C84: =C80-C81-C82-C83 -> -26822.607 | D84: =D80-D81-D82-D83 -> 135.90305 | E84: =E80-E81-E82-E83 -> 27094.413 | F84: =F80-F81-F82-F83 -> 54052.923 | G84: =G80-G81-G82-G83 -> 81011.434 | H84: =H80-H81-H82-H83 -> 107969.94 | I84: =I80-I81-I82-I83 -> 134928.45 | ... Y84: =Y80-Y81-Y82-Y83 -> 1673891.8
A86: Cons CF (helper TIR) | B86: =-'🎛️ Premissas'!$B$55 -> -1000000 | C86: =B60 -> -44240.949 | D86: =C60 -> -33481.899 | E86: =D60 -> -22722.848 | F86: =E60 -> -11963.797 | G86: =F60 -> -1204.7462 | H86: =G60 -> 9554.3045 | I86: =H60 -> 20313.355 | J86: =I60 -> 31072.406 | ... Z86: =Y60 -> 801109
A87: Base CF (helper TIR) | B87: =-'🎛️ Premissas'!$B$55 -> -1000000 | C87: =B72 -> -46584.596 | D87: =C72 -> -27433.291 | E87: =D72 -> -8281.986 | F87: =E72 -> 10869.319 | G87: =F72 -> 30020.624 | H87: =G72 -> 49171.929 | I87: =H72 -> 68323.234 | J87: =I72 -> 87474.539 | ... Z87: =Y72 -> 1323467.7
A88: Otim CF (helper TIR) | B88: =-'🎛️ Premissas'!$B$55 -> -1000000 | C88: =B84 -> -53781.117 | D88: =C84 -> -26822.607 | E88: =D84 -> 135.90305 | F88: =E84 -> 27094.413 | G88: =F84 -> 54052.923 | H88: =G84 -> 81011.434 | I88: =H84 -> 107969.94 | J88: =I84 -> 134928.45 | ... Z88: =Y84 -> 1673891.8
